Workbook
Name NativeTimeline_Leased_Date: #N/A
Name Scenario: #REF!
Name Scenario: 'Pro Forma Model'!#REF!
Name Slicer_Beds: #N/A
Name Slicer_Property_Name: #N/A

Sheet Intro
B7: Click "Enable Editing" to update.
B9: Index
B10: 1 | C10: Weekly Market Updates
B11: 2 | C11: 30-Day Trends
B12: 3 | C12: Data Analysis
B13: 4 | C13: Leasing Trends
B14: 5 | C14: Rent Comps
B15: 6 | C15: Rent Comparison
B16: 7 | C16: Unit-Level Data
B17: 8 | C17: Unit Mix
B18: 9 | C18: Fees & Amenities
B19: 10 | C19: Specials

Sheet Weekly Market Updates
B2: Weekly Market Updates | O2: Week of: | P2: =IFERROR(TEXT(Q2 - 7, "m/d/yyyy") & " - ","") | Q2: 45785
B3: Note: Delta (△) figures show change from previous 7-day period.
B5: Property | C5: Active Concessions | E5: Unit Type | F5: # Leased | G5: △ | H5: Leased Rents | I5: $△ | J5: %△ | K5: # New | L5: △ | M5: New Listing Rents | N5: # Active | O5: △ | P5: Active Listing Rents | Q5: Exposure
B6: =IF(OFFSET('Rent Comparison'!$A$1,1,2)="{{subject.building_name}}","",OFFSET('Rent Comparison'!$A$1,1,2)) | C6: =IF(ISBLANK(B6),"",IFERROR(INDEX(Specials!B:J,MATCH(B6&" - Active",Specials!I:I,0),2),"")) | E6: Studio | F6: =COUNTIFS('Unit-Level Data'!L:L, ">=" & ($Q$2 - 7), 'Unit-Level Data'!L:L, "<" & $Q$2, 'Unit-Level Data'!G:G, 0, 'Unit-Level Data'!B:B, B6) -> 0 | G6: =COUNTIFS('Unit-Level Data'!L:L, ">=" & ($Q$2 - 7), 'Unit-Level Data'!L:L, "<" & $Q$2, 'Unit-Level Data'!G:G, 0, 'Unit-Level Data'!B:B, B6) - COUNTIFS('Unit-Level Data'!L:L, ">=" & ($Q$2 - 14), 'Unit-Level Data'!L:L, "<=" & ($Q$2 - 7), 'Unit-Level Data'!G:G, 0, 'Unit-Level Data'!B:B, B6) -> 0 | H6: =IFERROR(AVERAGEIFS('Unit-Level Data'!O:O,'Unit-Level Data'!L:L, ">=" & ($Q$2 - 7), 'Unit-Level Data'!L:L, "<" & $Q$2, 'Unit-Level Data'!G:G, 0, 'Unit-Level Data'!B:B, B6),"") | I6: =IFERROR( AVERAGEIFS('Unit-Level Data'!O:O, 'Unit-Level Data'!L:L, ">=" & ($Q$2 - 7), 'Unit-Level Data'!L:L, "<" & $Q$2, 'Unit-Level Data'!G:G, 0, 'Unit-Level Data'!B:B, B6) - AVERAGEIFS('Unit-Level Data'!O:O, 'Unit-Level Data'!L:L, ">=" & ($Q$2 - 14), 'Unit-Level Data'!L:L, "<=" & ($Q$2 - 7), 'Unit-Level Data'!G:G, 0, 'Unit-Level Data'!B:B, B6), 0) -> 0 | J6: =IFERROR(I6/AVERAGEIFS('Unit-Level Data'!O:O, 'Unit-Level Data'!L:L, ">=" & ($Q$2 - 14), 'Unit-Level Data'!L:L, "<=" & ($Q$2 - 7), 'Unit-Level Data'!G:G, 0, 'Unit-Level Data'!B:B, B6),0) -> 0 | K6: =COUNTIFS('Unit-Level Data'!K:K, ">=" & ($Q$2 - 7), 'Unit-Level Data'!K:K, "<" & $Q$2, 'Unit-Level Data'!G:G, 0, 'Unit-Level Data'!B:B, B6) -> 0 | L6: =COUNTIFS( 'Unit-Level Data'!K:K, ">=" & ($Q$2 - 7), 'Unit-Level Data'!K:K, "<" & $Q$2, 'Unit-Level Data'!G:G, 0, 'Unit-Level Data'!B:B, B6 ) - COUNTIFS( 'Unit-Level Data'!K:K, ">=" & ($Q$2 - 14), 'Unit-Level Data'!K:K, "<=" & ($Q$2 - 7), 'Unit-Level Data'!G:G, 0, 'Unit-Level Data'!B:B, B6 ) -> 0 | M6: =IFERROR(AVERAGEIFS('Unit-Level Data'!O:O,'Unit-Level Data'!K:K,">="&($Q$2-7), 'Unit-Level Data'!K:K,"<="&$Q$2, 'Unit-Level Data'!G:G,0, 'Unit-Level Data'!B:B,B6),"") | N6: =COUNTIFS('Unit-Level Data'!B:B, B6, 'Unit-Level Data'!G:G, 0, 'Unit-Level Data'!L:L, "") -> 0 | O6: =N6-(N6-K6+F6) -> 0 | P6: =IFERROR(AVERAGEIFS('Unit-Level Data'!O:O,'Unit-Level Data'!B:B, B6, 'Unit-Level Data'!G:G, 0, 'Unit-Level Data'!L:L, ""),"") | Q6: =IFERROR(N6/SUMIFS('Unit Mix'!G:G,'Unit Mix'!D:D,0,'Unit Mix'!B:B,B6),"")
B7: =IF(OFFSET('Rent Comps'!$A$1,3,2)="{{subject.full_address}}","",OFFSET('Rent Comps'!$A$1,3,2)) | E7: 1 BR | F7: =COUNTIFS('Unit-Level Data'!L:L, ">=" & ($Q$2 - 7), 'Unit-Level Data'!L:L, "<" & $Q$2, 'Unit-Level Data'!G:G, 1, 'Unit-Level Data'!B:B, B6) -> 0 | G7: =COUNTIFS('Unit-Level Data'!L:L, ">=" & ($Q$2 - 7), 'Unit-Level Data'!L:L, "<" & $Q$2, 'Unit-Level Data'!G:G, 1, 'Unit-Level Data'!B:B, B6) - COUNTIFS('Unit-Level Data'!L:L, ">=" & ($Q$2 - 14), 'Unit-Level Data'!L:L, "<=" & ($Q$2 - 7), 'Unit-Level Data'!G:G, 1, 'Unit-Level Data'!B:B, B6) -> 0 | H7: =IFERROR(AVERAGEIFS('Unit-Level Data'!O:O,'Unit-Level Data'!L:L, ">=" & ($Q$2 - 7), 'Unit-Level Data'!L:L, "<" & $Q$2, 'Unit-Level Data'!G:G, 1, 'Unit-Level Data'!B:B, B6),"") | I7: =IFERROR( AVERAGEIFS('Unit-Level Data'!O:O, 'Unit-Level Data'!L:L, ">=" & ($Q$2 - 7), 'Unit-Level Data'!L:L, "<" & $Q$2, 'Unit-Level Data'!G:G, 1, 'Unit-Level Data'!B:B, B6) - AVERAGEIFS('Unit-Level Data'!O:O, 'Unit-Level Data'!L:L, ">=" & ($Q$2 - 14), 'Unit-Level Data'!L:L, "<=" & ($Q$2 - 7), 'Unit-Level Data'!G:G, 1, 'Unit-Level Data'!B:B, B6), 0) -> 0 | J7: =IFERROR(I7/AVERAGEIFS('Unit-Level Data'!O:O, 'Unit-Level Data'!L:L, ">=" & ($Q$2 - 14), 'Unit-Level Data'!L:L, "<=" & ($Q$2 - 7), 'Unit-Level Data'!G:G, 1, 'Unit-Level Data'!B:B, B6),0) -> 0 | K7: =COUNTIFS('Unit-Level Data'!K:K, ">=" & ($Q$2 - 7), 'Unit-Level Data'!K:K, "<" & $Q$2, 'Unit-Level Data'!G:G, 1, 'Unit-Level Data'!B:B, B6) -> 0 | L7: =COUNTIFS( 'Unit-Level Data'!K:K, ">=" & ($Q$2 - 7), 'Unit-Level Data'!K:K, "<" & $Q$2, 'Unit-Level Data'!G:G, 1, 'Unit-Level Data'!B:B, B6 ) - COUNTIFS( 'Unit-Level Data'!K:K, ">=" & ($Q$2 - 14), 'Unit-Level Data'!K:K, "<=" & ($Q$2 - 7), 'Unit-Level Data'!G:G, 1, 'Unit-Level Data'!B:B, B6 ) -> 0 | M7: =IFERROR(AVERAGEIFS('Unit-Level Data'!O:O,'Unit-Level Data'!K:K,">="&($Q$2-7), 'Unit-Level Data'!K:K,"<="&$Q$2, 'Unit-Level Data'!G:G,1, 'Unit-Level Data'!B:B,B6),"") | N7: =COUNTIFS('Unit-Level Data'!B:B, B6, 'Unit-Level Data'!G:G, 1, 'Unit-Level Data'!L:L, "") -> 0 | O7: =N7-(N7-K7+F7) -> 0 | P7: =IFERROR(AVERAGEIFS('Unit-Level Data'!O:O,'Unit-Level Data'!B:B, B6, 'Unit-Level Data'!G:G, 1, 'Unit-Level Data'!L:L, ""),"") | Q7: =IFERROR(N7/SUMIFS('Unit Mix'!G:G,'Unit Mix'!D:D,1,'Unit Mix'!B:B,B6),"")
B8: =IF(OFFSET('Rent Comparison'!$A$1,2,2)="{{subject.management_company}}","",OFFSET('Rent Comparison'!$A$1,2,2)) | E8: 2 BR | F8: =COUNTIFS('Unit-Level Data'!L:L, ">=" & ($Q$2 - 7), 'Unit-Level Data'!L:L, "<" & $Q$2, 'Unit-Level Data'!G:G, 2, 'Unit-Level Data'!B:B, B6) -> 0 | G8: =COUNTIFS('Unit-Level Data'!L:L, ">=" & ($Q$2 - 7), 'Unit-Level Data'!L:L, "<" & $Q$2, 'Unit-Level Data'!G:G, 2, 'Unit-Level Data'!B:B, B6) - COUNTIFS('Unit-Level Data'!L:L, ">=" & ($Q$2 - 14), 'Unit-Level Data'!L:L, "<=" & ($Q$2 - 7), 'Unit-Level Data'!G:G, 2, 'Unit-Level Data'!B:B, B6) -> 0 | H8: =IFERROR(AVERAGEIFS('Unit-Level Data'!O:O,'Unit-Level Data'!L:L, ">=" & ($Q$2 - 7), 'Unit-Level Data'!L:L, "<" & $Q$2, 'Unit-Level Data'!G:G, 2, 'Unit-Level Data'!B:B, B6),"") | I8: =IFERROR( AVERAGEIFS('Unit-Level Data'!O:O, 'Unit-Level Data'!L:L, ">=" & ($Q$2 - 7), 'Unit-Level Data'!L:L, "<" & $Q$2, 'Unit-Level Data'!G:G, 2, 'Unit-Level Data'!B:B, B6) - AVERAGEIFS('Unit-Level Data'!O:O, 'Unit-Level Data'!L:L, ">=" & ($Q$2 - 14), 'Unit-Level Data'!L:L, "<=" & ($Q$2 - 7), 'Unit-Level Data'!G:G, 2, 'Unit-Level Data'!B:B, B6), 0) -> 0 | J8: =IFERROR(I8/AVERAGEIFS('Unit-Level Data'!O:O, 'Unit-Level Data'!L:L, ">=" & ($Q$2 - 14), 'Unit-Level Data'!L:L, "<=" & ($Q$2 - 7), 'Unit-Level Data'!G:G, 2, 'Unit-Level Data'!B:B, B6),0) -> 0 | K8: =COUNTIFS('Unit-Level Data'!K:K, ">=" & ($Q$2 - 7), 'Unit-Level Data'!K:K, "<" & $Q$2, 'Unit-Level Data'!G:G, 2, 'Unit-Level Data'!B:B, B6) -> 0 | L8: =COUNTIFS( 'Unit-Level Data'!K:K, ">=" & ($Q$2 - 7), 'Unit-Level Data'!K:K, "<" & $Q$2, 'Unit-Level Data'!G:G, 2, 'Unit-Level Data'!B:B, B6 ) - COUNTIFS( 'Unit-Level Data'!K:K, ">=" & ($Q$2 - 14), 'Unit-Level Data'!K:K, "<=" & ($Q$2 - 7), 'Unit-Level Data'!G:G, 2, 'Unit-Level Data'!B:B, B6 ) -> 0 | M8: =IFERROR(AVERAGEIFS('Unit-Level Data'!O:O,'Unit-Level Data'!K:K,">="&($Q$2-7), 'Unit-Level Data'!K:K,"<="&$Q$2, 'Unit-Level Data'!G:G,2, 'Unit-Level Data'!B:B,B6),"") | N8: =COUNTIFS('Unit-Level Data'!B:B, B6, 'Unit-Level Data'!G:G, 2, 'Unit-Level Data'!L:L, "") -> 0 | O8: =N8-(N8-K8+F8) -> 0 | P8: =IFERROR(AVERAGEIFS('Unit-Level Data'!O:O,'Unit-Level Data'!B:B, B6, 'Unit-Level Data'!G:G, 2, 'Unit-Level Data'!L:L, ""),"") | Q8: =IFERROR(N8/SUMIFS('Unit Mix'!G:G,'Unit Mix'!D:D,2,'Unit Mix'!B:B,B6),"")
B9: =IF(OFFSET('Rent Comparison'!$A$1,3,2)="{{subject.property_website}}","",OFFSET('Rent Comparison'!$A$1,3,2)) | E9: 3 BR | F9: =COUNTIFS('Unit-Level Data'!L:L, ">=" & ($Q$2 - 7), 'Unit-Level Data'!L:L, "<" & $Q$2, 'Unit-Level Data'!G:G, 3, 'Unit-Level Data'!B:B, B6) -> 0 | G9: =COUNTIFS('Unit-Level Data'!L:L, ">=" & ($Q$2 - 7), 'Unit-Level Data'!L:L, "<" & $Q$2, 'Unit-Level Data'!G:G, 3, 'Unit-Level Data'!B:B, B6) - COUNTIFS('Unit-Level Data'!L:L, ">=" & ($Q$2 - 14), 'Unit-Level Data'!L:L, "<=" & ($Q$2 - 7), 'Unit-Level Data'!G:G, 3, 'Unit-Level Data'!B:B, B6) -> 0 | H9: =IFERROR(AVERAGEIFS('Unit-Level Data'!O:O,'Unit-Level Data'!L:L, ">=" & ($Q$2 - 7), 'Unit-Level Data'!L:L, "<" & $Q$2, 'Unit-Level Data'!G:G, 3, 'Unit-Level Data'!B:B, B6),"") | I9: =IFERROR( AVERAGEIFS('Unit-Level Data'!O:O, 'Unit-Level Data'!L:L, ">=" & ($Q$2 - 7), 'Unit-Level Data'!L:L, "<" & $Q$2, 'Unit-Level Data'!G:G, 3, 'Unit-Level Data'!B:B, B6) - AVERAGEIFS('Unit-Level Data'!O:O, 'Unit-Level Data'!L:L, ">=" & ($Q$2 - 14), 'Unit-Level Data'!L:L, "<=" & ($Q$2 - 7), 'Unit-Level Data'!G:G, 3, 'Unit-Level Data'!B:B, B6), 0) -> 0 | J9: =IFERROR(I9/AVERAGEIFS('Unit-Level Data'!O:O, 'Unit-Level Data'!L:L, ">=" & ($Q$2 - 14), 'Unit-Level Data'!L:L, "<=" & ($Q$2 - 7), 'Unit-Level Data'!G:G, 3, 'Unit-Level Data'!B:B, B6),0) -> 0 | K9: =COUNTIFS('Unit-Level Data'!K:K, ">=" & ($Q$2 - 7), 'Unit-Level Data'!K:K, "<" & $Q$2, 'Unit-Level Data'!G:G, 3, 'Unit-Level Data'!B:B, B6) -> 0 | L9: =COUNTIFS( 'Unit-Level Data'!K:K, ">=" & ($Q$2 - 7), 'Unit-Level Data'!K:K, "<" & $Q$2, 'Unit-Level Data'!G:G, 3, 'Unit-Level Data'!B:B, B6 ) - COUNTIFS( 'Unit-Level Data'!K:K, ">=" & ($Q$2 - 14), 'Unit-Level Data'!K:K, "<=" & ($Q$2 - 7), 'Unit-Level Data'!G:G, 3, 'Unit-Level Data'!B:B, B6 ) -> 0 | M9: =IFERROR(AVERAGEIFS('Unit-Level Data'!O:O,'Unit-Level Data'!K:K,">="&($Q$2-7), 'Unit-Level Data'!K:K,"<="&$Q$2, 'Unit-Level Data'!G:G,3, 'Unit-Level Data'!B:B,B6),"") | N9: =COUNTIFS('Unit-Level Data'!B:B, B6, 'Unit-Level Data'!G:G, 3, 'Unit-Level Data'!L:L, "") -> 0 | O9: =N9-(N9-K9+F9) -> 0 | P9: =IFERROR(AVERAGEIFS('Unit-Level Data'!O:O,'Unit-Level Data'!B:B, B6, 'Unit-Level Data'!G:G, 3, 'Unit-Level Data'!L:L, ""),"") | Q9: =IFERROR(N9/SUMIFS('Unit Mix'!G:G,'Unit Mix'!D:D,3,'Unit Mix'!B:B,B6),"")
B10: =IF(OFFSET('Rent Comparison'!$A$1,1,6)="{{h:comparables.#.building_name}}","",OFFSET('Rent Comparison'!$A$1,1,6)) | C10: =IF(ISBLANK(B10),"",IFERROR(INDEX(Specials!B:J,MATCH(B10&" - Active",Specials!I:I,0),2),"")) | E10: Studio | F10: =COUNTIFS('Unit-Level Data'!L:L, ">=" & ($Q$2 - 7), 'Unit-Level Data'!L:L, "<" & $Q$2, 'Unit-Level Data'!G:G, 0, 'Unit-Level Data'!B:B, B10) -> 0 | G10: =COUNTIFS('Unit-Level Data'!L:L, ">=" & ($Q$2 - 7), 'Unit-Level Data'!L:L, "<" & $Q$2, 'Unit-Level Data'!G:G, 0, 'Unit-Level Data'!B:B, B10) - COUNTIFS('Unit-Level Data'!L:L, ">=" & ($Q$2 - 14), 'Unit-Level Data'!L:L, "<=" & ($Q$2 - 7), 'Unit-Level Data'!G:G, 0, 'Unit-Level Data'!B:B, B10) -> 0 | H10: =IFERROR(AVERAGEIFS('Unit-Level Data'!O:O,'Unit-Level Data'!L:L, ">=" & ($Q$2 - 7), 'Unit-Level Data'!L:L, "<" & $Q$2, 'Unit-Level Data'!G:G, 0, 'Unit-Level Data'!B:B, B10),"") | I10: =IFERROR( AVERAGEIFS('Unit-Level Data'!O:O, 'Unit-Level Data'!L:L, ">=" & ($Q$2 - 7), 'Unit-Level Data'!L:L, "<" & $Q$2, 'Unit-Level Data'!G:G, 0, 'Unit-Level Data'!B:B, B10) - AVERAGEIFS('Unit-Level Data'!O:O, 'Unit-Level Data'!L:L, ">=" & ($Q$2 - 14), 'Unit-Level Data'!L:L, "<=" & ($Q$2 - 7), 'Unit-Level Data'!G:G, 0, 'Unit-Level Data'!B:B, B10), 0) -> 0 | J10: =IFERROR(I10/AVERAGEIFS('Unit-Level Data'!O:O, 'Unit-Level Data'!L:L, ">=" & ($Q$2 - 14), 'Unit-Level Data'!L:L, "<=" & ($Q$2 - 7), 'Unit-Level Data'!G:G, 0, 'Unit-Level Data'!B:B, B10),0) -> 0 | K10: =COUNTIFS('Unit-Level Data'!K:K, ">=" & ($Q$2 - 7), 'Unit-Level Data'!K:K, "<" & $Q$2, 'Unit-Level Data'!G:G, 0, 'Unit-Level Data'!B:B, B10) -> 0 | L10: =COUNTIFS( 'Unit-Level Data'!K:K, ">=" & ($Q$2 - 7), 'Unit-Level Data'!K:K, "<" & $Q$2, 'Unit-Level Data'!G:G, 0, 'Unit-Level Data'!B:B, B10 ) - COUNTIFS( 'Unit-Level Data'!K:K, ">=" & ($Q$2 - 14), 'Unit-Level Data'!K:K, "<=" & ($Q$2 - 7), 'Unit-Level Data'!G:G, 0, 'Unit-Level Data'!B:B, B10 ) -> 0 | M10: =IFERROR(AVERAGEIFS('Unit-Level Data'!O:O,'Unit-Level Data'!K:K,">="&($Q$2-7), 'Unit-Level Data'!K:K,"<="&$Q$2, 'Unit-Level Data'!G:G,0, 'Unit-Level Data'!B:B,B10),"") | N10: =COUNTIFS('Unit-Level Data'!B:B, B10, 'Unit-Level Data'!G:G, 0, 'Unit-Level Data'!L:L, "") -> 0 | O10: =N10-(N10-K10+F10) -> 0 | P10: =IFERROR(AVERAGEIFS('Unit-Level Data'!O:O,'Unit-Level Data'!B:B, B10, 'Unit-Level Data'!G:G, 0, 'Unit-Level Data'!L:L, ""),"") | Q10: =IFERROR(N10/SUMIFS('Unit Mix'!G:G,'Unit Mix'!D:D,0,'Unit Mix'!B:B,B10),"")
B11: =IF(OFFSET('Rent Comps'!$A$1,4,2)="{{v:comparables.#.full_address}}","",OFFSET('Rent Comps'!$A$1,4,2)) | E11: 1 BR | F11: =COUNTIFS('Unit-Level Data'!L:L, ">=" & ($Q$2 - 7), 'Unit-Level Data'!L:L, "<" & $Q$2, 'Unit-Level Data'!G:G, 1, 'Unit-Level Data'!B:B, B10) -> 0 | G11: =COUNTIFS('Unit-Level Data'!L:L, ">=" & ($Q$2 - 7), 'Unit-Level Data'!L:L, "<" & $Q$2, 'Unit-Level Data'!G:G, 1, 'Unit-Level Data'!B:B, B10) - COUNTIFS('Unit-Level Data'!L:L, ">=" & ($Q$2 - 14), 'Unit-Level Data'!L:L, "<=" & ($Q$2 - 7), 'Unit-Level Data'!G:G, 1, 'Unit-Level Data'!B:B, B10) -> 0 | H11: =IFERROR(AVERAGEIFS('Unit-Level Data'!O:O,'Unit-Level Data'!L:L, ">=" & ($Q$2 - 7), 'Unit-Level Data'!L:L, "<" & $Q$2, 'Unit-Level Data'!G:G, 1, 'Unit-Level Data'!B:B, B10),"") | I11: =IFERROR( AVERAGEIFS('Unit-Level Data'!O:O, 'Unit-Level Data'!L:L, ">=" & ($Q$2 - 7), 'Unit-Level Data'!L:L, "<" & $Q$2, 'Unit-Level Data'!G:G, 1, 'Unit-Level Data'!B:B, B10) - AVERAGEIFS('Unit-Level Data'!O:O, 'Unit-Level Data'!L:L, ">=" & ($Q$2 - 14), 'Unit-Level Data'!L:L, "<=" & ($Q$2 - 7), 'Unit-Level Data'!G:G, 1, 'Unit-Level Data'!B:B, B10), 0) -> 0 | J11: =IFERROR(I11/AVERAGEIFS('Unit-Level Data'!O:O, 'Unit-Level Data'!L:L, ">=" & ($Q$2 - 14), 'Unit-Level Data'!L:L, "<=" & ($Q$2 - 7), 'Unit-Level Data'!G:G, 1, 'Unit-Level Data'!B:B, B10),0) -> 0 | K11: =COUNTIFS('Unit-Level Data'!K:K, ">=" & ($Q$2 - 7), 'Unit-Level Data'!K:K, "<" & $Q$2, 'Unit-Level Data'!G:G, 1, 'Unit-Level Data'!B:B, B10) -> 0 | L11: =COUNTIFS( 'Unit-Level Data'!K:K, ">=" & ($Q$2 - 7), 'Unit-Level Data'!K:K, "<" & $Q$2, 'Unit-Level Data'!G:G, 1, 'Unit-Level Data'!B:B, B10 ) - COUNTIFS( 'Unit-Level Data'!K:K, ">=" & ($Q$2 - 14), 'Unit-Level Data'!K:K, "<=" & ($Q$2 - 7), 'Unit-Level Data'!G:G, 1, 'Unit-Level Data'!B:B, B10 ) -> 0 | M11: =IFERROR(AVERAGEIFS('Unit-Level Data'!O:O,'Unit-Level Data'!K:K,">="&($Q$2-7), 'Unit-Level Data'!K:K,"<="&$Q$2, 'Unit-Level Data'!G:G,1, 'Unit-Level Data'!B:B,B10),"") | N11: =COUNTIFS('Unit-Level Data'!B:B, B10, 'Unit-Level Data'!G:G, 1, 'Unit-Level Data'!L:L, "") -> 0 | O11: =N11-(N11-K11+F11) -> 0 | P11: =IFERROR(AVERAGEIFS('Unit-Level Data'!O:O,'Unit-Level Data'!B:B, B10, 'Unit-Level Data'!G:G, 1, 'Unit-Level Data'!L:L, ""),"") | Q11: =IFERROR(N11/SUMIFS('Unit Mix'!G:G,'Unit Mix'!D:D,1,'Unit Mix'!B:B,B10),"")
B12: =IF(OFFSET('Rent Comparison'!$A$1,2,6)="{{h:comparables.#.management_company}}","",OFFSET('Rent Comparison'!$A$1,2,6)) | E12: 2 BR | F12: =COUNTIFS('Unit-Level Data'!L:L, ">=" & ($Q$2 - 7), 'Unit-Level Data'!L:L, "<" & $Q$2, 'Unit-Level Data'!G:G, 2, 'Unit-Level Data'!B:B, B10) -> 0 | G12: =COUNTIFS('Unit-Level Data'!L:L, ">=" & ($Q$2 - 7), 'Unit-Level Data'!L:L, "<" & $Q$2, 'Unit-Level Data'!G:G, 2, 'Unit-Level Data'!B:B, B10) - COUNTIFS('Unit-Level Data'!L:L, ">=" & ($Q$2 - 14), 'Unit-Level Data'!L:L, "<=" & ($Q$2 - 7), 'Unit-Level Data'!G:G, 2, 'Unit-Level Data'!B:B, B10) -> 0 | H12: =IFERROR(AVERAGEIFS('Unit-Level Data'!O:O,'Unit-Level Data'!L:L, ">=" & ($Q$2 - 7), 'Unit-Level Data'!L:L, "<" & $Q$2, 'Unit-Level Data'!G:G, 2, 'Unit-Level Data'!B:B, B10),"") | I12: =IFERROR( AVERAGEIFS('Unit-Level Data'!O:O, 'Unit-Level Data'!L:L, ">=" & ($Q$2 - 7), 'Unit-Level Data'!L:L, "<" & $Q$2, 'Unit-Level Data'!G:G, 2, 'Unit-Level Data'!B:B, B10) - AVERAGEIFS('Unit-Level Data'!O:O, 'Unit-Level Data'!L:L, ">=" & ($Q$2 - 14), 'Unit-Level Data'!L:L, "<=" & ($Q$2 - 7), 'Unit-Level Data'!G:G, 2, 'Unit-Level Data'!B:B, B10), 0) -> 0 | J12: =IFERROR(I12/AVERAGEIFS('Unit-Level Data'!O:O, 'Unit-Level Data'!L:L, ">=" & ($Q$2 - 14), 'Unit-Level Data'!L:L, "<=" & ($Q$2 - 7), 'Unit-Level Data'!G:G, 2, 'Unit-Level Data'!B:B, B10),0) -> 0 | K12: =COUNTIFS('Unit-Level Data'!K:K, ">=" & ($Q$2 - 7), 'Unit-Level Data'!K:K, "<" & $Q$2, 'Unit-Level Data'!G:G, 2, 'Unit-Level Data'!B:B, B10) -> 0 | L12: =COUNTIFS( 'Unit-Level Data'!K:K, ">=" & ($Q$2 - 7), 'Unit-Level Data'!K:K, "<" & $Q$2, 'Unit-Level Data'!G:G, 2, 'Unit-Level Data'!B:B, B10 ) - COUNTIFS( 'Unit-Level Data'!K:K, ">=" & ($Q$2 - 14), 'Unit-Level Data'!K:K, "<=" & ($Q$2 - 7), 'Unit-Level Data'!G:G, 2, 'Unit-Level Data'!B:B, B10 ) -> 0 | M12: =IFERROR(AVERAGEIFS('Unit-Level Data'!O:O,'Unit-Level Data'!K:K,">="&($Q$2-7), 'Unit-Level Data'!K:K,"<="&$Q$2, 'Unit-Level Data'!G:G,2, 'Unit-Level Data'!B:B,B10),"") | N12: =COUNTIFS('Unit-Level Data'!B:B, B10, 'Unit-Level Data'!G:G, 2, 'Unit-Level Data'!L:L, "") -> 0 | O12: =N12-(N12-K12+F12) -> 0 | P12: =IFERROR(AVERAGEIFS('Unit-Level Data'!O:O,'Unit-Level Data'!B:B, B10, 'Unit-Level Data'!G:G, 2, 'Unit-Level Data'!L:L, ""),"") | Q12: =IFERROR(N12/SUMIFS('Unit Mix'!G:G,'Unit Mix'!D:D,2,'Unit Mix'!B:B,B10),"")
B13: =IF(OFFSET('Rent Comparison'!$A$1,3,6)="{{h:comparables.#.property_website}}","",OFFSET('Rent Comparison'!$A$1,3,6)) | E13: 3 BR | F13: =COUNTIFS('Unit-Level Data'!L:L, ">=" & ($Q$2 - 7), 'Unit-Level Data'!L:L, "<" & $Q$2, 'Unit-Level Data'!G:G, 3, 'Unit-Level Data'!B:B, B10) -> 0 | G13: =COUNTIFS('Unit-Level Data'!L:L, ">=" & ($Q$2 - 7), 'Unit-Level Data'!L:L, "<" & $Q$2, 'Unit-Level Data'!G:G, 3, 'Unit-Level Data'!B:B, B10) - COUNTIFS('Unit-Level Data'!L:L, ">=" & ($Q$2 - 14), 'Unit-Level Data'!L:L, "<=" & ($Q$2 - 7), 'Unit-Level Data'!G:G, 3, 'Unit-Level Data'!B:B, B10) -> 0 | H13: =IFERROR(AVERAGEIFS('Unit-Level Data'!O:O,'Unit-Level Data'!L:L, ">=" & ($Q$2 - 7), 'Unit-Level Data'!L:L, "<" & $Q$2, 'Unit-Level Data'!G:G, 3, 'Unit-Level Data'!B:B, B10),"") | I13: =IFERROR( AVERAGEIFS('Unit-Level Data'!O:O, 'Unit-Level Data'!L:L, ">=" & ($Q$2 - 7), 'Unit-Level Data'!L:L, "<" & $Q$2, 'Unit-Level Data'!G:G, 3, 'Unit-Level Data'!B:B, B10) - AVERAGEIFS('Unit-Level Data'!O:O, 'Unit-Level Data'!L:L, ">=" & ($Q$2 - 14), 'Unit-Level Data'!L:L, "<=" & ($Q$2 - 7), 'Unit-Level Data'!G:G, 3, 'Unit-Level Data'!B:B, B10), 0) -> 0 | J13: =IFERROR(I13/AVERAGEIFS('Unit-Level Data'!O:O, 'Unit-Level Data'!L:L, ">=" & ($Q$2 - 14), 'Unit-Level Data'!L:L, "<=" & ($Q$2 - 7), 'Unit-Level Data'!G:G, 3, 'Unit-Level Data'!B:B, B10),0) -> 0 | K13: =COUNTIFS('Unit-Level Data'!K:K, ">=" & ($Q$2 - 7), 'Unit-Level Data'!K:K, "<" & $Q$2, 'Unit-Level Data'!G:G, 3, 'Unit-Level Data'!B:B, B10) -> 0 | L13: =COUNTIFS( 'Unit-Level Data'!K:K, ">=" & ($Q$2 - 7), 'Unit-Level Data'!K:K, "<" & $Q$2, 'Unit-Level Data'!G:G, 3, 'Unit-Level Data'!B:B, B10 ) - COUNTIFS( 'Unit-Level Data'!K:K, ">=" & ($Q$2 - 14), 'Unit-Level Data'!K:K, "<=" & ($Q$2 - 7), 'Unit-Level Data'!G:G, 3, 'Unit-Level Data'!B:B, B10 ) -> 0 | M13: =IFERROR(AVERAGEIFS('Unit-Level Data'!O:O,'Unit-Level Data'!K:K,">="&($Q$2-7), 'Unit-Level Data'!K:K,"<="&$Q$2, 'Unit-Level Data'!G:G,3, 'Unit-Level Data'!B:B,B10),"") | N13: =COUNTIFS('Unit-Level Data'!B:B, B10, 'Unit-Level Data'!G:G, 3, 'Unit-Level Data'!L:L, "") -> 0 | O13: =N13-(N13-K13+F13) -> 0 | P13: =IFERROR(AVERAGEIFS('Unit-Level Data'!O:O,'Unit-Level Data'!B:B, B10, 'Unit-Level Data'!G:G, 3, 'Unit-Level Data'!L:L, ""),"") | Q13: =IFERROR(N13/SUMIFS('Unit Mix'!G:G,'Unit Mix'!D:D,3,'Unit Mix'!B:B,B10),"")
B14: =IF(ISBLANK(OFFSET('Rent Comparison'!$A$1,1,7)),"",OFFSET('Rent Comparison'!$A$1,1,7)) | C14: =IF(ISBLANK(B14),"",IFERROR(INDEX(Specials!B:J,MATCH(B14&" - Active",Specials!I:I,0),2),"")) | E14: Studio | F14: =COUNTIFS('Unit-Level Data'!L:L, ">=" & ($Q$2 - 7), 'Unit-Level Data'!L:L, "<" & $Q$2, 'Unit-Level Data'!G:G, 0, 'Unit-Level Data'!B:B, B14) -> 0 | G14: =COUNTIFS('Unit-Level Data'!L:L, ">=" & ($Q$2 - 7), 'Unit-Level Data'!L:L, "<" & $Q$2, 'Unit-Level Data'!G:G, 0, 'Unit-Level Data'!B:B, B14) - COUNTIFS('Unit-Level Data'!L:L, ">=" & ($Q$2 - 14), 'Unit-Level Data'!L:L, "<=" & ($Q$2 - 7), 'Unit-Level Data'!G:G, 0, 'Unit-Level Data'!B:B, B14) -> 0 | H14: =IFERROR(AVERAGEIFS('Unit-Level Data'!O:O,'Unit-Level Data'!L:L, ">=" & ($Q$2 - 7), 'Unit-Level Data'!L:L, "<" & $Q$2, 'Unit-Level Data'!G:G, 0, 'Unit-Level Data'!B:B, B14),"") | I14: =IFERROR( AVERAGEIFS('Unit-Level Data'!O:O, 'Unit-Level Data'!L:L, ">=" & ($Q$2 - 7), 'Unit-Level Data'!L:L, "<" & $Q$2, 'Unit-Level Data'!G:G, 0, 'Unit-Level Data'!B:B, B14) - AVERAGEIFS('Unit-Level Data'!O:O, 'Unit-Level Data'!L:L, ">=" & ($Q$2 - 14), 'Unit-Level Data'!L:L, "<=" & ($Q$2 - 7), 'Unit-Level Data'!G:G, 0, 'Unit-Level Data'!B:B, B14), 0) -> 0 | J14: =IFERROR(I14/AVERAGEIFS('Unit-Level Data'!O:O, 'Unit-Level Data'!L:L, ">=" & ($Q$2 - 14), 'Unit-Level Data'!L:L, "<=" & ($Q$2 - 7), 'Unit-Level Data'!G:G, 0, 'Unit-Level Data'!B:B, B14),0) -> 0 | K14: =COUNTIFS('Unit-Level Data'!K:K, ">=" & ($Q$2 - 7), 'Unit-Level Data'!K:K, "<" & $Q$2, 'Unit-Level Data'!G:G, 0, 'Unit-Level Data'!B:B, B14) -> 0 | L14: =COUNTIFS( 'Unit-Level Data'!K:K, ">=" & ($Q$2 - 7), 'Unit-Level Data'!K:K, "<" & $Q$2, 'Unit-Level Data'!G:G, 0, 'Unit-Level Data'!B:B, B14 ) - COUNTIFS( 'Unit-Level Data'!K:K, ">=" & ($Q$2 - 14), 'Unit-Level Data'!K:K, "<=" & ($Q$2 - 7), 'Unit-Level Data'!G:G, 0, 'Unit-Level Data'!B:B, B14 ) -> 0 | M14: =IFERROR(AVERAGEIFS('Unit-Level Data'!O:O,'Unit-Level Data'!K:K,">="&($Q$2-7), 'Unit-Level Data'!K:K,"<="&$Q$2, 'Unit-Level Data'!G:G,0, 'Unit-Level Data'!B:B,B14),"") | N14: =COUNTIFS('Unit-Level Data'!B:B, B14, 'Unit-Level Data'!G:G, 0, 'Unit-Level Data'!L:L, "") -> 0 | O14: =N14-(N14-K14+F14) -> 0 | P14: =IFERROR(AVERAGEIFS('Unit-Level Data'!O:O,'Unit-Level Data'!B:B, B14, 'Unit-Level Data'!G:G, 0, 'Unit-Level Data'!L:L, ""),"") | Q14: =IFERROR(N14/SUMIFS('Unit Mix'!G:G,'Unit Mix'!D:D,0,'Unit Mix'!B:B,B14),"")
B15: =IF(ISBLANK(OFFSET('Rent Comps'!$A$1,5,2)),"",OFFSET('Rent Comps'!$A$1,5,2)) | E15: 1 BR | F15: =COUNTIFS('Unit-Level Data'!L:L, ">=" & ($Q$2 - 7), 'Unit-Level Data'!L:L, "<" & $Q$2, 'Unit-Level Data'!G:G, 1, 'Unit-Level Data'!B:B, B14) -> 0 | G15: =COUNTIFS('Unit-Level Data'!L:L, ">=" & ($Q$2 - 7), 'Unit-Level Data'!L:L, "<" & $Q$2, 'Unit-Level Data'!G:G, 1, 'Unit-Level Data'!B:B, B14) - COUNTIFS('Unit-Level Data'!L:L, ">=" & ($Q$2 - 14), 'Unit-Level Data'!L:L, "<=" & ($Q$2 - 7), 'Unit-Level Data'!G:G, 1, 'Unit-Level Data'!B:B, B14) -> 0 | H15: =IFERROR(AVERAGEIFS('Unit-Level Data'!O:O,'Unit-Level Data'!L:L, ">=" & ($Q$2 - 7), 'Unit-Level Data'!L:L, "<" & $Q$2, 'Unit-Level Data'!G:G, 1, 'Unit-Level Data'!B:B, B14),"") | I15: =IFERROR( AVERAGEIFS('Unit-Level Data'!O:O, 'Unit-Level Data'!L:L, ">=" & ($Q$2 - 7), 'Unit-Level Data'!L:L, "<" & $Q$2, 'Unit-Level Data'!G:G, 1, 'Unit-Level Data'!B:B, B14) - AVERAGEIFS('Unit-Level Data'!O:O, 'Unit-Level Data'!L:L, ">=" & ($Q$2 - 14), 'Unit-Level Data'!L:L, "<=" & ($Q$2 - 7), 'Unit-Level Data'!G:G, 1, 'Unit-Level Data'!B:B, B14), 0) -> 0 | J15: =IFERROR(I15/AVERAGEIFS('Unit-Level Data'!O:O, 'Unit-Level Data'!L:L, ">=" & ($Q$2 - 14), 'Unit-Level Data'!L:L, "<=" & ($Q$2 - 7), 'Unit-Level Data'!G:G, 1, 'Unit-Level Data'!B:B, B14),0) -> 0 | K15: =COUNTIFS('Unit-Level Data'!K:K, ">=" & ($Q$2 - 7), 'Unit-Level Data'!K:K, "<" & $Q$2, 'Unit-Level Data'!G:G, 1, 'Unit-Level Data'!B:B, B14) -> 0 | L15: =COUNTIFS( 'Unit-Level Data'!K:K, ">=" & ($Q$2 - 7), 'Unit-Level Data'!K:K, "<" & $Q$2, 'Unit-Level Data'!G:G, 1, 'Unit-Level Data'!B:B, B14 ) - COUNTIFS( 'Unit-Level Data'!K:K, ">=" & ($Q$2 - 14), 'Unit-Level Data'!K:K, "<=" & ($Q$2 - 7), 'Unit-Level Data'!G:G, 1, 'Unit-Level Data'!B:B, B14 ) -> 0 | M15: =IFERROR(AVERAGEIFS('Unit-Level Data'!O:O,'Unit-Level Data'!K:K,">="&($Q$2-7), 'Unit-Level Data'!K:K,"<="&$Q$2, 'Unit-Level Data'!G:G,1, 'Unit-Level Data'!B:B,B14),"") | N15: =COUNTIFS('Unit-Level Data'!B:B, B14, 'Unit-Level Data'!G:G, 1, 'Unit-Level Data'!L:L, "") -> 0 | O15: =N15-(N15-K15+F15) -> 0 | P15: =IFERROR(AVERAGEIFS('Unit-Level Data'!O:O,'Unit-Level Data'!B:B, B14, 'Unit-Level Data'!G:G, 1, 'Unit-Level Data'!L:L, ""),"") | Q15: =IFERROR(N15/SUMIFS('Unit Mix'!G:G,'Unit Mix'!D:D,1,'Unit Mix'!B:B,B14),"")
B16: =IF(ISBLANK(OFFSET('Rent Comparison'!$A$1,2,7)),"",OFFSET('Rent Comparison'!$A$1,2,7)) | E16: 2 BR | F16: =COUNTIFS('Unit-Level Data'!L:L, ">=" & ($Q$2 - 7), 'Unit-Level Data'!L:L, "<" & $Q$2, 'Unit-Level Data'!G:G, 2, 'Unit-Level Data'!B:B, B14) -> 0 | G16: =COUNTIFS('Unit-Level Data'!L:L, ">=" & ($Q$2 - 7), 'Unit-Level Data'!L:L, "<" & $Q$2, 'Unit-Level Data'!G:G, 2, 'Unit-Level Data'!B:B, B14) - COUNTIFS('Unit-Level Data'!L:L, ">=" & ($Q$2 - 14), 'Unit-Level Data'!L:L, "<=" & ($Q$2 - 7), 'Unit-Level Data'!G:G, 2, 'Unit-Level Data'!B:B, B14) -> 0 | H16: =IFERROR(AVERAGEIFS('Unit-Level Data'!O:O,'Unit-Level Data'!L:L, ">=" & ($Q$2 - 7), 'Unit-Level Data'!L:L, "<" & $Q$2, 'Unit-Level Data'!G:G, 2, 'Unit-Level Data'!B:B, B14),"") | I16: =IFERROR( AVERAGEIFS('Unit-Level Data'!O:O, 'Unit-Level Data'!L:L, ">=" & ($Q$2 - 7), 'Unit-Level Data'!L:L, "<" & $Q$2, 'Unit-Level Data'!G:G, 2, 'Unit-Level Data'!B:B, B14) - AVERAGEIFS('Unit-Level Data'!O:O, 'Unit-Level Data'!L:L, ">=" & ($Q$2 - 14), 'Unit-Level Data'!L:L, "<=" & ($Q$2 - 7), 'Unit-Level Data'!G:G, 2, 'Unit-Level Data'!B:B, B14), 0) -> 0 | J16: =IFERROR(I16/AVERAGEIFS('Unit-Level Data'!O:O, 'Unit-Level Data'!L:L, ">=" & ($Q$2 - 14), 'Unit-Level Data'!L:L, "<=" & ($Q$2 - 7), 'Unit-Level Data'!G:G, 2, 'Unit-Level Data'!B:B, B14),0) -> 0 | K16: =COUNTIFS('Unit-Level Data'!K:K, ">=" & ($Q$2 - 7), 'Unit-Level Data'!K:K, "<" & $Q$2, 'Unit-Level Data'!G:G, 2, 'Unit-Level Data'!B:B, B14) -> 0 | L16: =COUNTIFS( 'Unit-Level Data'!K:K, ">=" & ($Q$2 - 7), 'Unit-Level Data'!K:K, "<" & $Q$2, 'Unit-Level Data'!G:G, 2, 'Unit-Level Data'!B:B, B14 ) - COUNTIFS( 'Unit-Level Data'!K:K, ">=" & ($Q$2 - 14), 'Unit-Level Data'!K:K, "<=" & ($Q$2 - 7), 'Unit-Level Data'!G:G, 2, 'Unit-Level Data'!B:B, B14 ) -> 0 | M16: =IFERROR(AVERAGEIFS('Unit-Level Data'!O:O,'Unit-Level Data'!K:K,">="&($Q$2-7), 'Unit-Level Data'!K:K,"<="&$Q$2, 'Unit-Level Data'!G:G,2, 'Unit-Level Data'!B:B,B14),"") | N16: =COUNTIFS('Unit-Level Data'!B:B, B14, 'Unit-Level Data'!G:G, 2, 'Unit-Level Data'!L:L, "") -> 0 | O16: =N16-(N16-K16+F16) -> 0 | P16: =IFERROR(AVERAGEIFS('Unit-Level Data'!O:O,'Unit-Level Data'!B:B, B14, 'Unit-Level Data'!G:G, 2, 'Unit-Level Data'!L:L, ""),"") | Q16: =IFERROR(N16/SUMIFS('Unit Mix'!G:G,'Unit Mix'!D:D,2,'Unit Mix'!B:B,B14),"")
B17: =IF(ISBLANK(OFFSET('Rent Comparison'!$A$1,3,7)),"",OFFSET('Rent Comparison'!$A$1,3,7)) | E17: 3 BR | F17: =COUNTIFS('Unit-Level Data'!L:L, ">=" & ($Q$2 - 7), 'Unit-Level Data'!L:L, "<" & $Q$2, 'Unit-Level Data'!G:G, 3, 'Unit-Level Data'!B:B, B14) -> 0 | G17: =COUNTIFS('Unit-Level Data'!L:L, ">=" & ($Q$2 - 7), 'Unit-Level Data'!L:L, "<" & $Q$2, 'Unit-Level Data'!G:G, 3, 'Unit-Level Data'!B:B, B14) - COUNTIFS('Unit-Level Data'!L:L, ">=" & ($Q$2 - 14), 'Unit-Level Data'!L:L, "<=" & ($Q$2 - 7), 'Unit-Level Data'!G:G, 3, 'Unit-Level Data'!B:B, B14) -> 0 | H17: =IFERROR(AVERAGEIFS('Unit-Level Data'!O:O,'Unit-Level Data'!L:L, ">=" & ($Q$2 - 7), 'Unit-Level Data'!L:L, "<" & $Q$2, 'Unit-Level Data'!G:G, 3, 'Unit-Level Data'!B:B, B14),"") | I17: =IFERROR( AVERAGEIFS('Unit-Level Data'!O:O, 'Unit-Level Data'!L:L, ">=" & ($Q$2 - 7), 'Unit-Level Data'!L:L, "<" & $Q$2, 'Unit-Level Data'!G:G, 3, 'Unit-Level Data'!B:B, B14) - AVERAGEIFS('Unit-Level Data'!O:O, 'Unit-Level Data'!L:L, ">=" & ($Q$2 - 14), 'Unit-Level Data'!L:L, "<=" & ($Q$2 - 7), 'Unit-Level Data'!G:G, 3, 'Unit-Level Data'!B:B, B14), 0) -> 0 | J17: =IFERROR(I17/AVERAGEIFS('Unit-Level Data'!O:O, 'Unit-Level Data'!L:L, ">=" & ($Q$2 - 14), 'Unit-Level Data'!L:L, "<=" & ($Q$2 - 7), 'Unit-Level Data'!G:G, 3, 'Unit-Level Data'!B:B, B14),0) -> 0 | K17: =COUNTIFS('Unit-Level Data'!K:K, ">=" & ($Q$2 - 7), 'Unit-Level Data'!K:K, "<" & $Q$2, 'Unit-Level Data'!G:G, 3, 'Unit-Level Data'!B:B, B14) -> 0 | L17: =COUNTIFS( 'Unit-Level Data'!K:K, ">=" & ($Q$2 - 7), 'Unit-Level Data'!K:K, "<" & $Q$2, 'Unit-Level Data'!G:G, 3, 'Unit-Level Data'!B:B, B14 ) - COUNTIFS( 'Unit-Level Data'!K:K, ">=" & ($Q$2 - 14), 'Unit-Level Data'!K:K, "<=" & ($Q$2 - 7), 'Unit-Level Data'!G:G, 3, 'Unit-Level Data'!B:B, B14 ) -> 0 | M17: =IFERROR(AVERAGEIFS('Unit-Level Data'!O:O,'Unit-Level Data'!K:K,">="&($Q$2-7), 'Unit-Level Data'!K:K,"<="&$Q$2, 'Unit-Level Data'!G:G,3, 'Unit-Level Data'!B:B,B14),"") | N17: =COUNTIFS('Unit-Level Data'!B:B, B14, 'Unit-Level Data'!G:G, 3, 'Unit-Level Data'!L:L, "") -> 0 | O17: =N17-(N17-K17+F17) -> 0 | P17: =IFERROR(AVERAGEIFS('Unit-Level Data'!O:O,'Unit-Level Data'!B:B, B14, 'Unit-Level Data'!G:G, 3, 'Unit-Level Data'!L:L, ""),"") | Q17: =IFERROR(N17/SUMIFS('Unit Mix'!G:G,'Unit Mix'!D:D,3,'Unit Mix'!B:B,B14),"")
B18: =IF(ISBLANK(OFFSET('Rent Comparison'!$A$1,1,8)),"",OFFSET('Rent Comparison'!$A$1,1,8)) | C18: =IF(ISBLANK(B18),"",IFERROR(INDEX(Specials!B:J,MATCH(B18&" - Active",Specials!I:I,0),2),"")) | E18: Studio | F18: =COUNTIFS('Unit-Level Data'!L:L, ">=" & ($Q$2 - 7), 'Unit-Level Data'!L:L, "<" & $Q$2, 'Unit-Level Data'!G:G, 0, 'Unit-Level Data'!B:B, B18) -> 0 | G18: =COUNTIFS('Unit-Level Data'!L:L, ">=" & ($Q$2 - 7), 'Unit-Level Data'!L:L, "<" & $Q$2, 'Unit-Level Data'!G:G, 0, 'Unit-Level Data'!B:B, B18) - COUNTIFS('Unit-Level Data'!L:L, ">=" & ($Q$2 - 14), 'Unit-Level Data'!L:L, "<=" & ($Q$2 - 7), 'Unit-Level Data'!G:G, 0, 'Unit-Level Data'!B:B, B18) -> 0 | H18: =IFERROR(AVERAGEIFS('Unit-Level Data'!O:O,'Unit-Level Data'!L:L, ">=" & ($Q$2 - 7), 'Unit-Level Data'!L:L, "<" & $Q$2, 'Unit-Level Data'!G:G, 0, 'Unit-Level Data'!B:B, B18),"") | I18: =IFERROR( AVERAGEIFS('Unit-Level Data'!O:O, 'Unit-Level Data'!L:L, ">=" & ($Q$2 - 7), 'Unit-Level Data'!L:L, "<" & $Q$2, 'Unit-Level Data'!G:G, 0, 'Unit-Level Data'!B:B, B18) - AVERAGEIFS('Unit-Level Data'!O:O, 'Unit-Level Data'!L:L, ">=" & ($Q$2 - 14), 'Unit-Level Data'!L:L, "<=" & ($Q$2 - 7), 'Unit-Level Data'!G:G, 0, 'Unit-Level Data'!B:B, B18), 0) -> 0 | J18: =IFERROR(I18/AVERAGEIFS('Unit-Level Data'!O:O, 'Unit-Level Data'!L:L, ">=" & ($Q$2 - 14), 'Unit-Level Data'!L:L, "<=" & ($Q$2 - 7), 'Unit-Level Data'!G:G, 0, 'Unit-Level Data'!B:B, B18),0) -> 0 | K18: =COUNTIFS('Unit-Level Data'!K:K, ">=" & ($Q$2 - 7), 'Unit-Level Data'!K:K, "<" & $Q$2, 'Unit-Level Data'!G:G, 0, 'Unit-Level Data'!B:B, B18) -> 0 | L18: =COUNTIFS( 'Unit-Level Data'!K:K, ">=" & ($Q$2 - 7), 'Unit-Level Data'!K:K, "<" & $Q$2, 'Unit-Level Data'!G:G, 0, 'Unit-Level Data'!B:B, B18 ) - COUNTIFS( 'Unit-Level Data'!K:K, ">=" & ($Q$2 - 14), 'Unit-Level Data'!K:K, "<=" & ($Q$2 - 7), 'Unit-Level Data'!G:G, 0, 'Unit-Level Data'!B:B, B18 ) -> 0 | M18: =IFERROR(AVERAGEIFS('Unit-Level Data'!O:O,'Unit-Level Data'!K:K,">="&($Q$2-7), 'Unit-Level Data'!K:K,"<="&$Q$2, 'Unit-Level Data'!G:G,0, 'Unit-Level Data'!B:B,B18),"") | N18: =COUNTIFS('Unit-Level Data'!B:B, B18, 'Unit-Level Data'!G:G, 0, 'Unit-Level Data'!L:L, "") -> 0 | O18: =N18-(N18-K18+F18) -> 0 | P18: =IFERROR(AVERAGEIFS('Unit-Level Data'!O:O,'Unit-Level Data'!B:B, B18, 'Unit-Level Data'!G:G, 0, 'Unit-Level Data'!L:L, ""),"") | Q18: =IFERROR(N18/SUMIFS('Unit Mix'!G:G,'Unit Mix'!D:D,0,'Unit Mix'!B:B,B18),"")
B19: =IF(ISBLANK(OFFSET('Rent Comps'!$A$1,6,2)),"",OFFSET('Rent Comps'!$A$1,6,2)) | E19: 1 BR | F19: =COUNTIFS('Unit-Level Data'!L:L, ">=" & ($Q$2 - 7), 'Unit-Level Data'!L:L, "<" & $Q$2, 'Unit-Level Data'!G:G, 1, 'Unit-Level Data'!B:B, B18) -> 0 | G19: =COUNTIFS('Unit-Level Data'!L:L, ">=" & ($Q$2 - 7), 'Unit-Level Data'!L:L, "<" & $Q$2, 'Unit-Level Data'!G:G, 1, 'Unit-Level Data'!B:B, B18) - COUNTIFS('Unit-Level Data'!L:L, ">=" & ($Q$2 - 14), 'Unit-Level Data'!L:L, "<=" & ($Q$2 - 7), 'Unit-Level Data'!G:G, 1, 'Unit-Level Data'!B:B, B18) -> 0 | H19: =IFERROR(AVERAGEIFS('Unit-Level Data'!O:O,'Unit-Level Data'!L:L, ">=" & ($Q$2 - 7), 'Unit-Level Data'!L:L, "<" & $Q$2, 'Unit-Level Data'!G:G, 1, 'Unit-Level Data'!B:B, B18),"") | I19: =IFERROR( AVERAGEIFS('Unit-Level Data'!O:O, 'Unit-Level Data'!L:L, ">=" & ($Q$2 - 7), 'Unit-Level Data'!L:L, "<" & $Q$2, 'Unit-Level Data'!G:G, 1, 'Unit-Level Data'!B:B, B18) - AVERAGEIFS('Unit-Level Data'!O:O, 'Unit-Level Data'!L:L, ">=" & ($Q$2 - 14), 'Unit-Level Data'!L:L, "<=" & ($Q$2 - 7), 'Unit-Level Data'!G:G, 1, 'Unit-Level Data'!B:B, B18), 0) -> 0 | J19: =IFERROR(I19/AVERAGEIFS('Unit-Level Data'!O:O, 'Unit-Level Data'!L:L, ">=" & ($Q$2 - 14), 'Unit-Level Data'!L:L, "<=" & ($Q$2 - 7), 'Unit-Level Data'!G:G, 1, 'Unit-Level Data'!B:B, B18),0) -> 0 | K19: =COUNTIFS('Unit-Level Data'!K:K, ">=" & ($Q$2 - 7), 'Unit-Level Data'!K:K, "<" & $Q$2, 'Unit-Level Data'!G:G, 1, 'Unit-Level Data'!B:B, B18) -> 0 | L19: =COUNTIFS( 'Unit-Level Data'!K:K, ">=" & ($Q$2 - 7), 'Unit-Level Data'!K:K, "<" & $Q$2, 'Unit-Level Data'!G:G, 1, 'Unit-Level Data'!B:B, B18 ) - COUNTIFS( 'Unit-Level Data'!K:K, ">=" & ($Q$2 - 14), 'Unit-Level Data'!K:K, "<=" & ($Q$2 - 7), 'Unit-Level Data'!G:G, 1, 'Unit-Level Data'!B:B, B18 ) -> 0 | M19: =IFERROR(AVERAGEIFS('Unit-Level Data'!O:O,'Unit-Level Data'!K:K,">="&($Q$2-7), 'Unit-Level Data'!K:K,"<="&$Q$2, 'Unit-Level Data'!G:G,1, 'Unit-Level Data'!B:B,B18),"") | N19: =COUNTIFS('Unit-Level Data'!B:B, B18, 'Unit-Level Data'!G:G, 1, 'Unit-Level Data'!L:L, "") -> 0 | O19: =N19-(N19-K19+F19) -> 0 | P19: =IFERROR(AVERAGEIFS('Unit-Level Data'!O:O,'Unit-Level Data'!B:B, B18, 'Unit-Level Data'!G:G, 1, 'Unit-Level Data'!L:L, ""),"") | Q19: =IFERROR(N19/SUMIFS('Unit Mix'!G:G,'Unit Mix'!D:D,1,'Unit Mix'!B:B,B18),"")
B20: =IF(ISBLANK(OFFSET('Rent Comparison'!$A$1,2,8)),"",OFFSET('Rent Comparison'!$A$1,2,8)) | E20: 2 BR | F20: =COUNTIFS('Unit-Level Data'!L:L, ">=" & ($Q$2 - 7), 'Unit-Level Data'!L:L, "<" & $Q$2, 'Unit-Level Data'!G:G, 2, 'Unit-Level Data'!B:B, B18) -> 0 | G20: =COUNTIFS('Unit-Level Data'!L:L, ">=" & ($Q$2 - 7), 'Unit-Level Data'!L:L, "<" & $Q$2, 'Unit-Level Data'!G:G, 2, 'Unit-Level Data'!B:B, B18) - COUNTIFS('Unit-Level Data'!L:L, ">=" & ($Q$2 - 14), 'Unit-Level Data'!L:L, "<=" & ($Q$2 - 7), 'Unit-Level Data'!G:G, 2, 'Unit-Level Data'!B:B, B18) -> 0 | H20: =IFERROR(AVERAGEIFS('Unit-Level Data'!O:O,'Unit-Level Data'!L:L, ">=" & ($Q$2 - 7), 'Unit-Level Data'!L:L, "<" & $Q$2, 'Unit-Level Data'!G:G, 2, 'Unit-Level Data'!B:B, B18),"") | I20: =IFERROR( AVERAGEIFS('Unit-Level Data'!O:O, 'Unit-Level Data'!L:L, ">=" & ($Q$2 - 7), 'Unit-Level Data'!L:L, "<" & $Q$2, 'Unit-Level Data'!G:G, 2, 'Unit-Level Data'!B:B, B18) - AVERAGEIFS('Unit-Level Data'!O:O, 'Unit-Level Data'!L:L, ">=" & ($Q$2 - 14), 'Unit-Level Data'!L:L, "<=" & ($Q$2 - 7), 'Unit-Level Data'!G:G, 2, 'Unit-Level Data'!B:B, B18), 0) -> 0 | J20: =IFERROR(I20/AVERAGEIFS('Unit-Level Data'!O:O, 'Unit-Level Data'!L:L, ">=" & ($Q$2 - 14), 'Unit-Level Data'!L:L, "<=" & ($Q$2 - 7), 'Unit-Level Data'!G:G, 2, 'Unit-Level Data'!B:B, B18),0) -> 0 | K20: =COUNTIFS('Unit-Level Data'!K:K, ">=" & ($Q$2 - 7), 'Unit-Level Data'!K:K, "<" & $Q$2, 'Unit-Level Data'!G:G, 2, 'Unit-Level Data'!B:B, B18) -> 0 | L20: =COUNTIFS( 'Unit-Level Data'!K:K, ">=" & ($Q$2 - 7), 'Unit-Level Data'!K:K, "<" & $Q$2, 'Unit-Level Data'!G:G, 2, 'Unit-Level Data'!B:B, B18 ) - COUNTIFS( 'Unit-Level Data'!K:K, ">=" & ($Q$2 - 14), 'Unit-Level Data'!K:K, "<=" & ($Q$2 - 7), 'Unit-Level Data'!G:G, 2, 'Unit-Level Data'!B:B, B18 ) -> 0 | M20: =IFERROR(AVERAGEIFS('Unit-Level Data'!O:O,'Unit-Level Data'!K:K,">="&($Q$2-7), 'Unit-Level Data'!K:K,"<="&$Q$2, 'Unit-Level Data'!G:G,2, 'Unit-Level Data'!B:B,B18),"") | N20: =COUNTIFS('Unit-Level Data'!B:B, B18, 'Unit-Level Data'!G:G, 2, 'Unit-Level Data'!L:L, "") -> 0 | O20: =N20-(N20-K20+F20) -> 0 | P20: =IFERROR(AVERAGEIFS('Unit-Level Data'!O:O,'Unit-Level Data'!B:B, B18, 'Unit-Level Data'!G:G, 2, 'Unit-Level Data'!L:L, ""),"") | Q20: =IFERROR(N20/SUMIFS('Unit Mix'!G:G,'Unit Mix'!D:D,2,'Unit Mix'!B:B,B18),"")
B21: =IF(ISBLANK(OFFSET('Rent Comparison'!$A$1,3,8)),"",OFFSET('Rent Comparison'!$A$1,3,8)) | E21: 3 BR | F21: =COUNTIFS('Unit-Level Data'!L:L, ">=" & ($Q$2 - 7), 'Unit-Level Data'!L:L, "<" & $Q$2, 'Unit-Level Data'!G:G, 3, 'Unit-Level Data'!B:B, B18) -> 0 | G21: =COUNTIFS('Unit-Level Data'!L:L, ">=" & ($Q$2 - 7), 'Unit-Level Data'!L:L, "<" & $Q$2, 'Unit-Level Data'!G:G, 3, 'Unit-Level Data'!B:B, B18) - COUNTIFS('Unit-Level Data'!L:L, ">=" & ($Q$2 - 14), 'Unit-Level Data'!L:L, "<=" & ($Q$2 - 7), 'Unit-Level Data'!G:G, 3, 'Unit-Level Data'!B:B, B18) -> 0 | H21: =IFERROR(AVERAGEIFS('Unit-Level Data'!O:O,'Unit-Level Data'!L:L, ">=" & ($Q$2 - 7), 'Unit-Level Data'!L:L, "<" & $Q$2, 'Unit-Level Data'!G:G, 3, 'Unit-Level Data'!B:B, B18),"") | I21: =IFERROR( AVERAGEIFS('Unit-Level Data'!O:O, 'Unit-Level Data'!L:L, ">=" & ($Q$2 - 7), 'Unit-Level Data'!L:L, "<" & $Q$2, 'Unit-Level Data'!G:G, 3, 'Unit-Level Data'!B:B, B18) - AVERAGEIFS('Unit-Level Data'!O:O, 'Unit-Level Data'!L:L, ">=" & ($Q$2 - 14), 'Unit-Level Data'!L:L, "<=" & ($Q$2 - 7), 'Unit-Level Data'!G:G, 3, 'Unit-Level Data'!B:B, B18), 0) -> 0 | J21: =IFERROR(I21/AVERAGEIFS('Unit-Level Data'!O:O, 'Unit-Level Data'!L:L, ">=" & ($Q$2 - 14), 'Unit-Level Data'!L:L, "<=" & ($Q$2 - 7), 'Unit-Level Data'!G:G, 3, 'Unit-Level Data'!B:B, B18),0) -> 0 | K21: =COUNTIFS('Unit-Level Data'!K:K, ">=" & ($Q$2 - 7), 'Unit-Level Data'!K:K, "<" & $Q$2, 'Unit-Level Data'!G:G, 3, 'Unit-Level Data'!B:B, B18) -> 0 | L21: =COUNTIFS( 'Unit-Level Data'!K:K, ">=" & ($Q$2 - 7), 'Unit-Level Data'!K:K, "<" & $Q$2, 'Unit-Level Data'!G:G, 3, 'Unit-Level Data'!B:B, B18 ) - COUNTIFS( 'Unit-Level Data'!K:K, ">=" & ($Q$2 - 14), 'Unit-Level Data'!K:K, "<=" & ($Q$2 - 7), 'Unit-Level Data'!G:G, 3, 'Unit-Level Data'!B:B, B18 ) -> 0 | M21: =IFERROR(AVERAGEIFS('Unit-Level Data'!O:O,'Unit-Level Data'!K:K,">="&($Q$2-7), 'Unit-Level Data'!K:K,"<="&$Q$2, 'Unit-Level Data'!G:G,3, 'Unit-Level Data'!B:B,B18),"") | N21: =COUNTIFS('Unit-Level Data'!B:B, B18, 'Unit-Level Data'!G:G, 3, 'Unit-Level Data'!L:L, "") -> 0 | O21: =N21-(N21-K21+F21) -> 0 | P21: =IFERROR(AVERAGEIFS('Unit-Level Data'!O:O,'Unit-Level Data'!B:B, B18, 'Unit-Level Data'!G:G, 3, 'Unit-Level Data'!L:L, ""),"") | Q21: =IFERROR(N21/SUMIFS('Unit Mix'!G:G,'Unit Mix'!D:D,3,'Unit Mix'!B:B,B18),"")
B22: =IF(ISBLANK(OFFSET('Rent Comparison'!$A$1,1,9)),"",OFFSET('Rent Comparison'!$A$1,1,9)) | C22: =IF(ISBLANK(B22),"",IFERROR(INDEX(Specials!B:J,MATCH(B22&" - Active",Specials!I:I,0),2),"")) | E22: Studio | F22: =COUNTIFS('Unit-Level Data'!L:L, ">=" & ($Q$2 - 7), 'Unit-Level Data'!L:L, "<" & $Q$2, 'Unit-Level Data'!G:G, 0, 'Unit-Level Data'!B:B, B22) -> 0 | G22: =COUNTIFS('Unit-Level Data'!L:L, ">=" & ($Q$2 - 7), 'Unit-Level Data'!L:L, "<" & $Q$2, 'Unit-Level Data'!G:G, 0, 'Unit-Level Data'!B:B, B22) - COUNTIFS('Unit-Level Data'!L:L, ">=" & ($Q$2 - 14), 'Unit-Level Data'!L:L, "<=" & ($Q$2 - 7), 'Unit-Level Data'!G:G, 0, 'Unit-Level Data'!B:B, B22) -> 0 | H22: =IFERROR(AVERAGEIFS('Unit-Level Data'!O:O,'Unit-Level Data'!L:L, ">=" & ($Q$2 - 7), 'Unit-Level Data'!L:L, "<" & $Q$2, 'Unit-Level Data'!G:G, 0, 'Unit-Level Data'!B:B, B22),"") | I22: =IFERROR( AVERAGEIFS('Unit-Level Data'!O:O, 'Unit-Level Data'!L:L, ">=" & ($Q$2 - 7), 'Unit-Level Data'!L:L, "<" & $Q$2, 'Unit-Level Data'!G:G, 0, 'Unit-Level Data'!B:B, B22) - AVERAGEIFS('Unit-Level Data'!O:O, 'Unit-Level Data'!L:L, ">=" & ($Q$2 - 14), 'Unit-Level Data'!L:L, "<=" & ($Q$2 - 7), 'Unit-Level Data'!G:G, 0, 'Unit-Level Data'!B:B, B22), 0) -> 0 | J22: =IFERROR(I22/AVERAGEIFS('Unit-Level Data'!O:O, 'Unit-Level Data'!L:L, ">=" & ($Q$2 - 14), 'Unit-Level Data'!L:L, "<=" & ($Q$2 - 7), 'Unit-Level Data'!G:G, 0, 'Unit-Level Data'!B:B, B22),0) -> 0 | K22: =COUNTIFS('Unit-Level Data'!K:K, ">=" & ($Q$2 - 7), 'Unit-Level Data'!K:K, "<" & $Q$2, 'Unit-Level Data'!G:G, 0, 'Unit-Level Data'!B:B, B22) -> 0 | L22: =COUNTIFS( 'Unit-Level Data'!K:K, ">=" & ($Q$2 - 7), 'Unit-Level Data'!K:K, "<" & $Q$2, 'Unit-Level Data'!G:G, 0, 'Unit-Level Data'!B:B, B22 ) - COUNTIFS( 'Unit-Level Data'!K:K, ">=" & ($Q$2 - 14), 'Unit-Level Data'!K:K, "<=" & ($Q$2 - 7), 'Unit-Level Data'!G:G, 0, 'Unit-Level Data'!B:B, B22 ) -> 0 | M22: =IFERROR(AVERAGEIFS('Unit-Level Data'!O:O,'Unit-Level Data'!K:K,">="&($Q$2-7), 'Unit-Level Data'!K:K,"<="&$Q$2, 'Unit-Level Data'!G:G,0, 'Unit-Level Data'!B:B,B22),"") | N22: =COUNTIFS('Unit-Level Data'!B:B, B22, 'Unit-Level Data'!G:G, 0, 'Unit-Level Data'!L:L, "") -> 0 | O22: =N22-(N22-K22+F22) -> 0 | P22: =IFERROR(AVERAGEIFS('Unit-Level Data'!O:O,'Unit-Level Data'!B:B, B22, 'Unit-Level Data'!G:G, 0, 'Unit-Level Data'!L:L, ""),"") | Q22: =IFERROR(N22/SUMIFS('Unit Mix'!G:G,'Unit Mix'!D:D,0,'Unit Mix'!B:B,B22),"")
B23: =IF(ISBLANK(OFFSET('Rent Comps'!$A$1,7,2)),"",OFFSET('Rent Comps'!$A$1,7,2)) | E23: 1 BR | F23: =COUNTIFS('Unit-Level Data'!L:L, ">=" & ($Q$2 - 7), 'Unit-Level Data'!L:L, "<" & $Q$2, 'Unit-Level Data'!G:G, 1, 'Unit-Level Data'!B:B, B22) -> 0 | G23: =COUNTIFS('Unit-Level Data'!L:L, ">=" & ($Q$2 - 7), 'Unit-Level Data'!L:L, "<" & $Q$2, 'Unit-Level Data'!G:G, 1, 'Unit-Level Data'!B:B, B22) - COUNTIFS('Unit-Level Data'!L:L, ">=" & ($Q$2 - 14), 'Unit-Level Data'!L:L, "<=" & ($Q$2 - 7), 'Unit-Level Data'!G:G, 1, 'Unit-Level Data'!B:B, B22) -> 0 | H23: =IFERROR(AVERAGEIFS('Unit-Level Data'!O:O,'Unit-Level Data'!L:L, ">=" & ($Q$2 - 7), 'Unit-Level Data'!L:L, "<" & $Q$2, 'Unit-Level Data'!G:G, 1, 'Unit-Level Data'!B:B, B22),"") | I23: =IFERROR( AVERAGEIFS('Unit-Level Data'!O:O, 'Unit-Level Data'!L:L, ">=" & ($Q$2 - 7), 'Unit-Level Data'!L:L, "<" & $Q$2, 'Unit-Level Data'!G:G, 1, 'Unit-Level Data'!B:B, B22) - AVERAGEIFS('Unit-Level Data'!O:O, 'Unit-Level Data'!L:L, ">=" & ($Q$2 - 14), 'Unit-Level Data'!L:L, "<=" & ($Q$2 - 7), 'Unit-Level Data'!G:G, 1, 'Unit-Level Data'!B:B, B22), 0) -> 0 | J23: =IFERROR(I23/AVERAGEIFS('Unit-Level Data'!O:O, 'Unit-Level Data'!L:L, ">=" & ($Q$2 - 14), 'Unit-Level Data'!L:L, "<=" & ($Q$2 - 7), 'Unit-Level Data'!G:G, 1, 'Unit-Level Data'!B:B, B22),0) -> 0 | K23: =COUNTIFS('Unit-Level Data'!K:K, ">=" & ($Q$2 - 7), 'Unit-Level Data'!K:K, "<" & $Q$2, 'Unit-Level Data'!G:G, 1, 'Unit-Level Data'!B:B, B22) -> 0 | L23: =COUNTIFS( 'Unit-Level Data'!K:K, ">=" & ($Q$2 - 7), 'Unit-Level Data'!K:K, "<" & $Q$2, 'Unit-Level Data'!G:G, 1, 'Unit-Level Data'!B:B, B22 ) - COUNTIFS( 'Unit-Level Data'!K:K, ">=" & ($Q$2 - 14), 'Unit-Level Data'!K:K, "<=" & ($Q$2 - 7), 'Unit-Level Data'!G:G, 1, 'Unit-Level Data'!B:B, B22 ) -> 0 | M23: =IFERROR(AVERAGEIFS('Unit-Level Data'!O:O,'Unit-Level Data'!K:K,">="&($Q$2-7), 'Unit-Level Data'!K:K,"<="&$Q$2, 'Unit-Level Data'!G:G,1, 'Unit-Level Data'!B:B,B22),"") | N23: =COUNTIFS('Unit-Level Data'!B:B, B22, 'Unit-Level Data'!G:G, 1, 'Unit-Level Data'!L:L, "") -> 0 | O23: =N23-(N23-K23+F23) -> 0 | P23: =IFERROR(AVERAGEIFS('Unit-Level Data'!O:O,'Unit-Level Data'!B:B, B22, 'Unit-Level Data'!G:G, 1, 'Unit-Level Data'!L:L, ""),"") | Q23: =IFERROR(N23/SUMIFS('Unit Mix'!G:G,'Unit Mix'!D:D,1,'Unit Mix'!B:B,B22),"")
B24: =IF(ISBLANK(OFFSET('Rent Comparison'!$A$1,2,9)),"",OFFSET('Rent Comparison'!$A$1,2,9)) | E24: 2 BR | F24: =COUNTIFS('Unit-Level Data'!L:L, ">=" & ($Q$2 - 7), 'Unit-Level Data'!L:L, "<" & $Q$2, 'Unit-Level Data'!G:G, 2, 'Unit-Level Data'!B:B, B22) -> 0 | G24: =COUNTIFS('Unit-Level Data'!L:L, ">=" & ($Q$2 - 7), 'Unit-Level Data'!L:L, "<" & $Q$2, 'Unit-Level Data'!G:G, 2, 'Unit-Level Data'!B:B, B22) - COUNTIFS('Unit-Level Data'!L:L, ">=" & ($Q$2 - 14), 'Unit-Level Data'!L:L, "<=" & ($Q$2 - 7), 'Unit-Level Data'!G:G, 2, 'Unit-Level Data'!B:B, B22) -> 0 | H24: =IFERROR(AVERAGEIFS('Unit-Level Data'!O:O,'Unit-Level Data'!L:L, ">=" & ($Q$2 - 7), 'Unit-Level Data'!L:L, "<" & $Q$2, 'Unit-Level Data'!G:G, 2, 'Unit-Level Data'!B:B, B22),"") | I24: =IFERROR( AVERAGEIFS('Unit-Level Data'!O:O, 'Unit-Level Data'!L:L, ">=" & ($Q$2 - 7), 'Unit-Level Data'!L:L, "<" & $Q$2, 'Unit-Level Data'!G:G, 2, 'Unit-Level Data'!B:B, B22) - AVERAGEIFS('Unit-Level Data'!O:O, 'Unit-Level Data'!L:L, ">=" & ($Q$2 - 14), 'Unit-Level Data'!L:L, "<=" & ($Q$2 - 7), 'Unit-Level Data'!G:G, 2, 'Unit-Level Data'!B:B, B22), 0) -> 0 | J24: =IFERROR(I24/AVERAGEIFS('Unit-Level Data'!O:O, 'Unit-Level Data'!L:L, ">=" & ($Q$2 - 14), 'Unit-Level Data'!L:L, "<=" & ($Q$2 - 7), 'Unit-Level Data'!G:G, 2, 'Unit-Level Data'!B:B, B22),0) -> 0 | K24: =COUNTIFS('Unit-Level Data'!K:K, ">=" & ($Q$2 - 7), 'Unit-Level Data'!K:K, "<" & $Q$2, 'Unit-Level Data'!G:G, 2, 'Unit-Level Data'!B:B, B22) -> 0 | L24: =COUNTIFS( 'Unit-Level Data'!K:K, ">=" & ($Q$2 - 7), 'Unit-Level Data'!K:K, "<" & $Q$2, 'Unit-Level Data'!G:G, 2, 'Unit-Level Data'!B:B, B22 ) - COUNTIFS( 'Unit-Level Data'!K:K, ">=" & ($Q$2 - 14), 'Unit-Level Data'!K:K, "<=" & ($Q$2 - 7), 'Unit-Level Data'!G:G, 2, 'Unit-Level Data'!B:B, B22 ) -> 0 | M24: =IFERROR(AVERAGEIFS('Unit-Level Data'!O:O,'Unit-Level Data'!K:K,">="&($Q$2-7), 'Unit-Level Data'!K:K,"<="&$Q$2, 'Unit-Level Data'!G:G,2, 'Unit-Level Data'!B:B,B22),"") | N24: =COUNTIFS('Unit-Level Data'!B:B, B22, 'Unit-Level Data'!G:G, 2, 'Unit-Level Data'!L:L, "") -> 0 | O24: =N24-(N24-K24+F24) -> 0 | P24: =IFERROR(AVERAGEIFS('Unit-Level Data'!O:O,'Unit-Level Data'!B:B, B22, 'Unit-Level Data'!G:G, 2, 'Unit-Level Data'!L:L, ""),"") | Q24: =IFERROR(N24/SUMIFS('Unit Mix'!G:G,'Unit Mix'!D:D,2,'Unit Mix'!B:B,B22),"")
B25: =IF(ISBLANK(OFFSET('Rent Comparison'!$A$1,3,9)),"",OFFSET('Rent Comparison'!$A$1,3,9)) | E25: 3 BR | F25: =COUNTIFS('Unit-Level Data'!L:L, ">=" & ($Q$2 - 7), 'Unit-Level Data'!L:L, "<" & $Q$2, 'Unit-Level Data'!G:G, 3, 'Unit-Level Data'!B:B, B22) -> 0 | G25: =COUNTIFS('Unit-Level Data'!L:L, ">=" & ($Q$2 - 7), 'Unit-Level Data'!L:L, "<" & $Q$2, 'Unit-Level Data'!G:G, 3, 'Unit-Level Data'!B:B, B22) - COUNTIFS('Unit-Level Data'!L:L, ">=" & ($Q$2 - 14), 'Unit-Level Data'!L:L, "<=" & ($Q$2 - 7), 'Unit-Level Data'!G:G, 3, 'Unit-Level Data'!B:B, B22) -> 0 | H25: =IFERROR(AVERAGEIFS('Unit-Level Data'!O:O,'Unit-Level Data'!L:L, ">=" & ($Q$2 - 7), 'Unit-Level Data'!L:L, "<" & $Q$2, 'Unit-Level Data'!G:G, 3, 'Unit-Level Data'!B:B, B22),"") | I25: =IFERROR( AVERAGEIFS('Unit-Level Data'!O:O, 'Unit-Level Data'!L:L, ">=" & ($Q$2 - 7), 'Unit-Level Data'!L:L, "<" & $Q$2, 'Unit-Level Data'!G:G, 3, 'Unit-Level Data'!B:B, B22) - AVERAGEIFS('Unit-Level Data'!O:O, 'Unit-Level Data'!L:L, ">=" & ($Q$2 - 14), 'Unit-Level Data'!L:L, "<=" & ($Q$2 - 7), 'Unit-Level Data'!G:G, 3, 'Unit-Level Data'!B:B, B22), 0) -> 0 | J25: =IFERROR(I25/AVERAGEIFS('Unit-Level Data'!O:O, 'Unit-Level Data'!L:L, ">=" & ($Q$2 - 14), 'Unit-Level Data'!L:L, "<=" & ($Q$2 - 7), 'Unit-Level Data'!G:G, 3, 'Unit-Level Data'!B:B, B22),0) -> 0 | K25: =COUNTIFS('Unit-Level Data'!K:K, ">=" & ($Q$2 - 7), 'Unit-Level Data'!K:K, "<" & $Q$2, 'Unit-Level Data'!G:G, 3, 'Unit-Level Data'!B:B, B22) -> 0 | L25: =COUNTIFS( 'Unit-Level Data'!K:K, ">=" & ($Q$2 - 7), 'Unit-Level Data'!K:K, "<" & $Q$2, 'Unit-Level Data'!G:G, 3, 'Unit-Level Data'!B:B, B22 ) - COUNTIFS( 'Unit-Level Data'!K:K, ">=" & ($Q$2 - 14), 'Unit-Level Data'!K:K, "<=" & ($Q$2 - 7), 'Unit-Level Data'!G:G, 3, 'Unit-Level Data'!B:B, B22 ) -> 0 | M25: =IFERROR(AVERAGEIFS('Unit-Level Data'!O:O,'Unit-Level Data'!K:K,">="&($Q$2-7), 'Unit-Level Data'!K:K,"<="&$Q$2, 'Unit-Level Data'!G:G,3, 'Unit-Level Data'!B:B,B22),"") | N25: =COUNTIFS('Unit-Level Data'!B:B, B22, 'Unit-Level Data'!G:G, 3, 'Unit-Level Data'!L:L, "") -> 0 | O25: =N25-(N25-K25+F25) -> 0 | P25: =IFERROR(AVERAGEIFS('Unit-Level Data'!O:O,'Unit-Level Data'!B:B, B22, 'Unit-Level Data'!G:G, 3, 'Unit-Level Data'!L:L, ""),"") | Q25: =IFERROR(N25/SUMIFS('Unit Mix'!G:G,'Unit Mix'!D:D,3,'Unit Mix'!B:B,B22),"")
B26: =IF(ISBLANK(OFFSET('Rent Comparison'!$A$1,1,10)),"",OFFSET('Rent Comparison'!$A$1,1,10)) | C26: =IF(ISBLANK(B26),"",IFERROR(INDEX(Specials!B:J,MATCH(B26&" - Active",Specials!I:I,0),2),"")) | E26: Studio | F26: =COUNTIFS('Unit-Level Data'!L:L, ">=" & ($Q$2 - 7), 'Unit-Level Data'!L:L, "<" & $Q$2, 'Unit-Level Data'!G:G, 0, 'Unit-Level Data'!B:B, B26) -> 0 | G26: =COUNTIFS('Unit-Level Data'!L:L, ">=" & ($Q$2 - 7), 'Unit-Level Data'!L:L, "<" & $Q$2, 'Unit-Level Data'!G:G, 0, 'Unit-Level Data'!B:B, B26) - COUNTIFS('Unit-Level Data'!L:L, ">=" & ($Q$2 - 14), 'Unit-Level Data'!L:L, "<=" & ($Q$2 - 7), 'Unit-Level Data'!G:G, 0, 'Unit-Level Data'!B:B, B26) -> 0 | H26: =IFERROR(AVERAGEIFS('Unit-Level Data'!O:O,'Unit-Level Data'!L:L, ">=" & ($Q$2 - 7), 'Unit-Level Data'!L:L, "<" & $Q$2, 'Unit-Level Data'!G:G, 0, 'Unit-Level Data'!B:B, B26),"") | I26: =IFERROR( AVERAGEIFS('Unit-Level Data'!O:O, 'Unit-Level Data'!L:L, ">=" & ($Q$2 - 7), 'Unit-Level Data'!L:L, "<" & $Q$2, 'Unit-Level Data'!G:G, 0, 'Unit-Level Data'!B:B, B26) - AVERAGEIFS('Unit-Level Data'!O:O, 'Unit-Level Data'!L:L, ">=" & ($Q$2 - 14), 'Unit-Level Data'!L:L, "<=" & ($Q$2 - 7), 'Unit-Level Data'!G:G, 0, 'Unit-Level Data'!B:B, B26), 0) -> 0 | J26: =IFERROR(I26/AVERAGEIFS('Unit-Level Data'!O:O, 'Unit-Level Data'!L:L, ">=" & ($Q$2 - 14), 'Unit-Level Data'!L:L, "<=" & ($Q$2 - 7), 'Unit-Level Data'!G:G, 0, 'Unit-Level Data'!B:B, B26),0) -> 0 | K26: =COUNTIFS('Unit-Level Data'!K:K, ">=" & ($Q$2 - 7), 'Unit-Level Data'!K:K, "<" & $Q$2, 'Unit-Level Data'!G:G, 0, 'Unit-Level Data'!B:B, B26) -> 0 | L26: =COUNTIFS( 'Unit-Level Data'!K:K, ">=" & ($Q$2 - 7), 'Unit-Level Data'!K:K, "<" & $Q$2, 'Unit-Level Data'!G:G, 0, 'Unit-Level Data'!B:B, B26 ) - COUNTIFS( 'Unit-Level Data'!K:K, ">=" & ($Q$2 - 14), 'Unit-Level Data'!K:K, "<=" & ($Q$2 - 7), 'Unit-Level Data'!G:G, 0, 'Unit-Level Data'!B:B, B26 ) -> 0 | M26: =IFERROR(AVERAGEIFS('Unit-Level Data'!O:O,'Unit-Level Data'!K:K,">="&($Q$2-7), 'Unit-Level Data'!K:K,"<="&$Q$2, 'Unit-Level Data'!G:G,0, 'Unit-Level Data'!B:B,B26),"") | N26: =COUNTIFS('Unit-Level Data'!B:B, B26, 'Unit-Level Data'!G:G, 0, 'Unit-Level Data'!L:L, "") -> 0 | O26: =N26-(N26-K26+F26) -> 0 | P26: =IFERROR(AVERAGEIFS('Unit-Level Data'!O:O,'Unit-Level Data'!B:B, B26, 'Unit-Level Data'!G:G, 0, 'Unit-Level Data'!L:L, ""),"") | Q26: =IFERROR(N26/SUMIFS('Unit Mix'!G:G,'Unit Mix'!D:D,0,'Unit Mix'!B:B,B26),"")
B27: =IF(ISBLANK(OFFSET('Rent Comps'!$A$1,8,2)),"",OFFSET('Rent Comps'!$A$1,8,2)) | E27: 1 BR | F27: =COUNTIFS('Unit-Level Data'!L:L, ">=" & ($Q$2 - 7), 'Unit-Level Data'!L:L, "<" & $Q$2, 'Unit-Level Data'!G:G, 1, 'Unit-Level Data'!B:B, B26) -> 0 | G27: =COUNTIFS('Unit-Level Data'!L:L, ">=" & ($Q$2 - 7), 'Unit-Level Data'!L:L, "<" & $Q$2, 'Unit-Level Data'!G:G, 1, 'Unit-Level Data'!B:B, B26) - COUNTIFS('Unit-Level Data'!L:L, ">=" & ($Q$2 - 14), 'Unit-Level Data'!L:L, "<=" & ($Q$2 - 7), 'Unit-Level Data'!G:G, 1, 'Unit-Level Data'!B:B, B26) -> 0 | H27: =IFERROR(AVERAGEIFS('Unit-Level Data'!O:O,'Unit-Level Data'!L:L, ">=" & ($Q$2 - 7), 'Unit-Level Data'!L:L, "<" & $Q$2, 'Unit-Level Data'!G:G, 1, 'Unit-Level Data'!B:B, B26),"") | I27: =IFERROR( AVERAGEIFS('Unit-Level Data'!O:O, 'Unit-Level Data'!L:L, ">=" & ($Q$2 - 7), 'Unit-Level Data'!L:L, "<" & $Q$2, 'Unit-Level Data'!G:G, 1, 'Unit-Level Data'!B:B, B26) - AVERAGEIFS('Unit-Level Data'!O:O, 'Unit-Level Data'!L:L, ">=" & ($Q$2 - 14), 'Unit-Level Data'!L:L, "<=" & ($Q$2 - 7), 'Unit-Level Data'!G:G, 1, 'Unit-Level Data'!B:B, B26), 0) -> 0 | J27: =IFERROR(I27/AVERAGEIFS('Unit-Level Data'!O:O, 'Unit-Level Data'!L:L, ">=" & ($Q$2 - 14), 'Unit-Level Data'!L:L, "<=" & ($Q$2 - 7), 'Unit-Level Data'!G:G, 1, 'Unit-Level Data'!B:B, B26),0) -> 0 | K27: =COUNTIFS('Unit-Level Data'!K:K, ">=" & ($Q$2 - 7), 'Unit-Level Data'!K:K, "<" & $Q$2, 'Unit-Level Data'!G:G, 1, 'Unit-Level Data'!B:B, B26) -> 0 | L27: =COUNTIFS( 'Unit-Level Data'!K:K, ">=" & ($Q$2 - 7), 'Unit-Level Data'!K:K, "<" & $Q$2, 'Unit-Level Data'!G:G, 1, 'Unit-Level Data'!B:B, B26 ) - COUNTIFS( 'Unit-Level Data'!K:K, ">=" & ($Q$2 - 14), 'Unit-Level Data'!K:K, "<=" & ($Q$2 - 7), 'Unit-Level Data'!G:G, 1, 'Unit-Level Data'!B:B, B26 ) -> 0 | M27: =IFERROR(AVERAGEIFS('Unit-Level Data'!O:O,'Unit-Level Data'!K:K,">="&($Q$2-7), 'Unit-Level Data'!K:K,"<="&$Q$2, 'Unit-Level Data'!G:G,1, 'Unit-Level Data'!B:B,B26),"") | N27: =COUNTIFS('Unit-Level Data'!B:B, B26, 'Unit-Level Data'!G:G, 1, 'Unit-Level Data'!L:L, "") -> 0 | O27: =N27-(N27-K27+F27) -> 0 | P27: =IFERROR(AVERAGEIFS('Unit-Level Data'!O:O,'Unit-Level Data'!B:B, B26, 'Unit-Level Data'!G:G, 1, 'Unit-Level Data'!L:L, ""),"") | Q27: =IFERROR(N27/SUMIFS('Unit Mix'!G:G,'Unit Mix'!D:D,1,'Unit Mix'!B:B,B26),"")
B28: =IF(ISBLANK(OFFSET('Rent Comparison'!$A$1,2,10)),"",OFFSET('Rent Comparison'!$A$1,2,10)) | E28: 2 BR | F28: =COUNTIFS('Unit-Level Data'!L:L, ">=" & ($Q$2 - 7), 'Unit-Level Data'!L:L, "<" & $Q$2, 'Unit-Level Data'!G:G, 2, 'Unit-Level Data'!B:B, B26) -> 0 | G28: =COUNTIFS('Unit-Level Data'!L:L, ">=" & ($Q$2 - 7), 'Unit-Level Data'!L:L, "<" & $Q$2, 'Unit-Level Data'!G:G, 2, 'Unit-Level Data'!B:B, B26) - COUNTIFS('Unit-Level Data'!L:L, ">=" & ($Q$2 - 14), 'Unit-Level Data'!L:L, "<=" & ($Q$2 - 7), 'Unit-Level Data'!G:G, 2, 'Unit-Level Data'!B:B, B26) -> 0 | H28: =IFERROR(AVERAGEIFS('Unit-Level Data'!O:O,'Unit-Level Data'!L:L, ">=" & ($Q$2 - 7), 'Unit-Level Data'!L:L, "<" & $Q$2, 'Unit-Level Data'!G:G, 2, 'Unit-Level Data'!B:B, B26),"") | I28: =IFERROR( AVERAGEIFS('Unit-Level Data'!O:O, 'Unit-Level Data'!L:L, ">=" & ($Q$2 - 7), 'Unit-Level Data'!L:L, "<" & $Q$2, 'Unit-Level Data'!G:G, 2, 'Unit-Level Data'!B:B, B26) - AVERAGEIFS('Unit-Level Data'!O:O, 'Unit-Level Data'!L:L, ">=" & ($Q$2 - 14), 'Unit-Level Data'!L:L, "<=" & ($Q$2 - 7), 'Unit-Level Data'!G:G, 2, 'Unit-Level Data'!B:B, B26), 0) -> 0 | J28: =IFERROR(I28/AVERAGEIFS('Unit-Level Data'!O:O, 'Unit-Level Data'!L:L, ">=" & ($Q$2 - 14), 'Unit-Level Data'!L:L, "<=" & ($Q$2 - 7), 'Unit-Level Data'!G:G, 2, 'Unit-Level Data'!B:B, B26),0) -> 0 | K28: =COUNTIFS('Unit-Level Data'!K:K, ">=" & ($Q$2 - 7), 'Unit-Level Data'!K:K, "<" & $Q$2, 'Unit-Level Data'!G:G, 2, 'Unit-Level Data'!B:B, B26) -> 0 | L28: =COUNTIFS( 'Unit-Level Data'!K:K, ">=" & ($Q$2 - 7), 'Unit-Level Data'!K:K, "<" & $Q$2, 'Unit-Level Data'!G:G, 2, 'Unit-Level Data'!B:B, B26 ) - COUNTIFS( 'Unit-Level Data'!K:K, ">=" & ($Q$2 - 14), 'Unit-Level Data'!K:K, "<=" & ($Q$2 - 7), 'Unit-Level Data'!G:G, 2, 'Unit-Level Data'!B:B, B26 ) -> 0 | M28: =IFERROR(AVERAGEIFS('Unit-Level Data'!O:O,'Unit-Level Data'!K:K,">="&($Q$2-7), 'Unit-Level Data'!K:K,"<="&$Q$2, 'Unit-Level Data'!G:G,2, 'Unit-Level Data'!B:B,B26),"") | N28: =COUNTIFS('Unit-Level Data'!B:B, B26, 'Unit-Level Data'!G:G, 2, 'Unit-Level Data'!L:L, "") -> 0 | O28: =N28-(N28-K28+F28) -> 0 | P28: =IFERROR(AVERAGEIFS('Unit-Level Data'!O:O,'Unit-Level Data'!B:B, B26, 'Unit-Level Data'!G:G, 2, 'Unit-Level Data'!L:L, ""),"") | Q28: =IFERROR(N28/SUMIFS('Unit Mix'!G:G,'Unit Mix'!D:D,2,'Unit Mix'!B:B,B26),"")
B29: =IF(ISBLANK(OFFSET('Rent Comparison'!$A$1,3,10)),"",OFFSET('Rent Comparison'!$A$1,3,10)) | E29: 3 BR | F29: =COUNTIFS('Unit-Level Data'!L:L, ">=" & ($Q$2 - 7), 'Unit-Level Data'!L:L, "<" & $Q$2, 'Unit-Level Data'!G:G, 3, 'Unit-Level Data'!B:B, B26) -> 0 | G29: =COUNTIFS('Unit-Level Data'!L:L, ">=" & ($Q$2 - 7), 'Unit-Level Data'!L:L, "<" & $Q$2, 'Unit-Level Data'!G:G, 3, 'Unit-Level Data'!B:B, B26) - COUNTIFS('Unit-Level Data'!L:L, ">=" & ($Q$2 - 14), 'Unit-Level Data'!L:L, "<=" & ($Q$2 - 7), 'Unit-Level Data'!G:G, 3, 'Unit-Level Data'!B:B, B26) -> 0 | H29: =IFERROR(AVERAGEIFS('Unit-Level Data'!O:O,'Unit-Level Data'!L:L, ">=" & ($Q$2 - 7), 'Unit-Level Data'!L:L, "<" & $Q$2, 'Unit-Level Data'!G:G, 3, 'Unit-Level Data'!B:B, B26),"") | I29: =IFERROR( AVERAGEIFS('Unit-Level Data'!O:O, 'Unit-Level Data'!L:L, ">=" & ($Q$2 - 7), 'Unit-Level Data'!L:L, "<" & $Q$2, 'Unit-Level Data'!G:G, 3, 'Unit-Level Data'!B:B, B26) - AVERAGEIFS('Unit-Level Data'!O:O, 'Unit-Level Data'!L:L, ">=" & ($Q$2 - 14), 'Unit-Level Data'!L:L, "<=" & ($Q$2 - 7), 'Unit-Level Data'!G:G, 3, 'Unit-Level Data'!B:B, B26), 0) -> 0 | J29: =IFERROR(I29/AVERAGEIFS('Unit-Level Data'!O:O, 'Unit-Level Data'!L:L, ">=" & ($Q$2 - 14), 'Unit-Level Data'!L:L, "<=" & ($Q$2 - 7), 'Unit-Level Data'!G:G, 3, 'Unit-Level Data'!B:B, B26),0) -> 0 | K29: =COUNTIFS('Unit-Level Data'!K:K, ">=" & ($Q$2 - 7), 'Unit-Level Data'!K:K, "<" & $Q$2, 'Unit-Level Data'!G:G, 3, 'Unit-Level Data'!B:B, B26) -> 0 | L29: =COUNTIFS( 'Unit-Level Data'!K:K, ">=" & ($Q$2 - 7), 'Unit-Level Data'!K:K, "<" & $Q$2, 'Unit-Level Data'!G:G, 3, 'Unit-Level Data'!B:B, B26 ) - COUNTIFS( 'Unit-Level Data'!K:K, ">=" & ($Q$2 - 14), 'Unit-Level Data'!K:K, "<=" & ($Q$2 - 7), 'Unit-Level Data'!G:G, 3, 'Unit-Level Data'!B:B, B26 ) -> 0 | M29: =IFERROR(AVERAGEIFS('Unit-Level Data'!O:O,'Unit-Level Data'!K:K,">="&($Q$2-7), 'Unit-Level Data'!K:K,"<="&$Q$2, 'Unit-Level Data'!G:G,3, 'Unit-Level Data'!B:B,B26),"") | N29: =COUNTIFS('Unit-Level Data'!B:B, B26, 'Unit-Level Data'!G:G, 3, 'Unit-Level Data'!L:L, "") -> 0 | O29: =N29-(N29-K29+F29) -> 0 | P29: =IFERROR(AVERAGEIFS('Unit-Level Data'!O:O,'Unit-Level Data'!B:B, B26, 'Unit-Level Data'!G:G, 3, 'Unit-Level Data'!L:L, ""),"") | Q29: =IFERROR(N29/SUMIFS('Unit Mix'!G:G,'Unit Mix'!D:D,3,'Unit Mix'!B:B,B26),"")
B30: =IF(ISBLANK(OFFSET('Rent Comparison'!$A$1,1,11)),"",OFFSET('Rent Comparison'!$A$1,1,11)) | C30: =IF(ISBLANK(B30),"",IFERROR(INDEX(Specials!B:J,MATCH(B30&" - Active",Specials!I:I,0),2),"")) | E30: Studio | F30: =COUNTIFS('Unit-Level Data'!L:L, ">=" & ($Q$2 - 7), 'Unit-Level Data'!L:L, "<" & $Q$2, 'Unit-Level Data'!G:G, 0, 'Unit-Level Data'!B:B, B30) -> 0 | G30: =COUNTIFS('Unit-Level Data'!L:L, ">=" & ($Q$2 - 7), 'Unit-Level Data'!L:L, "<" & $Q$2, 'Unit-Level Data'!G:G, 0, 'Unit-Level Data'!B:B, B30) - COUNTIFS('Unit-Level Data'!L:L, ">=" & ($Q$2 - 14), 'Unit-Level Data'!L:L, "<=" & ($Q$2 - 7), 'Unit-Level Data'!G:G, 0, 'Unit-Level Data'!B:B, B30) -> 0 | H30: =IFERROR(AVERAGEIFS('Unit-Level Data'!O:O,'Unit-Level Data'!L:L, ">=" & ($Q$2 - 7), 'Unit-Level Data'!L:L, "<" & $Q$2, 'Unit-Level Data'!G:G, 0, 'Unit-Level Data'!B:B, B30),"") | I30: =IFERROR( AVERAGEIFS('Unit-Level Data'!O:O, 'Unit-Level Data'!L:L, ">=" & ($Q$2 - 7), 'Unit-Level Data'!L:L, "<" & $Q$2, 'Unit-Level Data'!G:G, 0, 'Unit-Level Data'!B:B, B30) - AVERAGEIFS('Unit-Level Data'!O:O, 'Unit-Level Data'!L:L, ">=" & ($Q$2 - 14), 'Unit-Level Data'!L:L, "<=" & ($Q$2 - 7), 'Unit-Level Data'!G:G, 0, 'Unit-Level Data'!B:B, B30), 0) -> 0 | J30: =IFERROR(I30/AVERAGEIFS('Unit-Level Data'!O:O, 'Unit-Level Data'!L:L, ">=" & ($Q$2 - 14), 'Unit-Level Data'!L:L, "<=" & ($Q$2 - 7), 'Unit-Level Data'!G:G, 0, 'Unit-Level Data'!B:B, B30),0) -> 0 | K30: =COUNTIFS('Unit-Level Data'!K:K, ">=" & ($Q$2 - 7), 'Unit-Level Data'!K:K, "<" & $Q$2, 'Unit-Level Data'!G:G, 0, 'Unit-Level Data'!B:B, B30) -> 0 | L30: =COUNTIFS( 'Unit-Level Data'!K:K, ">=" & ($Q$2 - 7), 'Unit-Level Data'!K:K, "<" & $Q$2, 'Unit-Level Data'!G:G, 0, 'Unit-Level Data'!B:B, B30 ) - COUNTIFS( 'Unit-Level Data'!K:K, ">=" & ($Q$2 - 14), 'Unit-Level Data'!K:K, "<=" & ($Q$2 - 7), 'Unit-Level Data'!G:G, 0, 'Unit-Level Data'!B:B, B30 ) -> 0 | M30: =IFERROR(AVERAGEIFS('Unit-Level Data'!O:O,'Unit-Level Data'!K:K,">="&($Q$2-7), 'Unit-Level Data'!K:K,"<="&$Q$2, 'Unit-Level Data'!G:G,0, 'Unit-Level Data'!B:B,B30),"") | N30: =COUNTIFS('Unit-Level Data'!B:B, B30, 'Unit-Level Data'!G:G, 0, 'Unit-Level Data'!L:L, "") -> 0 | O30: =N30-(N30-K30+F30) -> 0 | P30: =IFERROR(AVERAGEIFS('Unit-Level Data'!O:O,'Unit-Level Data'!B:B, B30, 'Unit-Level Data'!G:G, 0, 'Unit-Level Data'!L:L, ""),"") | Q30: =IFERROR(N30/SUMIFS('Unit Mix'!G:G,'Unit Mix'!D:D,0,'Unit Mix'!B:B,B30),"")
B31: =IF(ISBLANK(OFFSET('Rent Comps'!$A$1,9,2)),"",OFFSET('Rent Comps'!$A$1,9,2)) | E31: 1 BR | F31: =COUNTIFS('Unit-Level Data'!L:L, ">=" & ($Q$2 - 7), 'Unit-Level Data'!L:L, "<" & $Q$2, 'Unit-Level Data'!G:G, 1, 'Unit-Level Data'!B:B, B30) -> 0 | G31: =COUNTIFS('Unit-Level Data'!L:L, ">=" & ($Q$2 - 7), 'Unit-Level Data'!L:L, "<" & $Q$2, 'Unit-Level Data'!G:G, 1, 'Unit-Level Data'!B:B, B30) - COUNTIFS('Unit-Level Data'!L:L, ">=" & ($Q$2 - 14), 'Unit-Level Data'!L:L, "<=" & ($Q$2 - 7), 'Unit-Level Data'!G:G, 1, 'Unit-Level Data'!B:B, B30) -> 0 | H31: =IFERROR(AVERAGEIFS('Unit-Level Data'!O:O,'Unit-Level Data'!L:L, ">=" & ($Q$2 - 7), 'Unit-Level Data'!L:L, "<" & $Q$2, 'Unit-Level Data'!G:G, 1, 'Unit-Level Data'!B:B, B30),"") | I31: =IFERROR( AVERAGEIFS('Unit-Level Data'!O:O, 'Unit-Level Data'!L:L, ">=" & ($Q$2 - 7), 'Unit-Level Data'!L:L, "<" & $Q$2, 'Unit-Level Data'!G:G, 1, 'Unit-Level Data'!B:B, B30) - AVERAGEIFS('Unit-Level Data'!O:O, 'Unit-Level Data'!L:L, ">=" & ($Q$2 - 14), 'Unit-Level Data'!L:L, "<=" & ($Q$2 - 7), 'Unit-Level Data'!G:G, 1, 'Unit-Level Data'!B:B, B30), 0) -> 0 | J31: =IFERROR(I31/AVERAGEIFS('Unit-Level Data'!O:O, 'Unit-Level Data'!L:L, ">=" & ($Q$2 - 14), 'Unit-Level Data'!L:L, "<=" & ($Q$2 - 7), 'Unit-Level Data'!G:G, 1, 'Unit-Level Data'!B:B, B30),0) -> 0 | K31: =COUNTIFS('Unit-Level Data'!K:K, ">=" & ($Q$2 - 7), 'Unit-Level Data'!K:K, "<" & $Q$2, 'Unit-Level Data'!G:G, 1, 'Unit-Level Data'!B:B, B30) -> 0 | L31: =COUNTIFS( 'Unit-Level Data'!K:K, ">=" & ($Q$2 - 7), 'Unit-Level Data'!K:K, "<" & $Q$2, 'Unit-Level Data'!G:G, 1, 'Unit-Level Data'!B:B, B30 ) - COUNTIFS( 'Unit-Level Data'!K:K, ">=" & ($Q$2 - 14), 'Unit-Level Data'!K:K, "<=" & ($Q$2 - 7), 'Unit-Level Data'!G:G, 1, 'Unit-Level Data'!B:B, B30 ) -> 0 | M31: =IFERROR(AVERAGEIFS('Unit-Level Data'!O:O,'Unit-Level Data'!K:K,">="&($Q$2-7), 'Unit-Level Data'!K:K,"<="&$Q$2, 'Unit-Level Data'!G:G,1, 'Unit-Level Data'!B:B,B30),"") | N31: =COUNTIFS('Unit-Level Data'!B:B, B30, 'Unit-Level Data'!G:G, 1, 'Unit-Level Data'!L:L, "") -> 0 | O31: =N31-(N31-K31+F31) -> 0 | P31: =IFERROR(AVERAGEIFS('Unit-Level Data'!O:O,'Unit-Level Data'!B:B, B30, 'Unit-Level Data'!G:G, 1, 'Unit-Level Data'!L:L, ""),"") | Q31: =IFERROR(N31/SUMIFS('Unit Mix'!G:G,'Unit Mix'!D:D,1,'Unit Mix'!B:B,B30),"")
B32: =IF(ISBLANK(OFFSET('Rent Comparison'!$A$1,2,11)),"",OFFSET('Rent Comparison'!$A$1,2,11)) | E32: 2 BR | F32: =COUNTIFS('Unit-Level Data'!L:L, ">=" & ($Q$2 - 7), 'Unit-Level Data'!L:L, "<" & $Q$2, 'Unit-Level Data'!G:G, 2, 'Unit-Level Data'!B:B, B30) -> 0 | G32: =COUNTIFS('Unit-Level Data'!L:L, ">=" & ($Q$2 - 7), 'Unit-Level Data'!L:L, "<" & $Q$2, 'Unit-Level Data'!G:G, 2, 'Unit-Level Data'!B:B, B30) - COUNTIFS('Unit-Level Data'!L:L, ">=" & ($Q$2 - 14), 'Unit-Level Data'!L:L, "<=" & ($Q$2 - 7), 'Unit-Level Data'!G:G, 2, 'Unit-Level Data'!B:B, B30) -> 0 | H32: =IFERROR(AVERAGEIFS('Unit-Level Data'!O:O,'Unit-Level Data'!L:L, ">=" & ($Q$2 - 7), 'Unit-Level Data'!L:L, "<" & $Q$2, 'Unit-Level Data'!G:G, 2, 'Unit-Level Data'!B:B, B30),"") | I32: =IFERROR( AVERAGEIFS('Unit-Level Data'!O:O, 'Unit-Level Data'!L:L, ">=" & ($Q$2 - 7), 'Unit-Level Data'!L:L, "<" & $Q$2, 'Unit-Level Data'!G:G, 2, 'Unit-Level Data'!B:B, B30) - AVERAGEIFS('Unit-Level Data'!O:O, 'Unit-Level Data'!L:L, ">=" & ($Q$2 - 14), 'Unit-Level Data'!L:L, "<=" & ($Q$2 - 7), 'Unit-Level Data'!G:G, 2, 'Unit-Level Data'!B:B, B30), 0) -> 0 | J32: =IFERROR(I32/AVERAGEIFS('Unit-Level Data'!O:O, 'Unit-Level Data'!L:L, ">=" & ($Q$2 - 14), 'Unit-Level Data'!L:L, "<=" & ($Q$2 - 7), 'Unit-Level Data'!G:G, 2, 'Unit-Level Data'!B:B, B30),0) -> 0 | K32: =COUNTIFS('Unit-Level Data'!K:K, ">=" & ($Q$2 - 7), 'Unit-Level Data'!K:K, "<" & $Q$2, 'Unit-Level Data'!G:G, 2, 'Unit-Level Data'!B:B, B30) -> 0 | L32: =COUNTIFS( 'Unit-Level Data'!K:K, ">=" & ($Q$2 - 7), 'Unit-Level Data'!K:K, "<" & $Q$2, 'Unit-Level Data'!G:G, 2, 'Unit-Level Data'!B:B, B30 ) - COUNTIFS( 'Unit-Level Data'!K:K, ">=" & ($Q$2 - 14), 'Unit-Level Data'!K:K, "<=" & ($Q$2 - 7), 'Unit-Level Data'!G:G, 2, 'Unit-Level Data'!B:B, B30 ) -> 0 | M32: =IFERROR(AVERAGEIFS('Unit-Level Data'!O:O,'Unit-Level Data'!K:K,">="&($Q$2-7), 'Unit-Level Data'!K:K,"<="&$Q$2, 'Unit-Level Data'!G:G,2, 'Unit-Level Data'!B:B,B30),"") | N32: =COUNTIFS('Unit-Level Data'!B:B, B30, 'Unit-Level Data'!G:G, 2, 'Unit-Level Data'!L:L, "") -> 0 | O32: =N32-(N32-K32+F32) -> 0 | P32: =IFERROR(AVERAGEIFS('Unit-Level Data'!O:O,'Unit-Level Data'!B:B, B30, 'Unit-Level Data'!G:G, 2, 'Unit-Level Data'!L:L, ""),"") | Q32: =IFERROR(N32/SUMIFS('Unit Mix'!G:G,'Unit Mix'!D:D,2,'Unit Mix'!B:B,B30),"")
B33: =IF(ISBLANK(OFFSET('Rent Comparison'!$A$1,3,11)),"",OFFSET('Rent Comparison'!$A$1,3,11)) | E33: 3 BR | F33: =COUNTIFS('Unit-Level Data'!L:L, ">=" & ($Q$2 - 7), 'Unit-Level Data'!L:L, "<" & $Q$2, 'Unit-Level Data'!G:G, 3, 'Unit-Level Data'!B:B, B30) -> 0 | G33: =COUNTIFS('Unit-Level Data'!L:L, ">=" & ($Q$2 - 7), 'Unit-Level Data'!L:L, "<" & $Q$2, 'Unit-Level Data'!G:G, 3, 'Unit-Level Data'!B:B, B30) - COUNTIFS('Unit-Level Data'!L:L, ">=" & ($Q$2 - 14), 'Unit-Level Data'!L:L, "<=" & ($Q$2 - 7), 'Unit-Level Data'!G:G, 3, 'Unit-Level Data'!B:B, B30) -> 0 | H33: =IFERROR(AVERAGEIFS('Unit-Level Data'!O:O,'Unit-Level Data'!L:L, ">=" & ($Q$2 - 7), 'Unit-Level Data'!L:L, "<" & $Q$2, 'Unit-Level Data'!G:G, 3, 'Unit-Level Data'!B:B, B30),"") | I33: =IFERROR( AVERAGEIFS('Unit-Level Data'!O:O, 'Unit-Level Data'!L:L, ">=" & ($Q$2 - 7), 'Unit-Level Data'!L:L, "<" & $Q$2, 'Unit-Level Data'!G:G, 3, 'Unit-Level Data'!B:B, B30) - AVERAGEIFS('Unit-Level Data'!O:O, 'Unit-Level Data'!L:L, ">=" & ($Q$2 - 14), 'Unit-Level Data'!L:L, "<=" & ($Q$2 - 7), 'Unit-Level Data'!G:G, 3, 'Unit-Level Data'!B:B, B30), 0) -> 0 | J33: =IFERROR(I33/AVERAGEIFS('Unit-Level Data'!O:O, 'Unit-Level Data'!L:L, ">=" & ($Q$2 - 14), 'Unit-Level Data'!L:L, "<=" & ($Q$2 - 7), 'Unit-Level Data'!G:G, 3, 'Unit-Level Data'!B:B, B30),0) -> 0 | K33: =COUNTIFS('Unit-Level Data'!K:K, ">=" & ($Q$2 - 7), 'Unit-Level Data'!K:K, "<" & $Q$2, 'Unit-Level Data'!G:G, 3, 'Unit-Level Data'!B:B, B30) -> 0 | L33: =COUNTIFS( 'Unit-Level Data'!K:K, ">=" & ($Q$2 - 7), 'Unit-Level Data'!K:K, "<" & $Q$2, 'Unit-Level Data'!G:G, 3, 'Unit-Level Data'!B:B, B30 ) - COUNTIFS( 'Unit-Level Data'!K:K, ">=" & ($Q$2 - 14), 'Unit-Level Data'!K:K, "<=" & ($Q$2 - 7), 'Unit-Level Data'!G:G, 3, 'Unit-Level Data'!B:B, B30 ) -> 0 | M33: =IFERROR(AVERAGEIFS('Unit-Level Data'!O:O,'Unit-Level Data'!K:K,">="&($Q$2-7), 'Unit-Level Data'!K:K,"<="&$Q$2, 'Unit-Level Data'!G:G,3, 'Unit-Level Data'!B:B,B30),"") | N33: =COUNTIFS('Unit-Level Data'!B:B, B30, 'Unit-Level Data'!G:G, 3, 'Unit-Level Data'!L:L, "") -> 0 | O33: =N33-(N33-K33+F33) -> 0 | P33: =IFERROR(AVERAGEIFS('Unit-Level Data'!O:O,'Unit-Level Data'!B:B, B30, 'Unit-Level Data'!G:G, 3, 'Unit-Level Data'!L:L, ""),"") | Q33: =IFERROR(N33/SUMIFS('Unit Mix'!G:G,'Unit Mix'!D:D,3,'Unit Mix'!B:B,B30),"")
B34: =IF(ISBLANK(OFFSET('Rent Comparison'!$A$1,1,12)),"",OFFSET('Rent Comparison'!$A$1,1,12)) | C34: =IF(ISBLANK(B34),"",IFERROR(INDEX(Specials!B:J,MATCH(B34&" - Active",Specials!I:I,0),2),"")) | E34: Studio | F34: =COUNTIFS('Unit-Level Data'!L:L, ">=" & ($Q$2 - 7), 'Unit-Level Data'!L:L, "<" & $Q$2, 'Unit-Level Data'!G:G, 0, 'Unit-Level Data'!B:B, B34) -> 0 | G34: =COUNTIFS('Unit-Level Data'!L:L, ">=" & ($Q$2 - 7), 'Unit-Level Data'!L:L, "<" & $Q$2, 'Unit-Level Data'!G:G, 0, 'Unit-Level Data'!B:B, B34) - COUNTIFS('Unit-Level Data'!L:L, ">=" & ($Q$2 - 14), 'Unit-Level Data'!L:L, "<=" & ($Q$2 - 7), 'Unit-Level Data'!G:G, 0, 'Unit-Level Data'!B:B, B34) -> 0 | H34: =IFERROR(AVERAGEIFS('Unit-Level Data'!O:O,'Unit-Level Data'!L:L, ">=" & ($Q$2 - 7), 'Unit-Level Data'!L:L, "<" & $Q$2, 'Unit-Level Data'!G:G, 0, 'Unit-Level Data'!B:B, B34),"") | I34: =IFERROR( AVERAGEIFS('Unit-Level Data'!O:O, 'Unit-Level Data'!L:L, ">=" & ($Q$2 - 7), 'Unit-Level Data'!L:L, "<" & $Q$2, 'Unit-Level Data'!G:G, 0, 'Unit-Level Data'!B:B, B34) - AVERAGEIFS('Unit-Level Data'!O:O, 'Unit-Level Data'!L:L, ">=" & ($Q$2 - 14), 'Unit-Level Data'!L:L, "<=" & ($Q$2 - 7), 'Unit-Level Data'!G:G, 0, 'Unit-Level Data'!B:B, B34), 0) -> 0 | J34: =IFERROR(I34/AVERAGEIFS('Unit-Level Data'!O:O, 'Unit-Level Data'!L:L, ">=" & ($Q$2 - 14), 'Unit-Level Data'!L:L, "<=" & ($Q$2 - 7), 'Unit-Level Data'!G:G, 0, 'Unit-Level Data'!B:B, B34),0) -> 0 | K34: =COUNTIFS('Unit-Level Data'!K:K, ">=" & ($Q$2 - 7), 'Unit-Level Data'!K:K, "<" & $Q$2, 'Unit-Level Data'!G:G, 0, 'Unit-Level Data'!B:B, B34) -> 0 | L34: =COUNTIFS( 'Unit-Level Data'!K:K, ">=" & ($Q$2 - 7), 'Unit-Level Data'!K:K, "<" & $Q$2, 'Unit-Level Data'!G:G, 0, 'Unit-Level Data'!B:B, B34 ) - COUNTIFS( 'Unit-Level Data'!K:K, ">=" & ($Q$2 - 14), 'Unit-Level Data'!K:K, "<=" & ($Q$2 - 7), 'Unit-Level Data'!G:G, 0, 'Unit-Level Data'!B:B, B34 ) -> 0 | M34: =IFERROR(AVERAGEIFS('Unit-Level Data'!O:O,'Unit-Level Data'!K:K,">="&($Q$2-7), 'Unit-Level Data'!K:K,"<="&$Q$2, 'Unit-Level Data'!G:G,0, 'Unit-Level Data'!B:B,B34),"") | N34: =COUNTIFS('Unit-Level Data'!B:B, B34, 'Unit-Level Data'!G:G, 0, 'Unit-Level Data'!L:L, "") -> 0 | O34: =N34-(N34-K34+F34) -> 0 | P34: =IFERROR(AVERAGEIFS('Unit-Level Data'!O:O,'Unit-Level Data'!B:B, B34, 'Unit-Level Data'!G:G, 0, 'Unit-Level Data'!L:L, ""),"") | Q34: =IFERROR(N34/SUMIFS('Unit Mix'!G:G,'Unit Mix'!D:D,0,'Unit Mix'!B:B,B34),"")
B35: =IF(ISBLANK(OFFSET('Rent Comps'!$A$1,10,2)),"",OFFSET('Rent Comps'!$A$1,10,2)) | E35: 1 BR | F35: =COUNTIFS('Unit-Level Data'!L:L, ">=" & ($Q$2 - 7), 'Unit-Level Data'!L:L, "<" & $Q$2, 'Unit-Level Data'!G:G, 1, 'Unit-Level Data'!B:B, B34) -> 0 | G35: =COUNTIFS('Unit-Level Data'!L:L, ">=" & ($Q$2 - 7), 'Unit-Level Data'!L:L, "<" & $Q$2, 'Unit-Level Data'!G:G, 1, 'Unit-Level Data'!B:B, B34) - COUNTIFS('Unit-Level Data'!L:L, ">=" & ($Q$2 - 14), 'Unit-Level Data'!L:L, "<=" & ($Q$2 - 7), 'Unit-Level Data'!G:G, 1, 'Unit-Level Data'!B:B, B34) -> 0 | H35: =IFERROR(AVERAGEIFS('Unit-Level Data'!O:O,'Unit-Level Data'!L:L, ">=" & ($Q$2 - 7), 'Unit-Level Data'!L:L, "<" & $Q$2, 'Unit-Level Data'!G:G, 1, 'Unit-Level Data'!B:B, B34),"") | I35: =IFERROR( AVERAGEIFS('Unit-Level Data'!O:O, 'Unit-Level Data'!L:L, ">=" & ($Q$2 - 7), 'Unit-Level Data'!L:L, "<" & $Q$2, 'Unit-Level Data'!G:G, 1, 'Unit-Level Data'!B:B, B34) - AVERAGEIFS('Unit-Level Data'!O:O, 'Unit-Level Data'!L:L, ">=" & ($Q$2 - 14), 'Unit-Level Data'!L:L, "<=" & ($Q$2 - 7), 'Unit-Level Data'!G:G, 1, 'Unit-Level Data'!B:B, B34), 0) -> 0 | J35: =IFERROR(I35/AVERAGEIFS('Unit-Level Data'!O:O, 'Unit-Level Data'!L:L, ">=" & ($Q$2 - 14), 'Unit-Level Data'!L:L, "<=" & ($Q$2 - 7), 'Unit-Level Data'!G:G, 1, 'Unit-Level Data'!B:B, B34),0) -> 0 | K35: =COUNTIFS('Unit-Level Data'!K:K, ">=" & ($Q$2 - 7), 'Unit-Level Data'!K:K, "<" & $Q$2, 'Unit-Level Data'!G:G, 1, 'Unit-Level Data'!B:B, B34) -> 0 | L35: =COUNTIFS( 'Unit-Level Data'!K:K, ">=" & ($Q$2 - 7), 'Unit-Level Data'!K:K, "<" & $Q$2, 'Unit-Level Data'!G:G, 1, 'Unit-Level Data'!B:B, B34 ) - COUNTIFS( 'Unit-Level Data'!K:K, ">=" & ($Q$2 - 14), 'Unit-Level Data'!K:K, "<=" & ($Q$2 - 7), 'Unit-Level Data'!G:G, 1, 'Unit-Level Data'!B:B, B34 ) -> 0 | M35: =IFERROR(AVERAGEIFS('Unit-Level Data'!O:O,'Unit-Level Data'!K:K,">="&($Q$2-7), 'Unit-Level Data'!K:K,"<="&$Q$2, 'Unit-Level Data'!G:G,1, 'Unit-Level Data'!B:B,B34),"") | N35: =COUNTIFS('Unit-Level Data'!B:B, B34, 'Unit-Level Data'!G:G, 1, 'Unit-Level Data'!L:L, "") -> 0 | O35: =N35-(N35-K35+F35) -> 0 | P35: =IFERROR(AVERAGEIFS('Unit-Level Data'!O:O,'Unit-Level Data'!B:B, B34, 'Unit-Level Data'!G:G, 1, 'Unit-Level Data'!L:L, ""),"") | Q35: =IFERROR(N35/SUMIFS('Unit Mix'!G:G,'Unit Mix'!D:D,1,'Unit Mix'!B:B,B34),"")
B36: =IF(ISBLANK(OFFSET('Rent Comparison'!$A$1,2,12)),"",OFFSET('Rent Comparison'!$A$1,2,12)) | E36: 2 BR | F36: =COUNTIFS('Unit-Level Data'!L:L, ">=" & ($Q$2 - 7), 'Unit-Level Data'!L:L, "<" & $Q$2, 'Unit-Level Data'!G:G, 2, 'Unit-Level Data'!B:B, B34) -> 0 | G36: =COUNTIFS('Unit-Level Data'!L:L, ">=" & ($Q$2 - 7), 'Unit-Level Data'!L:L, "<" & $Q$2, 'Unit-Level Data'!G:G, 2, 'Unit-Level Data'!B:B, B34) - COUNTIFS('Unit-Level Data'!L:L, ">=" & ($Q$2 - 14), 'Unit-Level Data'!L:L, "<=" & ($Q$2 - 7), 'Unit-Level Data'!G:G, 2, 'Unit-Level Data'!B:B, B34) -> 0 | H36: =IFERROR(AVERAGEIFS('Unit-Level Data'!O:O,'Unit-Level Data'!L:L, ">=" & ($Q$2 - 7), 'Unit-Level Data'!L:L, "<" & $Q$2, 'Unit-Level Data'!G:G, 2, 'Unit-Level Data'!B:B, B34),"") | I36: =IFERROR( AVERAGEIFS('Unit-Level Data'!O:O, 'Unit-Level Data'!L:L, ">=" & ($Q$2 - 7), 'Unit-Level Data'!L:L, "<" & $Q$2, 'Unit-Level Data'!G:G, 2, 'Unit-Level Data'!B:B, B34) - AVERAGEIFS('Unit-Level Data'!O:O, 'Unit-Level Data'!L:L, ">=" & ($Q$2 - 14), 'Unit-Level Data'!L:L, "<=" & ($Q$2 - 7), 'Unit-Level Data'!G:G, 2, 'Unit-Level Data'!B:B, B34), 0) -> 0 | J36: =IFERROR(I36/AVERAGEIFS('Unit-Level Data'!O:O, 'Unit-Level Data'!L:L, ">=" & ($Q$2 - 14), 'Unit-Level Data'!L:L, "<=" & ($Q$2 - 7), 'Unit-Level Data'!G:G, 2, 'Unit-Level Data'!B:B, B34),0) -> 0 | K36: =COUNTIFS('Unit-Level Data'!K:K, ">=" & ($Q$2 - 7), 'Unit-Level Data'!K:K, "<" & $Q$2, 'Unit-Level Data'!G:G, 2, 'Unit-Level Data'!B:B, B34) -> 0 | L36: =COUNTIFS( 'Unit-Level Data'!K:K, ">=" & ($Q$2 - 7), 'Unit-Level Data'!K:K, "<" & $Q$2, 'Unit-Level Data'!G:G, 2, 'Unit-Level Data'!B:B, B34 ) - COUNTIFS( 'Unit-Level Data'!K:K, ">=" & ($Q$2 - 14), 'Unit-Level Data'!K:K, "<=" & ($Q$2 - 7), 'Unit-Level Data'!G:G, 2, 'Unit-Level Data'!B:B, B34 ) -> 0 | M36: =IFERROR(AVERAGEIFS('Unit-Level Data'!O:O,'Unit-Level Data'!K:K,">="&($Q$2-7), 'Unit-Level Data'!K:K,"<="&$Q$2, 'Unit-Level Data'!G:G,2, 'Unit-Level Data'!B:B,B34),"") | N36: =COUNTIFS('Unit-Level Data'!B:B, B34, 'Unit-Level Data'!G:G, 2, 'Unit-Level Data'!L:L, "") -> 0 | O36: =N36-(N36-K36+F36) -> 0 | P36: =IFERROR(AVERAGEIFS('Unit-Level Data'!O:O,'Unit-Level Data'!B:B, B34, 'Unit-Level Data'!G:G, 2, 'Unit-Level Data'!L:L, ""),"") | Q36: =IFERROR(N36/SUMIFS('Unit Mix'!G:G,'Unit Mix'!D:D,2,'Unit Mix'!B:B,B34),"")
B37: =IF(ISBLANK(OFFSET('Rent Comparison'!$A$1,3,12)),"",OFFSET('Rent Comparison'!$A$1,3,12)) | E37: 3 BR | F37: =COUNTIFS('Unit-Level Data'!L:L, ">=" & ($Q$2 - 7), 'Unit-Level Data'!L:L, "<" & $Q$2, 'Unit-Level Data'!G:G, 3, 'Unit-Level Data'!B:B, B34) -> 0 | G37: =COUNTIFS('Unit-Level Data'!L:L, ">=" & ($Q$2 - 7), 'Unit-Level Data'!L:L, "<" & $Q$2, 'Unit-Level Data'!G:G, 3, 'Unit-Level Data'!B:B, B34) - COUNTIFS('Unit-Level Data'!L:L, ">=" & ($Q$2 - 14), 'Unit-Level Data'!L:L, "<=" & ($Q$2 - 7), 'Unit-Level Data'!G:G, 3, 'Unit-Level Data'!B:B, B34) -> 0 | H37: =IFERROR(AVERAGEIFS('Unit-Level Data'!O:O,'Unit-Level Data'!L:L, ">=" & ($Q$2 - 7), 'Unit-Level Data'!L:L, "<" & $Q$2, 'Unit-Level Data'!G:G, 3, 'Unit-Level Data'!B:B, B34),"") | I37: =IFERROR( AVERAGEIFS('Unit-Level Data'!O:O, 'Unit-Level Data'!L:L, ">=" & ($Q$2 - 7), 'Unit-Level Data'!L:L, "<" & $Q$2, 'Unit-Level Data'!G:G, 3, 'Unit-Level Data'!B:B, B34) - AVERAGEIFS('Unit-Level Data'!O:O, 'Unit-Level Data'!L:L, ">=" & ($Q$2 - 14), 'Unit-Level Data'!L:L, "<=" & ($Q$2 - 7), 'Unit-Level Data'!G:G, 3, 'Unit-Level Data'!B:B, B34), 0) -> 0 | J37: =IFERROR(I37/AVERAGEIFS('Unit-Level Data'!O:O, 'Unit-Level Data'!L:L, ">=" & ($Q$2 - 14), 'Unit-Level Data'!L:L, "<=" & ($Q$2 - 7), 'Unit-Level Data'!G:G, 3, 'Unit-Level Data'!B:B, B34),0) -> 0 | K37: =COUNTIFS('Unit-Level Data'!K:K, ">=" & ($Q$2 - 7), 'Unit-Level Data'!K:K, "<" & $Q$2, 'Unit-Level Data'!G:G, 3, 'Unit-Level Data'!B:B, B34) -> 0 | L37: =COUNTIFS( 'Unit-Level Data'!K:K, ">=" & ($Q$2 - 7), 'Unit-Level Data'!K:K, "<" & $Q$2, 'Unit-Level Data'!G:G, 3, 'Unit-Level Data'!B:B, B34 ) - COUNTIFS( 'Unit-Level Data'!K:K, ">=" & ($Q$2 - 14), 'Unit-Level Data'!K:K, "<=" & ($Q$2 - 7), 'Unit-Level Data'!G:G, 3, 'Unit-Level Data'!B:B, B34 ) -> 0 | M37: =IFERROR(AVERAGEIFS('Unit-Level Data'!O:O,'Unit-Level Data'!K:K,">="&($Q$2-7), 'Unit-Level Data'!K:K,"<="&$Q$2, 'Unit-Level Data'!G:G,3, 'Unit-Level Data'!B:B,B34),"") | N37: =COUNTIFS('Unit-Level Data'!B:B, B34, 'Unit-Level Data'!G:G, 3, 'Unit-Level Data'!L:L, "") -> 0 | O37: =N37-(N37-K37+F37) -> 0 | P37: =IFERROR(AVERAGEIFS('Unit-Level Data'!O:O,'Unit-Level Data'!B:B, B34, 'Unit-Level Data'!G:G, 3, 'Unit-Level Data'!L:L, ""),"") | Q37: =IFERROR(N37/SUMIFS('Unit Mix'!G:G,'Unit Mix'!D:D,3,'Unit Mix'!B:B,B34),"")
B38: =IF(ISBLANK(OFFSET('Rent Comparison'!$A$1,1,13)),"",OFFSET('Rent Comparison'!$A$1,1,13)) | C38: =IF(ISBLANK(B38),"",IFERROR(INDEX(Specials!B:J,MATCH(B38&" - Active",Specials!I:I,0),2),"")) | E38: Studio | F38: =COUNTIFS('Unit-Level Data'!L:L, ">=" & ($Q$2 - 7), 'Unit-Level Data'!L:L, "<" & $Q$2, 'Unit-Level Data'!G:G, 0, 'Unit-Level Data'!B:B, B38) -> 0 | G38: =COUNTIFS('Unit-Level Data'!L:L, ">=" & ($Q$2 - 7), 'Unit-Level Data'!L:L, "<" & $Q$2, 'Unit-Level Data'!G:G, 0, 'Unit-Level Data'!B:B, B38) - COUNTIFS('Unit-Level Data'!L:L, ">=" & ($Q$2 - 14), 'Unit-Level Data'!L:L, "<=" & ($Q$2 - 7), 'Unit-Level Data'!G:G, 0, 'Unit-Level Data'!B:B, B38) -> 0 | H38: =IFERROR(AVERAGEIFS('Unit-Level Data'!O:O,'Unit-Level Data'!L:L, ">=" & ($Q$2 - 7), 'Unit-Level Data'!L:L, "<" & $Q$2, 'Unit-Level Data'!G:G, 0, 'Unit-Level Data'!B:B, B38),"") | I38: =IFERROR( AVERAGEIFS('Unit-Level Data'!O:O, 'Unit-Level Data'!L:L, ">=" & ($Q$2 - 7), 'Unit-Level Data'!L:L, "<" & $Q$2, 'Unit-Level Data'!G:G, 0, 'Unit-Level Data'!B:B, B38) - AVERAGEIFS('Unit-Level Data'!O:O, 'Unit-Level Data'!L:L, ">=" & ($Q$2 - 14), 'Unit-Level Data'!L:L, "<=" & ($Q$2 - 7), 'Unit-Level Data'!G:G, 0, 'Unit-Level Data'!B:B, B38), 0) -> 0 | J38: =IFERROR(I38/AVERAGEIFS('Unit-Level Data'!O:O, 'Unit-Level Data'!L:L, ">=" & ($Q$2 - 14), 'Unit-Level Data'!L:L, "<=" & ($Q$2 - 7), 'Unit-Level Data'!G:G, 0, 'Unit-Level Data'!B:B, B38),0) -> 0 | K38: =COUNTIFS('Unit-Level Data'!K:K, ">=" & ($Q$2 - 7), 'Unit-Level Data'!K:K, "<" & $Q$2, 'Unit-Level Data'!G:G, 0, 'Unit-Level Data'!B:B, B38) -> 0 | L38: =COUNTIFS( 'Unit-Level Data'!K:K, ">=" & ($Q$2 - 7), 'Unit-Level Data'!K:K, "<" & $Q$2, 'Unit-Level Data'!G:G, 0, 'Unit-Level Data'!B:B, B38 ) - COUNTIFS( 'Unit-Level Data'!K:K, ">=" & ($Q$2 - 14), 'Unit-Level Data'!K:K, "<=" & ($Q$2 - 7), 'Unit-Level Data'!G:G, 0, 'Unit-Level Data'!B:B, B38 ) -> 0 | M38: =IFERROR(AVERAGEIFS('Unit-Level Data'!O:O,'Unit-Level Data'!K:K,">="&($Q$2-7), 'Unit-Level Data'!K:K,"<="&$Q$2, 'Unit-Level Data'!G:G,0, 'Unit-Level Data'!B:B,B38),"") | N38: =COUNTIFS('Unit-Level Data'!B:B, B38, 'Unit-Level Data'!G:G, 0, 'Unit-Level Data'!L:L, "") -> 0 | O38: =N38-(N38-K38+F38) -> 0 | P38: =IFERROR(AVERAGEIFS('Unit-Level Data'!O:O,'Unit-Level Data'!B:B, B38, 'Unit-Level Data'!G:G, 0, 'Unit-Level Data'!L:L, ""),"") | Q38: =IFERROR(N38/SUMIFS('Unit Mix'!G:G,'Unit Mix'!D:D,0,'Unit Mix'!B:B,B38),"")
B39: =IF(ISBLANK(OFFSET('Rent Comps'!$A$1,11,2)),"",OFFSET('Rent Comps'!$A$1,11,2)) | E39: 1 BR | F39: =COUNTIFS('Unit-Level Data'!L:L, ">=" & ($Q$2 - 7), 'Unit-Level Data'!L:L, "<" & $Q$2, 'Unit-Level Data'!G:G, 1, 'Unit-Level Data'!B:B, B38) -> 0 | G39: =COUNTIFS('Unit-Level Data'!L:L, ">=" & ($Q$2 - 7), 'Unit-Level Data'!L:L, "<" & $Q$2, 'Unit-Level Data'!G:G, 1, 'Unit-Level Data'!B:B, B38) - COUNTIFS('Unit-Level Data'!L:L, ">=" & ($Q$2 - 14), 'Unit-Level Data'!L:L, "<=" & ($Q$2 - 7), 'Unit-Level Data'!G:G, 1, 'Unit-Level Data'!B:B, B38) -> 0 | H39: =IFERROR(AVERAGEIFS('Unit-Level Data'!O:O,'Unit-Level Data'!L:L, ">=" & ($Q$2 - 7), 'Unit-Level Data'!L:L, "<" & $Q$2, 'Unit-Level Data'!G:G, 1, 'Unit-Level Data'!B:B, B38),"") | I39: =IFERROR( AVERAGEIFS('Unit-Level Data'!O:O, 'Unit-Level Data'!L:L, ">=" & ($Q$2 - 7), 'Unit-Level Data'!L:L, "<" & $Q$2, 'Unit-Level Data'!G:G, 1, 'Unit-Level Data'!B:B, B38) - AVERAGEIFS('Unit-Level Data'!O:O, 'Unit-Level Data'!L:L, ">=" & ($Q$2 - 14), 'Unit-Level Data'!L:L, "<=" & ($Q$2 - 7), 'Unit-Level Data'!G:G, 1, 'Unit-Level Data'!B:B, B38), 0) -> 0 | J39: =IFERROR(I39/AVERAGEIFS('Unit-Level Data'!O:O, 'Unit-Level Data'!L:L, ">=" & ($Q$2 - 14), 'Unit-Level Data'!L:L, "<=" & ($Q$2 - 7), 'Unit-Level Data'!G:G, 1, 'Unit-Level Data'!B:B, B38),0) -> 0 | K39: =COUNTIFS('Unit-Level Data'!K:K, ">=" & ($Q$2 - 7), 'Unit-Level Data'!K:K, "<" & $Q$2, 'Unit-Level Data'!G:G, 1, 'Unit-Level Data'!B:B, B38) -> 0 | L39: =COUNTIFS( 'Unit-Level Data'!K:K, ">=" & ($Q$2 - 7), 'Unit-Level Data'!K:K, "<" & $Q$2, 'Unit-Level Data'!G:G, 1, 'Unit-Level Data'!B:B, B38 ) - COUNTIFS( 'Unit-Level Data'!K:K, ">=" & ($Q$2 - 14), 'Unit-Level Data'!K:K, "<=" & ($Q$2 - 7), 'Unit-Level Data'!G:G, 1, 'Unit-Level Data'!B:B, B38 ) -> 0 | M39: =IFERROR(AVERAGEIFS('Unit-Level Data'!O:O,'Unit-Level Data'!K:K,">="&($Q$2-7), 'Unit-Level Data'!K:K,"<="&$Q$2, 'Unit-Level Data'!G:G,1, 'Unit-Level Data'!B:B,B38),"") | N39: =COUNTIFS('Unit-Level Data'!B:B, B38, 'Unit-Level Data'!G:G, 1, 'Unit-Level Data'!L:L, "") -> 0 | O39: =N39-(N39-K39+F39) -> 0 | P39: =IFERROR(AVERAGEIFS('Unit-Level Data'!O:O,'Unit-Level Data'!B:B, B38, 'Unit-Level Data'!G:G, 1, 'Unit-Level Data'!L:L, ""),"") | Q39: =IFERROR(N39/SUMIFS('Unit Mix'!G:G,'Unit Mix'!D:D,1,'Unit Mix'!B:B,B38),"")
B40: =IF(ISBLANK(OFFSET('Rent Comparison'!$A$1,2,13)),"",OFFSET('Rent Comparison'!$A$1,2,13)) | E40: 2 BR | F40: =COUNTIFS('Unit-Level Data'!L:L, ">=" & ($Q$2 - 7), 'Unit-Level Data'!L:L, "<" & $Q$2, 'Unit-Level Data'!G:G, 2, 'Unit-Level Data'!B:B, B38) -> 0 | G40: =COUNTIFS('Unit-Level Data'!L:L, ">=" & ($Q$2 - 7), 'Unit-Level Data'!L:L, "<" & $Q$2, 'Unit-Level Data'!G:G, 2, 'Unit-Level Data'!B:B, B38) - COUNTIFS('Unit-Level Data'!L:L, ">=" & ($Q$2 - 14), 'Unit-Level Data'!L:L, "<=" & ($Q$2 - 7), 'Unit-Level Data'!G:G, 2, 'Unit-Level Data'!B:B, B38) -> 0 | H40: =IFERROR(AVERAGEIFS('Unit-Level Data'!O:O,'Unit-Level Data'!L:L, ">=" & ($Q$2 - 7), 'Unit-Level Data'!L:L, "<" & $Q$2, 'Unit-Level Data'!G:G, 2, 'Unit-Level Data'!B:B, B38),"") | I40: =IFERROR( AVERAGEIFS('Unit-Level Data'!O:O, 'Unit-Level Data'!L:L, ">=" & ($Q$2 - 7), 'Unit-Level Data'!L:L, "<" & $Q$2, 'Unit-Level Data'!G:G, 2, 'Unit-Level Data'!B:B, B38) - AVERAGEIFS('Unit-Level Data'!O:O, 'Unit-Level Data'!L:L, ">=" & ($Q$2 - 14), 'Unit-Level Data'!L:L, "<=" & ($Q$2 - 7), 'Unit-Level Data'!G:G, 2, 'Unit-Level Data'!B:B, B38), 0) -> 0 | J40: =IFERROR(I40/AVERAGEIFS('Unit-Level Data'!O:O, 'Unit-Level Data'!L:L, ">=" & ($Q$2 - 14), 'Unit-Level Data'!L:L, "<=" & ($Q$2 - 7), 'Unit-Level Data'!G:G, 2, 'Unit-Level Data'!B:B, B38),0) -> 0 | K40: =COUNTIFS('Unit-Level Data'!K:K, ">=" & ($Q$2 - 7), 'Unit-Level Data'!K:K, "<" & $Q$2, 'Unit-Level Data'!G:G, 2, 'Unit-Level Data'!B:B, B38) -> 0 | L40: =COUNTIFS( 'Unit-Level Data'!K:K, ">=" & ($Q$2 - 7), 'Unit-Level Data'!K:K, "<" & $Q$2, 'Unit-Level Data'!G:G, 2, 'Unit-Level Data'!B:B, B38 ) - COUNTIFS( 'Unit-Level Data'!K:K, ">=" & ($Q$2 - 14), 'Unit-Level Data'!K:K, "<=" & ($Q$2 - 7), 'Unit-Level Data'!G:G, 2, 'Unit-Level Data'!B:B, B38 ) -> 0 | M40: =IFERROR(AVERAGEIFS('Unit-Level Data'!O:O,'Unit-Level Data'!K:K,">="&($Q$2-7), 'Unit-Level Data'!K:K,"<="&$Q$2, 'Unit-Level Data'!G:G,2, 'Unit-Level Data'!B:B,B38),"") | N40: =COUNTIFS('Unit-Level Data'!B:B, B38, 'Unit-Level Data'!G:G, 2, 'Unit-Level Data'!L:L, "") -> 0 | O40: =N40-(N40-K40+F40) -> 0 | P40: =IFERROR(AVERAGEIFS('Unit-Level Data'!O:O,'Unit-Level Data'!B:B, B38, 'Unit-Level Data'!G:G, 2, 'Unit-Level Data'!L:L, ""),"") | Q40: =IFERROR(N40/SUMIFS('Unit Mix'!G:G,'Unit Mix'!D:D,2,'Unit Mix'!B:B,B38),"")
B41: =IF(ISBLANK(OFFSET('Rent Comparison'!$A$1,3,13)),"",OFFSET('Rent Comparison'!$A$1,3,13)) | E41: 3 BR | F41: =COUNTIFS('Unit-Level Data'!L:L, ">=" & ($Q$2 - 7), 'Unit-Level Data'!L:L, "<" & $Q$2, 'Unit-Level Data'!G:G, 3, 'Unit-Level Data'!B:B, B38) -> 0 | G41: =COUNTIFS('Unit-Level Data'!L:L, ">=" & ($Q$2 - 7), 'Unit-Level Data'!L:L, "<" & $Q$2, 'Unit-Level Data'!G:G, 3, 'Unit-Level Data'!B:B, B38) - COUNTIFS('Unit-Level Data'!L:L, ">=" & ($Q$2 - 14), 'Unit-Level Data'!L:L, "<=" & ($Q$2 - 7), 'Unit-Level Data'!G:G, 3, 'Unit-Level Data'!B:B, B38) -> 0 | H41: =IFERROR(AVERAGEIFS('Unit-Level Data'!O:O,'Unit-Level Data'!L:L, ">=" & ($Q$2 - 7), 'Unit-Level Data'!L:L, "<" & $Q$2, 'Unit-Level Data'!G:G, 3, 'Unit-Level Data'!B:B, B38),"") | I41: =IFERROR( AVERAGEIFS('Unit-Level Data'!O:O, 'Unit-Level Data'!L:L, ">=" & ($Q$2 - 7), 'Unit-Level Data'!L:L, "<" & $Q$2, 'Unit-Level Data'!G:G, 3, 'Unit-Level Data'!B:B, B38) - AVERAGEIFS('Unit-Level Data'!O:O, 'Unit-Level Data'!L:L, ">=" & ($Q$2 - 14), 'Unit-Level Data'!L:L, "<=" & ($Q$2 - 7), 'Unit-Level Data'!G:G, 3, 'Unit-Level Data'!B:B, B38), 0) -> 0 | J41: =IFERROR(I41/AVERAGEIFS('Unit-Level Data'!O:O, 'Unit-Level Data'!L:L, ">=" & ($Q$2 - 14), 'Unit-Level Data'!L:L, "<=" & ($Q$2 - 7), 'Unit-Level Data'!G:G, 3, 'Unit-Level Data'!B:B, B38),0) -> 0 | K41: =COUNTIFS('Unit-Level Data'!K:K, ">=" & ($Q$2 - 7), 'Unit-Level Data'!K:K, "<" & $Q$2, 'Unit-Level Data'!G:G, 3, 'Unit-Level Data'!B:B, B38) -> 0 | L41: =COUNTIFS( 'Unit-Level Data'!K:K, ">=" & ($Q$2 - 7), 'Unit-Level Data'!K:K, "<" & $Q$2, 'Unit-Level Data'!G:G, 3, 'Unit-Level Data'!B:B, B38 ) - COUNTIFS( 'Unit-Level Data'!K:K, ">=" & ($Q$2 - 14), 'Unit-Level Data'!K:K, "<=" & ($Q$2 - 7), 'Unit-Level Data'!G:G, 3, 'Unit-Level Data'!B:B, B38 ) -> 0 | M41: =IFERROR(AVERAGEIFS('Unit-Level Data'!O:O,'Unit-Level Data'!K:K,">="&($Q$2-7), 'Unit-Level Data'!K:K,"<="&$Q$2, 'Unit-Level Data'!G:G,3, 'Unit-Level Data'!B:B,B38),"") | N41: =COUNTIFS('Unit-Level Data'!B:B, B38, 'Unit-Level Data'!G:G, 3, 'Unit-Level Data'!L:L, "") -> 0 | O41: =N41-(N41-K41+F41) -> 0 | P41: =IFERROR(AVERAGEIFS('Unit-Level Data'!O:O,'Unit-Level Data'!B:B, B38, 'Unit-Level Data'!G:G, 3, 'Unit-Level Data'!L:L, ""),"") | Q41: =IFERROR(N41/SUMIFS('Unit Mix'!G:G,'Unit Mix'!D:D,3,'Unit Mix'!B:B,B38),"")
B42: =IF(ISBLANK(OFFSET('Rent Comparison'!$A$1,1,14)),"",OFFSET('Rent Comparison'!$A$1,1,14)) | C42: =IF(ISBLANK(B42),"",IFERROR(INDEX(Specials!B:J,MATCH(B42&" - Active",Specials!I:I,0),2),"")) | E42: Studio | F42: =COUNTIFS('Unit-Level Data'!L:L, ">=" & ($Q$2 - 7), 'Unit-Level Data'!L:L, "<" & $Q$2, 'Unit-Level Data'!G:G, 0, 'Unit-Level Data'!B:B, B42) -> 0 | G42: =COUNTIFS('Unit-Level Data'!L:L, ">=" & ($Q$2 - 7), 'Unit-Level Data'!L:L, "<" & $Q$2, 'Unit-Level Data'!G:G, 0, 'Unit-Level Data'!B:B, B42) - COUNTIFS('Unit-Level Data'!L:L, ">=" & ($Q$2 - 14), 'Unit-Level Data'!L:L, "<=" & ($Q$2 - 7), 'Unit-Level Data'!G:G, 0, 'Unit-Level Data'!B:B, B42) -> 0 | H42: =IFERROR(AVERAGEIFS('Unit-Level Data'!O:O,'Unit-Level Data'!L:L, ">=" & ($Q$2 - 7), 'Unit-Level Data'!L:L, "<" & $Q$2, 'Unit-Level Data'!G:G, 0, 'Unit-Level Data'!B:B, B42),"") | I42: =IFERROR( AVERAGEIFS('Unit-Level Data'!O:O, 'Unit-Level Data'!L:L, ">=" & ($Q$2 - 7), 'Unit-Level Data'!L:L, "<" & $Q$2, 'Unit-Level Data'!G:G, 0, 'Unit-Level Data'!B:B, B42) - AVERAGEIFS('Unit-Level Data'!O:O, 'Unit-Level Data'!L:L, ">=" & ($Q$2 - 14), 'Unit-Level Data'!L:L, "<=" & ($Q$2 - 7), 'Unit-Level Data'!G:G, 0, 'Unit-Level Data'!B:B, B42), 0) -> 0 | J42: =IFERROR(I42/AVERAGEIFS('Unit-Level Data'!O:O, 'Unit-Level Data'!L:L, ">=" & ($Q$2 - 14), 'Unit-Level Data'!L:L, "<=" & ($Q$2 - 7), 'Unit-Level Data'!G:G, 0, 'Unit-Level Data'!B:B, B42),0) -> 0 | K42: =COUNTIFS('Unit-Level Data'!K:K, ">=" & ($Q$2 - 7), 'Unit-Level Data'!K:K, "<" & $Q$2, 'Unit-Level Data'!G:G, 0, 'Unit-Level Data'!B:B, B42) -> 0 | L42: =COUNTIFS( 'Unit-Level Data'!K:K, ">=" & ($Q$2 - 7), 'Unit-Level Data'!K:K, "<" & $Q$2, 'Unit-Level Data'!G:G, 0, 'Unit-Level Data'!B:B, B42 ) - COUNTIFS( 'Unit-Level Data'!K:K, ">=" & ($Q$2 - 14), 'Unit-Level Data'!K:K, "<=" & ($Q$2 - 7), 'Unit-Level Data'!G:G, 0, 'Unit-Level Data'!B:B, B42 ) -> 0 | M42: =IFERROR(AVERAGEIFS('Unit-Level Data'!O:O,'Unit-Level Data'!K:K,">="&($Q$2-7), 'Unit-Level Data'!K:K,"<="&$Q$2, 'Unit-Level Data'!G:G,0, 'Unit-Level Data'!B:B,B42),"") | N42: =COUNTIFS('Unit-Level Data'!B:B, B42, 'Unit-Level Data'!G:G, 0, 'Unit-Level Data'!L:L, "") -> 0 | O42: =N42-(N42-K42+F42) -> 0 | P42: =IFERROR(AVERAGEIFS('Unit-Level Data'!O:O,'Unit-Level Data'!B:B, B42, 'Unit-Level Data'!G:G, 0, 'Unit-Level Data'!L:L, ""),"") | Q42: =IFERROR(N42/SUMIFS('Unit Mix'!G:G,'Unit Mix'!D:D,0,'Unit Mix'!B:B,B42),"")
B43: =IF(ISBLANK(OFFSET('Rent Comps'!$A$1,12,2)),"",OFFSET('Rent Comps'!$A$1,12,2)) | E43: 1 BR | F43: =COUNTIFS('Unit-Level Data'!L:L, ">=" & ($Q$2 - 7), 'Unit-Level Data'!L:L, "<" & $Q$2, 'Unit-Level Data'!G:G, 1, 'Unit-Level Data'!B:B, B42) -> 0 | G43: =COUNTIFS('Unit-Level Data'!L:L, ">=" & ($Q$2 - 7), 'Unit-Level Data'!L:L, "<" & $Q$2, 'Unit-Level Data'!G:G, 1, 'Unit-Level Data'!B:B, B42) - COUNTIFS('Unit-Level Data'!L:L, ">=" & ($Q$2 - 14), 'Unit-Level Data'!L:L, "<=" & ($Q$2 - 7), 'Unit-Level Data'!G:G, 1, 'Unit-Level Data'!B:B, B42) -> 0 | H43: =IFERROR(AVERAGEIFS('Unit-Level Data'!O:O,'Unit-Level Data'!L:L, ">=" & ($Q$2 - 7), 'Unit-Level Data'!L:L, "<" & $Q$2, 'Unit-Level Data'!G:G, 1, 'Unit-Level Data'!B:B, B42),"") | I43: =IFERROR( AVERAGEIFS('Unit-Level Data'!O:O, 'Unit-Level Data'!L:L, ">=" & ($Q$2 - 7), 'Unit-Level Data'!L:L, "<" & $Q$2, 'Unit-Level Data'!G:G, 1, 'Unit-Level Data'!B:B, B42) - AVERAGEIFS('Unit-Level Data'!O:O, 'Unit-Level Data'!L:L, ">=" & ($Q$2 - 14), 'Unit-Level Data'!L:L, "<=" & ($Q$2 - 7), 'Unit-Level Data'!G:G, 1, 'Unit-Level Data'!B:B, B42), 0) -> 0 | J43: =IFERROR(I43/AVERAGEIFS('Unit-Level Data'!O:O, 'Unit-Level Data'!L:L, ">=" & ($Q$2 - 14), 'Unit-Level Data'!L:L, "<=" & ($Q$2 - 7), 'Unit-Level Data'!G:G, 1, 'Unit-Level Data'!B:B, B42),0) -> 0 | K43: =COUNTIFS('Unit-Level Data'!K:K, ">=" & ($Q$2 - 7), 'Unit-Level Data'!K:K, "<" & $Q$2, 'Unit-Level Data'!G:G, 1, 'Unit-Level Data'!B:B, B42) -> 0 | L43: =COUNTIFS( 'Unit-Level Data'!K:K, ">=" & ($Q$2 - 7), 'Unit-Level Data'!K:K, "<" & $Q$2, 'Unit-Level Data'!G:G, 1, 'Unit-Level Data'!B:B, B42 ) - COUNTIFS( 'Unit-Level Data'!K:K, ">=" & ($Q$2 - 14), 'Unit-Level Data'!K:K, "<=" & ($Q$2 - 7), 'Unit-Level Data'!G:G, 1, 'Unit-Level Data'!B:B, B42 ) -> 0 | M43: =IFERROR(AVERAGEIFS('Unit-Level Data'!O:O,'Unit-Level Data'!K:K,">="&($Q$2-7), 'Unit-Level Data'!K:K,"<="&$Q$2, 'Unit-Level Data'!G:G,1, 'Unit-Level Data'!B:B,B42),"") | N43: =COUNTIFS('Unit-Level Data'!B:B, B42, 'Unit-Level Data'!G:G, 1, 'Unit-Level Data'!L:L, "") -> 0 | O43: =N43-(N43-K43+F43) -> 0 | P43: =IFERROR(AVERAGEIFS('Unit-Level Data'!O:O,'Unit-Level Data'!B:B, B42, 'Unit-Level Data'!G:G, 1, 'Unit-Level Data'!L:L, ""),"") | Q43: =IFERROR(N43/SUMIFS('Unit Mix'!G:G,'Unit Mix'!D:D,1,'Unit Mix'!B:B,B42),"")
B44: =IF(ISBLANK(OFFSET('Rent Comparison'!$A$1,2,14)),"",OFFSET('Rent Comparison'!$A$1,2,14)) | E44: 2 BR | F44: =COUNTIFS('Unit-Level Data'!L:L, ">=" & ($Q$2 - 7), 'Unit-Level Data'!L:L, "<" & $Q$2, 'Unit-Level Data'!G:G, 2, 'Unit-Level Data'!B:B, B42) -> 0 | G44: =COUNTIFS('Unit-Level Data'!L:L, ">=" & ($Q$2 - 7), 'Unit-Level Data'!L:L, "<" & $Q$2, 'Unit-Level Data'!G:G, 2, 'Unit-Level Data'!B:B, B42) - COUNTIFS('Unit-Level Data'!L:L, ">=" & ($Q$2 - 14), 'Unit-Level Data'!L:L, "<=" & ($Q$2 - 7), 'Unit-Level Data'!G:G, 2, 'Unit-Level Data'!B:B, B42) -> 0 | H44: =IFERROR(AVERAGEIFS('Unit-Level Data'!O:O,'Unit-Level Data'!L:L, ">=" & ($Q$2 - 7), 'Unit-Level Data'!L:L, "<" & $Q$2, 'Unit-Level Data'!G:G, 2, 'Unit-Level Data'!B:B, B42),"") | I44: =IFERROR( AVERAGEIFS('Unit-Level Data'!O:O, 'Unit-Level Data'!L:L, ">=" & ($Q$2 - 7), 'Unit-Level Data'!L:L, "<" & $Q$2, 'Unit-Level Data'!G:G, 2, 'Unit-Level Data'!B:B, B42) - AVERAGEIFS('Unit-Level Data'!O:O, 'Unit-Level Data'!L:L, ">=" & ($Q$2 - 14), 'Unit-Level Data'!L:L, "<=" & ($Q$2 - 7), 'Unit-Level Data'!G:G, 2, 'Unit-Level Data'!B:B, B42), 0) -> 0 | J44: =IFERROR(I44/AVERAGEIFS('Unit-Level Data'!O:O, 'Unit-Level Data'!L:L, ">=" & ($Q$2 - 14), 'Unit-Level Data'!L:L, "<=" & ($Q$2 - 7), 'Unit-Level Data'!G:G, 2, 'Unit-Level Data'!B:B, B42),0) -> 0 | K44: =COUNTIFS('Unit-Level Data'!K:K, ">=" & ($Q$2 - 7), 'Unit-Level Data'!K:K, "<" & $Q$2, 'Unit-Level Data'!G:G, 2, 'Unit-Level Data'!B:B, B42) -> 0 | L44: =COUNTIFS( 'Unit-Level Data'!K:K, ">=" & ($Q$2 - 7), 'Unit-Level Data'!K:K, "<" & $Q$2, 'Unit-Level Data'!G:G, 2, 'Unit-Level Data'!B:B, B42 ) - COUNTIFS( 'Unit-Level Data'!K:K, ">=" & ($Q$2 - 14), 'Unit-Level Data'!K:K, "<=" & ($Q$2 - 7), 'Unit-Level Data'!G:G, 2, 'Unit-Level Data'!B:B, B42 ) -> 0 | M44: =IFERROR(AVERAGEIFS('Unit-Level Data'!O:O,'Unit-Level Data'!K:K,">="&($Q$2-7), 'Unit-Level Data'!K:K,"<="&$Q$2, 'Unit-Level Data'!G:G,2, 'Unit-Level Data'!B:B,B42),"") | N44: =COUNTIFS('Unit-Level Data'!B:B, B42, 'Unit-Level Data'!G:G, 2, 'Unit-Level Data'!L:L, "") -> 0 | O44: =N44-(N44-K44+F44) -> 0 | P44: =IFERROR(AVERAGEIFS('Unit-Level Data'!O:O,'Unit-Level Data'!B:B, B42, 'Unit-Level Data'!G:G, 2, 'Unit-Level Data'!L:L, ""),"") | Q44: =IFERROR(N44/SUMIFS('Unit Mix'!G:G,'Unit Mix'!D:D,2,'Unit Mix'!B:B,B42),"")
B45: =IF(ISBLANK(OFFSET('Rent Comparison'!$A$1,3,14)),"",OFFSET('Rent Comparison'!$A$1,3,14)) | E45: 3 BR | F45: =COUNTIFS('Unit-Level Data'!L:L, ">=" & ($Q$2 - 7), 'Unit-Level Data'!L:L, "<" & $Q$2, 'Unit-Level Data'!G:G, 3, 'Unit-Level Data'!B:B, B42) -> 0 | G45: =COUNTIFS('Unit-Level Data'!L:L, ">=" & ($Q$2 - 7), 'Unit-Level Data'!L:L, "<" & $Q$2, 'Unit-Level Data'!G:G, 3, 'Unit-Level Data'!B:B, B42) - COUNTIFS('Unit-Level Data'!L:L, ">=" & ($Q$2 - 14), 'Unit-Level Data'!L:L, "<=" & ($Q$2 - 7), 'Unit-Level Data'!G:G, 3, 'Unit-Level Data'!B:B, B42) -> 0 | H45: =IFERROR(AVERAGEIFS('Unit-Level Data'!O:O,'Unit-Level Data'!L:L, ">=" & ($Q$2 - 7), 'Unit-Level Data'!L:L, "<" & $Q$2, 'Unit-Level Data'!G:G, 3, 'Unit-Level Data'!B:B, B42),"") | I45: =IFERROR( AVERAGEIFS('Unit-Level Data'!O:O, 'Unit-Level Data'!L:L, ">=" & ($Q$2 - 7), 'Unit-Level Data'!L:L, "<" & $Q$2, 'Unit-Level Data'!G:G, 3, 'Unit-Level Data'!B:B, B42) - AVERAGEIFS('Unit-Level Data'!O:O, 'Unit-Level Data'!L:L, ">=" & ($Q$2 - 14), 'Unit-Level Data'!L:L, "<=" & ($Q$2 - 7), 'Unit-Level Data'!G:G, 3, 'Unit-Level Data'!B:B, B42), 0) -> 0 | J45: =IFERROR(I45/AVERAGEIFS('Unit-Level Data'!O:O, 'Unit-Level Data'!L:L, ">=" & ($Q$2 - 14), 'Unit-Level Data'!L:L, "<=" & ($Q$2 - 7), 'Unit-Level Data'!G:G, 3, 'Unit-Level Data'!B:B, B42),0) -> 0 | K45: =COUNTIFS('Unit-Level Data'!K:K, ">=" & ($Q$2 - 7), 'Unit-Level Data'!K:K, "<" & $Q$2, 'Unit-Level Data'!G:G, 3, 'Unit-Level Data'!B:B, B42) -> 0 | L45: =COUNTIFS( 'Unit-Level Data'!K:K, ">=" & ($Q$2 - 7), 'Unit-Level Data'!K:K, "<" & $Q$2, 'Unit-Level Data'!G:G, 3, 'Unit-Level Data'!B:B, B42 ) - COUNTIFS( 'Unit-Level Data'!K:K, ">=" & ($Q$2 - 14), 'Unit-Level Data'!K:K, "<=" & ($Q$2 - 7), 'Unit-Level Data'!G:G, 3, 'Unit-Level Data'!B:B, B42 ) -> 0 | M45: =IFERROR(AVERAGEIFS('Unit-Level Data'!O:O,'Unit-Level Data'!K:K,">="&($Q$2-7), 'Unit-Level Data'!K:K,"<="&$Q$2, 'Unit-Level Data'!G:G,3, 'Unit-Level Data'!B:B,B42),"") | N45: =COUNTIFS('Unit-Level Data'!B:B, B42, 'Unit-Level Data'!G:G, 3, 'Unit-Level Data'!L:L, "") -> 0 | O45: =N45-(N45-K45+F45) -> 0 | P45: =IFERROR(AVERAGEIFS('Unit-Level Data'!O:O,'Unit-Level Data'!B:B, B42, 'Unit-Level Data'!G:G, 3, 'Unit-Level Data'!L:L, ""),"") | Q45: =IFERROR(N45/SUMIFS('Unit Mix'!G:G,'Unit Mix'!D:D,3,'Unit Mix'!B:B,B42),"")
B46: =IF(ISBLANK(OFFSET('Rent Comparison'!$A$1,1,15)),"",OFFSET('Rent Comparison'!$A$1,1,15)) | C46: =IF(ISBLANK(B46),"",IFERROR(INDEX(Specials!B:J,MATCH(B46&" - Active",Specials!I:I,0),2),"")) | E46: Studio | F46: =COUNTIFS('Unit-Level Data'!L:L, ">=" & ($Q$2 - 7), 'Unit-Level Data'!L:L, "<" & $Q$2, 'Unit-Level Data'!G:G, 0, 'Unit-Level Data'!B:B, B46) -> 0 | G46: =COUNTIFS('Unit-Level Data'!L:L, ">=" & ($Q$2 - 7), 'Unit-Level Data'!L:L, "<" & $Q$2, 'Unit-Level Data'!G:G, 0, 'Unit-Level Data'!B:B, B46) - COUNTIFS('Unit-Level Data'!L:L, ">=" & ($Q$2 - 14), 'Unit-Level Data'!L:L, "<=" & ($Q$2 - 7), 'Unit-Level Data'!G:G, 0, 'Unit-Level Data'!B:B, B46) -> 0 | H46: =IFERROR(AVERAGEIFS('Unit-Level Data'!O:O,'Unit-Level Data'!L:L, ">=" & ($Q$2 - 7), 'Unit-Level Data'!L:L, "<" & $Q$2, 'Unit-Level Data'!G:G, 0, 'Unit-Level Data'!B:B, B46),"") | I46: =IFERROR( AVERAGEIFS('Unit-Level Data'!O:O, 'Unit-Level Data'!L:L, ">=" & ($Q$2 - 7), 'Unit-Level Data'!L:L, "<" & $Q$2, 'Unit-Level Data'!G:G, 0, 'Unit-Level Data'!B:B, B46) - AVERAGEIFS('Unit-Level Data'!O:O, 'Unit-Level Data'!L:L, ">=" & ($Q$2 - 14), 'Unit-Level Data'!L:L, "<=" & ($Q$2 - 7), 'Unit-Level Data'!G:G, 0, 'Unit-Level Data'!B:B, B46), 0) -> 0 | J46: =IFERROR(I46/AVERAGEIFS('Unit-Level Data'!O:O, 'Unit-Level Data'!L:L, ">=" & ($Q$2 - 14), 'Unit-Level Data'!L:L, "<=" & ($Q$2 - 7), 'Unit-Level Data'!G:G, 0, 'Unit-Level Data'!B:B, B46),0) -> 0 | K46: =COUNTIFS('Unit-Level Data'!K:K, ">=" & ($Q$2 - 7), 'Unit-Level Data'!K:K, "<" & $Q$2, 'Unit-Level Data'!G:G, 0, 'Unit-Level Data'!B:B, B46) -> 0 | L46: =COUNTIFS( 'Unit-Level Data'!K:K, ">=" & ($Q$2 - 7), 'Unit-Level Data'!K:K, "<" & $Q$2, 'Unit-Level Data'!G:G, 0, 'Unit-Level Data'!B:B, B46 ) - COUNTIFS( 'Unit-Level Data'!K:K, ">=" & ($Q$2 - 14), 'Unit-Level Data'!K:K, "<=" & ($Q$2 - 7), 'Unit-Level Data'!G:G, 0, 'Unit-Level Data'!B:B, B46 ) -> 0 | M46: =IFERROR(AVERAGEIFS('Unit-Level Data'!O:O,'Unit-Level Data'!K:K,">="&($Q$2-7), 'Unit-Level Data'!K:K,"<="&$Q$2, 'Unit-Level Data'!G:G,0, 'Unit-Level Data'!B:B,B46),"") | N46: =COUNTIFS('Unit-Level Data'!B:B, B46, 'Unit-Level Data'!G:G, 0, 'Unit-Level Data'!L:L, "") -> 0 | O46: =N46-(N46-K46+F46) -> 0 | P46: =IFERROR(AVERAGEIFS('Unit-Level Data'!O:O,'Unit-Level Data'!B:B, B46, 'Unit-Level Data'!G:G, 0, 'Unit-Level Data'!L:L, ""),"") | Q46: =IFERROR(N46/SUMIFS('Unit Mix'!G:G,'Unit Mix'!D:D,0,'Unit Mix'!B:B,B46),"")
B47: =IF(ISBLANK(OFFSET('Rent Comps'!$A$1,13,2)),"",OFFSET('Rent Comps'!$A$1,13,2)) | E47: 1 BR | F47: =COUNTIFS('Unit-Level Data'!L:L, ">=" & ($Q$2 - 7), 'Unit-Level Data'!L:L, "<" & $Q$2, 'Unit-Level Data'!G:G, 1, 'Unit-Level Data'!B:B, B46) -> 0 | G47: =COUNTIFS('Unit-Level Data'!L:L, ">=" & ($Q$2 - 7), 'Unit-Level Data'!L:L, "<" & $Q$2, 'Unit-Level Data'!G:G, 1, 'Unit-Level Data'!B:B, B46) - COUNTIFS('Unit-Level Data'!L:L, ">=" & ($Q$2 - 14), 'Unit-Level Data'!L:L, "<=" & ($Q$2 - 7), 'Unit-Level Data'!G:G, 1, 'Unit-Level Data'!B:B, B46) -> 0 | H47: =IFERROR(AVERAGEIFS('Unit-Level Data'!O:O,'Unit-Level Data'!L:L, ">=" & ($Q$2 - 7), 'Unit-Level Data'!L:L, "<" & $Q$2, 'Unit-Level Data'!G:G, 1, 'Unit-Level Data'!B:B, B46),"") | I47: =IFERROR( AVERAGEIFS('Unit-Level Data'!O:O, 'Unit-Level Data'!L:L, ">=" & ($Q$2 - 7), 'Unit-Level Data'!L:L, "<" & $Q$2, 'Unit-Level Data'!G:G, 1, 'Unit-Level Data'!B:B, B46) - AVERAGEIFS('Unit-Level Data'!O:O, 'Unit-Level Data'!L:L, ">=" & ($Q$2 - 14), 'Unit-Level Data'!L:L, "<=" & ($Q$2 - 7), 'Unit-Level Data'!G:G, 1, 'Unit-Level Data'!B:B, B46), 0) -> 0 | J47: =IFERROR(I47/AVERAGEIFS('Unit-Level Data'!O:O, 'Unit-Level Data'!L:L, ">=" & ($Q$2 - 14), 'Unit-Level Data'!L:L, "<=" & ($Q$2 - 7), 'Unit-Level Data'!G:G, 1, 'Unit-Level Data'!B:B, B46),0) -> 0 | K47: =COUNTIFS('Unit-Level Data'!K:K, ">=" & ($Q$2 - 7), 'Unit-Level Data'!K:K, "<" & $Q$2, 'Unit-Level Data'!G:G, 1, 'Unit-Level Data'!B:B, B46) -> 0 | L47: =COUNTIFS( 'Unit-Level Data'!K:K, ">=" & ($Q$2 - 7), 'Unit-Level Data'!K:K, "<" & $Q$2, 'Unit-Level Data'!G:G, 1, 'Unit-Level Data'!B:B, B46 ) - COUNTIFS( 'Unit-Level Data'!K:K, ">=" & ($Q$2 - 14), 'Unit-Level Data'!K:K, "<=" & ($Q$2 - 7), 'Unit-Level Data'!G:G, 1, 'Unit-Level Data'!B:B, B46 ) -> 0 | M47: =IFERROR(AVERAGEIFS('Unit-Level Data'!O:O,'Unit-Level Data'!K:K,">="&($Q$2-7), 'Unit-Level Data'!K:K,"<="&$Q$2, 'Unit-Level Data'!G:G,1, 'Unit-Level Data'!B:B,B46),"") | N47: =COUNTIFS('Unit-Level Data'!B:B, B46, 'Unit-Level Data'!G:G, 1, 'Unit-Level Data'!L:L, "") -> 0 | O47: =N47-(N47-K47+F47) -> 0 | P47: =IFERROR(AVERAGEIFS('Unit-Level Data'!O:O,'Unit-Level Data'!B:B, B46, 'Unit-Level Data'!G:G, 1, 'Unit-Level Data'!L:L, ""),"") | Q47: =IFERROR(N47/SUMIFS('Unit Mix'!G:G,'Unit Mix'!D:D,1,'Unit Mix'!B:B,B46),"")
B48: =IF(ISBLANK(OFFSET('Rent Comparison'!$A$1,2,15)),"",OFFSET('Rent Comparison'!$A$1,2,15)) | E48: 2 BR | F48: =COUNTIFS('Unit-Level Data'!L:L, ">=" & ($Q$2 - 7), 'Unit-Level Data'!L:L, "<" & $Q$2, 'Unit-Level Data'!G:G, 2, 'Unit-Level Data'!B:B, B46) -> 0 | G48: =COUNTIFS('Unit-Level Data'!L:L, ">=" & ($Q$2 - 7), 'Unit-Level Data'!L:L, "<" & $Q$2, 'Unit-Level Data'!G:G, 2, 'Unit-Level Data'!B:B, B46) - COUNTIFS('Unit-Level Data'!L:L, ">=" & ($Q$2 - 14), 'Unit-Level Data'!L:L, "<=" & ($Q$2 - 7), 'Unit-Level Data'!G:G, 2, 'Unit-Level Data'!B:B, B46) -> 0 | H48: =IFERROR(AVERAGEIFS('Unit-Level Data'!O:O,'Unit-Level Data'!L:L, ">=" & ($Q$2 - 7), 'Unit-Level Data'!L:L, "<" & $Q$2, 'Unit-Level Data'!G:G, 2, 'Unit-Level Data'!B:B, B46),"") | I48: =IFERROR( AVERAGEIFS('Unit-Level Data'!O:O, 'Unit-Level Data'!L:L, ">=" & ($Q$2 - 7), 'Unit-Level Data'!L:L, "<" & $Q$2, 'Unit-Level Data'!G:G, 2, 'Unit-Level Data'!B:B, B46) - AVERAGEIFS('Unit-Level Data'!O:O, 'Unit-Level Data'!L:L, ">=" & ($Q$2 - 14), 'Unit-Level Data'!L:L, "<=" & ($Q$2 - 7), 'Unit-Level Data'!G:G, 2, 'Unit-Level Data'!B:B, B46), 0) -> 0 | J48: =IFERROR(I48/AVERAGEIFS('Unit-Level Data'!O:O, 'Unit-Level Data'!L:L, ">=" & ($Q$2 - 14), 'Unit-Level Data'!L:L, "<=" & ($Q$2 - 7), 'Unit-Level Data'!G:G, 2, 'Unit-Level Data'!B:B, B46),0) -> 0 | K48: =COUNTIFS('Unit-Level Data'!K:K, ">=" & ($Q$2 - 7), 'Unit-Level Data'!K:K, "<" & $Q$2, 'Unit-Level Data'!G:G, 2, 'Unit-Level Data'!B:B, B46) -> 0 | L48: =COUNTIFS( 'Unit-Level Data'!K:K, ">=" & ($Q$2 - 7), 'Unit-Level Data'!K:K, "<" & $Q$2, 'Unit-Level Data'!G:G, 2, 'Unit-Level Data'!B:B, B46 ) - COUNTIFS( 'Unit-Level Data'!K:K, ">=" & ($Q$2 - 14), 'Unit-Level Data'!K:K, "<=" & ($Q$2 - 7), 'Unit-Level Data'!G:G, 2, 'Unit-Level Data'!B:B, B46 ) -> 0 | M48: =IFERROR(AVERAGEIFS('Unit-Level Data'!O:O,'Unit-Level Data'!K:K,">="&($Q$2-7), 'Unit-Level Data'!K:K,"<="&$Q$2, 'Unit-Level Data'!G:G,2, 'Unit-Level Data'!B:B,B46),"") | N48: =COUNTIFS('Unit-Level Data'!B:B, B46, 'Unit-Level Data'!G:G, 2, 'Unit-Level Data'!L:L, "") -> 0 | O48: =N48-(N48-K48+F48) -> 0 | P48: =IFERROR(AVERAGEIFS('Unit-Level Data'!O:O,'Unit-Level Data'!B:B, B46, 'Unit-Level Data'!G:G, 2, 'Unit-Level Data'!L:L, ""),"") | Q48: =IFERROR(N48/SUMIFS('Unit Mix'!G:G,'Unit Mix'!D:D,2,'Unit Mix'!B:B,B46),"")
B49: =IF(ISBLANK(OFFSET('Rent Comparison'!$A$1,3,15)),"",OFFSET('Rent Comparison'!$A$1,3,15)) | E49: 3 BR | F49: =COUNTIFS('Unit-Level Data'!L:L, ">=" & ($Q$2 - 7), 'Unit-Level Data'!L:L, "<" & $Q$2, 'Unit-Level Data'!G:G, 3, 'Unit-Level Data'!B:B, B46) -> 0 | G49: =COUNTIFS('Unit-Level Data'!L:L, ">=" & ($Q$2 - 7), 'Unit-Level Data'!L:L, "<" & $Q$2, 'Unit-Level Data'!G:G, 3, 'Unit-Level Data'!B:B, B46) - COUNTIFS('Unit-Level Data'!L:L, ">=" & ($Q$2 - 14), 'Unit-Level Data'!L:L, "<=" & ($Q$2 - 7), 'Unit-Level Data'!G:G, 3, 'Unit-Level Data'!B:B, B46) -> 0 | H49: =IFERROR(AVERAGEIFS('Unit-Level Data'!O:O,'Unit-Level Data'!L:L, ">=" & ($Q$2 - 7), 'Unit-Level Data'!L:L, "<" & $Q$2, 'Unit-Level Data'!G:G, 3, 'Unit-Level Data'!B:B, B46),"") | I49: =IFERROR( AVERAGEIFS('Unit-Level Data'!O:O, 'Unit-Level Data'!L:L, ">=" & ($Q$2 - 7), 'Unit-Level Data'!L:L, "<" & $Q$2, 'Unit-Level Data'!G:G, 3, 'Unit-Level Data'!B:B, B46) - AVERAGEIFS('Unit-Level Data'!O:O, 'Unit-Level Data'!L:L, ">=" & ($Q$2 - 14), 'Unit-Level Data'!L:L, "<=" & ($Q$2 - 7), 'Unit-Level Data'!G:G, 3, 'Unit-Level Data'!B:B, B46), 0) -> 0 | J49: =IFERROR(I49/AVERAGEIFS('Unit-Level Data'!O:O, 'Unit-Level Data'!L:L, ">=" & ($Q$2 - 14), 'Unit-Level Data'!L:L, "<=" & ($Q$2 - 7), 'Unit-Level Data'!G:G, 3, 'Unit-Level Data'!B:B, B46),0) -> 0 | K49: =COUNTIFS('Unit-Level Data'!K:K, ">=" & ($Q$2 - 7), 'Unit-Level Data'!K:K, "<" & $Q$2, 'Unit-Level Data'!G:G, 3, 'Unit-Level Data'!B:B, B46) -> 0 | L49: =COUNTIFS( 'Unit-Level Data'!K:K, ">=" & ($Q$2 - 7), 'Unit-Level Data'!K:K, "<" & $Q$2, 'Unit-Level Data'!G:G, 3, 'Unit-Level Data'!B:B, B46 ) - COUNTIFS( 'Unit-Level Data'!K:K, ">=" & ($Q$2 - 14), 'Unit-Level Data'!K:K, "<=" & ($Q$2 - 7), 'Unit-Level Data'!G:G, 3, 'Unit-Level Data'!B:B, B46 ) -> 0 | M49: =IFERROR(AVERAGEIFS('Unit-Level Data'!O:O,'Unit-Level Data'!K:K,">="&($Q$2-7), 'Unit-Level Data'!K:K,"<="&$Q$2, 'Unit-Level Data'!G:G,3, 'Unit-Level Data'!B:B,B46),"") | N49: =COUNTIFS('Unit-Level Data'!B:B, B46, 'Unit-Level Data'!G:G, 3, 'Unit-Level Data'!L:L, "") -> 0 | O49: =N49-(N49-K49+F49) -> 0 | P49: =IFERROR(AVERAGEIFS('Unit-Level Data'!O:O,'Unit-Level Data'!B:B, B46, 'Unit-Level Data'!G:G, 3, 'Unit-Level Data'!L:L, ""),"") | Q49: =IFERROR(N49/SUMIFS('Unit Mix'!G:G,'Unit Mix'!D:D,3,'Unit Mix'!B:B,B46),"")

Sheet 30-Day Trends
B2: Hillendale Gate Apartments | O2: Report Date: | P2: 45785
B3: 30-Day Trend Analysis. Note: Figures and charts on the 30-Day Trends tab include active listings and listings that closed in the last 30-Days.
C5: Avg Rent | D5: Avg Rent PSF | E5: Effective Rent | F5: Effective Rent PSF | G5: Avg Concession Amt | H5: Leased % | J5: Exposure %
B6: Hillendale Gate Apartments | C6: =IF(ISNUMBER(OFFSET('Rent Comps'!A1,3,24))=TRUE,OFFSET('Rent Comps'!A1,3,24),"") | D6: =IF(ISNUMBER(OFFSET('Rent Comps'!A1,3,25))=TRUE,OFFSET('Rent Comps'!A1,3,25),"") | E6: =IF(ISNUMBER(OFFSET('Rent Comps'!A1,3,38))=TRUE,OFFSET('Rent Comps'!A1,3,38),"") | F6: =IF(ISNUMBER(OFFSET('Rent Comps'!A1,3,39))=TRUE,OFFSET('Rent Comps'!A1,3,39),"") | G6: =IFERROR((C6-E6)/C6,"") | H6: =IF(ISNUMBER(OFFSET('Rent Comps'!A1,3,10))=TRUE,OFFSET('Rent Comps'!A1,3,10),"") | J6: =IF(ISNUMBER(OFFSET('Rent Comps'!A1,3,11))=TRUE,OFFSET('Rent Comps'!A1,3,11),"")
B7: Comps Average | C7: =GETPIVOTDATA("Asking Rent",Data!$A$3) -> 3192.1308 | D7: =GETPIVOTDATA("Asking PSF",Data!$A$3) -> 3.98607 | E7: =GETPIVOTDATA("Effective Rent",Data!$E$3) -> 3184.9308 | F7: =GETPIVOTDATA("Effective PSF",Data!$E$3) -> 3.9778373 | G7: =(C7-E7)/C7 -> 0.0022555466 | H7: =GETPIVOTDATA("Average of Leased %",Data!$AG$3) -> 0.96888804 | J7: =GETPIVOTDATA("Average of Exposure %",Data!$AG$3) -> 0.058139407
B8: Difference | C8: =IFERROR(C6-C7,0) -> 0 | D8: =IFERROR(D6-D7,0) -> 0 | E8: =IFERROR(E6-E7,0) -> 0 | F8: =IFERROR(F6-F7,0) -> 0 | G8: =IFERROR(G6-G7,0) -> 0 | H8: =IFERROR(H6-H7,0) -> 0 | J8: =IFERROR(J6-J7,0) -> 0
C9: =IFERROR(IF(C6-C7>0,"above market","below market"),"") | D9: =IFERROR(IF(D6-D7>0,"above market","below market"),"") | E9: =IFERROR(IF(E6-E7>0,"above market","below market"),"") | F9: =IFERROR(IF(F6-F7>0,"above market","below market"),"") | G9: =IFERROR(IF(G6-G7>0,"above market","below market"),"") | H9: =IFERROR(IF(H6-H7>0,"above market","below market"),"") | J9: =IFERROR(IF(J6-J7>0,"above market","below market"),"")
B11: Asking Rents: 30-Day Avg | J11: Effective Rents: 30-Day Avg

Sheet Data
A1: 30-Day Averages | AM1: Analytics Tab
A2: Asking Rent vs Rent PSF | E2: Effective Rent vs Rent PSF | I2: Studio Asking vs Effective | M2: 1BR Asking vs Effective | Q2: 2BR Asking vs Effective | U2: 3BR Asking vs Effective | Y2: 4BR Asking vs Effective | AC2: 5BR Asking vs Effective | AG2: Concession %
A3: Row Labels | B3: Asking Rent | C3: Asking PSF | E3: Row Labels | F3: Effective Rent | G3: Effective PSF | I3: Row Labels | J3: Asking | K3: Effective | M3: Row Labels | N3: Asking | O3: Effective | Q3: Row Labels | R3: Asking | S3: Effective | U3: Row Labels | V3: Asking | W3: Effective | Y3: Row Labels | Z3: Asking | AA3: Effective | AC3: Row Labels | AD3: Asking | AE3: Effective | AG3: Row Labels | AH3: Average of Leased % | AI3: Average of Exposure % | AM3: Row Labels | AN3: Average of Days on Mkt | AP3: Active Listing? | AQ3: TRUE | AS3: Row Labels | AT3: Average of Days on Mkt | AZ3: Active Listing? | BA3: TRUE | BH3: Active Listing? | BI3: TRUE | BU3: Row Labels | BV3: Average of Days on Mkt | BX3: Row Labels | BY3: Leased % | BZ3: Exposure % | CB3: Average of Asking Rent | CJ3: Row Labels | CK3: Average of Asking PSF | CL3: Effective Rent PSF | CN3: Row Labels | CO3: Average of Asking Rent | CP3: Average of Effective Rent | CR3: Row Labels | CS3: Avg Days on Mkt | CU3: Row Labels | CV3: # Leases
A4: Marquee at Block 37 | B4: 2647.7447 | C4: 3.4232113 | E4: Marquee at Block 37 | F4: 2647.7447 | G4: 3.4232113 | I4: Hubbard Place | J4: 2194 | K4: 2194 | M4: MILA | N4: 2728.2857 | O4: 2728.2857 | Q4: Marquee at Block 37 | R4: 3897.4 | S4: 3897.4 | U4: Coast at Lakeshore East | V4: 6418.5 | W4: 6418.5 | Y4: The Gallery on Wells | Z4: 4500 | AA4: 4500 | AC4: OneEleven | AG4: OneEleven | AH4: 0.97425743 | AI4: 0.043564356 | AM4: Coast at Lakeshore East | AN4: 44.978102 | AS4: 4BR | AT4: 24 | BU4: Coast at Lakeshore East | BV4: 44.978102 | BX4: OneEleven | BY4: 0.97425743 | BZ4: 0.043564356 | CB4: Row Labels | CC4: 0 | CD4: 1 | CE4: 2 | CF4: 3 | CG4: 4 | CJ4: 2023 | CN4: 2023 | CO4: 3102.1345 | CP4: 3083.7213 | CR4: 2023 | CU4: 2023
A5: MILA | B5: 2758.75 | C5: 3.7859165 | E5: MILA | F5: 2758.75 | G5: 3.7859165 | I5: Coast at Lakeshore East | J5: 2210.9412 | K5: 2210.9412 | M5: Marquee at Block 37 | N5: 2772.8 | O5: 2772.8 | Q5: MILA | R5: 3900.6667 | S5: 3900.6667 | U5: Optima Signature | V5: 6740.8889 | W5: 6740.8889 | Y5: OneEleven | Z5: 5000 | AA5: 5000 | AC5: MILA | AD5: 8000 | AE5: 8000 | AG5: MILA | AH5: 0.96268657 | AI5: 0.062189055 | AM5: Wolf Point West | AN5: 49.86 | AP5: Row Labels | AQ5: Count of Asking Rent | AS5: 1BR | AT5: 57.252964 | AV5: Row Labels | AW5: Average of Asking Rent | AX5: Average of Effective Rent | AZ5: Row Labels | BA5: Average of Asking Rent | BB5: Average of Effective Rent | BD5: Row Labels | BE5: Average of Asking PSF | BF5: Average of Effective PSF | BH5: Row Labels | BI5: Average of Asking PSF | BJ5: Average of Effective PSF | BL5: Row Labels | BM5: Average of Concessions as % of Asking Rent | BO5: Row Labels | BP5: Average of Concessions as % of Asking Rent | BR5: Row Labels | BS5: Avg Sqft | BU5: Wolf Point West | BV5: 49.86 | BX5: MILA | BY5: 0.96268657 | BZ5: 0.062189055 | CB5: 2023 | CJ5: Jul | CK5: 3.8981631 | CL5: 3.8695673 | CN5: Jul | CO5: 3012.1188 | CP5: 2993.5248 | CR5: Jul | CS5: 11.75 | CU5: Jul | CV5: 101
A6: Coast at Lakeshore East | B6: 2935.2195 | C6: 3.9756855 | E6: Coast at Lakeshore East | F6: 2935.2195 | G6: 3.9756855 | I6: Wolf Point West | J6: 2277.6429 | K6: 2277.6429 | M6: Coast at Lakeshore East | N6: 2988.2632 | O6: 2988.2632 | Q6: AMLI River North | R6: 4299.375 | S6: 4299.375 | U6: Wolf Point West | V6: 7142 | W6: 7142 | Y6: AMLI River North | Z6: 6000 | AA6: 6000 | AC6: AMLI River North | AG6: AMLI River North | AH6: 0.97310513 | AI6: 0.046454768 | AM6: The Gallery on Wells | AN6: 60.217213 | AP6: Hubbard Place | AQ6: 19 | AS6: Studio | AT6: 59.969856 | AV6: The Gallery on Wells | AW6: 2710.9927 | AX6: 2696.8278 | AZ6: Marquee at Block 37 | BA6: 2470.875 | BB6: 2470.875 | BD6: Marquee at Block 37 | BE6: 3.3222574 | BF6: 3.3129139 | BH6: Marquee at Block 37 | BI6: 3.6073645 | BJ6: 3.6073645 | BL6: Marquee at Block 37 | BM6: 0.0027122559 | BO6: 4BR | BP6: 0.0051686616 | BR6: Studio | BS6: 594.93348 | BU6: The Gallery on Wells | BV6: 60.217213 | BX6: AMLI River North | BY6: 0.97310513 | BZ6: 0.046454768 | CB6: Jul | CC6: 2274.4483 | CD6: 2985.0345 | CE6: 4386.6667 | CF6: 6246.5 | CJ6: Aug | CK6: 3.8170595 | CL6: 3.8045949 | CN6: Aug | CO6: 3210.1818 | CP6: 3195 | CR6: Aug | CS6: 24.589286 | CU6: Aug | CV6: 79
A7: The Gallery on Wells | B7: 3044.9804 | C7: 3.8381157 | E7: The Gallery on Wells | F7: 3044.9804 | G7: 3.8381157 | I7: Marquee at Block 37 | J7: 2346.8519 | K7: 2346.8519 | M7: Wolf Point West | N7: 3026.8824 | O7: 3026.8824 | Q7: The Gallery on Wells | R7: 4321.3333 | S7: 4321.3333 | U7: OneEleven | V7: 8282.75 | W7: 8047 | Y7: Hubbard Place | Z7: 6500 | AA7: 6500 | AC7: Wolf Point West | AG7: Wolf Point West | AH7: 0.98109641 | AI7: 0.060491493 | AM7: Millie on Michigan | AN7: 62.592391 | AP7: AMLI River North | AQ7: 19 | AS7: 2BR | AT7: 75.271462 | AV7: Marquee at Block 37 | AW7: 2816.877 | AX7: 2809.2369 | AZ7: MILA | BA7: 2744.6 | BB7: 2744.6 | BD7: AMLI River North | BE7: 3.7099561 | BF7: 3.7099561 | BH7: MILA | BI7: 3.9571472 | BJ7: 3.9571472 | BL7: Coast at Lakeshore East | BM7: 0.0042845559 | BO7: Studio | BP7: 0.0068639351 | BR7: 4BR | BS7: 654 | BU7: Millie on Michigan | BV7: 62.592391 | BX7: Wolf Point West | BY7: 0.98109641 | BZ7: 0.060491493 | CB7: Aug | CC7: 2390.5455 | CD7: 3035.9268 | CE7: 4585 | CF7: 6561.3333 | CJ7: Sep | CK7: 3.8218642 | CL7: 3.8165084 | CN7: Sep | CO7: 3077.2419 | CP7: 3073.0323 | CR7: Sep | CS7: 31.566038 | CU7: Sep | CV7: 62
A8: AMLI River North | B8: 3072.8 | C8: 3.7419323 | E8: AMLI River North | F8: 3072.8 | G8: 3.7419323 | I8: MILA | J8: 2410.5 | K8: 2410.5 | M8: Millie on Michigan | N8: 3070.6667 | O8: 3070.6667 | Q8: Coast at Lakeshore East | R8: 4381.3333 | S8: 4381.3333 | U8: Grand Total | V8: 7146.0347 | W8: 7087.0972 | Y8: Grand Total | Z8: 5500 | AA8: 5500 | AC8: Marquee at Block 37 | AD8: 6500 | AE8: 6500 | AG8: Marquee at Block 37 | AH8: 0.97681159 | AI8: 0.034782609 | AM8: Optima Signature | AN8: 63.372951 | AP8: Coast at Lakeshore East | AQ8: 20 | AS8: 3BR | AT8: 100.93617 | AV8: MILA | AW8: 2838.9959 | AX8: 2785.5265 | AZ8: AMLI River North | BA8: 2796.7368 | BB8: 2796.7368 | BD8: The Gallery on Wells | BE8: 3.7252741 | BF8: 3.7052744 | BH8: The Gallery on Wells | BI8: 4.0416957 | BJ8: 4.0416957 | BL8: The Gallery on Wells | BM8: 0.0052249625 | BO8: 2BR | BP8: 0.0076605002 | BR8: 1BR | BS8: 781.90063 | BU8: Optima Signature | BV8: 63.372951 | BX8: Marquee at Block 37 | BY8: 0.97681159 | BZ8: 0.034782609 | CB8: Sep | CC8: 2259.25 | CD8: 2920.1 | CE8: 3993.6429 | CJ8: Oct | CK8: 3.7396403 | CL8: 3.698202 | CN8: Oct | CO8: 3078.0943 | CP8: 3053.3396 | CR8: Oct | CS8: 38.265306 | CU8: Oct | CV8: 55
A9: Hubbard Place | B9: 3087.8049 | C9: 3.9982314 | E9: Hubbard Place | F9: 3087.8049 | G9: 3.9982314 | I9: AMLI River North | J9: 2435.36 | K9: 2435.36 | M9: The Gallery on Wells | N9: 3071.8333 | O9: 3071.8333 | Q9: Hubbard Place | R9: 4707 | S9: 4707 | AC9: Optima Signature | AG9: Optima Signature | AH9: 0.93061224 | AI9: 0.081632653 | AM9: AMLI River North | AN9: 64.858407 | AP9: OneEleven | AQ9: 22 | AS9: Grand Total | AT9: 61.968102 | AV9: Coast at Lakeshore East | AW9: 2865.33 | AX9: 2853.0533 | AZ9: Hubbard Place | BA9: 2842.5789 | BB9: 2842.5789 | BD9: MILA | BE9: 3.7255387 | BF9: 3.6616087 | BH9: AMLI River North | BI9: 4.0453066 | BJ9: 4.0453066 | BL9: Wolf Point West | BM9: 0.0060296834 | BO9: 1BR | BP9: 0.0089485721 | BR9: 2BR | BS9: 1198.2665 | BU9: AMLI River North | BV9: 64.858407 | BX9: Optima Signature | BY9: 0.93061224 | BZ9: 0.081632653 | CB9: Oct | CC9: 2331.2857 | CD9: 2791.9615 | CE9: 4360.5 | CF9: 5584 | CJ9: Nov | CK9: 3.7238384 | CL9: 3.6634174 | CN9: Nov | CO9: 2928.587 | CP9: 2887.7174 | CR9: Nov | CS9: 61.511628 | CU9: Nov | CV9: 46
A10: Wolf Point West | B10: 3148.25 | C10: 4.1948592 | E10: Wolf Point West | F10: 3148.25 | G10: 4.1948592 | I10: OneEleven | J10: 2437.8333 | K10: 2393.5833 | M10: OneEleven | N10: 3233.9474 | O10: 3163.7368 | Q10: OneEleven | R10: 4711.25 | S10: 4711.25 | AC10: Hubbard Place | AG10: Hubbard Place | AH10: 0.97555556 | AI10: 0.042222222 | AM10: Hubbard Place | AN10: 65.224771 | AP10: Marquee at Block 37 | AQ10: 24 | AV10: Wolf Point West | AW10: 2925.4779 | AX10: 2907.8382 | AZ10: The Gallery on Wells | BA10: 2982.7 | BB10: 2982.7 | BD10: Coast at Lakeshore East | BE10: 3.7261172 | BF10: 3.7109454 | BH10: Coast at Lakeshore East | BI10: 4.0796471 | BJ10: 4.0796471 | BL10: MILA | BM10: 0.018833908 | BO10: 3BR | BP10: 0.014956701 | BR10: 3BR | BS10: 1680.2769 | BU10: Hubbard Place | BV10: 65.224771 | BX10: Hubbard Place | BY10: 0.97555556 | BZ10: 0.042222222 | CB10: Nov | CC10: 2424.1 | CD10: 2849.0333 | CE10: 4167.1667 | CJ10: Dec | CK10: 3.6651136 | CL10: 3.6475723 | CN10: Dec | CO10: 3267.4571 | CP10: 3252.7286 | CR10: Dec | CS10: 70.313433 | CU10: Dec | CV10: 70
A11: Millie on Michigan | B11: 3334.2286 | C11: 4.5189746 | E11: Millie on Michigan | F11: 3334.2286 | G11: 4.5189746 | I11: The Gallery on Wells | J11: 2546.2083 | K11: 2546.2083 | M11: Hubbard Place | N11: 3302.0833 | O11: 3302.0833 | Q11: Wolf Point West | R11: 4908.4286 | S11: 4908.4286 | AC11: The Gallery on Wells | AD11: 9000 | AE11: 9000 | AG11: The Gallery on Wells | AH11: 0.96404494 | AI11: 0.06741573 | AM11: OneEleven | AN11: 66.937743 | AP11: MILA | AQ11: 25 | AV11: Millie on Michigan | AW11: 3055.6697 | AX11: 3055.6697 | AZ11: Coast at Lakeshore East | BA11: 3114.1 | BB11: 3114.1 | BD11: Hubbard Place | BE11: 3.8979072 | BF11: 3.8979072 | BH11: OneEleven | BI11: 4.1876992 | BJ11: 4.1876992 | BL11: OneEleven | BM11: 0.047728878 | BO11: Grand Total | BP11: 0.0084289627 | BR11: Grand Total | BS11: 816.56504 | BU11: OneEleven | BV11: 66.937743 | BX11: The Gallery on Wells | BY11: 0.96404494 | BZ11: 0.06741573 | CB11: Dec | CC11: 2214.1538 | CD11: 2919 | CE11: 4348.4706 | CF11: 6003.6667 | CJ11: 2024 | CN11: 2024 | CO11: 3029.8359 | CP11: 2995.875 | CR11: 2024 | CU11: 2024
A12: OneEleven | B12: 3658.3333 | C12: 4.1830362 | E12: OneEleven | F12: 3586.3333 | G12: 4.1007095 | I12: Optima Signature | J12: 2767.7778 | K12: 2767.7778 | M12: AMLI River North | N12: 3433 | O12: 3433 | Q12: Millie on Michigan | R12: 5131 | S12: 5131 | AC12: Millie on Michigan | AG12: Millie on Michigan | AH12: 0.95847751 | AI12: 0.10380623 | AM12: Marquee at Block 37 | AN12: 67.412821 | AP12: The Gallery on Wells | AQ12: 30 | AV12: AMLI River North | AW12: 3090.815 | AX12: 3090.815 | AZ12: Wolf Point West | BA12: 3300.7812 | BB12: 3300.7812 | BD12: Wolf Point West | BE12: 3.95556 | BF12: 3.9317138 | BH12: Hubbard Place | BI12: 4.2448578 | BJ12: 4.2448578 | BL12: Grand Total | BM12: 0.013957013 | BU12: Marquee at Block 37 | BV12: 67.412821 | BX12: Millie on Michigan | BY12: 0.95847751 | BZ12: 0.10380623 | CB12: 2024 | CJ12: Jan | CK12: 3.6236784 | CL12: 3.5702247 | CN12: Jan | CO12: 2958.1455 | CP12: 2913.2364 | CR12: Jan | CS12: 55.375 | CU12: Jan | CV12: 58
A13: Optima Signature | B13: 4233.197 | C13: 4.2007367 | E13: Optima Signature | F13: 4233.197 | G13: 4.2007367 | I13: Millie on Michigan | J13: 2785.4545 | K13: 2785.4545 | M13: Optima Signature | N13: 3433.7097 | O13: 3433.7097 | Q13: Optima Signature | R13: 5139.2941 | S13: 5139.2941 | AC13: Coast at Lakeshore East | AG13: Coast at Lakeshore East | AH13: 0.99223301 | AI13: 0.038834951 | AM13: MILA | AN13: 75.036199 | AP13: Millie on Michigan | AQ13: 30 | AV13: Hubbard Place | AW13: 3123.9762 | AX13: 3123.9762 | AZ13: OneEleven | BA13: 3360.9091 | BB13: 3360.9091 | BD13: OneEleven | BE13: 4.0417362 | BF13: 3.851598 | BH13: Wolf Point West | BI13: 4.2838476 | BJ13: 4.2838476 | BU13: MILA | BV13: 75.036199 | BX13: Coast at Lakeshore East | BY13: 0.99223301 | BZ13: 0.038834951 | CB13: Jan | CC13: 2178.9091 | CD13: 2930.7619 | CE13: 4116.8 | CF13: 6024 | CJ13: Feb | CK13: 3.5670817 | CL13: 3.5514715 | CN13: Feb | CO13: 3011.9444 | CP13: 3000.4722 | CR13: Feb | CS13: 63.888889 | CU13: Feb | CV13: 76
A14: Grand Total | B14: 3192.1308 | C14: 3.98607 | E14: Grand Total | F14: 3184.9308 | G14: 3.9778373 | I14: Grand Total | J14: 2441.257 | K14: 2436.832 | M14: Grand Total | N14: 3106.1472 | O14: 3099.1261 | Q14: Grand Total | R14: 4539.7081 | S14: 4539.7081 | AC14: Grand Total | AD14: 7833.3333 | AE14: 7833.3333 | AG14: Grand Total | AH14: 0.96888804 | AI14: 0.058139407 | AM14: Grand Total | AN14: 61.968102 | AP14: Wolf Point West | AQ14: 32 | AV14: OneEleven | AW14: 3294.5035 | AX14: 3137.2606 | AZ14: Millie on Michigan | BA14: 3452.7333 | BB14: 3452.7333 | BD14: Optima Signature | BE14: 4.0600766 | BF14: 4.0600766 | BH14: Optima Signature | BI14: 4.4545959 | BJ14: 4.4545959 | BU14: Grand Total | BV14: 61.968102 | BX14: Grand Total | BY14: 0.96888804 | BZ14: 0.058139407 | CB14: Feb | CC14: 2224 | CD14: 2910.075 | CE14: 4225.1818 | CF14: 5862 | CJ14: Mar | CK14: 3.7160011 | CL14: 3.6510351 | CN14: Mar | CO14: 2992.2389 | CP14: 2939.4779 | CR14: Mar | CS14: 67.775862 | CU14: Mar | CV14: 119
AP15: Optima Signature | AQ15: 40 | AV15: Optima Signature | AW15: 3935.3791 | AX15: 3935.3791 | AZ15: Optima Signature | BA15: 4415.55 | BB15: 4415.55 | BD15: Millie on Michigan | BE15: 4.1848211 | BF15: 4.1848211 | BH15: Millie on Michigan | BI15: 4.5363729 | BJ15: 4.5363729 | CB15: Mar | CC15: 2284.6923 | CD15: 2852.8955 | CE15: 4197.7647 | CF15: 5405 | CJ15: Apr | CK15: 3.8247428 | CL15: 3.7904892 | CN15: Apr | CO15: 3194.7907 | CP15: 3162.3798 | CR15: Apr | CS15: 53.977444 | CU15: Apr | CV15: 135
AP16: Grand Total | AQ16: 261 | AV16: Grand Total | AW16: 3062.2171 | AX16: 3036.4058 | AZ16: Grand Total | BA16: 3243.659 | BB16: 3243.659 | BD16: Grand Total | BE16: 3.8019782 | BF16: 3.7702408 | BH16: Grand Total | BI16: 4.1720409 | BJ16: 4.1720409 | CB16: Apr | CC16: 2277.6098 | CD16: 3054.4407 | CE16: 4442.84 | CF16: 6865.75 | CJ16: May | CK16: 3.8505964 | CL16: 3.8069766 | CN16: May | CO16: 3087.5833 | CP16: 3052.912 | CR16: May | CS16: 49.180258 | CU16: May | CV16: 236
CB17: May | CC17: 2293.102 | CD17: 2937.1128 | CE17: 4608.2069 | CF17: 6056.4 | CJ17: Jul | CK17: 3.9237275 | CL17: 3.9007857 | CN17: Jul | CO17: 3080.6807 | CP17: 3062.1265 | CR17: Jul | CS17: 64.630303 | CU17: Jul | CV17: 166
CB18: Jul | CC18: 2394.7377 | CD18: 3118.7105 | CE18: 4423.8621 | CJ18: Aug | CK18: 3.8974876 | CL18: 3.8918953 | CN18: Aug | CO18: 3014.2414 | CP18: 3009.2874 | CR18: Aug | CS18: 64.264368 | CU18: Aug | CV18: 174
CB19: Aug | CC19: 2375.5152 | CD19: 2937.1842 | CE19: 4400.2069 | CF19: 7330 | CG19: 2202 | CJ19: Sep | CK19: 3.717531 | CL19: 3.702101 | CN19: Sep | CO19: 3091.1885 | CP19: 3075.918 | CR19: Sep | CS19: 53.479339 | CU19: Sep | CV19: 122
CB20: Sep | CC20: 2376.12 | CD20: 2901.4603 | CE20: 3907.8788 | CF20: 5970 | CJ20: Oct | CK20: 3.646284 | CL20: 3.6112829 | CN20: Oct | CO20: 3037.1908 | CP20: 3008.5191 | CR20: Oct | CS20: 70.473282 | CU20: Oct | CV20: 131
CB21: Oct | CC21: 2264.5135 | CD21: 2775.5238 | CE21: 4237.8889 | CF21: 6201 | CJ21: Nov | CK21: 3.6860444 | CL21: 3.6115113 | CN21: Nov | CO21: 2961.608 | CP21: 2901.456 | CR21: Nov | CS21: 86.427419 | CU21: Nov | CV21: 125
CB22: Nov | CC22: 2242.0278 | CD22: 2826.6393 | CE22: 4096.2222 | CF22: 6465 | CJ22: Dec | CK22: 3.569985 | CL22: 3.4728789 | CN22: Dec | CO22: 2834.281 | CP22: 2759.5163 | CR22: Dec | CS22: 89.512987 | CU22: Dec | CV22: 154
CB23: Dec | CC23: 2148.549 | CD23: 2753.1972 | CE23: 4127.75 | CF23: 5258.5 | CG23: 2498 | CJ23: 2025 | CN23: 2025 | CO23: 3080.7175 | CP23: 3051.7732 | CR23: 2025 | CU23: 2025
CB24: 2025 | CJ24: Jan | CK24: 3.6337634 | CL24: 3.5759536 | CN24: Jan | CO24: 2958.5543 | CP24: 2910.4114 | CR24: Jan | CS24: 87.954286 | CU24: Jan | CV24: 175
CB25: Jan | CC25: 2247.807 | CD25: 2843.8571 | CE25: 4157.0667 | CF25: 6506.5 | CJ25: Feb | CK25: 3.7301932 | CL25: 3.7094659 | CN25: Feb | CO25: 3153.4564 | CP25: 3135.7315 | CR25: Feb | CS25: 73.912162 | CU25: Feb | CV25: 149
CB26: Feb | CC26: 2286.2391 | CD26: 3010.9254 | CE26: 4402.3636 | CF26: 5896 | CJ26: Mar | CK26: 3.8862998 | CL26: 3.8758449 | CN26: Mar | CO26: 3236.3101 | CP26: 3224.0078 | CR26: Mar | CS26: 58.968992 | CU26: Mar | CV26: 129
CB27: Mar | CC27: 2326.7436 | CD27: 3132.2571 | CE27: 4404.2143 | CF27: 7637.3333 | CJ27: Apr | CK27: 3.7036649 | CL27: 3.7036649 | CN27: Apr | CO27: 2307.5 | CP27: 2307.5 | CR27: Apr | CS27: 111.75 | CU27: Apr | CV27: 4
CB28: Apr | CC28: 2307.5 | CJ28: May | CK28: 4.0283976 | CL28: 4.0283976 | CN28: May | CO28: 1986 | CP28: 1986 | CR28: May | CS28: 3 | CU28: May | CV28: 1
CB29: May | CC29: 1986 | CJ29: Jul | CK29: 3.9859737 | CL29: 3.9859737 | CN29: Jul | CO29: 2553.5 | CP29: 2553.5 | CR29: Jul | CS29: 55 | CU29: Jul | CV29: 4
CB30: Jul | CC30: 2296.3333 | CD30: 3325 | CJ30: Aug | CK30: 3.7290532 | CL30: 3.5677904 | CN30: Aug | CO30: 2217.5 | CP30: 2123 | CR30: Aug | CS30: 41 | CU30: Aug | CV30: 2
CB31: Aug | CC31: 2166 | CD31: 2269 | CJ31: Sep | CK31: 3.5987522 | CL31: 3.555357 | CN31: Sep | CO31: 2551 | CP31: 2515.2857 | CR31: Sep | CS31: 48.142857 | CU31: Sep | CV31: 7
CB32: Sep | CC32: 2303.6 | CD32: 3169.5 | CJ32: Oct | CK32: 3.4589505 | CL32: 3.3766122 | CN32: Oct | CO32: 4337.6667 | CP32: 4227.3333 | CR32: Oct | CS32: 39 | CU32: Oct | CV32: 3
CB33: Oct | CC33: 2346 | CE33: 3974 | CF33: 6693 | CJ33: Nov | CK33: 3.5812583 | CL33: 3.5812583 | CN33: Nov | CO33: 2315.25 | CP33: 2315.25 | CR33: Nov | CS33: 46.5 | CU33: Nov | CV33: 4
CB34: Nov | CC34: 2132 | CD34: 2865 | CJ34: Dec | CK34: 3.8704905 | CL34: 3.811231 | CN34: Dec | CO34: 3293.7143 | CP34: 3205.8571 | CR34: Dec | CS34: 42.142857 | CU34: Dec | CV34: 7
CB35: Dec | CC35: 2347.5 | CD35: 2815.6667 | CE35: 3665 | CF35: 6249 | CJ35: Grand Total | CK35: 3.7582278 | CL35: 3.7212583 | CN35: Grand Total | CO35: 3052.92 | CP35: 3022.7004 | CR35: Grand Total | CS35: 63.052197 | CU35: Grand Total | CV35: 2394
CB36: Grand Total | CC36: 2291.2142 | CD36: 2929.7515 | CE36: 4275.7188 | CF36: 6368 | CG36: 2350

Sheet Data Analysis
B1: Hillendale Gate Apartments | J1: Report Date: | K1: 45785
A2: Report Filters | K2: Note: Figures and charts on the Data Analysis tab only utilize data from closed listings.
D4: Avg Sqft | E4: Avg Rent | F4: Avg Effective Rent | G4: Avg Rent PSF | H4: Avg Effective Rent PSF | I4: Avg Concession Amt | J4: Avg Days on Mkt | K4: # Leases
D5: =GETPIVOTDATA("Avg Sqft",$B$89) -> 816.56504 | E5: =GETPIVOTDATA("Avg Rent",$B$89) -> 3062.2171 | F5: =GETPIVOTDATA(" Avg Effective Rent",$B$89) -> 3036.4058 | G5: =GETPIVOTDATA("Avg Rent PSF",$B$89) -> 3.8019782 | H5: =GETPIVOTDATA("Avg Effective Rent PSF",$B$89) -> 3.7702408 | I5: =GETPIVOTDATA("Concession %",$B$89) -> 0.0084289627 | J5: =GETPIVOTDATA("Avg Days on Mkt",$B$89) -> 61.968102 | K5: =GETPIVOTDATA("# Leases",$B$89) -> 2846
M7: Unit Amenity | O7: Timeframe | Q7: Metric
M8: [Select Amenity] | N8: Last | O8: 180 | P8: Days | Q8: Leased Rent
N10: ="Leased Units Tagged With "&M8 -> Leased Units Tagged With [Select Amenity] | Q10: ="Leased Units NOT Tagged with "&M8 -> Leased Units NOT Tagged with [Select Amenity]
M11: Unit Type | N11: Avg Sqft | O11: =Q8 -> Leased Rent | P11: # Leases | Q11: Avg Sqft | R11: =Q8 -> Leased Rent | S11: # Leases | U11: $△ | V11: %△
M12: 0 | N12: =IFERROR(AVERAGEIFS( unit_details[Sqft], unit_details[Beds], $M12, unit_details[Detected Unit Amenities], "*"&$M$8&"*", unit_details[Leased Date], ">=" & ('Weekly Market Updates'!$Q$2 - $O$8) ),0) -> 0 | O12: =IFERROR(AVERAGEIFS( IF($Q$8="Leased Rent",unit_details[Asking Rent],IF($Q$8="Effective Rent",unit_details[Effective Rent],IF($Q$8="Leased Rent PSF",unit_details[Asking PSF],unit_details[Effective PSF]))), unit_details[Beds], $M12, unit_details[Detected Unit Amenities], "*"&$M$8&"*", unit_details[Leased Date], ">=" & ('Weekly Market Updates'!$Q$2 - $O$8) ),0) -> 0 | P12: =IFERROR(COUNTIFS( unit_details[Beds], $M12, unit_details[Detected Unit Amenities], "*"&$M$8&"*", unit_details[Leased Date], ">=" & ('Weekly Market Updates'!$Q$2 - $O$8) ),0) -> 0 | Q12: =IFERROR(IF(N12=0,0,AVERAGEIFS( unit_details[Sqft], unit_details[Beds], $M12, unit_details[Detected Unit Amenities], "<>*"&$M$8&"*", unit_details[Leased Date], ">=" & ('Weekly Market Updates'!$Q$2 - $O$8) )),0) -> 0 | R12: =IFERROR(IF(O12=0,0,AVERAGEIFS( IF($Q$8="Leased Rent",unit_details[Asking Rent],IF($Q$8="Effective Rent",unit_details[Effective Rent],IF($Q$8="Leased Rent PSF",unit_details[Asking PSF],unit_details[Effective PSF]))), unit_details[Beds], $M12, unit_details[Detected Unit Amenities], "<>*"&$M$8&"*", unit_details[Leased Date], ">=" & ('Weekly Market Updates'!$Q$2 - $O$8) )),0) -> 0 | S12: =IFERROR(IF(P12=0,0,COUNTIFS( unit_details[Beds], $M12, unit_details[Detected Unit Amenities], "<>*"&$M$8&"*", unit_details[Leased Date], ">=" & ('Weekly Market Updates'!$Q$2 - $O$8) )),0) -> 0 | U12: =IFERROR(O12-R12,0) -> 0 | V12: =IFERROR(U12/R12,0) -> 0
M13: 1 | N13: =IFERROR(AVERAGEIFS( unit_details[Sqft], unit_details[Beds], $M13, unit_details[Detected Unit Amenities], "*"&$M$8&"*", unit_details[Leased Date], ">=" & ('Weekly Market Updates'!$Q$2 - $O$8) ),0) -> 0 | O13: =IFERROR(AVERAGEIFS( IF($Q$8="Leased Rent",unit_details[Asking Rent],IF($Q$8="Effective Rent",unit_details[Effective Rent],IF($Q$8="Leased Rent PSF",unit_details[Asking PSF],unit_details[Effective PSF]))), unit_details[Beds], $M13, unit_details[Detected Unit Amenities], "*"&$M$8&"*", unit_details[Leased Date], ">=" & ('Weekly Market Updates'!$Q$2 - $O$8) ),0) -> 0 | P13: =IFERROR(COUNTIFS( unit_details[Beds], $M13, unit_details[Detected Unit Amenities], "*"&$M$8&"*", unit_details[Leased Date], ">=" & ('Weekly Market Updates'!$Q$2 - $O$8) ),0) -> 0 | Q13: =IFERROR(IF(N13=0,0,AVERAGEIFS( unit_details[Sqft], unit_details[Beds], $M13, unit_details[Detected Unit Amenities], "<>*"&$M$8&"*", unit_details[Leased Date], ">=" & ('Weekly Market Updates'!$Q$2 - $O$8) )),0) -> 0 | R13: =IFERROR(IF(O13=0,0,AVERAGEIFS( IF($Q$8="Leased Rent",unit_details[Asking Rent],IF($Q$8="Effective Rent",unit_details[Effective Rent],IF($Q$8="Leased Rent PSF",unit_details[Asking PSF],unit_details[Effective PSF]))), unit_details[Beds], $M13, unit_details[Detected Unit Amenities], "<>*"&$M$8&"*", unit_details[Leased Date], ">=" & ('Weekly Market Updates'!$Q$2 - $O$8) )),0) -> 0 | S13: =IFERROR(IF(P13=0,0,COUNTIFS( unit_details[Beds], $M13, unit_details[Detected Unit Amenities], "<>*"&$M$8&"*", unit_details[Leased Date], ">=" & ('Weekly Market Updates'!$Q$2 - $O$8) )),0) -> 0 | U13: =IFERROR(O13-R13,0) -> 0 | V13: =IFERROR(U13/R13,0) -> 0
M14: 2 | N14: =IFERROR(AVERAGEIFS( unit_details[Sqft], unit_details[Beds], $M14, unit_details[Detected Unit Amenities], "*"&$M$8&"*", unit_details[Leased Date], ">=" & ('Weekly Market Updates'!$Q$2 - $O$8) ),0) -> 0 | O14: =IFERROR(AVERAGEIFS( IF($Q$8="Leased Rent",unit_details[Asking Rent],IF($Q$8="Effective Rent",unit_details[Effective Rent],IF($Q$8="Leased Rent PSF",unit_details[Asking PSF],unit_details[Effective PSF]))), unit_details[Beds], $M14, unit_details[Detected Unit Amenities], "*"&$M$8&"*", unit_details[Leased Date], ">=" & ('Weekly Market Updates'!$Q$2 - $O$8) ),0) -> 0 | P14: =IFERROR(COUNTIFS( unit_details[Beds], $M14, unit_details[Detected Unit Amenities], "*"&$M$8&"*", unit_details[Leased Date], ">=" & ('Weekly Market Updates'!$Q$2 - $O$8) ),0) -> 0 | Q14: =IFERROR(IF(N14=0,0,AVERAGEIFS( unit_details[Sqft], unit_details[Beds], $M14, unit_details[Detected Unit Amenities], "<>*"&$M$8&"*", unit_details[Leased Date], ">=" & ('Weekly Market Updates'!$Q$2 - $O$8) )),0) -> 0 | R14: =IFERROR(IF(O14=0,0,AVERAGEIFS( IF($Q$8="Leased Rent",unit_details[Asking Rent],IF($Q$8="Effective Rent",unit_details[Effective Rent],IF($Q$8="Leased Rent PSF",unit_details[Asking PSF],unit_details[Effective PSF]))), unit_details[Beds], $M14, unit_details[Detected Unit Amenities], "<>*"&$M$8&"*", unit_details[Leased Date], ">=" & ('Weekly Market Updates'!$Q$2 - $O$8) )),0) -> 0 | S14: =IFERROR(IF(P14=0,0,COUNTIFS( unit_details[Beds], $M14, unit_details[Detected Unit Amenities], "<>*"&$M$8&"*", unit_details[Leased Date], ">=" & ('Weekly Market Updates'!$Q$2 - $O$8) )),0) -> 0 | U14: =IFERROR(O14-R14,0) -> 0 | V14: =IFERROR(U14/R14,0) -> 0
M15: 3 | N15: =IFERROR(AVERAGEIFS( unit_details[Sqft], unit_details[Beds], $M15, unit_details[Detected Unit Amenities], "*"&$M$8&"*", unit_details[Leased Date], ">=" & ('Weekly Market Updates'!$Q$2 - $O$8) ),0) -> 0 | O15: =IFERROR(AVERAGEIFS( IF($Q$8="Leased Rent",unit_details[Asking Rent],IF($Q$8="Effective Rent",unit_details[Effective Rent],IF($Q$8="Leased Rent PSF",unit_details[Asking PSF],unit_details[Effective PSF]))), unit_details[Beds], $M15, unit_details[Detected Unit Amenities], "*"&$M$8&"*", unit_details[Leased Date], ">=" & ('Weekly Market Updates'!$Q$2 - $O$8) ),0) -> 0 | P15: =IFERROR(COUNTIFS( unit_details[Beds], $M15, unit_details[Detected Unit Amenities], "*"&$M$8&"*", unit_details[Leased Date], ">=" & ('Weekly Market Updates'!$Q$2 - $O$8) ),0) -> 0 | Q15: =IFERROR(IF(N15=0,0,AVERAGEIFS( unit_details[Sqft], unit_details[Beds], $M15, unit_details[Detected Unit Amenities], "<>*"&$M$8&"*", unit_details[Leased Date], ">=" & ('Weekly Market Updates'!$Q$2 - $O$8) )),0) -> 0 | R15: =IFERROR(IF(O15=0,0,AVERAGEIFS( IF($Q$8="Leased Rent",unit_details[Asking Rent],IF($Q$8="Effective Rent",unit_details[Effective Rent],IF($Q$8="Leased Rent PSF",unit_details[Asking PSF],unit_details[Effective PSF]))), unit_details[Beds], $M15, unit_details[Detected Unit Amenities], "<>*"&$M$8&"*", unit_details[Leased Date], ">=" & ('Weekly Market Updates'!$Q$2 - $O$8) )),0) -> 0 | S15: =IFERROR(IF(P15=0,0,COUNTIFS( unit_details[Beds], $M15, unit_details[Detected Unit Amenities], "<>*"&$M$8&"*", unit_details[Leased Date], ">=" & ('Weekly Market Updates'!$Q$2 - $O$8) )),0) -> 0 | U15: =IFERROR(O15-R15,0) -> 0 | V15: =IFERROR(U15/R15,0) -> 0
M16: 4 | N16: =IFERROR(AVERAGEIFS( unit_details[Sqft], unit_details[Beds], $M16, unit_details[Detected Unit Amenities], "*"&$M$8&"*", unit_details[Leased Date], ">=" & ('Weekly Market Updates'!$Q$2 - $O$8) ),0) -> 0 | O16: =IFERROR(AVERAGEIFS( IF($Q$8="Leased Rent",unit_details[Asking Rent],IF($Q$8="Effective Rent",unit_details[Effective Rent],IF($Q$8="Leased Rent PSF",unit_details[Asking PSF],unit_details[Effective PSF]))), unit_details[Beds], $M16, unit_details[Detected Unit Amenities], "*"&$M$8&"*", unit_details[Leased Date], ">=" & ('Weekly Market Updates'!$Q$2 - $O$8) ),0) -> 0 | P16: =IFERROR(COUNTIFS( unit_details[Beds], $M16, unit_details[Detected Unit Amenities], "*"&$M$8&"*", unit_details[Leased Date], ">=" & ('Weekly Market Updates'!$Q$2 - $O$8) ),0) -> 0 | Q16: =IFERROR(IF(N16=0,0,AVERAGEIFS( unit_details[Sqft], unit_details[Beds], $M16, unit_details[Detected Unit Amenities], "<>*"&$M$8&"*", unit_details[Leased Date], ">=" & ('Weekly Market Updates'!$Q$2 - $O$8) )),0) -> 0 | R16: =IFERROR(IF(O16=0,0,AVERAGEIFS( IF($Q$8="Leased Rent",unit_details[Asking Rent],IF($Q$8="Effective Rent",unit_details[Effective Rent],IF($Q$8="Leased Rent PSF",unit_details[Asking PSF],unit_details[Effective PSF]))), unit_details[Beds], $M16, unit_details[Detected Unit Amenities], "<>*"&$M$8&"*", unit_details[Leased Date], ">=" & ('Weekly Market Updates'!$Q$2 - $O$8) )),0) -> 0 | S16: =IFERROR(IF(P16=0,0,COUNTIFS( unit_details[Beds], $M16, unit_details[Detected Unit Amenities], "<>*"&$M$8&"*", unit_details[Leased Date], ">=" & ('Weekly Market Updates'!$Q$2 - $O$8) )),0) -> 0 | U16: =IFERROR(O16-R16,0) -> 0 | V16: =IFERROR(U16/R16,0) -> 0
M17: All | N17: =IFERROR(AVERAGEIFS( unit_details[Sqft], unit_details[Detected Unit Amenities], "*" & $M$8 & "*", unit_details[Leased Date], ">=" & ('Weekly Market Updates'!$Q$2 - $O$8) ),0) -> 0 | O17: =IFERROR(SUMPRODUCT(O12:O16,P12:P16)/P17,0) -> 0 | P17: =SUM(P12:P16) -> 0 | Q17: =IFERROR(IF(N17=0,0,AVERAGEIFS( unit_details[Sqft], unit_details[Detected Unit Amenities], "<>*" & $M$8 & "*", unit_details[Leased Date], ">=" & ('Weekly Market Updates'!$Q$2 - $O$8) )),0) -> 0 | R17: =IFERROR(SUMPRODUCT(R12:R16,S12:S16)/S17,0) -> 0 | S17: =SUM(S12:S16) -> 0 | U17: =IFERROR(O17-R17,0) -> 0 | V17: =IFERROR(U17/R17,0) -> 0
M18: Note: Select unit amenitiy and timeframe above to update data in table.
B89: Floorplan Data (closed listings) | C89: Avg Floor # | D89: Avg Sqft | E89: Avg Rent | F89: Avg Effective Rent | G89: Avg Rent PSF | H89: Avg Effective Rent PSF | I89: Concession % | J89: Avg Days on Mkt | K89: # Leases
B90: AMLI River North | C90: 30.122047 | D90: 844.03543 | E90: 3090.815 | F90: 3090.815 | G90: 3.7099561 | H90: 3.7099561 | I90: 0 | J90: 64.858407 | K90: 254
B91: Studio | C91: 27.891892 | D91: 599.11712 | E91: 2323.1441 | F91: 2323.1441 | G91: 3.8829583 | H91: 3.8829583 | I91: 0 | J91: 63.947917 | K91: 111
B92: E100 | C92: 39 | D92: 560 | E92: 2311.6667 | F92: 2311.6667 | G92: 4.1279762 | H92: 4.1279762 | I92: 0 | J92: 163.33333 | K92: 9
B93: E110 | C93: 30.125 | D93: 572 | E93: 2413.0833 | F93: 2413.0833 | G93: 4.2186772 | H93: 4.2186772 | I93: 0 | J93: 59.6 | K93: 24
B94: E120 | C94: 22.75 | D94: 575 | E94: 2132.0833 | F94: 2132.0833 | G94: 3.707971 | H94: 3.707971 | I94: 0 | J94: 75.75 | K94: 12
B95: E130 | C95: 23.941176 | D95: 585 | E95: 2149.9412 | F95: 2149.9412 | G95: 3.6751131 | H95: 3.6751131 | I95: 0 | J95: 47.266667 | K95: 17
B96: E140 | C96: 23.272727 | D96: 593 | E96: 2416.0909 | F96: 2416.0909 | G96: 4.0743523 | H96: 4.0743523 | I96: 0 | J96: 31.285714 | K96: 11
B97: E200 | C97: 23.75 | D97: 604 | E97: 2107.25 | F97: 2107.25 | G97: 3.4888245 | H97: 3.4888245 | I97: 0 | J97: 53 | K97: 12
B98: E210 | C98: 37.333333 | D98: 653 | E98: 2430.3333 | F98: 2430.3333 | G98: 3.7217968 | H98: 3.7217968 | I98: 0 | J98: 87 | K98: 6
B99: E220 | C99: 28.85 | D99: 660 | E99: 2528.5 | F99: 2528.5 | G99: 3.8310606 | H99: 3.8310606 | I99: 0 | J99: 55.736842 | K99: 20
B100: 1BR | C100: 31.333333 | D100: 914.01111 | E100: 3250.6667 | F100: 3250.6667 | G100: 3.5724981 | H100: 3.5724981 | I100: 0 | J100: 65.430233 | K100: 90
B101: A400 | C101: 23 | D101: 801 | E101: 3004.2727 | F101: 3004.2727 | G101: 3.7506526 | H101: 3.7506526 | I101: 0 | J101: 58.1 | K101: 11
... B119: P-D800 | C119: 45.5 | D119: 1752 | E119: 6585.5 | F119: 6585.5 | G119: 3.758847 | H119: 3.758847 | I119: 0 | J119: 146 | K119: 2
B120: 4 | C120: 35 | D120: 660 | E120: 2575 | F120: 2575 | G120: 3.9015152 | H120: 3.9015152 | I120: 0 | J120: 40 | K120: 2
B121: E220 | C121: 35 | D121: 660 | E121: 2575 | F121: 2575 | G121: 3.9015152 | H121: 3.9015152 | I121: 0 | J121: 40 | K121: 2
B122: Hubbard Place | C122: 24.420635 | D122: 815.31349 | E122: 3123.9762 | F122: 3123.9762 | G122: 3.8979072 | H122: 3.8979072 | I122: 0 | J122: 65.224771 | K122: 252
B123: Studio | C123: 25.075472 | D123: 512.37736 | E123: 2103.0377 | F123: 2103.0377 | G123: 4.1113272 | H123: 4.1113272 | I123: 0 | J123: 69.977778 | K123: 53
B124: Studio_hub 02 | C124: 25.608696 | D124: 546 | E124: 2235.5217 | F124: 2235.5217 | G124: 4.0943622 | H124: 4.0943622 | I124: 0 | J124: 87.944444 | K124: 23
B125: Studio_hub 02a | C125: 6 | D125: 546 | E125: 1802.3333 | F125: 1802.3333 | G125: 3.3009768 | H125: 3.3009768 | I125: 0 | J125: 3.6666667 | K125: 3
B126: Studio_hub 11 | C126: 26.740741 | D126: 480 | E126: 2023.5926 | F126: 2023.5926 | G126: 4.2158179 | H126: 4.2158179 | I126: 0 | J126: 64.791667 | K126: 27
B127: 1BR | C127: 24.823899 | D127: 803.81761 | E127: 3140.2767 | F127: 3140.2767 | G127: 3.9285385 | H127: 3.9285385 | I127: 0 | J127: 62.680851 | K127: 159
B128: Convertible_hub 06 | C128: 22.590909 | D128: 654.59091 | E128: 2689.9545 | F128: 2689.9545 | G128: 4.1097991 | H128: 4.1097991 | I128: 0 | J128: 76 | K128: 22
B129: Convertible_hub 11a | C129: 4.5 | D129: 878 | E129: 2531.5 | F129: 2531.5 | G129: 2.8832574 | H129: 2.8832574 | I129: 0 | J129: 59 | K129: 2
B130: One Bedroom_hub 03 | C130: 25.818182 | D130: 734.90909 | E130: 3023.3636 | F130: 3023.3636 | G130: 4.1144564 | H130: 4.1144564 | I130: 0 | J130: 97.5625 | K130: 22
B131: One Bedroom_hub 04 | C131: 24.5 | D131: 1103.7273 | E131: 4097 | F131: 4097 | G131: 3.7112871 | H131: 3.7112871 | I131: 0 | J131: 57.714286 | K131: 22
B132: One Bedroom_hub 05 | C132: 26.588235 | D132: 828.64706 | E132: 3261.2353 | F132: 3261.2353 | G132: 3.9357499 | H132: 3.9357499 | I132: 0 | J132: 74.6 | K132: 17
... B138: Two Bedroom_hub 01 | C138: 22.285714 | D138: 1325 | E138: 4727.5714 | F138: 4727.5714 | G138: 3.5679784 | H138: 3.5679784 | I138: 0 | J138: 103.7 | K138: 14
B139: Two Bedroom_hub 01a | C139: 6 | D139: 1177 | E139: 3484 | F139: 3484 | G139: 2.960068 | H139: 2.960068 | I139: 0 | K139: 2
B140: Two Bedroom_hub 12 | C140: 26.6 | D140: 1223 | E140: 4354.9 | F140: 4354.9 | G140: 3.560834 | H140: 3.560834 | I140: 0 | J140: 61.944444 | K140: 20
B141: Two Bedroom_hub 12a | C141: 5.5 | D141: 1283 | E141: 4056.25 | F141: 4056.25 | G141: 3.1615355 | H141: 3.1615355 | I141: 0 | J141: 20 | K141: 4
B142: Marquee at Block 37 | C142: 20.474328 | D142: 861.99318 | E142: 2816.877 | F142: 2809.2369 | G142: 3.3222574 | H142: 3.3129139 | I142: 0.0027122559 | J142: 67.412821 | K142: 439
B143: Studio | C143: 20.360759 | D143: 669.04142 | E143: 2281.3988 | F143: 2274.75 | G143: 3.4248082 | H143: 3.415255 | I143: 0.0029143565 | J143: 61.107914 | K143: 168
B144: Convertible x 1B | C144: 19.75 | D144: 671 | E144: 2346.6154 | F144: 2346.6154 | G144: 3.4971913 | H144: 3.4971913 | I144: 0 | J144: 48.230769 | K144: 13
B145: Convertible x 1C | C145: 18.6 | D145: 675 | E145: 2306.5 | F145: 2283.2273 | G145: 3.417037 | H145: 3.3825589 | I145: 0.010090062 | J145: 82.6 | K145: 22
B146: Convertible x 1D | C146: 7 | D146: 707 | E146: 2493 | F146: 2493 | G146: 3.5261669 | H146: 3.5261669 | I146: 0 | J146: 29 | K146: 1
B147: Convertible x 1E | C147: 22.125 | D147: 712 | E147: 2403.8824 | F147: 2398.3529 | G147: 3.3762393 | H147: 3.3684732 | I147: 0.0023002007 | J147: 64.764706 | K147: 17
B148: Convertible x 1F | C148: 19.047619 | D148: 715 | E148: 2310.7273 | F148: 2296.0455 | G148: 3.2317864 | H148: 3.2112524 | I148: 0.006353765 | J148: 94.421053 | K148: 22
B149: Studio x 05 | C149: 21.642857 | D149: 581.4 | E149: 2226.7333 | F149: 2226.7333 | G149: 3.8307101 | H149: 3.8307101 | I149: 0 | J149: 64.090909 | K149: 15
B150: Studio x 1A | C150: 19 | D150: 572 | E150: 2060.6667 | F150: 2060.6667 | G150: 3.6025641 | H150: 3.6025641 | I150: 0 | J150: 84.333333 | K150: 3
B151: Studio x 1B | C151: 18 | D151: 574 | E151: 2160.4286 | F151: 2160.4286 | G151: 3.7638128 | H151: 3.7638128 | I151: 0 | J151: 31.666667 | K151: 7
... B166: Convertible x 16 | C166: 18.333333 | D166: 712 | E166: 2443.25 | F166: 2443.25 | G166: 3.4315309 | H166: 3.4315309 | I166: 0 | J166: 64.666667 | K166: 4
B167: Convertible x 10 | C167: 30 | D167: 715 | E167: 2369 | F167: 2369 | G167: 3.3132867 | H167: 3.3132867 | I167: 0 | K167: 1
B168: 1BR | C168: 20.727811 | D168: 803.96685 | E168: 2705.5138 | F168: 2696.9227 | G168: 3.3773449 | H168: 3.3664592 | I168: 0.0031754265 | J168: 59.644578 | K168: 181
B169: 1x1A | C169: 20.75 | D169: 715 | E169: 2568.4706 | F169: 2568.4706 | G169: 3.5922666 | H169: 3.5922666 | I169: 0 | J169: 61.1875 | K169: 17
B170: 1x1B | C170: 24.555556 | D170: 728 | E170: 2747.5556 | F170: 2747.5556 | G170: 3.7741148 | H170: 3.7741148 | I170: 0 | J170: 67.5 | K170: 9
B171: 1x1C | C171: 18.666667 | D171: 728 | E171: 2561.5789 | F171: 2533.1053 | G171: 3.5186524 | H171: 3.4795402 | I171: 0.011115677 | J171: 103.52941 | K171: 19
B172: 1x1E | C172: 23.368421 | D172: 795 | E172: 2727.2857 | F172: 2714.7143 | G172: 3.4305481 | H172: 3.414735 | I172: 0.0046095019 | J172: 54.571429 | K172: 21
B173: 1x1F | C173: 6 | D173: 808 | E173: 2307 | F173: 2307 | G173: 2.855198 | H173: 2.855198 | I173: 0 | J173: 137 | K173: 1
B174: 1x1G | C174: 26 | D174: 812 | E174: 2602.6667 | F174: 2576.3333 | G174: 3.2052545 | H174: 3.1728243 | I174: 0.010117828 | J174: 108.83333 | K174: 6
B175: 1x1H | C175: 21.727273 | D175: 813 | E175: 2873.3333 | F175: 2873.3333 | G175: 3.5342353 | H175: 3.5342353 | I175: 0 | J175: 64.083333 | K175: 12
B176: 1x1I | C176: 15.571429 | D176: 816 | E176: 2586.5714 | F176: 2586.5714 | G176: 3.1698179 | H176: 3.1698179 | I176: 0 | J176: 103.71429 | K176: 7
B177: 1x1J | C177: 6 | D177: 819 | E177: 3036 | F177: 3036 | G177: 3.7069597 | H177: 3.7069597 | I177: 0 | J177: 39 | K177: 1
B178: 1x1K | C178: 22.6 | D178: 822 | E178: 2667.6 | F178: 2648.8 | G178: 3.2452555 | H178: 3.2223844 | I178: 0.0070475334 | J178: 55 | K178: 5
B179: 1x1L | C179: 22.4 | D179: 822 | E179: 2715.5 | F179: 2689 | G179: 3.303528 | H179: 3.2712895 | I179: 0.0097587921 | J179: 28.666667 | K179: 6
... B189: 1 Bedroom x 20 | C189: 21 | D189: 728 | E189: 2495.4 | F189: 2495.4 | G189: 3.4277473 | H189: 3.4277473 | I189: 0 | J189: 18.75 | K189: 5
B190: 1 Bedroom x 18 | C190: 29 | D190: 728 | E190: 2764 | F190: 2764 | G190: 3.7967033 | H190: 3.7967033 | I190: 0 | K190: 2
B191: 1 Bedroom x 09 | D191: 812 | E191: 2862 | F191: 2862 | G191: 3.5246305 | H191: 3.5246305 | I191: 0 | J191: 75 | K191: 1
B192: 1 Bedroom x 06 | C192: 19.666667 | D192: 813 | E192: 2852 | F192: 2852 | G192: 3.5079951 | H192: 3.5079951 | I192: 0 | J192: 188 | K192: 3
B193: 1 Bedroom x 07 | C193: 27.5 | D193: 838.5 | E193: 2672.5 | F193: 2672.5 | G193: 3.1887191 | H193: 3.1887191 | I193: 0 | J193: 6.5 | K193: 2
B194: 1 Bedroom x 04 | C194: 17.5 | D194: 855 | E194: 2913.5 | F194: 2913.5 | G194: 3.4076023 | H194: 3.4076023 | I194: 0 | J194: 6.5 | K194: 2
B195: 1 Bedroom x 23 | C195: 26 | D195: 895.5 | E195: 2847 | F195: 2847 | G195: 3.1802952 | H195: 3.1802952 | I195: 0 | J195: 3 | K195: 2
B196: 1 Bedroom x 11 | C196: 6 | D196: 904 | E196: 2774.5 | F196: 2774.5 | G196: 3.0691372 | H196: 3.0691372 | I196: 0 | J196: 55.5 | K196: 2
B197: 1 Bedroom x 03 | C197: 6 | D197: 985 | E197: 2910 | F197: 2910 | G197: 2.9543147 | H197: 2.9543147 | I197: 0 | K197: 1
B198: 2BR | C198: 19.311688 | D198: 1279.1341 | E198: 3871.6341 | F198: 3863.3171 | G198: 3.0292547 | H198: 3.0228334 | I198: 0.0021482074 | J198: 94.683544 | K198: 82
B199: 2x2B | C199: 22.25 | D199: 1228 | E199: 3874.9444 | F199: 3874.9444 | G199: 3.1554922 | H199: 3.1554922 | I199: 0 | J199: 92.111111 | K199: 18
B200: 2x2C | C200: 17 | D200: 1248 | E200: 3817.5556 | F200: 3812.3333 | G200: 3.0589387 | H200: 3.0547543 | I200: 0.0013679492 | J200: 86.833333 | K200: 18
B201: 2x2D | C201: 16.571429 | D201: 1289 | E201: 3826.5714 | F201: 3805.1429 | G201: 2.9686357 | H201: 2.9520115 | I201: 0.0055999403 | J201: 101.28571 | K201: 7
B202: 2x2E | C202: 17.833333 | D202: 1301 | E202: 3770.8333 | F202: 3734.6667 | G202: 2.8984115 | H202: 2.8706123 | I202: 0.0095911602 | J202: 97.4 | K202: 6
B203: 2x2F | C203: 22.75 | D203: 1305 | E203: 3922.8333 | F203: 3922.8333 | G203: 3.0060026 | H203: 3.0060026 | I203: 0 | J203: 111.66667 | K203: 6
B204: 2x2G | C204: 22 | D204: 1315 | E204: 3883.4444 | F204: 3858.8889 | G204: 2.9531897 | H204: 2.9345163 | I204: 0.0063231381 | J204: 113.28571 | K204: 9
B205: 2x2H | C205: 18.666667 | D205: 1337 | E205: 3877 | F205: 3877 | G205: 2.8997756 | H205: 2.8997756 | I205: 0 | J205: 87.833333 | K205: 6
B206: 2x2I | C206: 21.4 | D206: 1358 | E206: 4146.2 | F206: 4146.2 | G206: 3.0531664 | H206: 3.0531664 | I206: 0 | J206: 76.2 | K206: 5
B207: 2x2J | C207: 6 | D207: 1363 | E207: 3625 | F207: 3625 | G207: 2.6595745 | H207: 2.6595745 | I207: 0 | J207: 152 | K207: 1
B208: 2 Bedroom x 24 | C208: 23.666667 | D208: 1228 | E208: 3820.3333 | F208: 3820.3333 | G208: 3.1110206 | H208: 3.1110206 | I208: 0 | J208: 97.666667 | K208: 3
B209: 2 Bedroom x 25 | C209: 13 | D209: 1322.6667 | E209: 4010.3333 | F209: 4010.3333 | G209: 3.0321203 | H209: 3.0321203 | I209: 0 | J209: 82.333333 | K209: 3
... B213: 3x3D | C213: 34 | D213: 2102 | E213: 5926.3333 | F213: 5926.3333 | G213: 2.8193784 | H213: 2.8193784 | I213: 0 | J213: 25 | K213: 3
B214: 3x3B | D214: 1911 | E214: 5447.5 | F214: 5447.5 | G214: 2.8506018 | H214: 2.8506018 | I214: 0 | J214: 62.5 | K214: 2
B215: MILA | C215: 23.466942 | D215: 771.7439 | E215: 2838.9959 | F215: 2785.5265 | G215: 3.7255387 | H215: 3.6616087 | I215: 0.018833908 | J215: 75.036199 | K215: 245
B216: Studio | C216: 21.9375 | D216: 542.14286 | E216: 2296.9167 | F216: 2273.3542 | G216: 4.2402347 | H216: 4.1977121 | I216: 0.010258317 | J216: 81.880952 | K216: 48
B217: 0A | C217: 19.913043 | D217: 540 | E217: 2233.6957 | F217: 2233.6957 | G217: 4.1364734 | H217: 4.1364734 | I217: 0 | J217: 90.391304 | K217: 23
B218: SA | C218: 22.6875 | D218: 546.17647 | E218: 2292.75 | F218: 2222.0625 | G218: 4.2058893 | H218: 4.0783215 | I218: 0.03083088 | J218: 114 | K218: 16
B219: Residence 06 | C219: 24.25 | D219: 540 | E219: 2742.75 | F219: 2742.75 | G219: 5.0791667 | H219: 5.0791667 | I219: 0 | J219: 42 | K219: 4
B220: Residence 11 | C220: 27 | D220: 540 | E220: 2244.4 | F220: 2244.4 | G220: 4.1562963 | H220: 4.1562963 | I220: 0 | J220: 10.4 | K220: 5
B221: 1BR | C221: 23.662577 | D221: 776.90964 | E221: 2777.9699 | F221: 2727.9036 | G221: 3.5967929 | H221: 3.5346403 | I221: 0.018022609 | J221: 60.933333 | K221: 166
...

Sheet Leasing Trends
B2: Leasing Trends by Property
B3: Note: Figures only utilize data from closed listings. Click pivot table to edit variables.
C5: Column Labels
C6: AMLI River North | E6: Hubbard Place | G6: Marquee at Block 37 | I6: MILA | K6: OneEleven | M6: Optima Signature | O6: The Gallery on Wells | Q6: Wolf Point West | S6: Millie on Michigan | U6: Coast at Lakeshore East
C7: Avg Rent | D7: # Leases | E7: Avg Rent | F7: # Leases | G7: Avg Rent | H7: # Leases | I7: Avg Rent | J7: # Leases | K7: Avg Rent | L7: # Leases | M7: Avg Rent | N7: # Leases | O7: Avg Rent | P7: # Leases | Q7: Avg Rent | R7: # Leases | S7: Avg Rent | T7: # Leases | U7: Avg Rent | V7: # Leases
B8: 2023
B9: Jul | C9: 3011 | D9: 8 | E9: 3545.8333 | F9: 6 | G9: 2980 | H9: 21 | I9: 3326.2857 | J9: 14 | K9: 2609 | L9: 6 | M9: 3940.8 | N9: 5 | O9: 2685.75 | P9: 8 | Q9: 2646.0588 | R9: 17 | S9: 3338.1667 | T9: 6 | U9: 2785.7 | V9: 10
B10: Aug | C10: 2909.2857 | D10: 7 | E10: 3618.3 | F10: 10 | G10: 2645.2353 | H10: 18 | I10: 4224 | J10: 1 | K10: 4677.3333 | L10: 3 | M10: 4130.4444 | N10: 9 | O10: 2801.5 | P10: 3 | Q10: 2732.3529 | R10: 17 | S10: 5294 | T10: 2 | U10: 3066.2222 | V10: 9
B11: Sep | C11: 3653.5 | D11: 2 | E11: 3379 | F11: 6 | G11: 3491.5 | H11: 8 | I11: 3639.25 | J11: 4 | K11: 3134 | L11: 1 | M11: 2974.75 | N11: 4 | O11: 2774 | P11: 3 | Q11: 2830.3571 | R11: 28 | S11: 2505.6667 | T11: 3 | U11: 3532.3333 | V11: 3
B12: Oct | C12: 3406.5 | D12: 4 | E12: 3858.5 | F12: 4 | G12: 2447 | H12: 7 | I12: 3296.6667 | J12: 3 | K12: 2621.6667 | L12: 6 | M12: 3442.3077 | N12: 13 | O12: 2587 | P12: 10 | Q12: 2886.25 | R12: 4 | S12: 3030 | T12: 1 | U12: 3769.6667 | V12: 3
B13: Nov | C13: 2523 | D13: 3 | E13: 3465.5 | F13: 2 | G13: 2678.6667 | H13: 3 | I13: 2953 | J13: 3 | K13: 2819.375 | L13: 8 | M13: 3653.1111 | N13: 9 | O13: 2566.4 | P13: 10 | Q13: 2905 | R13: 3 | S13: 3184 | T13: 1 | U13: 2581 | V13: 4
B14: Dec | C14: 3053.8 | D14: 10 | E14: 2822.5 | F14: 12 | G14: 2038 | H14: 1 | I14: 2951.1667 | J14: 6 | K14: 3094.5 | L14: 4 | M14: 4139.2308 | N14: 13 | O14: 2458.3333 | P14: 6 | Q14: 3623 | R14: 13 | S14: 3250.25 | T14: 4 | U14: 3531 | V14: 1
B15: 2024
B16: Jan | C16: 2940.6667 | D16: 12 | E16: 2860.1111 | F16: 9 | G16: 2055.75 | H16: 4 | K16: 3288.8571 | L16: 7 | M16: 3368.2 | N16: 10 | O16: 2735.2 | P16: 7 | R16: 1 | U16: 2883.25 | V16: 8
B17: Feb | C17: 2812.5 | D17: 12 | E17: 3221.2222 | F17: 9 | G17: 3302 | H17: 7 | I17: 3006.4167 | J17: 12 | K17: 2803.5 | L17: 6 | M17: 3559 | N17: 11 | O17: 2543 | P17: 13 | R17: 1 | S17: 2671 | T17: 4 | U17: 2844 | V17: 1
B18: Mar | C18: 3502.1 | D18: 10 | E18: 2608.25 | F18: 12 | G18: 2970.5263 | H18: 19 | I18: 2479.7692 | J18: 13 | K18: 3252.1818 | L18: 23 | M18: 3677.5556 | N18: 9 | O18: 2801.4286 | P18: 10 | R18: 2 | S18: 3174 | T18: 6 | U18: 2655.0667 | V18: 15
B19: Apr | C19: 3617.6364 | D19: 11 | E19: 3190 | F19: 22 | G19: 2691.963 | H19: 27 | K19: 3718.3571 | L19: 17 | M19: 4229.4 | N19: 15 | O19: 2664.4667 | P19: 16 | R19: 2 | S19: 3083.1667 | T19: 6 | U19: 2921.4211 | V19: 19
B20: May | C20: 3446 | D20: 17 | E20: 3254.0667 | F20: 15 | G20: 2632.5833 | H20: 24 | I20: 2561.5625 | J20: 32 | K20: 3467.4583 | L20: 26 | M20: 3945.44 | N20: 25 | O20: 2697.3333 | P20: 12 | Q20: 2814.0455 | R20: 40 | S20: 3126.8333 | T20: 12 | U20: 3052.0909 | V20: 33
B21: Jun | C21: 3037 | D21: 16 | E21: 3539 | F21: 9 | G21: 2752.3889 | H21: 36 | I21: 2834.1176 | J21: 34 | K21: 2866 | L21: 18 | M21: 4078.9091 | N21: 11 | O21: 2683.0769 | P21: 13 | Q21: 2683.75 | R21: 8 | S21: 2914.3636 | T21: 22 | U21: 2727.4 | V21: 25
B22: Jul | C22: 2705.375 | D22: 8 | E22: 3000.6667 | F22: 9 | G22: 2961.7586 | H22: 29 | I22: 3170.6667 | J22: 15 | K22: 3310 | L22: 15 | M22: 3748.6667 | N22: 21 | O22: 2785.2727 | P22: 11 | Q22: 3423.0588 | R22: 17 | S22: 2748.2632 | T22: 19 | U22: 2721.5455 | V22: 22
B23: Aug | C23: 2853.3 | D23: 10 | E23: 3222.5714 | F23: 14 | G23: 2818.1556 | H23: 45 | I23: 2747.1429 | J23: 14 | K23: 3081.4583 | L23: 24 | M23: 4335.2857 | N23: 14 | O23: 2285.5455 | P23: 11 | Q23: 2720.8462 | R23: 13 | S23: 3305.7857 | T23: 14 | U23: 2940.6667 | V23: 15
B24: Sep | C24: 3166 | D24: 5 | E24: 3137 | F24: 4 | G24: 3509 | H24: 15 | I24: 2380 | J24: 3 | K24: 3573.8235 | L24: 17 | M24: 3230.5556 | N24: 9 | O24: 2818.0833 | P24: 24 | Q24: 2783 | R24: 18 | S24: 3090.6154 | T24: 13 | U24: 2945.4286 | V24: 14
B25: Oct | C25: 3529.5385 | D25: 13 | E25: 3046.875 | F25: 16 | G25: 2944.4815 | H25: 27 | I25: 2513.7778 | J25: 9 | K25: 3354.9167 | L25: 12 | M25: 3932.7778 | N25: 9 | O25: 2703 | P25: 7 | Q25: 2955.3333 | R25: 9 | S25: 2845.0556 | T25: 18 | U25: 2611.7273 | V25: 11
B26: Nov | C26: 3190 | D26: 4 | E26: 2729.8462 | F26: 13 | G26: 2945.8182 | H26: 11 | I26: 2856.6 | J26: 15 | K26: 3328.2727 | L26: 11 | M26: 3548.4444 | N26: 9 | O26: 2679.2609 | P26: 23 | Q26: 3072.3 | R26: 10 | S26: 3146.1176 | T26: 17 | U26: 2693.5833 | V26: 12
B27: Dec | C27: 2988.0909 | D27: 11 | E27: 3252.6667 | F27: 6 | G27: 2618.1333 | H27: 30 | I27: 2686.4375 | J27: 17 | K27: 2893.2667 | L27: 15 | M27: 4055.9231 | N27: 13 | O27: 2624.2632 | P27: 19 | Q27: 2627.6 | R27: 10 | S27: 2539.4118 | T27: 17 | U27: 2768.75 | V27: 16
B28: 2025
B29: Jan | C29: 2754.35 | D29: 20 | E29: 2992.1875 | F29: 16 | G29: 2720.3824 | H29: 34 | I29: 3101.4615 | J29: 13 | K29: 3149.7222 | L29: 18 | M29: 4037.3889 | N29: 18 | O29: 2423.7647 | P29: 17 | Q29: 2629.6429 | R29: 14 | S29: 3199.5 | T29: 8 | U29: 2881.7647 | V29: 17
B30: Feb | C30: 3162.6957 | D30: 23 | E30: 3196.8261 | F30: 23 | G30: 3009.8148 | H30: 27 | I30: 2905 | J30: 5 | K30: 3258.3333 | L30: 12 | M30: 4192.3333 | N30: 12 | O30: 2977.7333 | P30: 15 | Q30: 3190.5 | R30: 8 | S30: 3604.6667 | T30: 6 | U30: 2587.7778 | V30: 18
B31: Mar | C31: 3285.3333 | D31: 21 | E31: 3297.125 | F31: 8 | G31: 2534.7778 | H31: 9 | I31: 2809.2857 | J31: 7 | K31: 4506.9167 | L31: 12 | M31: 3745.4286 | N31: 21 | O31: 3022.0833 | P31: 12 | Q31: 2816.5 | R31: 20 | S31: 2561.75 | T31: 4 | U31: 2937.2 | V31: 15
B32: Apr | C32: 2277 | D32: 2 | G32: 2311 | H32: 1 | I32: 2365 | J32: 1
B33: May | Q33: 1986 | R33: 1
B34: Jun | M34: 2414 | N34: 1 | O34: 2139 | P34: 1 | R34: 1
B35: Jul | C35: 2110 | D35: 1 | M35: 2564 | N35: 1 | O35: 2215 | P35: 1 | Q35: 3325 | R35: 1
B36: Aug | C36: 2166 | D36: 1 | K36: 2269 | L36: 1
B37: Sep | C37: 3338 | D37: 1 | E37: 2104 | F37: 1 | G37: 2104.5 | H37: 2 | K37: 3001 | L37: 1 | M37: 2776 | N37: 1 | O37: 2429 | P37: 1
B38: Oct | G38: 2346 | H38: 1 | K38: 3974 | L38: 1 | M38: 6693 | N38: 1
B39: Nov | E39: 2026 | F39: 1 | G39: 2488 | H39: 1 | S39: 1882 | T39: 1 | U39: 2865 | V39: 1
B40: Dec | E40: 3010 | F40: 2 | G40: 2427 | H40: 1 | K40: 6249 | L40: 1 | S40: 2426 | T40: 1 | U40: 2967 | V40: 2
B42: Rent Trends by Unit Type and Sqft
B43: Note: Figures only utilize data from closed listings. Click pivot table to edit variables.
B45: Avg Rent | C45: Column Labels
C46: 2023 | I46: 2024 | U46: 2025
C47: Jul | D47: Aug | E47: Sep | F47: Oct | G47: Nov | H47: Dec | I47: Jan | J47: Feb | K47: Mar | L47: Apr | M47: May | N47: Jun | O47: Jul | P47: Aug | Q47: Sep | R47: Oct | S47: Nov | T47: Dec | U47: Jan | V47: Feb | W47: Mar | X47: Apr | Y47: May | Z47: Jun | AA47: Jul | AB47: Aug | AC47: Sep | AD47: Oct | AE47: Nov | AF47: Dec
B48: AMLI River North
B49: Studio
B50: 560 | C50: 2257.5 | D50: 2316 | N50: 2371 | P50: 2470 | U50: 2274 | V50: 2216
B51: 572 | D51: 2524 | G51: 2301 | H51: 2283 | I51: 2308 | J51: 2289 | K51: 2410 | N51: 2582.5 | O51: 2570.5 | Q51: 2494 | T51: 2263 | U51: 2316.25 | V51: 2311.5 | W51: 2435
B52: 575 | I52: 2144 | J52: 2030 | L52: 2163 | P52: 2257.3333 | R52: 2098 | T52: 2059 | U52: 2054 | W52: 2157
B53: 585 | C53: 2110 | I53: 1973 | J53: 2034.5 | L53: 2182 | M53: 2231 | N53: 2213.3333 | O53: 2238 | P53: 2287 | R53: 2154 | S53: 2068 | T53: 2015 | AA53: 2110
B54: 593 | D54: 2386 | G54: 2249 | L54: 2323 | N54: 2569 | O54: 2386 | P54: 2425
B55: 604 | H55: 2088.5 | I55: 2076 | N55: 2159 | R55: 2101 | T55: 2063 | U55: 2096 | V55: 2135 | X55: 2059 | AB55: 2166
B56: 653 | D56: 2581 | U56: 2372 | W56: 2340
B57: 660 | C57: 2465 | I57: 2468.5 | J57: 2477 | K57: 2481 | N57: 2626 | O57: 2676 | Q57: 2660 | R57: 2561 | T57: 2541 | U57: 2463.5 | V57: 2515 | W57: 2488.5 | X57: 2495
B58: 1BR
B59: 801 | C59: 3109 | H59: 2880 | I59: 2909 | K59: 2844 | L59: 2946 | M59: 2966 | Q59: 3134 | V59: 3203 | W59: 3096
B60: 827 | F60: 2832 | M60: 3098.6 | N60: 3177.5 | O60: 3254 | Q60: 3220 | R60: 3009 | S60: 3039 | V60: 2866
B61: 850 | M61: 3243 | U61: 2947.5 | V61: 3063.5
B62: 857 | V62: 3515
B63: 865 | C63: 3431 | D63: 3221 | E63: 3195 | F63: 2927 | I63: 2910 | J63: 2982 | M63: 3243.6667 | N63: 3207 | P63: 3380 | S63: 3274 | T63: 3045 | U63: 3134.5 | W63: 3205.6667
B64: 913 | D64: 3546 | V64: 3518
B65: 961 | G65: 3019 | H65: 2996 | K65: 3181 | L65: 3304 | T65: 3164
B66: 966 | K66: 3446 | L66: 3269 | R66: 3424
B67: 980 | M67: 3451 | O67: 3710 | W67: 3482
B68: 993 | H68: 2945 | J68: 3133 | K68: 3140 | U68: 3239 | V68: 3233 | AC68: 3338
B69: 1081 | D69: 3791 | F69: 3886 | H69: 3691 | I69: 3384 | J69: 3447 | K69: 3515 | L69: 3639 | R69: 3930 | V69: 3882 | W69: 3717
B70: 2BR
B71: 1197 | C71: 4278 | E71: 4112 | F71: 3981 | H71: 3981 | K71: 4006 | M71: 4196 | P71: 4433 | R71: 4413 | T71: 4359 | U71: 4062 | V71: 4319 | W71: 4189
B72: 1199 | C72: 4180 | I72: 4189 | L72: 4409 | M72: 4439.5 | N72: 4594.5 | P72: 4341 | Q72: 4322 | R72: 4316.5 | S72: 4379 | T72: 4131 | V72: 4102 | W72: 4287.6667
B73: 1257 | I73: 4269 | T73: 4731 | W73: 4523
B74: 1293 | H74: 4705 | R74: 4699 | V74: 4643
B75: 1742 | K75: 5992 | N75: 6152 | R75: 5853
B76: 3BR
B77: 1752 | L77: 6741 | U77: 6430
B78: 4BR
B79: 660 | T79: 2498
B80: Hubbard Place
B81: Studio
B82: 480 | I82: 1892.5 | J82: 1985.5 | K82: 2034.6667 | L82: 2029.75 | M82: 2098 | N82: 2031 | O82: 2162 | P82: 2276 | R82: 1796 | S82: 1911.6667 | U82: 2077.5 | V82: 1816 | W82: 1980 | AE82: 2026
B83: 546 | H83: 2154 | I83: 2518 | M83: 1781 | O83: 2079.3333 | P83: 2359.5 | Q83: 2159.5 | R83: 2193 | S83: 2157 | U83: 2144 | V83: 2156.5 | W83: 2098 | AC83: 2104
B84: 1BR
B85: 629 | K85: 2649 | M85: 2566 | P85: 2702 | S85: 2375
B86: 658 | H86: 2357 | I86: 2452 | K86: 2679 | L86: 2529 | N86: 2806 | R86: 2661.5 | S86: 2729 | U86: 2758.5 | V86: 2805 | AF86: 2760
B87: 672 | C87: 2865 | H87: 2567 | L87: 2804
B88: 678 | L88: 3068 | R88: 2881 | S88: 2698 | V88: 2655
B89: 689 | H89: 2439 | K89: 2335 | L89: 2811 | M89: 2661 | P89: 3095 | U89: 2652 | V89: 2480
B90: 692 | K90: 2703
B91: 704 | C91: 3211 | E91: 2919 | H91: 2648 | I91: 2845 | J91: 2800 | K91: 2672.5 | L91: 2750 | P91: 2983 | R91: 2694 | T91: 2538.3333
B92: 723 | E92: 2804 | M92: 3103 | N92: 3140 | P92: 3179 | S92: 2850 | V92: 2724
B93: 724 | D93: 3144 | N93: 3108 | P93: 3065 | R93: 2917 | U93: 3034 | W93: 3017
B94: 737 | D94: 2855
B95: 739 | D95: 3022 | F95: 2757 | H95: 2723.5 | I95: 2709 | L95: 3185 | U95: 2983 | V95: 2995 | W95: 3209
B96: 785 | R96: 2733
B97: 799 | K97: 3089 | M97: 3363 | Q97: 3199
B98: 806 | L98: 3127 | N98: 3374 | P98: 3095 | U98: 3039.5
B99: 811 | C99: 3248 | T99: 3225
B100: 818 | I100: 3071 | U100: 3340
B101: 820 | E101: 2811 | H101: 2813 | K101: 3159 | L101: 3243.3333 | O101: 3372 | R101: 3005.5 | V101: 3270 | AF101: 3260
B102: 833 | C102: 3292 | D102: 3316 | E102: 2993 | L102: 3271 | O102: 3270 | P102: 3435 | R102: 3105 | U102: 3182 | V102: 3337
B103: 878 | M103: 2577 | R103: 2486
B104: 883 | G104: 3057 | M104: 3541
...

Sheet Rent Comps
B2: Rent Comps | M2: 30-Day Avg Rents | AA2: 30-Day Avg Net Effective Rents | AO2: 60-Day Avg Rents | BC2: 60-Day Avg Net Effective Rents | BQ2: 90-Day Avg Rents | CE2: 90-Day Avg Net Effective Rents
B3: Property | C3: Address | D3: Similarity | E3: Dist. (mi) | F3: Quality | G3: Yr Built | H3: # Units | I3: Stories | J3: Avg Sqft | K3: Leased % | L3: Exposure % | M3: Studio | N3: Studio PSF | O3: 1BR | P3: 1BR PSF | Q3: 2BR | R3: 2BR PSF | S3: 3BR | T3: 3BR PSF | U3: 4BR | V3: 4BR PSF | W3: 5BR | X3: 5BR PSF | Y3: Avg | Z3: Avg PSF | AA3: Studio | AB3: Studio PSF | AC3: 1BR | AD3: 1BR PSF | AE3: 2BR | AF3: 2BR PSF | AG3: 3BR | AH3: 3BR PSF | AI3: 4BR | AJ3: 4BR PSF | AK3: 5BR | AL3: 5BR PSF | AM3: Avg | AN3: Avg PSF | AO3: Studio | AP3: Studio PSF | AQ3: 1BR | AR3: 1BR PSF | AS3: 2BR | AT3: 2BR PSF | AU3: 3BR | AV3: 3BR PSF | AW3: 4BR | AX3: 4BR PSF | AY3: 5BR | AZ3: 5BR PSF | BA3: Avg | BB3: Avg PSF | BC3: Studio | BD3: Studio PSF | BE3: 1BR | BF3: 1BR PSF | BG3: 2BR | BH3: 2BR PSF | BI3: 3BR | BJ3: 3BR PSF | BK3: 4BR | BL3: 4BR PSF | BM3: 5BR | BN3: 5BR PSF | BO3: Avg | BP3: Avg PSF | BQ3: Studio | BR3: Studio PSF | BS3: 1BR | BT3: 1BR PSF | BU3: 2BR | BV3: 2BR PSF | BW3: 3BR | BX3: 3BR PSF | BY3: 4BR | BZ3: 4BR PSF | CA3: 5BR | CB3: 5BR PSF | CC3: Avg | CD3: Avg PSF | CE3: Studio | CF3: Studio PSF | CG3: 1BR | CH3: 1BR PSF | CI3: 2BR | CJ3: 2BR PSF | CK3: 3BR | CL3: 3BR PSF | CM3: 4BR | CN3: 4BR PSF | CO3: 5BR | CP3: 5BR PSF | CQ3: Avg | CR3: Avg PSF
B4: Hillendale Gate Apartments | C4: 6612 Wycombe Way, Baltimore, MD 21234 | D4: -- | E4: -- | F4: 0.46531648 | G4: 1955 | H4: 330 | I4: 3 | J4: 588 | K4: 1 | L4: 0.003030303 | O4: 1085.5 | P4: 1.8460884 | Y4: 1085.5 | Z4: 1.8460884 | AC4: 1085.5 | AD4: 1.8460884 | AM4: 1085.5 | AN4: 1.8460884 | AQ4: 1085.5 | AR4: 1.8460884 | BA4: 1085.5 | BB4: 1.8460884 | BE4: 1085.5 | BF4: 1.8460884 | BO4: 1085.5 | BP4: 1.8460884 | BS4: 1085.5 | BT4: 1.8460884 | CC4: 1085.5 | CD4: 1.8460884 | CG4: 1085.5 | CH4: 1.8460884 | CQ4: 1085.5 | CR4: 1.8460884
B5: Tall Oaks Apartments | C5: 1002 Pleasant Oaks Road, Baltimore, MD 21234 | D5: 0.92568807 | E5: 0.18377753 | F5: 0.49408513 | G5: 1971 | H5: 296 | I5: 3 | J5: 851 | K5: 1 | L5: 0
B6: Towson Crossing Apartment Homes | C6: 34 Dowling Circle, Baltimore, MD 21234 | D6: 0.83286473 | E6: 0.19578744 | F6: 0.60824421 | G6: 1966 | H6: 465 | I6: 3 | J6: 864.35766 | K6: 0.97204301 | L6: 0.064516129 | O6: 1324.375 | P6: 1.7541266 | Q6: 1344.6 | R6: 1.3790769 | Y6: 1333.2456 | Z6: 1.5640371 | AC6: 1324.375 | AD6: 1.7541266 | AE6: 1344.6 | AF6: 1.3790769 | AM6: 1333.2456 | AN6: 1.5640371 | AQ6: 1331.25 | AR6: 1.7509888 | AS6: 1360.9375 | AT6: 1.3958333 | BA6: 1345.2206 | BB6: 1.5601549 | BE6: 1331.25 | BF6: 1.7509888 | BG6: 1360.9375 | BH6: 1.3958333 | BO6: 1345.2206 | BP6: 1.5601549 | BS6: 1336.5854 | BT6: 1.7561973 | BU6: 1365.9211 | BV6: 1.4009447 | CC6: 1350.6962 | CD6: 1.5617042 | CG6: 1336.5854 | CH6: 1.7561973 | CI6: 1365.9211 | CJ6: 1.4009447 | CQ6: 1350.6962 | CR6: 1.5617042
B7: Northern Village Apartments I | C7: 6624 Pioneer Drive, Baltimore, MD 21214 | D7: 0.86721456 | E7: 0.80443021 | F7: 0.36557161 | G7: 1972 | H7: 228 | I7: 3 | J7: 600 | K7: 1 | L7: 0 | O7: 1117.5 | P7: 1.8625 | Y7: 1117.5 | Z7: 1.8625 | AC7: 1117.5 | AD7: 1.8625 | AM7: 1117.5 | AN7: 1.8625 | AQ7: 1117.5 | AR7: 1.8625 | BA7: 1117.5 | BB7: 1.8625 | BE7: 1117.5 | BF7: 1.8625 | BO7: 1117.5 | BP7: 1.8625 | BS7: 1117.5 | BT7: 1.8625 | CC7: 1117.5 | CD7: 1.8625 | CG7: 1117.5 | CH7: 1.8625 | CQ7: 1117.5 | CR7: 1.8625
B8: Dutch Village | C8: 2349 Perring Manor Road, Baltimore, MD 21234 | D8: 0.83133438 | E8: 0.80733028 | F8: 0.54792949 | G8: 1967 | H8: 544 | I8: 2 | J8: 777.42791 | K8: 0.95955882 | L8: 0.042279412 | O8: 1300 | P8: 2.2908291 | Q8: 1601.5625 | R8: 1.9206913 | S8: 1800 | T8: 1.7786561 | Y8: 1591.3462 | Z8: 1.9248215 | AC8: 1300 | AD8: 2.2908291 | AE8: 1601.5625 | AF8: 1.9206913 | AG8: 1800 | AH8: 1.7786561 | AM8: 1591.3462 | AN8: 1.9248215 | AQ8: 1300 | AR8: 2.2726273 | AS8: 1601.2821 | AT8: 1.9190575 | AU8: 1800 | AV8: 1.7786561 | BA8: 1581.746 | BB8: 1.9303037 | BE8: 1300 | BF8: 2.2726273 | BG8: 1601.2821 | BH8: 1.9190575 | BI8: 1800 | BJ8: 1.7786561 | BO8: 1581.746 | BP8: 1.9303037 | BS8: 1300.8152 | BT8: 2.29257 | BU8: 1600.9091 | BV8: 1.9289114 | BW8: 1806.5789 | BX8: 1.7851571 | CC8: 1539.5349 | CD8: 1.9802928 | CG8: 1300.8152 | CH8: 2.29257 | CI8: 1600.9091 | CJ8: 1.9289114 | CK8: 1806.5789 | CL8: 1.7851571 | CQ8: 1539.5349 | CR8: 1.9802928
B9: The Metropolitan of Baltimore | C9: 6101 Loch Raven Boulevard, Baltimore, MD 21239 | D9: 0.79839532 | E9: 0.56638434 | F9: 0.58036401 | G9: 1961 | H9: 254 | I9: 6 | J9: 1083.287 | K9: 0.95669291 | L9: 0.062992126 | M9: 1436 | N9: 2.942623 | O9: 1651 | P9: 1.7829374 | Q9: 1896.6667 | R9: 1.4708319 | Y9: 1769.8261 | Z9: 1.6148048 | AA9: 1436 | AB9: 2.942623 | AC9: 1651 | AD9: 1.7829374 | AE9: 1896.6667 | AF9: 1.4708319 | AM9: 1769.8261 | AN9: 1.6148048 | AO9: 1436 | AP9: 2.942623 | AQ9: 1651 | AR9: 1.7829374 | AS9: 1864.7857 | AT9: 1.4494486 | BA9: 1762.12 | BB9: 1.5876099 | BC9: 1436 | BD9: 2.942623 | BE9: 1651 | BF9: 1.7829374 | BG9: 1864.7857 | BH9: 1.4494486 | BO9: 1762.12 | BP9: 1.5876099 | BQ9: 1278 | BR9: 2.6188525 | BS9: 1650.6923 | BT9: 1.7826051 | BU9: 1843.0625 | BV9: 1.44821 | CC9: 1725.9355 | CD9: 1.6036927 | CE9: 1278 | CF9: 2.6188525 | CG9: 1650.6923 | CH9: 1.7826051 | CI9: 1843.0625 | CJ9: 1.44821 | CQ9: 1725.9355 | CR9: 1.6036927
B10: Renaissance Club | C10: 1712 Waverly Way, Baltimore, MD 21239 | D10: 0.82162241 | E10: 0.82625578 | F10: 0.59688185 | G10: 1948 | H10: 515 | I10: 3 | J10: 681.75439 | K10: 0.98058252 | L10: 0.027184466 | O10: 1264.2308 | P10: 2.1064103 | Q10: 1425 | R10: 1.9 | Y10: 1350.3571 | Z10: 1.9816562 | AC10: 1264.2308 | AD10: 2.1064103 | AE10: 1425 | AF10: 1.9 | AM10: 1350.3571 | AN10: 1.9816562 | AQ10: 1261.5625 | AR10: 2.1020833 | AS10: 1434.2105 | AT10: 1.9122807 | BA10: 1355.2857 | BB10: 1.9863903 | BE10: 1261.5625 | BF10: 2.1020833 | BG10: 1434.2105 | BH10: 1.9122807 | BO10: 1355.2857 | BP10: 1.9863903 | BS10: 1258.4091 | BT10: 2.0817541 | BU10: 1424 | BV10: 1.8986667 | CC10: 1346.4894 | CD10: 1.972417 | CG10: 1258.4091 | CH10: 2.0817541 | CI10: 1424 | CJ10: 1.8986667 | CQ10: 1346.4894 | CR10: 1.972417
B11: Park Crescent | C11: 6535 Falkirk Road, Baltimore, MD 21239 | D11: 0.74459375 | E11: 0.44947935 | F11: 0.55043258 | G11: 1964 | H11: 168 | I11: 3 | J11: 619.49495 | K11: 0.9702381 | L11: 0.041666667 | O11: 1259 | P11: 2.2890909 | Q11: 1434.3125 | R11: 2.2766865 | Y11: 1424 | Z11: 2.2773283 | AC11: 1259 | AD11: 2.2890909 | AE11: 1322.0625 | AF11: 2.0985119 | AM11: 1318.3529 | AN11: 2.1083725 | AQ11: 1322.3333 | AR11: 2.4042424 | AS11: 1414.4545 | AT11: 2.2451659 | BA11: 1403.4 | BB11: 2.262089 | BE11: 1283.3333 | BF11: 2.3333333 | BG11: 1317.6364 | BH11: 2.0914863 | BO11: 1313.52 | BP11: 2.1172147 | BS11: 1322.3333 | BT11: 2.4042424 | BU11: 1416.7586 | BV11: 2.2488232 | CC11: 1407.9062 | CD11: 2.2616968 | CG11: 1283.3333 | CH11: 2.3333333 | CI11: 1343.3103 | CJ11: 2.1322386 | CQ11: 1337.6875 | CR11: 2.1488956

Sheet Rent Comparison
B2: Property Name | C2: Hillendale Gate Apartments | D2: Comps Avg | E2: $△ | F2: %△ | G2: Tall Oaks Apartments | H2: Towson Crossing Apartment Homes | I2: Northern Village Apartments I | J2: Dutch Village | K2: The Metropolitan of Baltimore | L2: Renaissance Club | M2: Park Crescent
B3: Management Company | C3: Hendersen Webb | G3: Hendersen Webb Inc | H3: Morgan Properties | I3: Habitat America | J3: Ross Companies | K3: Rocks Engineering Company | L3: Tryko Partners | M3: Maryland Management
B4: Property Website | H4: www.towsoncrossingapartments.com | I4: http://www.rentnorthernvillage.com/ | J4: https://www.dutchvillageapt.com/ | K4: https://metropolitanofbaltimore.com/ | L4: https://www.rcapts.com/ | M4: http://www.parkcrescentapts.com/
B5: Distance (mi) | C5: -- | D5: =IFERROR(AVERAGE(INDIRECT("G"&ROW()&":Z"&ROW())),"") | E5: -- | G5: 0.18377753 | H5: 0.19578744 | I5: 0.80443021 | J5: 0.80733028 | K5: 0.56638434 | L5: 0.82625578 | M5: 0.44947935
B6: Similarity | C6: -- | E6: -- | G6: 0.92568807 | H6: 0.83286473 | I6: 0.86721456 | J6: 0.83133438 | K6: 0.79839532 | L6: 0.82162241 | M6: 0.74459375
B7: Year Built | C7: 1955 | G7: 1971 | H7: 1966 | I7: 1972 | J7: 1967 | K7: 1961 | L7: 1948 | M7: 1964
B8: # Units | C8: 330 | D8: =IFERROR(AVERAGE(INDIRECT("G"&ROW()&":Z"&ROW())),"") | G8: 296 | H8: 465 | I8: 228 | J8: 544 | K8: 254 | L8: 515 | M8: 168
B9: Leased % (Advertised) | C9: 1 | D9: =IFERROR(AVERAGE(INDIRECT("G"&ROW()&":Z"&ROW())),"") | E9: =IF(C9>0,IFERROR((C9-D9),""),"") | F9: =IFERROR(E9/D9,"") | G9: 1 | H9: 0.97204301 | I9: 1 | J9: 0.95955882 | K9: 0.95669291 | L9: 0.98058252 | M9: 0.9702381
B10: Exposure | C10: 0.003030303 | D10: =IFERROR(AVERAGE(INDIRECT("G"&ROW()&":Z"&ROW())),"") | E10: =IF(C10>0,IFERROR((C10-D10),""),"") | F10: =IFERROR(E10/D10,"") | G10: 0 | H10: 0.064516129 | I10: 0 | J10: 0.042279412 | K10: 0.062992126 | L10: 0.027184466 | M10: 0.041666667
B11: Quality | C11: 0.46531648 | D11: =IFERROR(AVERAGE(INDIRECT("G"&ROW()&":Z"&ROW())),"") | E11: =IF(C11>0,IFERROR((C11-D11),""),"") | F11: =IFERROR(E11/D11,"") | G11: 0.49408513 | H11: 0.60824421 | I11: 0.36557161 | J11: 0.54792949 | K11: 0.58036401 | L11: 0.59688185 | M11: 0.55043258
B12: Avg Rents
B13: 30-Day Avg | C13: 1085.5 | D13: =IFERROR(AVERAGE(INDIRECT("G"&ROW()&":Z"&ROW())),"") | E13: =IF(C13>0,IFERROR((C13-D13),""),"") | F13: =IFERROR(E13/D13,"") | H13: 1333.2456 | I13: 1117.5 | J13: 1591.3462 | K13: 1769.8261 | L13: 1350.3571 | M13: 1424
B14: 60-Day Avg | C14: 1085.5 | D14: =IFERROR(AVERAGE(INDIRECT("G"&ROW()&":Z"&ROW())),"") | E14: =IF(C14>0,IFERROR((C14-D14),""),"") | F14: =IFERROR(E14/D14,"") | H14: 1345.2206 | I14: 1117.5 | J14: 1581.746 | K14: 1762.12 | L14: 1355.2857 | M14: 1403.4
B15: 90-Day Avg | C15: 1085.5 | D15: =IFERROR(AVERAGE(INDIRECT("G"&ROW()&":Z"&ROW())),"") | E15: =IF(C15>0,IFERROR((C15-D15),""),"") | F15: =IFERROR(E15/D15,"") | H15: 1350.6962 | I15: 1117.5 | J15: 1539.5349 | K15: 1725.9355 | L15: 1346.4894 | M15: 1407.9062
B16: Net Effective Rents
B17: 30-Day Avg | C17: 1085.5 | D17: =IFERROR(AVERAGE(INDIRECT("G"&ROW()&":Z"&ROW())),"") | E17: =IF(C17>0,IFERROR((C17-D17),""),"") | F17: =IFERROR(E17/D17,"") | H17: 1333.2456 | I17: 1117.5 | J17: 1591.3462 | K17: 1769.8261 | L17: 1350.3571 | M17: 1318.3529
B18: 60-Day Avg | C18: 1085.5 | D18: =IFERROR(AVERAGE(INDIRECT("G"&ROW()&":Z"&ROW())),"") | E18: =IF(C18>0,IFERROR((C18-D18),""),"") | F18: =IFERROR(E18/D18,"") | H18: 1345.2206 | I18: 1117.5 | J18: 1581.746 | K18: 1762.12 | L18: 1355.2857 | M18: 1313.52
B19: 90-Day Avg | C19: 1085.5 | D19: =IFERROR(AVERAGE(INDIRECT("G"&ROW()&":Z"&ROW())),"") | E19: =IF(C19>0,IFERROR((C19-D19),""),"") | F19: =IFERROR(E19/D19,"") | H19: 1350.6962 | I19: 1117.5 | J19: 1539.5349 | K19: 1725.9355 | L19: 1346.4894 | M19: 1337.6875
B20: Rent Per Sqft
B21: 30-Day Avg | C21: 1.8460884 | D21: =IFERROR(AVERAGE(INDIRECT("G"&ROW()&":Z"&ROW())),"") | E21: =IF(C21>0,IFERROR((C21-D21),""),"") | F21: =IFERROR(E21/D21,"") | H21: 1.5640371 | I21: 1.8625 | J21: 1.9248215 | K21: 1.6148048 | L21: 1.9816562 | M21: 2.2773283
B22: 60-Day Avg | C22: 1.8460884 | D22: =IFERROR(AVERAGE(INDIRECT("G"&ROW()&":Z"&ROW())),"") | E22: =IF(C22>0,IFERROR((C22-D22),""),"") | F22: =IFERROR(E22/D22,"") | H22: 1.5601549 | I22: 1.8625 | J22: 1.9303037 | K22: 1.5876099 | L22: 1.9863903 | M22: 2.262089
B23: 90-Day Avg | C23: 1.8460884 | D23: =IFERROR(AVERAGE(INDIRECT("G"&ROW()&":Z"&ROW())),"") | E23: =IF(C23>0,IFERROR((C23-D23),""),"") | F23: =IFERROR(E23/D23,"") | H23: 1.5617042 | I23: 1.8625 | J23: 1.9802928 | K23: 1.6036927 | L23: 1.972417 | M23: 2.2616968
B24: NER Per Sqft
B25: 30-Day Avg | C25: 1.8460884 | D25: =IFERROR(AVERAGE(INDIRECT("G"&ROW()&":Z"&ROW())),"") | E25: =IF(C25>0,IFERROR((C25-D25),""),"") | F25: =IFERROR(E25/D25,"") | H25: 1.5640371 | I25: 1.8625 | J25: 1.9248215 | K25: 1.6148048 | L25: 1.9816562 | M25: 2.1083725
B26: 60-Day Avg | C26: 1.8460884 | D26: =IFERROR(AVERAGE(INDIRECT("G"&ROW()&":Z"&ROW())),"") | E26: =IF(C26>0,IFERROR((C26-D26),""),"") | F26: =IFERROR(E26/D26,"") | H26: 1.5601549 | I26: 1.8625 | J26: 1.9303037 | K26: 1.5876099 | L26: 1.9863903 | M26: 2.1172147
B27: 90-Day Avg | C27: 1.8460884 | D27: =IFERROR(AVERAGE(INDIRECT("G"&ROW()&":Z"&ROW())),"") | E27: =IF(C27>0,IFERROR((C27-D27),""),"") | F27: =IFERROR(E27/D27,"") | H27: 1.5617042 | I27: 1.8625 | J27: 1.9802928 | K27: 1.6036927 | L27: 1.972417 | M27: 2.1488956
B28: Studio Rents
B29: 30-Day Avg | D29: =IFERROR(AVERAGE(INDIRECT("G"&ROW()&":Z"&ROW())),"") | E29: =IF(C29>0,IFERROR((C29-D29),""),"") | F29: =IFERROR(E29/D29,"") | K29: 1436
B30: 60-Day Avg | D30: =IFERROR(AVERAGE(INDIRECT("G"&ROW()&":Z"&ROW())),"") | E30: =IF(C30>0,IFERROR((C30-D30),""),"") | F30: =IFERROR(E30/D30,"") | K30: 1436
B31: 90-Day Avg | D31: =IFERROR(AVERAGE(INDIRECT("G"&ROW()&":Z"&ROW())),"") | E31: =IF(C31>0,IFERROR((C31-D31),""),"") | F31: =IFERROR(E31/D31,"") | K31: 1278
B32: Studio Effective Rents
B33: 30-Day Avg | D33: =IFERROR(AVERAGE(INDIRECT("G"&ROW()&":Z"&ROW())),"") | E33: =IF(C33>0,IFERROR((C33-D33),""),"") | F33: =IFERROR(E33/D33,"") | K33: 1436
B34: 60-Day Avg | D34: =IFERROR(AVERAGE(INDIRECT("G"&ROW()&":Z"&ROW())),"") | E34: =IF(C34>0,IFERROR((C34-D34),""),"") | F34: =IFERROR(E34/D34,"") | K34: 1436
B35: 90-Day Avg | D35: =IFERROR(AVERAGE(INDIRECT("G"&ROW()&":Z"&ROW())),"") | E35: =IF(C35>0,IFERROR((C35-D35),""),"") | F35: =IFERROR(E35/D35,"") | K35: 1278
B36: Studio Rents PSF
B37: 30-Day Avg | D37: =IFERROR(AVERAGE(INDIRECT("G"&ROW()&":Z"&ROW())),"") | E37: =IF(C37>0,IFERROR((C37-D37),""),"") | F37: =IFERROR(E37/D37,"") | K37: 2.942623
B38: 60-Day Avg | D38: =IFERROR(AVERAGE(INDIRECT("G"&ROW()&":Z"&ROW())),"") | E38: =IF(C38>0,IFERROR((C38-D38),""),"") | F38: =IFERROR(E38/D38,"") | K38: 2.942623
B39: 90-Day Avg | D39: =IFERROR(AVERAGE(INDIRECT("G"&ROW()&":Z"&ROW())),"") | E39: =IF(C39>0,IFERROR((C39-D39),""),"") | F39: =IFERROR(E39/D39,"") | K39: 2.6188525
B40: Studio Effective Rents PSF
B41: 30-Day Avg | D41: =IFERROR(AVERAGE(INDIRECT("G"&ROW()&":Z"&ROW())),"") | E41: =IF(C41>0,IFERROR((C41-D41),""),"") | F41: =IFERROR(E41/D41,"") | K41: 2.942623
B42: 60-Day Avg | D42: =IFERROR(AVERAGE(INDIRECT("G"&ROW()&":Z"&ROW())),"") | E42: =IF(C42>0,IFERROR((C42-D42),""),"") | F42: =IFERROR(E42/D42,"") | K42: 2.942623
B43: 90-Day Avg | D43: =IFERROR(AVERAGE(INDIRECT("G"&ROW()&":Z"&ROW())),"") | E43: =IF(C43>0,IFERROR((C43-D43),""),"") | F43: =IFERROR(E43/D43,"") | K43: 2.6188525
B44: 1BR Rents
B45: 30-Day Avg | C45: 1085.5 | D45: =IFERROR(AVERAGE(INDIRECT("G"&ROW()&":Z"&ROW())),"") | E45: =IF(C45>0,IFERROR((C45-D45),""),"") | F45: =IFERROR(E45/D45,"") | H45: 1324.375 | I45: 1117.5 | J45: 1300 | K45: 1651 | L45: 1264.2308 | M45: 1259
B46: 60-Day Avg | C46: 1085.5 | D46: =IFERROR(AVERAGE(INDIRECT("G"&ROW()&":Z"&ROW())),"") | E46: =IF(C46>0,IFERROR((C46-D46),""),"") | F46: =IFERROR(E46/D46,"") | H46: 1331.25 | I46: 1117.5 | J46: 1300 | K46: 1651 | L46: 1261.5625 | M46: 1322.3333
B47: 90-Day Avg | C47: 1085.5 | D47: =IFERROR(AVERAGE(INDIRECT("G"&ROW()&":Z"&ROW())),"") | E47: =IF(C47>0,IFERROR((C47-D47),""),"") | F47: =IFERROR(E47/D47,"") | H47: 1336.5854 | I47: 1117.5 | J47: 1300.8152 | K47: 1650.6923 | L47: 1258.4091 | M47: 1322.3333
B48: 1BR Effective Rents
B49: 30-Day Avg | C49: 1085.5 | D49: =IFERROR(AVERAGE(INDIRECT("G"&ROW()&":Z"&ROW())),"") | E49: =IF(C49>0,IFERROR((C49-D49),""),"") | F49: =IFERROR(E49/D49,"") | H49: 1324.375 | I49: 1117.5 | J49: 1300 | K49: 1651 | L49: 1264.2308 | M49: 1259
B50: 60-Day Avg | C50: 1085.5 | D50: =IFERROR(AVERAGE(INDIRECT("G"&ROW()&":Z"&ROW())),"") | E50: =IF(C50>0,IFERROR((C50-D50),""),"") | F50: =IFERROR(E50/D50,"") | H50: 1331.25 | I50: 1117.5 | J50: 1300 | K50: 1651 | L50: 1261.5625 | M50: 1283.3333
B51: 90-Day Avg | C51: 1085.5 | D51: =IFERROR(AVERAGE(INDIRECT("G"&ROW()&":Z"&ROW())),"") | E51: =IF(C51>0,IFERROR((C51-D51),""),"") | F51: =IFERROR(E51/D51,"") | H51: 1336.5854 | I51: 1117.5 | J51: 1300.8152 | K51: 1650.6923 | L51: 1258.4091 | M51: 1283.3333
B52: 1BR Rents PSF
B53: 30-Day Avg | C53: 1.8460884 | D53: =IFERROR(AVERAGE(INDIRECT("G"&ROW()&":Z"&ROW())),"") | E53: =IF(C53>0,IFERROR((C53-D53),""),"") | F53: =IFERROR(E53/D53,"") | H53: 1.7541266 | I53: 1.8625 | J53: 2.2908291 | K53: 1.7829374 | L53: 2.1064103 | M53: 2.2890909
B54: 60-Day Avg | C54: 1.8460884 | D54: =IFERROR(AVERAGE(INDIRECT("G"&ROW()&":Z"&ROW())),"") | E54: =IF(C54>0,IFERROR((C54-D54),""),"") | F54: =IFERROR(E54/D54,"") | H54: 1.7509888 | I54: 1.8625 | J54: 2.2726273 | K54: 1.7829374 | L54: 2.1020833 | M54: 2.4042424
B55: 90-Day Avg | C55: 1.8460884 | D55: =IFERROR(AVERAGE(INDIRECT("G"&ROW()&":Z"&ROW())),"") | E55: =IF(C55>0,IFERROR((C55-D55),""),"") | F55: =IFERROR(E55/D55,"") | H55: 1.7561973 | I55: 1.8625 | J55: 2.29257 | K55: 1.7826051 | L55: 2.0817541 | M55: 2.4042424
B56: 1BR Effective Rents PSF
B57: 30-Day Avg | C57: 1.8460884 | D57: =IFERROR(AVERAGE(INDIRECT("G"&ROW()&":Z"&ROW())),"") | E57: =IF(C57>0,IFERROR((C57-D57),""),"") | F57: =IFERROR(E57/D57,"") | H57: 1.7541266 | I57: 1.8625 | J57: 2.2908291 | K57: 1.7829374 | L57: 2.1064103 | M57: 2.2890909
B58: 60-Day Avg | C58: 1.8460884 | D58: =IFERROR(AVERAGE(INDIRECT("G"&ROW()&":Z"&ROW())),"") | E58: =IF(C58>0,IFERROR((C58-D58),""),"") | F58: =IFERROR(E58/D58,"") | H58: 1.7509888 | I58: 1.8625 | J58: 2.2726273 | K58: 1.7829374 | L58: 2.1020833 | M58: 2.3333333
B59: 90-Day Avg | C59: 1.8460884 | D59: =IFERROR(AVERAGE(INDIRECT("G"&ROW()&":Z"&ROW())),"") | E59: =IF(C59>0,IFERROR((C59-D59),""),"") | F59: =IFERROR(E59/D59,"") | H59: 1.7561973 | I59: 1.8625 | J59: 2.29257 | K59: 1.7826051 | L59: 2.0817541 | M59: 2.3333333
B60: 2BR Rents
B61: 30-Day Avg | D61: =IFERROR(AVERAGE(INDIRECT("G"&ROW()&":Z"&ROW())),"") | E61: =IF(C61>0,IFERROR((C61-D61),""),"") | F61: =IFERROR(E61/D61,"") | H61: 1344.6 | J61: 1601.5625 | K61: 1896.6667 | L61: 1425 | M61: 1434.3125
B62: 60-Day Avg | D62: =IFERROR(AVERAGE(INDIRECT("G"&ROW()&":Z"&ROW())),"") | E62: =IF(C62>0,IFERROR((C62-D62),""),"") | F62: =IFERROR(E62/D62,"") | H62: 1360.9375 | J62: 1601.2821 | K62: 1864.7857 | L62: 1434.2105 | M62: 1414.4545
B63: 90-Day Avg | D63: =IFERROR(AVERAGE(INDIRECT("G"&ROW()&":Z"&ROW())),"") | E63: =IF(C63>0,IFERROR((C63-D63),""),"") | F63: =IFERROR(E63/D63,"") | H63: 1365.9211 | J63: 1600.9091 | K63: 1843.0625 | L63: 1424 | M63: 1416.7586
B64: 2BR Effective Rents
B65: 30-Day Avg | D65: =IFERROR(AVERAGE(INDIRECT("G"&ROW()&":Z"&ROW())),"") | E65: =IF(C65>0,IFERROR((C65-D65),""),"") | F65: =IFERROR(E65/D65,"") | H65: 1344.6 | J65: 1601.5625 | K65: 1896.6667 | L65: 1425 | M65: 1322.0625
B66: 60-Day Avg | D66: =IFERROR(AVERAGE(INDIRECT("G"&ROW()&":Z"&ROW())),"") | E66: =IF(C66>0,IFERROR((C66-D66),""),"") | F66: =IFERROR(E66/D66,"") | H66: 1360.9375 | J66: 1601.2821 | K66: 1864.7857 | L66: 1434.2105 | M66: 1317.6364
B67: 90-Day Avg | D67: =IFERROR(AVERAGE(INDIRECT("G"&ROW()&":Z"&ROW())),"") | E67: =IF(C67>0,IFERROR((C67-D67),""),"") | F67: =IFERROR(E67/D67,"") | H67: 1365.9211 | J67: 1600.9091 | K67: 1843.0625 | L67: 1424 | M67: 1343.3103
B68: 2BR Rents PSF
B69: 30-Day Avg | D69: =IFERROR(AVERAGE(INDIRECT("G"&ROW()&":Z"&ROW())),"") | E69: =IF(C69>0,IFERROR((C69-D69),""),"") | F69: =IFERROR(E69/D69,"") | H69: 1.3790769 | J69: 1.9206913 | K69: 1.4708319 | L69: 1.9 | M69: 2.2766865
B70: 60-Day Avg | D70: =IFERROR(AVERAGE(INDIRECT("G"&ROW()&":Z"&ROW())),"") | E70: =IF(C70>0,IFERROR((C70-D70),""),"") | F70: =IFERROR(E70/D70,"") | H70: 1.3958333 | J70: 1.9190575 | K70: 1.4494486 | L70: 1.9122807 | M70: 2.2451659
B71: 90-Day Avg | D71: =IFERROR(AVERAGE(INDIRECT("G"&ROW()&":Z"&ROW())),"") | E71: =IF(C71>0,IFERROR((C71-D71),""),"") | F71: =IFERROR(E71/D71,"") | H71: 1.4009447 | J71: 1.9289114 | K71: 1.44821 | L71: 1.8986667 | M71: 2.2488232
B72: 2BR Effective Rents PSF
B73: 30-Day Avg | D73: =IFERROR(AVERAGE(INDIRECT("G"&ROW()&":Z"&ROW())),"") | E73: =IF(C73>0,IFERROR((C73-D73),""),"") | F73: =IFERROR(E73/D73,"") | H73: 1.3790769 | J73: 1.9206913 | K73: 1.4708319 | L73: 1.9 | M73: 2.0985119
B74: 60-Day Avg | D74: =IFERROR(AVERAGE(INDIRECT("G"&ROW()&":Z"&ROW())),"") | E74: =IF(C74>0,IFERROR((C74-D74),""),"") | F74: =IFERROR(E74/D74,"") | H74: 1.3958333 | J74: 1.9190575 | K74: 1.4494486 | L74: 1.9122807 | M74: 2.0914863
B75: 90-Day Avg | D75: =IFERROR(AVERAGE(INDIRECT("G"&ROW()&":Z"&ROW())),"") | E75: =IF(C75>0,IFERROR((C75-D75),""),"") | F75: =IFERROR(E75/D75,"") | H75: 1.4009447 | J75: 1.9289114 | K75: 1.44821 | L75: 1.8986667 | M75: 2.1322386
B76: 3BR Rents
B77: 30-Day Avg | D77: =IFERROR(AVERAGE(INDIRECT("G"&ROW()&":Z"&ROW())),"") | E77: =IF(C77>0,IFERROR((C77-D77),""),"") | F77: =IFERROR(E77/D77,"") | J77: 1800
B78: 60-Day Avg | D78: =IFERROR(AVERAGE(INDIRECT("G"&ROW()&":Z"&ROW())),"") | E78: =IF(C78>0,IFERROR((C78-D78),""),"") | F78: =IFERROR(E78/D78,"") | J78: 1800
B79: 90-Day Avg | D79: =IFERROR(AVERAGE(INDIRECT("G"&ROW()&":Z"&ROW())),"") | E79: =IF(C79>0,IFERROR((C79-D79),""),"") | F79: =IFERROR(E79/D79,"") | J79: 1806.5789
B80: 3BR Effective Rents
B81: 30-Day Avg | D81: =IFERROR(AVERAGE(INDIRECT("G"&ROW()&":Z"&ROW())),"") | E81: =IF(C81>0,IFERROR((C81-D81),""),"") | F81: =IFERROR(E81/D81,"") | J81: 1800
B82: 60-Day Avg | D82: =IFERROR(AVERAGE(INDIRECT("G"&ROW()&":Z"&ROW())),"") | E82: =IF(C82>0,IFERROR((C82-D82),""),"") | F82: =IFERROR(E82/D82,"") | J82: 1800
B83: 90-Day Avg | D83: =IFERROR(AVERAGE(INDIRECT("G"&ROW()&":Z"&ROW())),"") | E83: =IF(C83>0,IFERROR((C83-D83),""),"") | F83: =IFERROR(E83/D83,"") | J83: 1806.5789
B84: 3BR Rents PSF
B85: 30-Day Avg | D85: =IFERROR(AVERAGE(INDIRECT("G"&ROW()&":Z"&ROW())),"") | E85: =IF(C85>0,IFERROR((C85-D85),""),"") | F85: =IFERROR(E85/D85,"") | J85: 1.7786561
B86: 60-Day Avg | D86: =IFERROR(AVERAGE(INDIRECT("G"&ROW()&":Z"&ROW())),"") | E86: =IF(C86>0,IFERROR((C86-D86),""),"") | F86: =IFERROR(E86/D86,"") | J86: 1.7786561
B87: 90-Day Avg | D87: =IFERROR(AVERAGE(INDIRECT("G"&ROW()&":Z"&ROW())),"") | E87: =IF(C87>0,IFERROR((C87-D87),""),"") | F87: =IFERROR(E87/D87,"") | J87: 1.7851571
B88: 3BR Effective Rents PSF
B89: 30-Day Avg | D89: =IFERROR(AVERAGE(INDIRECT("G"&ROW()&":Z"&ROW())),"") | E89: =IF(C89>0,IFERROR((C89-D89),""),"") | F89: =IFERROR(E89/D89,"") | J89: 1.7786561
B90: 60-Day Avg | D90: =IFERROR(AVERAGE(INDIRECT("G"&ROW()&":Z"&ROW())),"") | E90: =IF(C90>0,IFERROR((C90-D90),""),"") | F90: =IFERROR(E90/D90,"") | J90: 1.7786561
B91: 90-Day Avg | D91: =IFERROR(AVERAGE(INDIRECT("G"&ROW()&":Z"&ROW())),"") | E91: =IF(C91>0,IFERROR((C91-D91),""),"") | F91: =IFERROR(E91/D91,"") | J91: 1.7851571
B92: 4BR Rents
B93: 30-Day Avg | D93: =IFERROR(AVERAGE(INDIRECT("G"&ROW()&":Z"&ROW())),"") | E93: =IF(C93>0,IFERROR((C93-D93),""),"") | F93: =IFERROR(E93/D93,"")
B94: 60-Day Avg | D94: =IFERROR(AVERAGE(INDIRECT("G"&ROW()&":Z"&ROW())),"") | E94: =IF(C94>0,IFERROR((C94-D94),""),"") | F94: =IFERROR(E94/D94,"")
B95: 90-Day Avg | D95: =IFERROR(AVERAGE(INDIRECT("G"&ROW()&":Z"&ROW())),"") | E95: =IF(C95>0,IFERROR((C95-D95),""),"") | F95: =IFERROR(E95/D95,"")
B96: 4BR Effective Rents
B97: 30-Day Avg | D97: =IFERROR(AVERAGE(INDIRECT("G"&ROW()&":Z"&ROW())),"") | E97: =IF(C97>0,IFERROR((C97-D97),""),"") | F97: =IFERROR(E97/D97,"")
B98: 60-Day Avg | D98: =IFERROR(AVERAGE(INDIRECT("G"&ROW()&":Z"&ROW())),"") | E98: =IF(C98>0,IFERROR((C98-D98),""),"") | F98: =IFERROR(E98/D98,"")
B99: 90-Day Avg | D99: =IFERROR(AVERAGE(INDIRECT("G"&ROW()&":Z"&ROW())),"") | E99: =IF(C99>0,IFERROR((C99-D99),""),"") | F99: =IFERROR(E99/D99,"")
B100: 4BR Rents PSF
B101: 30-Day Avg | D101: =IFERROR(AVERAGE(INDIRECT("G"&ROW()&":Z"&ROW())),"") | E101: =IF(C101>0,IFERROR((C101-D101),""),"") | F101: =IFERROR(E101/D101,"")
...

Sheet Unit-Level Data
B2: Unit-Level Data | T2: Note: Unit-Level Data includes ALL listings surveyed at the subject property and across the selected comps since June 2023.
B3: Property Name | C3: Address | D3: Floorplan Name | E3: Unit # | F3: Floor # | G3: Beds | H3: Baths | I3: Partial Baths | J3: Sqft | K3: First Listed | L3: Leased Date | M3: Active Listing? | N3: Days on Mkt | O3: Asking Rent | P3: Asking PSF | Q3: Effective Rent | R3: Effective PSF | S3: Advertised Unit Amenities | T3: Detected Unit Amenities
B4: Tall Oaks Apartments | C4: 1002 Pleasant Oaks Road | D4: 1 Bedroom | G4: 1 | H4: 1 | J4: 741 | K4: 45246 | L4: 45661 | M4: FALSE | N4: 416 | O4: 1150 | P4: 1.5519568 | Q4: 1150 | R4: 1.5519568 | S4: [] | T4: []
B5: Tall Oaks Apartments | C5: 1002 Pleasant Oaks Road | D5: 1 Bedroom with Den | G5: 1 | H5: 1 | J5: 852 | K5: 45246 | L5: 45661 | M5: FALSE | N5: 416 | O5: 1256 | P5: 1.4741784 | Q5: 1256 | R5: 1.4741784 | S5: [] | T5: [den]
B6: Tall Oaks Apartments | C6: 1002 Pleasant Oaks Road | D6: 2 Bedroom | G6: 2 | H6: 1 | J6: 960 | K6: 45246 | L6: 45661 | M6: FALSE | N6: 416 | O6: 1329 | P6: 1.384375 | Q6: 1329 | R6: 1.384375 | S6: [] | T6: []
B7: Towson Crossing Apartment Homes | C7: 34 Dowling Circle | D7: One Bedroom | E7: DB03A2 | F7: 2 | G7: 1 | H7: 1 | J7: 728 | K7: 45416 | L7: 45441 | M7: FALSE | N7: 26 | O7: 1150 | P7: 1.5796703 | Q7: 1150 | R7: 1.5796703 | S7: [Second Floor Stackable Washer and Dryer] | T7: [washer_dryer floor washer_dryer.stackable]
B8: Towson Crossing Apartment Homes | C8: 34 Dowling Circle | D8: One Bedroom | E8: DL18B2 | F8: 2 | G8: 1 | H8: 1 | J8: 728 | K8: 45442 | L8: 45447 | M8: FALSE | N8: 6 | O8: 1165 | P8: 1.6002747 | Q8: 1165 | R8: 1.6002747 | S8: [Third Floor Stackable Washer and Dryer] | T8: [washer_dryer floor washer_dryer.stackable]
B9: Towson Crossing Apartment Homes | C9: 34 Dowling Circle | D9: One Bedroom | E9: DB17A1 | F9: 1 | G9: 1 | H9: 1 | J9: 728 | K9: 45523 | L9: 45609 | M9: FALSE | N9: 87 | O9: 1195 | P9: 1.6414835 | Q9: 1195 | R9: 1.6414835 | S9: [Tile Backsplash Second Floor Oak Cabinets Black Appliances Stackable Washer and Dryer Microwave] | T9: [washer_dryer floor washer_dryer.stackable]
B10: Towson Crossing Apartment Homes | C10: 34 Dowling Circle | D10: One Bedroom | E10: HS13B4 | F10: 4 | G10: 1 | H10: 1 | J10: 728 | K10: 45435 | L10: 45586 | M10: FALSE | N10: 152 | O10: 1195 | P10: 1.6414835 | Q10: 1195 | R10: 1.6414835 | S10: [Tile Backsplash Third Floor Oak Cabinets Black Appliances Stackable Washer and Dryer Microwave] | T10: [washer_dryer floor washer_dryer.stackable]
B11: Towson Crossing Apartment Homes | C11: 34 Dowling Circle | D11: One Bedroom | E11: DL28A1 | F11: 1 | G11: 1 | H11: 1 | J11: 728 | K11: 45451 | L11: 45548 | M11: FALSE | N11: 98 | O11: 1195 | P11: 1.6414835 | Q11: 1160 | R11: 1.5934066 | S11: [Second Floor Stackable Washer and Dryer] | T11: [washer_dryer floor washer_dryer.stackable]
B12: Towson Crossing Apartment Homes | C12: 34 Dowling Circle | D12: One Bedroom | E12: DL06A1 | F12: 1 | G12: 1 | H12: 1 | J12: 728 | K12: 45673 | L12: 45680 | M12: FALSE | N12: 8 | O12: 1205 | P12: 1.6552198 | Q12: 1205 | R12: 1.6552198 | S12: [Second Floor Stackable Washer and Dryer] | T12: [washer_dryer floor washer_dryer.stackable]
B13: Towson Crossing Apartment Homes | C13: 34 Dowling Circle | D13: One Bedroom | E13: HS00A1 | F13: 1 | G13: 1 | H13: 1 | J13: 728 | K13: 45527 | L13: 45610 | M13: FALSE | N13: 84 | O13: 1230 | P13: 1.6895604 | Q13: 1107 | R13: 1.5206044 | S13: [Second Floor Tile Backsplash Oak Cabinets Black Appliances Stackable Washer and Dryer Microwave] | T13: [washer_dryer floor washer_dryer.stackable]
B14: Towson Crossing Apartment Homes | C14: 34 Dowling Circle | D14: One Bedroom | E14: DL18T3 | F14: 3 | G14: 1 | H14: 1 | J14: 728 | K14: 45679 | L14: 45765 | M14: FALSE | N14: 87 | O14: 1230 | P14: 1.6895604 | Q14: 1230 | R14: 1.6895604 | S14: [Tile Backsplash First Floor Vinyl Plank Flooring Espresso Cabinets Black Appliances Stackable Washer and Dryer Microwave] | T14: [washer_dryer floor washer_dryer.stackable]
B15: Towson Crossing Apartment Homes | C15: 34 Dowling Circle | D15: One Bedroom | E15: DL04A1 | F15: 1 | G15: 1 | H15: 1 | J15: 728 | K15: 45608 | L15: 45619 | M15: FALSE | N15: 12 | O15: 1240 | P15: 1.7032967 | Q15: 1240 | R15: 1.7032967 | S15: [Tile Backsplash Second Floor Espresso Cabinets Black Appliances Stackable Washer and Dryer Microwave] | T15: [washer_dryer floor washer_dryer.stackable]
B16: Towson Crossing Apartment Homes | C16: 34 Dowling Circle | D16: One Bedroom | E16: DW34T1 | F16: 1 | G16: 1 | H16: 1 | J16: 728 | K16: 45755 | L16: 45771 | M16: FALSE | N16: 17 | O16: 1240 | P16: 1.7032967 | Q16: 1240 | R16: 1.7032967 | S16: [First Floor Vinyl Plank Flooring Microwave Tile Backsplash Espresso Cabinets Black Appliances Stackable Washer and Dryer] | T16: [washer_dryer floor washer_dryer.stackable]
B17: Towson Crossing Apartment Homes | C17: 34 Dowling Circle | D17: One Bedroom | E17: AT04B1 | F17: 1 | G17: 1 | H17: 1 | J17: 728 | K17: 45493 | L17: 45618 | M17: FALSE | N17: 126 | O17: 1245 | P17: 1.7101648 | Q17: 1120 | R17: 1.5384615 | S17: [Tile Backsplash Third Floor Espresso Cabinets Black Appliances Stackable Washer and Dryer Microwave] | T17: [washer_dryer floor washer_dryer.stackable]
B18: Towson Crossing Apartment Homes | C18: 34 Dowling Circle | D18: One Bedroom | E18: DB11A4 | F18: 4 | G18: 1 | H18: 1 | J18: 728 | K18: 45730 | L18: 45766 | M18: FALSE | N18: 37 | O18: 1260 | P18: 1.7307692 | Q18: 1260 | R18: 1.7307692 | S18: [Tile Backsplash Second Floor Espresso Cabinets Black Appliances Stackable Washer and Dryer Microwave] | T18: [washer_dryer floor washer_dryer.stackable]
... B31: Towson Crossing Apartment Homes | C31: 34 Dowling Circle | D31: One Bedroom | E31: DL28B4 | F31: 4 | G31: 1 | H31: 1 | J31: 728 | K31: 45674 | L31: 45763 | M31: FALSE | N31: 90 | O31: 1275 | P31: 1.7513736 | Q31: 1275 | R31: 1.7513736 | S31: [Tile Backsplash Third Floor Espresso Cabinets Black Appliances Stackable Washer and Dryer Microwave Balcony] | T31: [washer_dryer floor washer_dryer.stackable balcony_patio]
B32: Towson Crossing Apartment Homes | C32: 34 Dowling Circle | D32: One Bedroom | E32: DB11B1 | F32: 1 | G32: 1 | H32: 1 | J32: 728 | L32: 45435 | M32: FALSE | O32: 1280 | P32: 1.7582418 | Q32: 1280 | R32: 1.7582418 | S32: [Third Floor Tile Backsplash Granite Countertops Microwave Modern White Cabinets Stainless Steel Appliances Stackable Washer and Dryer Dishwasher] | T32: [washer_dryer floor washer_dryer.stackable dishwasher]
B33: Towson Crossing Apartment Homes | C33: 34 Dowling Circle | D33: One Bedroom | E33: DL28A2 | F33: 2 | G33: 1 | H33: 1 | J33: 728 | K33: 45418 | L33: 45449 | M33: FALSE | N33: 32 | O33: 1285 | P33: 1.7651099 | Q33: 1285 | R33: 1.7651099 | S33: [Tile Backsplash Second Floor Oak Cabinets Black Appliances Stackable Washer and Dryer Microwave] | T33: [washer_dryer floor washer_dryer.stackable]
B34: Towson Crossing Apartment Homes | C34: 34 Dowling Circle | D34: One Bedroom | E34: AT10A2 | F34: 2 | G34: 1 | H34: 1 | J34: 728 | K34: 45511 | L34: 45612 | M34: FALSE | N34: 102 | O34: 1285 | P34: 1.7651099 | Q34: 1156 | R34: 1.5879121 | S34: [Second Floor Tile Backsplash Granite Countertops Microwave Modern White Cabinets Stainless Steel Appliances Stackable Washer and Dryer Dishwasher] | T34: [washer_dryer floor washer_dryer.stackable dishwasher]
B35: Towson Crossing Apartment Homes | C35: 34 Dowling Circle | D35: One Bedroom | E35: DL28B1 | F35: 1 | G35: 1 | H35: 1 | J35: 728 | K35: 45777 | L35: 45780 | M35: FALSE | N35: 4 | O35: 1295 | P35: 1.7788462 | Q35: 1295 | R35: 1.7788462 | S35: [Tile Backsplash Third Floor Espresso Cabinets Black Appliances Stackable Washer and Dryer Microwave Balcony] | T35: [washer_dryer floor washer_dryer.stackable balcony_patio]
B36: Towson Crossing Apartment Homes | C36: 34 Dowling Circle | D36: One Bedroom | E36: DL29T1 | F36: 1 | G36: 1 | H36: 1 | J36: 728 | K36: 45631 | L36: 45757 | M36: FALSE | N36: 127 | O36: 1295 | P36: 1.7788462 | Q36: 1295 | R36: 1.7788462 | S36: [Tile Backsplash First Floor Vinyl Plank Flooring Espresso Cabinets Black Appliances Stackable Washer and Dryer Microwave] | T36: [washer_dryer floor washer_dryer.stackable]
B37: Towson Crossing Apartment Homes | C37: 34 Dowling Circle | D37: One Bedroom | E37: DW32A4 | F37: 4 | G37: 1 | H37: 1 | J37: 728 | K37: 45645 | L37: 45784 | M37: FALSE | N37: 140 | O37: 1295 | P37: 1.7788462 | Q37: 1295 | R37: 1.7788462 | S37: [Second Floor Tile Backsplash Espresso Cabinets Black Appliances Stackable Washer and Dryer Microwave] | T37: [washer_dryer floor washer_dryer.stackable]
B38: Towson Crossing Apartment Homes | C38: 34 Dowling Circle | D38: One Bedroom | E38: HS00B4 | F38: 4 | G38: 1 | H38: 1 | J38: 728 | K38: 45777 | M38: TRUE | O38: 1300 | P38: 1.7857143 | Q38: 1300 | R38: 1.7857143 | S38: [Tile Backsplash Third Floor Espresso Cabinets Black Appliances Stackable Washer and Dryer Microwave] | T38: [washer_dryer floor washer_dryer.stackable]
B39: Towson Crossing Apartment Homes | C39: 34 Dowling Circle | D39: One Bedroom | E39: AT12A4 | F39: 4 | G39: 1 | H39: 1 | J39: 728 | K39: 45769 | L39: 45784 | M39: FALSE | N39: 16 | O39: 1305 | P39: 1.7925824 | Q39: 1305 | R39: 1.7925824 | S39: [Tile Backsplash Second Floor Espresso Cabinets Black Appliances Stackable Washer and Dryer Microwave Balcony] | T39: [washer_dryer floor washer_dryer.stackable balcony_patio]
B40: Towson Crossing Apartment Homes | C40: 34 Dowling Circle | D40: One Bedroom | E40: HS00T1 | F40: 1 | G40: 1 | H40: 1 | J40: 728 | K40: 45441 | L40: 45629 | M40: FALSE | N40: 189 | O40: 1305 | P40: 1.7925824 | Q40: 1305 | R40: 1.7925824 | S40: [First Floor Vinyl Plank Flooring Tile Backsplash Granite Countertops Microwave Modern White Cabinets Stainless Steel Appliances Stackable Washer and Dryer Dishwasher] | T40: [washer_dryer floor washer_dryer.stackable dishwasher]
B41: Towson Crossing Apartment Homes | C41: 34 Dowling Circle | D41: One Bedroom | E41: DW34B4 | F41: 4 | G41: 1 | H41: 1 | J41: 728 | K41: 45750 | M41: TRUE | O41: 1305 | P41: 1.7925824 | Q41: 1305 | R41: 1.7925824 | S41: [Tile Backsplash Third Floor Espresso Cabinets Black Appliances Stackable Washer and Dryer Microwave] | T41: [washer_dryer floor washer_dryer.stackable]
B42: Towson Crossing Apartment Homes | C42: 34 Dowling Circle | D42: One Bedroom | E42: DW34T3 | F42: 3 | G42: 1 | H42: 1 | J42: 728 | K42: 45371 | L42: 45453 | M42: FALSE | N42: 83 | O42: 1310 | P42: 1.7994505 | Q42: 1310 | R42: 1.7994505 | S42: [First Floor Vinyl Plank Flooring Tile Backsplash Granite Countertops Microwave Modern White Cabinets Stainless Steel Appliances Stackable Washer and Dryer Dishwasher] | T42: [washer_dryer floor washer_dryer.stackable dishwasher]
B43: Towson Crossing Apartment Homes | C43: 34 Dowling Circle | D43: One Bedroom | E43: DL12B4 | F43: 4 | G43: 1 | H43: 1 | J43: 728 | K43: 45755 | M43: TRUE | O43: 1310 | P43: 1.7994505 | Q43: 1310 | R43: 1.7994505 | S43: [Tile Backsplash Third Floor Espresso Cabinets Black Appliances Stackable Washer and Dryer Microwave Balcony] | T43: [washer_dryer floor washer_dryer.stackable balcony_patio]
B44: Towson Crossing Apartment Homes | C44: 34 Dowling Circle | D44: One Bedroom | E44: DB17A2 | F44: 2 | G44: 1 | H44: 1 | J44: 728 | K44: 45394 | L44: 45441 | M44: FALSE | N44: 48 | O44: 1320 | P44: 1.8131868 | Q44: 1320 | R44: 1.8131868 | S44: [Second Floor Tile Backsplash Granite Countertops Microwave Modern White Cabinets Stainless Steel Appliances Stackable Washer and Dryer Dishwasher] | T44: [washer_dryer floor washer_dryer.stackable dishwasher]
B45: Towson Crossing Apartment Homes | C45: 34 Dowling Circle | D45: One Bedroom | E45: DW32A1 | F45: 1 | G45: 1 | H45: 1 | J45: 728 | K45: 45474 | L45: 45483 | M45: FALSE | N45: 10 | O45: 1320 | P45: 1.8131868 | Q45: 1320 | R45: 1.8131868 | S45: [Tile Backsplash Second Floor Oak Cabinets Black Appliances Stackable Washer and Dryer Microwave] | T45: [washer_dryer floor washer_dryer.stackable]
B46: Towson Crossing Apartment Homes | C46: 34 Dowling Circle | D46: One Bedroom | E46: DL28T1 | F46: 1 | G46: 1 | H46: 1 | J46: 728 | K46: 45468 | L46: 45737 | M46: FALSE | N46: 270 | O46: 1320 | P46: 1.8131868 | Q46: 1320 | R46: 1.8131868 | S46: [Tile Backsplash First Floor Vinyl Plank Flooring Espresso Cabinets Black Appliances Stackable Washer and Dryer Microwave] | T46: [washer_dryer floor washer_dryer.stackable]
B47: Towson Crossing Apartment Homes | C47: 34 Dowling Circle | D47: One Bedroom | E47: AT10B2 | F47: 2 | G47: 1 | H47: 1 | J47: 728 | K47: 45715 | M47: TRUE | O47: 1320 | P47: 1.8131868 | Q47: 1320 | R47: 1.8131868 | S47: [Tile Backsplash Third Floor Espresso Cabinets Black Appliances Stackable Washer and Dryer Microwave Balcony] | T47: [washer_dryer floor washer_dryer.stackable balcony_patio]
B48: Towson Crossing Apartment Homes | C48: 34 Dowling Circle | D48: One Bedroom | E48: AT10B1 | F48: 1 | G48: 1 | H48: 1 | J48: 728 | K48: 45696 | M48: TRUE | O48: 1320 | P48: 1.8131868 | Q48: 1320 | R48: 1.8131868 | S48: [Tile Backsplash Third Floor Espresso Cabinets Black Appliances Stackable Washer and Dryer Microwave Balcony] | T48: [washer_dryer floor washer_dryer.stackable balcony_patio]
B49: Towson Crossing Apartment Homes | C49: 34 Dowling Circle | D49: One Bedroom | E49: LF03T3 | F49: 3 | G49: 1 | H49: 1 | J49: 728 | K49: 45729 | M49: TRUE | O49: 1325 | P49: 1.8200549 | Q49: 1325 | R49: 1.8200549 | S49: [First Floor Vinyl Plank Flooring Tile Backsplash Granite Countertops Microwave Modern White Cabinets Stainless Steel Appliances Stackable Washer and Dryer Dishwasher] | T49: [washer_dryer floor washer_dryer.stackable dishwasher]
B50: Towson Crossing Apartment Homes | C50: 34 Dowling Circle | D50: One Bedroom | E50: HS03A1 | F50: 1 | G50: 1 | H50: 1 | J50: 728 | K50: 45371 | L50: 45436 | M50: FALSE | N50: 66 | O50: 1325 | P50: 1.8200549 | Q50: 1325 | R50: 1.8200549 | S50: [Second Floor Tile Backsplash Granite Countertops Microwave Modern White Cabinets Stainless Steel Appliances Stackable Washer and Dryer Dishwasher] | T50: [washer_dryer floor washer_dryer.stackable dishwasher]
B51: Towson Crossing Apartment Homes | C51: 34 Dowling Circle | D51: One Bedroom | E51: DL12B2 | F51: 2 | G51: 1 | H51: 1 | J51: 728 | K51: 45712 | L51: 45764 | M51: FALSE | N51: 53 | O51: 1325 | P51: 1.8200549 | Q51: 1325 | R51: 1.8200549 | S51: [Third Floor Tile Backsplash Granite Countertops Microwave Modern White Cabinets Stainless Steel Appliances Stackable Washer and Dryer Dishwasher] | T51: [washer_dryer floor washer_dryer.stackable dishwasher]
B52: Towson Crossing Apartment Homes | C52: 34 Dowling Circle | D52: One Bedroom | E52: DL24T1 | F52: 1 | G52: 1 | H52: 1 | J52: 728 | K52: 45722 | M52: TRUE | O52: 1330 | P52: 1.8269231 | Q52: 1330 | R52: 1.8269231 | S52: [Tile Backsplash First Floor Vinyl Plank Flooring Espresso Cabinets Black Appliances Stackable Washer and Dryer Microwave] | T52: [washer_dryer floor washer_dryer.stackable]
B53: Towson Crossing Apartment Homes | C53: 34 Dowling Circle | D53: One Bedroom | E53: DL18A4 | F53: 4 | G53: 1 | H53: 1 | J53: 728 | K53: 45336 | L53: 45449 | M53: FALSE | N53: 114 | O53: 1345 | P53: 1.8475275 | Q53: 1345 | R53: 1.8475275 | S53: [Second Floor Tile Backsplash Granite Countertops Microwave Modern White Cabinets Stainless Steel Appliances Stackable Washer and Dryer Dishwasher] | T53: [washer_dryer floor washer_dryer.stackable dishwasher]
B54: Towson Crossing Apartment Homes | C54: 34 Dowling Circle | D54: One Bedroom | E54: DL24T3 | F54: 3 | G54: 1 | H54: 1 | J54: 728 | K54: 45395 | L54: 45494 | M54: FALSE | N54: 100 | O54: 1345 | P54: 1.8475275 | Q54: 1345 | R54: 1.8475275 | S54: [First Floor Vinyl Plank Flooring Tile Backsplash Granite Countertops Microwave Modern White Cabinets Stainless Steel Appliances Stackable Washer and Dryer Dishwasher] | T54: [washer_dryer floor washer_dryer.stackable dishwasher]
B55: Towson Crossing Apartment Homes | C55: 34 Dowling Circle | D55: One Bedroom | E55: DL04B1 | F55: 1 | G55: 1 | H55: 1 | J55: 728 | K55: 45577 | L55: 45707 | M55: FALSE | N55: 131 | O55: 1345 | P55: 1.8475275 | Q55: 1345 | R55: 1.8475275 | S55: [Tile Backsplash Third Floor Espresso Cabinets Black Appliances Stackable Washer and Dryer Microwave] | T55: [washer_dryer floor washer_dryer.stackable]
B56: Towson Crossing Apartment Homes | C56: 34 Dowling Circle | D56: One Bedroom | E56: LF03A1 | F56: 1 | G56: 1 | H56: 1 | J56: 728 | K56: 45681 | L56: 45719 | M56: FALSE | N56: 39 | O56: 1345 | P56: 1.8475275 | Q56: 1345 | R56: 1.8475275 | S56: [Second Floor Tile Backsplash Microwave Granite Countertops Modern White Cabinets Stainless Steel Appliances Stackable Washer and Dryer] | T56: [washer_dryer floor washer_dryer.stackable]
B57: Towson Crossing Apartment Homes | C57: 34 Dowling Circle | D57: One Bedroom | E57: DL29B2 | F57: 2 | G57: 1 | H57: 1 | J57: 728 | K57: 45773 | L57: 45776 | M57: FALSE | N57: 4 | O57: 1350 | P57: 1.8543956 | Q57: 1350 | R57: 1.8543956 | S57: [Third Floor Tile Backsplash Granite Countertops Microwave Modern White Cabinets Stainless Steel Appliances Stackable Washer and Dryer Dishwasher Balcony] | T57: [washer_dryer.stackable balcony_patio washer_dryer floor dishwasher]
B58: Towson Crossing Apartment Homes | C58: 34 Dowling Circle | D58: One Bedroom | E58: HS13A1 | F58: 1 | G58: 1 | H58: 1 | J58: 728 | K58: 45379 | L58: 45450 | M58: FALSE | N58: 72 | O58: 1350 | P58: 1.8543956 | Q58: 1350 | R58: 1.8543956 | S58: [Second Floor Tile Backsplash Granite Countertops Microwave Modern White Cabinets Stainless Steel Appliances Stackable Washer and Dryer Dishwasher] | T58: [washer_dryer floor washer_dryer.stackable dishwasher]
B59: Towson Crossing Apartment Homes | C59: 34 Dowling Circle | D59: One Bedroom | E59: AT04A1 | F59: 1 | G59: 1 | H59: 1 | J59: 728 | K59: 45784 | M59: TRUE | O59: 1355 | P59: 1.8612637 | Q59: 1355 | R59: 1.8612637 | S59: [Second Floor Tile Backsplash Granite Countertops Microwave Modern White Cabinets Stainless Steel Appliances Stackable Washer and Dryer Dishwasher] | T59: [washer_dryer floor washer_dryer.stackable dishwasher]
