Workbook

Sheet Pro-forma
B2: Name: Cherry Commons
B3: Address: 1718 North Sydenham Street Philadelphia, PA 19121
G4: Last Updated: | H4: 46056
B6: Project Summary
B7: Year Built | D7: 1950
B8: Lot Size
B9: Building Size
B10: Ask Price
B11: Offer Price | D11: 6200000
B12: Occupancy Rate | D12: 96.42
B13: Total Apartment Units | D13: 28
B14: Total Current Retal Units | D14: 0
B15: Total Parking Spaces | D15: -
B18: Residential Rent Roll | F18: 2025 | G18: 2026
B19: Unit Types | C19: # Units | D19: Bedroom | E19: SQF | F19: As-is rent | G19: Growth | H19: As-is Rent | I19: Projected Rent
B20: 1B | C20: 9 | D20: 1 | E20: 540 | F20: 1490 | G20: 1500 | H20: =F20*12*C20 -> 160920 | I20: =G20*12*C20 -> 162000
B21: 2B | C21: 15 | D21: 2 | E21: 840 | F21: 1850 | G21: 1990 | H21: =F21*12*C21 -> 333000 | I21: =G21*12*C21 -> 358200
B22: 2B Deluxe | C22: 3 | D22: 2 | F22: 1950 | G22: 2150 | H22: =F22*12*C22 -> 70200 | I22: =G22*12*C22 -> 77400
B23: Total/average | C23: =C20+#REF!+C22 -> #REF! | H23: =SUM(H20:H22) -> 564120 | I23: =SUM(I20:I22) -> 597600
B27: ASSUMPTIONS | F27: Tax Assessments
B28: Income
B29: Residential market annual rent growth | D29: 0.03 | F29: Property
B31: Expenses
B32: Operating expenses growth rates | D32: 0.03
B33: Property taxes growth rates | D33: 0.03 | F33: Total | G33: =SUM(G30:G32) -> 0
B36: Exhibit 1 Meadow Lane Projection
B37: Pro Forma
B38: Year | E38: NOV2023-OCT2024 | F38: NOV2024-OCT2025 | G38: NOV2025-OCT2026 | H38: NOV2026-OCT2027 | I38: NOV2027-OCT2028 | J38: NOV2028-OCT2029 | K38: NOV2029-OCT2030
B40: REVENUE | C40: Stabilized | D40: Per Unit
B41: Rent Income | D41: =G41/28 -> 21342.857 | E41: =F41 -> 536297.82 | F41: =SUM('T12'!N9:Y9) -> 536297.82 | G41: =I23 -> 597600 | H41: =I23 -> 597600 | I41: =H41*1.04 -> 621504 | J41: =I41*1.04 -> 646364.16 | K41: =J41*1.04 -> 672218.73
B42: Other Rental Income | D42: =G42/28 -> 45.620536 | E42: =SUM('T12'!B10:M10) -> 2554.75 | F42: =SUM('T12'!N10:Y10) -> 0 | G42: =AVERAGE(E42:F42) -> 1277.375 | H42: =G42*1.03 -> 1315.6962 | I42: =H42*1.03 -> 1355.1671 | J42: =I42*1.03 -> 1395.8222 | K42: =J42*1.03 -> 1437.6968
B43: Application Fee Income | D43: =G43/28 -> 35.625 | E43: =SUM('T12'!B11:M11) -> 1015 | F43: =SUM('T12'!N11:Y11) -> 980 | G43: =AVERAGE(E43:F43) -> 997.5 | H43: =G43*1.03 -> 1027.425 | I43: =H43*1.03 -> 1058.2477 | J43: =I43*1.03 -> 1089.9952 | K43: =J43*1.03 -> 1122.695
B44: NSF Fees Collected | D44: =G44/28 -> 0.71428571 | E44: =SUM('T12'!B12:M12) -> 5 | F44: =SUM('T12'!N12:Y12) -> 35 | G44: =AVERAGE(E44:F44) -> 20 | H44: =G44*1.03 -> 20.6 | I44: =H44*1.03 -> 21.218 | J44: =I44*1.03 -> 21.85454 | K44: =J44*1.03 -> 22.510176
B45: Late Fee | D45: =G45/28 -> 107.36232 | E45: =SUM('T12'!B13:M13) -> 3554.29 | F45: =SUM('T12'!N13:Y13) -> 2458 | G45: =AVERAGE(E45:F45) -> 3006.145 | H45: =G45*1.03 -> 3096.3293 | I45: =H45*1.03 -> 3189.2192 | J45: =I45*1.03 -> 3284.8958 | K45: =J45*1.03 -> 3383.4427
B46: Pet Fee | D46: =G46/28 -> 14.732143 | E46: =SUM('T12'!B14:M14) -> 825 | F46: =SUM('T12'!N14:Y14) -> 0 | G46: =AVERAGE(E46:F46) -> 412.5 | H46: =G46*1.03 -> 424.875 | I46: =H46*1.03 -> 437.62125 | J46: =I46*1.03 -> 450.74989 | K46: =J46*1.03 -> 464.27238
B47: Furniture Charge | D47: =G47/28 -> 23.214286 | E47: =SUM('T12'!B15:M15) -> 400 | F47: =SUM('T12'!N15:Y15) -> 900 | G47: =AVERAGE(E47:F47) -> 650 | H47: =G47*1.03 -> 669.5 | I47: =H47*1.03 -> 689.585 | J47: =I47*1.03 -> 710.27255 | K47: =J47*1.03 -> 731.58073
B48: Laundry Income | D48: =G48/28 -> 75.001786 | E48: =SUM('T12'!B16:M16) -> 2745.83 | F48: =SUM('T12'!N16:Y16) -> 1454.27 | G48: =AVERAGE(E48:F48) -> 2100.05 | H48: =G48*1.03 -> 2163.0515 | I48: =H48*1.03 -> 2227.943 | J48: =I48*1.03 -> 2294.7813 | K48: =J48*1.03 -> 2363.6248
B49: Insurance Services | D49: =G49/28 -> 22.529464 | E49: =SUM('T12'!B17:M17) -> 608.46 | F49: =SUM('T12'!N17:Y17) -> 653.19 | G49: =AVERAGE(E49:F49) -> 630.825 | H49: =G49*1.03 -> 649.74975 | I49: =H49*1.03 -> 669.24224 | J49: =I49*1.03 -> 689.31951 | K49: =J49*1.03 -> 709.9991
B50: Utility Reimbursement Fee | D50: =G50/28 -> 6.2916071 | E50: =SUM('T12'!B18:M18) -> 352.33 | F50: =SUM('T12'!N18:Y18) -> 0 | G50: =AVERAGE(E50:F50) -> 176.165 | H50: =G50*1.03 -> 181.44995 | I50: =H50*1.03 -> 186.89345 | J50: =I50*1.03 -> 192.50025 | K50: =J50*1.03 -> 198.27526
B51: Concessions | D51: =G51/28 -> -129.94839 | E51: =SUM('T12'!B19:M19) -> -7277.11 | F51: =SUM('T12'!N19:Y19) -> 0 | G51: =AVERAGE(E51:F51) -> -3638.555 | H51: =G51*1.03 -> -3747.7117 | I51: =H51*1.03 -> -3860.143 | J51: =I51*1.03 -> -3975.9473 | K51: =J51*1.03 -> -4095.2257
B52: Total Revenue | E52: =(SUM(E41:E51)) -> 541081.37 | F52: =(SUM(F41:F51)) -> 542778.28 | G52: =(SUM(G41:G51)) -> 603232.01 | H52: =(SUM(H41:H51)) -> 603400.97 | I52: =(SUM(I41:I51)) -> 627478.99 | J52: =(SUM(J41:J51)) -> 652518.4 | K52: =(SUM(K41:K51)) -> 678557.6
B54: EXPENSES | C54: Stabilized | D54: Per Unit | E54: NOV2023-OCT2024 | F54: NOV2024-OCT2025 | G54: NOV2025-OCT2026 | H54: NOV2026-OCT2027 | I54: NOV2027-OCT2028 | J54: NOV2028-OCT2029 | K54: NOV2029-OCT2030
B55: Cleaning and Janitorial Expense | D55: =G55/28 -> 77.446429 | E55: =SUM('T12'!B31:M31) -> 1475 | F55: =SUM('T12'!N31:Y31) -> 2862 | G55: =AVERAGE(E55:F55) -> 2168.5 | H55: =G55*1.03 -> 2233.555 | I55: =H55*1.03 -> 2300.5617 | J55: =I55*1.03 -> 2369.5785 | K55: =J55*1.03 -> 2440.6659
B56: Maintenance Labor Expense | D56: =G56/28 -> 1.6071429 | E56: =SUM('T12'!B32:M32) -> 90 | F56: =SUM('T12'!N32:Y32) -> 0 | G56: =AVERAGE(E56:F56) -> 45 | H56: =G56*1.03 -> 46.35 | I56: =H56*1.03 -> 47.7405 | J56: =I56*1.03 -> 49.172715 | K56: =J56*1.03 -> 50.647896
B57: Garbage and Recycling | D57: =G57/28 -> 345.36357 | E57: =SUM('T12'!B33:M33) -> 11475.02 | F57: =SUM('T12'!N33:Y33) -> 7865.34 | G57: =AVERAGE(E57:F57) -> 9670.18 | H57: =G57*1.03 -> 9960.2854 | I57: =H57*1.03 -> 10259.094 | J57: =I57*1.03 -> 10566.867 | K57: =J57*1.03 -> 10883.873
B58: Pest control | D58: =G58/28 -> 164.41071 | E58: =SUM('T12'!B34:M34) -> 4482 | F58: =SUM('T12'!N34:Y34) -> 4725 | G58: =AVERAGE(E58:F58) -> 4603.5 | H58: =G58*1.03 -> 4741.605 | I58: =H58*1.03 -> 4883.8531 | J58: =I58*1.03 -> 5030.3687 | K58: =J58*1.03 -> 5181.2798
B59: Property Insurance | D59: =G59/28 -> 964.28571 | E59: =SUM('T12'!B37:M37) -> 24205.82 | F59: =SUM('T12'!N37:Y37) -> 43274.39 | G59: 27000 | H59: =G59*1.03 -> 27810 | I59: =H59*1.03 -> 28644.3 | J59: =I59*1.03 -> 29503.629 | K59: =J59*1.03 -> 30388.738
B60: Insurance - Other | D60: =G60/28 -> 0 | E60: =SUM('T12'!B38:M38) -> 6911.76 | F60: =SUM('T12'!N38:Y38) -> -6911.76 | G60: =AVERAGE(E60:F60) -> 0 | H60: =G60*1.03 -> 0 | I60: =H60*1.03 -> 0 | J60: =I60*1.03 -> 0 | K60: =J60*1.03 -> 0
B61: Accounting | D61: =G61/28 -> 127.84661 | E61: =SUM('T12'!B41:M41) -> 4030.41 | F61: =SUM('T12'!N41:Y41) -> 3129 | G61: =AVERAGE(E61:F61) -> 3579.705 | H61: =G61*1.03 -> 3687.0961 | I61: =H61*1.03 -> 3797.709 | J61: =I61*1.03 -> 3911.6403 | K61: =J61*1.03 -> 4028.9895
B62: Appfolio/Yardi | D62: =G62/28 -> 19.285714 | E62: =SUM('T12'!B42:M42) -> 1080 | F62: =SUM('T12'!N42:Y42) -> 0 | G62: =AVERAGE(E62:F62) -> 540 | H62: =G62*1.03 -> 556.2 | I62: =H62*1.03 -> 572.886 | J62: =I62*1.03 -> 590.07258 | K62: =J62*1.03 -> 607.77476
B63: Management Fee Expense | D63: =G63/28 -> 539.73107 | E63: =SUM('T12'!B45:M45) -> 22157.13 | F63: =SUM('T12'!N45:Y45) -> 8067.81 | G63: =AVERAGE(E63:F63) -> 15112.47 | H63: =G63*1.03 -> 15565.844 | I63: =H63*1.03 -> 16032.819 | J63: =I63*1.03 -> 16513.804 | K63: =J63*1.03 -> 17009.218
B64: Commissions/Placement Fee Expense | D64: =G64/28 -> 31.25 | E64: =SUM('T12'!B46:M46) -> 1750 | F64: =SUM('T12'!N46:Y46) -> 0 | G64: =AVERAGE(E64:F64) -> 875 | H64: =G64*1.03 -> 901.25 | I64: =H64*1.03 -> 928.2875 | J64: =I64*1.03 -> 956.13612 | K64: =J64*1.03 -> 984.82021
B65: Painting | D65: =G65/28 -> 0 | E65: =SUM('T12'!B54:M54) -> 0 | F65: =SUM('T12'!N54:Y54) -> 0 | G65: =AVERAGE(E65:F65) -> 0 | H65: =G65*1.03 -> 0 | I65: =H65*1.03 -> 0 | J65: =I65*1.03 -> 0 | K65: =J65*1.03 -> 0
B66: Plumbing | D66: =G66/28 -> 102.76054 | E66: =SUM('T12'!B55:M55) -> 1809.59 | F66: =SUM('T12'!N55:Y55) -> 3945 | G66: =AVERAGE(E66:F66) -> 2877.295 | H66: =G66*1.03 -> 2963.6139 | I66: =H66*1.03 -> 3052.5223 | J66: =I66*1.03 -> 3144.0979 | K66: =J66*1.03 -> 3238.4209
B67: Flooring | D67: =G67/28 -> 0 | E67: =SUM('T12'!B56:M56) -> 0 | F67: =SUM('T12'!N56:Y56) -> 0 | G67: =AVERAGE(E67:F67) -> 0 | H67: =G67*1.03 -> 0 | I67: =H67*1.03 -> 0 | J67: =I67*1.03 -> 0 | K67: =J67*1.03 -> 0
B68: HVAC (Heat Ventilation Air) | D68: =G68/28 -> 224.00696 | E68: =SUM('T12'!B57:M57) -> 6190.42 | F68: =SUM('T12'!N57:Y57) -> 6353.97 | G68: =AVERAGE(E68:F68) -> 6272.195 | H68: =G68*1.03 -> 6460.3609 | I68: =H68*1.03 -> 6654.1717 | J68: =I68*1.03 -> 6853.7968 | K68: =J68*1.03 -> 7059.4107
B69: Sub Contractor | D69: =G69/28 -> 535.71429 | E69: =SUM('T12'!B58:M58) -> 0 | F69: =SUM('T12'!N58:Y58) -> 47100 | G69: 15000 | H69: =G69*1.03 -> 15450 | I69: =H69*1.03 -> 15913.5 | J69: =I69*1.03 -> 16390.905 | K69: =J69*1.03 -> 16882.632
B70: Key/Lock Replacement | D70: =G70/28 -> 0 | E70: =SUM('T12'!B59:M59) -> 0 | F70: =SUM('T12'!N59:Y59) -> 0 | G70: =AVERAGE(E70:F70) -> 0 | H70: =G70*1.03 -> 0 | I70: =H70*1.03 -> 0 | J70: =I70*1.03 -> 0 | K70: =J70*1.03 -> 0
B71: Security Service | D71: =G71/28 -> 21.428571 | E71: =SUM('T12'!B60:M60) -> 10353.4 | F71: =SUM('T12'!N60:Y60) -> 2260.07 | G71: 600 | H71: =G71*1.03 -> 618 | I71: =H71*1.03 -> 636.54 | J71: =I71*1.03 -> 655.6362 | K71: =J71*1.03 -> 675.30529
B72: Roof /Exterior Repair | D72: =G72/28 -> 145.89286 | E72: =SUM('T12'!B61:M61) -> 3780 | F72: =SUM('T12'!N61:Y61) -> 4390 | G72: =AVERAGE(E72:F72) -> 4085 | H72: =G72*1.03 -> 4207.55 | I72: =H72*1.03 -> 4333.7765 | J72: =I72*1.03 -> 4463.7898 | K72: =J72*1.03 -> 4597.7035
B73: Elevator Contract | D73: =G73/28 -> 371.61179 | E73: =SUM('T12'!B62:M62) -> 12803.62 | F73: =SUM('T12'!N62:Y62) -> 8006.64 | G73: =AVERAGE(E73:F73) -> 10405.13 | H73: =G73*1.03 -> 10717.284 | I73: =H73*1.03 -> 11038.802 | J73: =I73*1.03 -> 11369.966 | K73: =J73*1.03 -> 11711.065
B74: Elevator Repair Expense | D74: =G74/28 -> 18.4425 | E74: =SUM('T12'!B63:M63) -> 0 | F74: =SUM('T12'!N63:Y63) -> 1032.78 | G74: =AVERAGE(E74:F74) -> 516.39 | H74: =G74*1.03 -> 531.8817 | I74: =H74*1.03 -> 547.83815 | J74: =I74*1.03 -> 564.2733 | K74: =J74*1.03 -> 581.20149
B75: Appliance Repair | D75: =G75/28 -> 10.923929 | E75: =SUM('T12'!B64:M64) -> 611.74 | F75: =SUM('T12'!N64:Y64) -> 0 | G75: =AVERAGE(E75:F75) -> 305.87 | H75: =G75*1.03 -> 315.0461 | I75: =H75*1.03 -> 324.49748 | J75: =I75*1.03 -> 334.23241 | K75: =J75*1.03 -> 344.25938
B76: Repairs - Other | D76: =G76/28 -> 68.893571 | E76: =SUM('T12'!B65:M65) -> 577.5 | F76: =SUM('T12'!N65:Y65) -> 3280.54 | G76: =AVERAGE(E76:F76) -> 1929.02 | H76: =G76*1.03 -> 1986.8906 | I76: =H76*1.03 -> 2046.4973 | J76: =I76*1.03 -> 2107.8922 | K76: =J76*1.03 -> 2171.129
B77: Supplies | D77: =G77/28 -> 59.611607 | E77: =SUM('T12'!B66:M66) -> 1820.95 | F77: =SUM('T12'!N66:Y66) -> 1517.3 | G77: =AVERAGE(E77:F77) -> 1669.125 | H77: =G77*1.03 -> 1719.1988 | I77: =H77*1.03 -> 1770.7747 | J77: =I77*1.03 -> 1823.898 | K77: =J77*1.03 -> 1878.6149
B78: Property Tax | D78: =G78/28 -> 1471.2186 | E78: =SUM('T12'!B69:M69) -> 57156.06 | F78: =SUM('T12'!N69:Y69) -> 25232.18 | G78: =AVERAGE(E78:F78) -> 41194.12 | H78: =G78*1.03 -> 42429.944 | I78: =H78*1.03 -> 43702.842 | J78: =I78*1.03 -> 45013.927 | K78: =J78*1.03 -> 46364.345
B79: Taxes - Other | D79: =G79/28 -> 26.428571 | E79: =SUM('T12'!B70:M70) -> 1480 | F79: =SUM('T12'!N70:Y70) -> 0 | G79: =AVERAGE(E79:F79) -> 740 | H79: =G79*1.03 -> 762.2 | I79: =H79*1.03 -> 785.066 | J79: =I79*1.03 -> 808.61798 | K79: =J79*1.03 -> 832.87652
B80: Licenses and Registration Fees | D80: =G80/28 -> 188.42857 | E80: =SUM('T12'!B71:M71) -> 4008 | F80: =SUM('T12'!N71:Y71) -> 6544 | G80: =AVERAGE(E80:F80) -> 5276 | H80: =G80*1.03 -> 5434.28 | I80: =H80*1.03 -> 5597.3084 | J80: =I80*1.03 -> 5765.2277 | K80: =J80*1.03 -> 5938.1845
B81: Electricity | D81: =G81/28 -> 2350.4996 | E81: =SUM('T12'!B74:M74) -> 61218.3 | F81: =SUM('T12'!N74:Y74) -> 70409.68 | G81: =AVERAGE(E81:F81) -> 65813.99 | H81: =G81*1.03 -> 67788.41 | I81: =H81*1.03 -> 69822.062 | J81: =I81*1.03 -> 71916.724 | K81: =J81*1.03 -> 74074.226
B82: Gas | D82: =G82/28 -> 304.72 | E82: =SUM('T12'!B75:M75) -> 11746.71 | F82: =SUM('T12'!N75:Y75) -> 5317.61 | G82: =AVERAGE(E82:F82) -> 8532.16 | H82: =G82*1.03 -> 8788.1248 | I82: =H82*1.03 -> 9051.7685 | J82: =I82*1.03 -> 9323.3216 | K82: =J82*1.03 -> 9603.0212
B83: Water | D83: =G83/28 -> 137.58375 | E83: =SUM('T12'!B76:M76) -> 2223.26 | F83: =SUM('T12'!N76:Y76) -> 5481.43 | G83: =AVERAGE(E83:F83) -> 3852.345 | H83: =G83*1.03 -> 3967.9154 | I83: =H83*1.03 -> 4086.9528 | J83: =I83*1.03 -> 4209.5614 | K83: =J83*1.03 -> 4335.8482
B84: Telephone/Wifi | D84: =G84/28 -> 311.15018 | E84: =SUM('T12'!B77:M77) -> 10636.07 | F84: =SUM('T12'!N77:Y77) -> 6788.34 | G84: =AVERAGE(E84:F84) -> 8712.205 | H84: =G84*1.03 -> 8973.5711 | I84: =H84*1.03 -> 9242.7783 | J84: =I84*1.03 -> 9520.0616 | K84: =J84*1.03 -> 9805.6635
B85: Office Expense | D85: =G85/28 -> 1.23125 | E85: =SUM('T12'!B80:M80) -> 68.95 | F85: =SUM('T12'!N80:Y80) -> 0 | G85: =AVERAGE(E85:F85) -> 34.475 | H85: =G85*1.03 -> 35.50925 | I85: =H85*1.03 -> 36.574528 | J85: =I85*1.03 -> 37.671763 | K85: =J85*1.03 -> 38.801916
B86: Salary Expense | D86: =G86/28 -> 714.28571 | E86: =SUM('T12'!B81:M81) -> 68200 | F86: =SUM('T12'!N81:Y81) -> -14300 | G86: 20000 | H86: =G86*1.03 -> 20600 | I86: =H86*1.03 -> 21218 | J86: =I86*1.03 -> 21854.54 | K86: =J86*1.03 -> 22510.176
B87: Bank Fees | D87: =G87/28 -> 45.004464 | E87: =SUM('T12'!B82:M82) -> 2173.04 | F87: =SUM('T12'!N82:Y82) -> 347.21 | G87: =AVERAGE(E87:F87) -> 1260.125 | H87: =G87*1.03 -> 1297.9288 | I87: =H87*1.03 -> 1336.8666 | J87: =I87*1.03 -> 1376.9726 | K87: =J87*1.03 -> 1418.2818
B88: Advertising | D88: =G88/28 -> 225.81911 | E88: =SUM('T12'!B85:M85) -> 12645.87 | F88: =SUM('T12'!N85:Y85) -> 0 | G88: =AVERAGE(E88:F88) -> 6322.935 | H88: =G88*1.03 -> 6512.6231 | I88: =H88*1.03 -> 6708.0017 | J88: =I88*1.03 -> 6909.2418 | K88: =J88*1.03 -> 7116.519
B89: Meetings and Events | D89: =G89/28 -> 21.79875 | E89: =SUM('T12'!B86:M86) -> 1220.73 | F89: =SUM('T12'!N86:Y86) -> 0 | G89: =AVERAGE(E89:F89) -> 610.365 | H89: =G89*1.03 -> 628.67595 | I89: =H89*1.03 -> 647.53623 | J89: =I89*1.03 -> 666.96232 | K89: =J89*1.03 -> 686.97118
B90: Inspection Costs | D90: =G90/28 -> 60.535714 | E90: =SUM('T12'!B89:M89) -> 1790 | F90: =SUM('T12'!N89:Y89) -> 1600 | G90: =AVERAGE(E90:F90) -> 1695 | H90: =G90*1.03 -> 1745.85 | I90: =H90*1.03 -> 1798.2255 | J90: =I90*1.03 -> 1852.1723 | K90: =J90*1.03 -> 1907.7374
B91: Total Expenses | E91: =SUM(E55:E90) -> 350171.35 | F91: =SUM(F55:F90) -> 248318.53 | G91: =SUM(G55:G90) -> 271298.1 | H91: =SUM(H55:H90) -> 279437.04 | I91: =SUM(I55:I90) -> 287820.15 | J91: =SUM(J55:J90) -> 296454.76 | K91: =SUM(K55:K90) -> 305348.4
B92: % of revenue | E92: =E91/E52 -> 0.64716948 | F92: =F91/F52 -> 0.45749533 | G92: =G91/G52 -> 0.44974089 | H92: =H91/H52 -> 0.46310341 | I92: =I91/I52 -> 0.45869289 | J92: =J91/J52 -> 0.45432398 | K92: =K91/K52 -> 0.44999629
B94: Net Operating Income | E94: =E52-E91 -> 190910.02 | F94: =F52-F91 -> 294459.75 | G94: =G52-G91 -> 331933.91 | H94: =H52-H91 -> 323963.92 | I94: =I52-I91 -> 339658.84 | J94: =J52-J91 -> 356063.65 | K94: =K52-K91 -> 373209.2
B96: Adjustment | E96: =SUM('T12'!B110:M110) -> -17782.52 | F96: =SUM('T12'!L110:Y110) -> 2529.81 | G96: =F96*1.03 -> 2605.7043
B97: Debt service | E97: ='Debt Current'!$I$22 -> 219343.98 | F97: ='Debt Current'!$I$22 -> 219343.98 | G97: ='Debt Current'!$I$22 -> 219343.98 | H97: ='Debt Refinance'!$I$23 -> 217947.76 | I97: ='Debt Refinance'!$I$23 -> 217947.76 | J97: ='Debt Refinance'!$I$23 -> 217947.76 | K97: ='Debt Refinance'!$I$23 -> 217947.76
B99: Capex Reserves from Cash Flow
B101: Cash Flow after Debt Service | E101: =E94-E96-E97 -> -10651.445 | F101: =F94-F96-F97 -> 72585.955 | G101: =G94-G96-G97 -> 109984.22 | H101: =H94-H97 -> 106016.17 | I101: =I94-I97 -> 121711.08 | J101: =J94-J97 -> 138115.89 | K101: =K94-K97 -> 155261.44
B103: Reserve for Capex
B104: Capex Reserves from 2025 Cash Flow
B105: DSCR | H105: =H94/(H97) -> 1.4864293 | I105: =I94/(I97) -> 1.5584416 | J105: =J94/(J97) -> 1.633711 | K105: =K94/(K97) -> 1.7123792
B107: CLOSING COSTS | G107: PURCHASE PRICE | K107: SALE EVENT (regular) | Q107: SALE EVENT After refinance
B109: Due Diligence | C109: $ | G109: Purchase Price (As-is value) | I109: 6200000 | K109: Year of Sale | O109: 2026 | Q109: Year of Sale | U109: 2030
B110: Other | E110: 10000 | G110: Per Unit (Residential/Retail) | I110: =I109/D13 -> 221428.57 | K110: Date | O110: 11232 | Q110: Date | U110: 11232
B111: Appraisal | C111: 6000 | E111: 540 | G111: NOI for Year 1 | I111: =H94 -> 323963.92 | K111: NOI of that Year | O111: =G94 -> 331933.91 | Q111: NOI of that Year | U111: =K94 -> 373209.2
B112: Legal (Lender extra $27,900) | C112: 55000 | E112: 5000 | G112: Cap Rate on 2026 Income | I112: =(I111/I109) -> 0.052252246 | K112: Cap Rate | O112: 0.055 | Q112: Cap Rate | U112: 0.0575 | W112: PER UNIT COST MUST BE UNDER $110K PER UNIT
B113: Credit Reports Lender Charges | C113: 5000 | E113: 500 | G113: Closing Cost Percentage | I113: =I114/I109 -> 0.076567809 | K113: Value of Property | O113: =O111/O112 -> 6035161.9 | Q113: Value of Property | U113: =U111/U112 -> 6490594.7
B114: Origination Fee & Lender Fees | C114: 110400 | D114: 0.01 | E114: =D114*M129 -> 39626.865 | G114: Closing Costs | I114: =E135 -> 474720.41 | K114: Cost of sale | N114: 0.05 | O114: =O113*N114 -> 301758.1 | Q114: Cost of sale | T114: 0.05 | U114: =U113*T114 -> 324529.74 | W114: =U113/395 -> 16431.885
B115: Environmental & PCA (Asbestos and Radon Extra) | C115: 6000 | E115: 500 | G115: Total Acquisition Cost | I115: =I109+I114 -> 6674720.4 | K115: Loan of that Year (Beg of Year) | O115: ='Debt Current'!D98 -> 3651978.9 | Q115: Loan of that Year (Beg of OCT) | U115: ='Debt Refinance'!D145 -> 3278314.8
B116: Insurance Review | C116: 1000 | E116: 0 | G116: Total Cost (excludes capex) | I116: =I115 -> 6674720.4 | K116: Capital Transaction Fee to Sponsor | N116: 0.0025 | O116: =O113*N116 -> 15087.905 | Q116: Capital Transaction Fee to Sponsor | T116: 0.0075 | U116: =U113*T116 -> 48679.46
B117: Abstract and Title Charges besides Insurance | C117: 3000 | E117: =1500+905+165+164.8+3028.75+290 -> 6053.55
B118: Commitment Fee | K118: Final Proceeds from Sale | O118: =O113-O114-O115-O116 -> 2066337 | Q118: Final Proceeds from Sale | U118: =U113-U114-U115-U116 -> 2839070.7
B119: Title Insurance | C119: 24000 | E119: 3000 | Q119: Return of Capital | U119: =L152 -> 1558276.6
...

Sheet T12
A1: 12 Months Cash Flow Statement
A2: Cherry Commons - 1718 N Sydenham
A3: Period = Nov 2023-Oct 2025
A4: Book = Cash
A5: ACCOUNT | B5: 45231 | C5: 45261 | D5: 45292 | E5: 45323 | F5: 45352 | G5: 45383 | H5: 45413 | I5: 45444 | J5: 45474 | K5: 45505 | L5: 45536 | M5: 45566 | N5: 45597 | O5: 45627 | P5: 45658 | Q5: 45689 | R5: 45717 | S5: 45748 | T5: 45778 | U5: 45809 | V5: 45839 | W5: 45870 | X5: 45901 | Y5: 45931 | Z5: Total
A6: INCOME
A7: REVENUE
A8: RENTS
A9: Rent Income | B9: 537471.3 | C9: -12228.5 | D9: 50194.83 | E9: 51857.75 | F9: 44591 | G9: 52882.13 | H9: 46652 | I9: 40199 | J9: 28967.22 | K9: 38029.72 | L9: 40731.5 | M9: 44850.25 | N9: 42684.25 | O9: 54771.89 | P9: 48759.5 | Q9: 43993.25 | R9: 44925 | S9: 48759.25 | T9: 42258.39 | U9: 44938.5 | V9: 51607.03 | W9: 26576.94 | X9: 41964.04 | Y9: 45059.78 | Z9: 1500496
A10: Other Rental Income | B10: 500 | C10: 2054.75 | D10: 0 | E10: 0 | F10: 0 | G10: 0 | H10: 0 | I10: 0 | J10: 0 | K10: 0 | L10: 0 | M10: 0 | N10: 200 | O10: -200 | P10: 0 | Q10: 0 | R10: 0 | S10: 0 | T10: 0 | U10: 0 | V10: 0 | W10: 0 | X10: 0 | Y10: 0 | Z10: 2554.75
A11: Application Fee Income | B11: 0 | C11: 0 | D11: 70 | E11: 385 | F11: 175 | G11: 140 | H11: 0 | I11: 140 | J11: 105 | K11: 0 | L11: 0 | M11: 0 | N11: 35 | O11: 35 | P11: 0 | Q11: 140 | R11: 175 | S11: 35 | T11: 210 | U11: 245 | V11: 105 | W11: 0 | X11: 0 | Y11: 0 | Z11: 1995
A12: NSF Fees Collected | B12: 0 | C12: 0 | D12: 0 | E12: 0 | F12: 0 | G12: 0 | H12: 0 | I12: 0 | J12: 0 | K12: 0 | L12: 0 | M12: 5 | N12: 0 | O12: 0 | P12: 0 | Q12: -35 | R12: 35 | S12: 0 | T12: 0 | U12: 35 | V12: 0 | W12: 0 | X12: 0 | Y12: 0 | Z12: 40
A13: Late Fee | B13: 48.02 | C13: -48.02 | D13: 245.79 | E13: 50 | F13: 659.15 | G13: 480.25 | H13: 448.3 | I13: 454 | J13: 489.3 | K13: 275 | L13: 380 | M13: 72.5 | N13: 190 | O13: 242.5 | P13: 322.5 | Q13: 195 | R13: 220 | S13: 290 | T13: 92.5 | U13: 392.5 | V13: 152.5 | W13: 0 | X13: 175.5 | Y13: 185 | Z13: 6012.29
A14: Pet Fee | B14: 585 | C14: -40 | D14: 40 | E14: 40 | F14: 40 | G14: 40 | H14: 40 | I14: 40 | J14: 40 | K14: 0 | L14: 0 | M14: 0 | N14: 0 | O14: 0 | P14: 0 | Q14: 0 | R14: 0 | S14: 0 | T14: 0 | U14: 0 | V14: 0 | W14: 0 | X14: 0 | Y14: 0 | Z14: 825
A15: Furniture Charge | B15: 0 | C15: 0 | D15: 0 | E15: 0 | F15: 0 | G15: 0 | H15: 0 | I15: 0 | J15: 100 | K15: 100 | L15: 100 | M15: 100 | N15: 100 | O15: 100 | P15: 100 | Q15: 100 | R15: 100 | S15: 100 | T15: 100 | U15: 100 | V15: 100 | W15: 0 | X15: 0 | Y15: 0 | Z15: 1300
A16: Laundry Income | B16: 1147.5 | C16: 360.74 | D16: 156.96 | E16: 46.98 | F16: 186.57 | G16: 175.15 | H16: 217.25 | I16: 175.85 | J16: 0 | K16: 0 | L16: 86.45 | M16: 192.38 | N16: 294.97 | O16: 202.85 | P16: 0 | Q16: 288.46 | R16: 127.48 | S16: 0 | T16: 0 | U16: 152.61 | V16: 43.74 | W16: 0 | X16: 107.81 | Y16: 236.35 | Z16: 4200.1
A17: Insurance Services | B17: 181 | C17: -48 | D17: 76 | E17: 47.5 | F17: 66.5 | G17: 66.5 | H17: 57 | I17: 57 | J17: 38 | K17: 28.96 | L17: 19 | M17: 19 | N17: 9.5 | O17: 9.5 | P17: 9.5 | Q17: 9.5 | R17: 9.5 | S17: 9.5 | T17: 9.5 | U17: 9.5 | V17: 9.5 | W17: 0 | X17: 316.45 | Y17: 251.24 | Z17: 1261.65
A18: Utility Reimbursement Fee | B18: 352.33 | C18: 0 | D18: 0 | E18: 0 | F18: 0 | G18: 0 | H18: 0 | I18: 0 | J18: 0 | K18: 0 | L18: 0 | M18: 0 | N18: 0 | O18: 0 | P18: 0 | Q18: 0 | R18: 0 | S18: 0 | T18: 0 | U18: 0 | V18: 0 | W18: 0 | X18: 0 | Y18: 0 | Z18: 352.33
A19: Concessions | B19: -7277.11 | C19: 0 | D19: 0 | E19: 0 | F19: 0 | G19: 0 | H19: 0 | I19: 0 | J19: 0 | K19: 0 | L19: 0 | M19: 0 | N19: 0 | O19: 0 | P19: 0 | Q19: 0 | R19: 0 | S19: 0 | T19: 0 | U19: 0 | V19: 0 | W19: 0 | X19: 0 | Y19: 0 | Z19: -7277.11
A20: TOTAL RENTS | B20: 533008.04 | C20: -9949.03 | D20: 50783.58 | E20: 52427.23 | F20: 45718.22 | G20: 53784.03 | H20: 47414.55 | I20: 41065.85 | J20: 29739.52 | K20: 38433.68 | L20: 41316.95 | M20: 45239.13 | N20: 43513.72 | O20: 55161.74 | P20: 49191.5 | Q20: 44691.21 | R20: 45591.98 | S20: 49193.75 | T20: 42670.39 | U20: 45873.11 | V20: 52017.77 | W20: 26576.94 | X20: 42563.8 | Y20: 45732.37 | Z20: 1511760
A21: MANAGEMENT INCOME
A22: Maintenance Labor Fee Income and Materials Reimbursement | B22: 100 | C22: -100 | D22: 0 | E22: 0 | F22: 0 | G22: 0 | H22: 0 | I22: 0 | J22: 0 | K22: 0 | L22: 0 | M22: 0 | N22: 0 | O22: 0 | P22: 0 | Q22: 0 | R22: 0 | S22: 0 | T22: 0 | U22: 0 | V22: 0 | W22: 0 | X22: 0 | Y22: 0 | Z22: 0
A23: Prepaid Rent | B23: 14622.75 | C23: -14622.75 | D23: -5912.5 | E23: 3363.5 | F23: -657 | G23: -515 | H23: -70 | I23: -3434.5 | J23: -3995 | K23: 1630 | L23: 875 | M23: 450 | N23: -1325 | O23: 1905 | P23: -1905 | Q23: -820.25 | R23: 929.75 | S23: 1029 | T23: 50 | U23: -1768.5 | V23: 1007.25 | W23: 369.75 | X23: 392.25 | Y23: 0 | Z23: -8401.25
A24: TOTAL MANAGEMENT INCOME | B24: 14722.75 | C24: -14722.75 | D24: -5912.5 | E24: 3363.5 | F24: -657 | G24: -515 | H24: -70 | I24: -3434.5 | J24: -3995 | K24: 1630 | L24: 875 | M24: 450 | N24: -1325 | O24: 1905 | P24: -1905 | Q24: -820.25 | R24: 929.75 | S24: 1029 | T24: 50 | U24: -1768.5 | V24: 1007.25 | W24: 369.75 | X24: 392.25 | Y24: 0 | Z24: -8401.25
A25: FEES
A26: Miscellaneous Income | B26: 0.23 | C26: -26468.13 | D26: 0 | E26: 0 | F26: 0 | G26: 0 | H26: 0 | I26: 0 | J26: 0 | K26: 0 | L26: 0 | M26: 0 | N26: 0 | O26: 0 | P26: 0 | Q26: 0 | R26: 0 | S26: 0 | T26: 0 | U26: 0 | V26: 0 | W26: 0 | X26: 0 | Y26: 0 | Z26: -26467.9
A27: TOTAL FEES | B27: 0.23 | C27: -26468.13 | D27: 0 | E27: 0 | F27: 0 | G27: 0 | H27: 0 | I27: 0 | J27: 0 | K27: 0 | L27: 0 | M27: 0 | N27: 0 | O27: 0 | P27: 0 | Q27: 0 | R27: 0 | S27: 0 | T27: 0 | U27: 0 | V27: 0 | W27: 0 | X27: 0 | Y27: 0 | Z27: -26467.9
A28: TOTAL REVENUE | B28: 547731.02 | C28: -51139.91 | D28: 44871.08 | E28: 55790.73 | F28: 45061.22 | G28: 53269.03 | H28: 47344.55 | I28: 37631.35 | J28: 25744.52 | K28: 40063.68 | L28: 42191.95 | M28: 45689.13 | N28: 42188.72 | O28: 57066.74 | P28: 47286.5 | Q28: 43870.96 | R28: 46521.73 | S28: 50222.75 | T28: 42720.39 | U28: 44104.61 | V28: 53025.02 | W28: 26946.69 | X28: 42956.05 | Y28: 45732.37 | Z28: 1476890.9
A29: EXPENSES
A30: CLEANING AND JANITORIAL EXPENSE
A31: Cleaning and Janitorial Expense | B31: 1075 | C31: 0 | D31: 200 | E31: 0 | F31: 0 | G31: 0 | H31: 0 | I31: 200 | J31: 0 | K31: 0 | L31: 0 | M31: 0 | N31: 0 | O31: 0 | P31: 0 | Q31: 0 | R31: 0 | S31: 0 | T31: 0 | U31: 0 | V31: 0 | W31: 2862 | X31: 0 | Y31: 0 | Z31: 4337
A32: Maintenance Labor Expense | B32: 185 | C32: -150 | D32: 0 | E32: 0 | F32: 0 | G32: 0 | H32: 0 | I32: 55 | J32: 0 | K32: 0 | L32: 0 | M32: 0 | N32: -55 | O32: 0 | P32: 55 | Q32: 0 | R32: 0 | S32: 0 | T32: 0 | U32: 0 | V32: 0 | W32: 0 | X32: 0 | Y32: 0 | Z32: 90
A33: Garbage and Recycling | B33: 4433.98 | C33: 0 | D33: 948.65 | E33: 0 | F33: -1013.76 | G33: 0 | H33: 2111.69 | I33: 2125.68 | J33: 527.94 | K33: 489.5 | L33: 1753.94 | M33: 97.4 | N33: 621.66 | O33: 0 | P33: 1243.32 | Q33: 621.66 | R33: 621.66 | S33: 621.66 | T33: 621.66 | U33: 621.66 | V33: 621.66 | W33: 621.66 | X33: 621.66 | Y33: 1027.08 | Z33: 19340.36
A34: Pest control | B34: 2359.8 | C34: 0 | D34: 988.2 | E34: 0 | F34: 0 | G34: 378 | H34: 189 | I34: 567 | J34: 0 | K34: 0 | L34: 0 | M34: 0 | N34: 0 | O34: 0 | P34: 0 | Q34: 3213 | R34: 0 | S34: 0 | T34: 0 | U34: 0 | V34: 0 | W34: 0 | X34: 1323 | Y34: 189 | Z34: 9207
A35: TOTAL CLEANING AND JANITORIAL EXPENSE | B35: 8053.78 | C35: -150 | D35: 2136.85 | E35: 0 | F35: -1013.76 | G35: 378 | H35: 2300.69 | I35: 2947.68 | J35: 527.94 | K35: 489.5 | L35: 1753.94 | M35: 97.4 | N35: 566.66 | O35: 0 | P35: 1298.32 | Q35: 3834.66 | R35: 621.66 | S35: 621.66 | T35: 621.66 | U35: 621.66 | V35: 621.66 | W35: 3483.66 | X35: 1944.66 | Y35: 1216.08 | Z35: 32974.36
A36: INSURANCE
A37: Property Insurance | B37: 19020 | C37: -1585 | D37: 0 | E37: 0 | F37: 0 | G37: 0 | H37: 5183.82 | I37: 1587 | J37: 0 | K37: 0 | L37: 0 | M37: 0 | N37: 0 | O37: 6911.76 | P37: 0 | Q37: 0 | R37: 0 | S37: 0 | T37: 0 | U37: 36362.63 | V37: 0 | W37: 0 | X37: 0 | Y37: 0 | Z37: 67480.21
A38: Insurance - Other | B38: 0 | C38: 0 | D38: 0 | E38: 0 | F38: 6911.76 | G38: 0 | H38: 0 | I38: 0 | J38: 0 | K38: 0 | L38: 0 | M38: 0 | N38: 0 | O38: -6911.76 | P38: 0 | Q38: 0 | R38: 0 | S38: 0 | T38: 0 | U38: 0 | V38: 0 | W38: 0 | X38: 0 | Y38: 0 | Z38: 0
A39: TOTAL INSURANCE | B39: 19020 | C39: -1585 | D39: 0 | E39: 0 | F39: 6911.76 | G39: 0 | H39: 5183.82 | I39: 1587 | J39: 0 | K39: 0 | L39: 0 | M39: 0 | N39: 0 | O39: 0 | P39: 0 | Q39: 0 | R39: 0 | S39: 0 | T39: 0 | U39: 36362.63 | V39: 0 | W39: 0 | X39: 0 | Y39: 0 | Z39: 67480.21
A40: LEGAL AND OTHER PROFESSIONAL FEES
A41: Accounting | B41: 1605 | C41: 0 | D41: 2425.41 | E41: 0 | F41: 0 | G41: 0 | H41: 0 | I41: 0 | J41: 0 | K41: 0 | L41: 0 | M41: 0 | N41: 2658 | O41: 0 | P41: 0 | Q41: 0 | R41: 0 | S41: 0 | T41: 0 | U41: 0 | V41: 0 | W41: 0 | X41: 471 | Y41: 0 | Z41: 7159.41
A42: Appfolio | B42: 1080 | C42: 0 | D42: 0 | E42: 0 | F42: 0 | G42: 0 | H42: 0 | I42: 0 | J42: 0 | K42: 0 | L42: 0 | M42: 0 | N42: 0 | O42: 0 | P42: 0 | Q42: 0 | R42: 0 | S42: 0 | T42: 0 | U42: 0 | V42: 0 | W42: 0 | X42: 0 | Y42: 0 | Z42: 1080
A43: TOTAL LEGAL AND OTHER PROFESSIONAL FEES | B43: 2685 | C43: 0 | D43: 2425.41 | E43: 0 | F43: 0 | G43: 0 | H43: 0 | I43: 0 | J43: 0 | K43: 0 | L43: 0 | M43: 0 | N43: 2658 | O43: 0 | P43: 0 | Q43: 0 | R43: 0 | S43: 0 | T43: 0 | U43: 0 | V43: 0 | W43: 0 | X43: 471 | Y43: 0 | Z43: 8239.41
A44: MANAGEMENT FEES EXPENSE
A45: Management Fee Expense | B45: 22157.13 | C45: 0 | D45: 0 | E45: 0 | F45: 0 | G45: 0 | H45: 0 | I45: 0 | J45: 0 | K45: 0 | L45: 0 | M45: 0 | N45: 0 | O45: 0 | P45: 6698.71 | Q45: 0 | R45: 0 | S45: 0 | T45: 0 | U45: 0 | V45: 0 | W45: 0 | X45: 1369.1 | Y45: 0 | Z45: 30224.94
A46: Commissions/Placement Fee Expense | B46: 1750 | C46: 0 | D46: 0 | E46: 0 | F46: 0 | G46: 0 | H46: 0 | I46: 0 | J46: 0 | K46: 0 | L46: 0 | M46: 0 | N46: 0 | O46: 0 | P46: 0 | Q46: 0 | R46: 0 | S46: 0 | T46: 0 | U46: 0 | V46: 0 | W46: 0 | X46: 0 | Y46: 0 | Z46: 1750
A47: TOTAL MANAGEMENT FEES EXPENSE | B47: 23907.13 | C47: 0 | D47: 0 | E47: 0 | F47: 0 | G47: 0 | H47: 0 | I47: 0 | J47: 0 | K47: 0 | L47: 0 | M47: 0 | N47: 0 | O47: 0 | P47: 6698.71 | Q47: 0 | R47: 0 | S47: 0 | T47: 0 | U47: 0 | V47: 0 | W47: 0 | X47: 1369.1 | Y47: 0 | Z47: 31974.94
A48: MORTGAGE
A49: Mortgage Interest | B49: 0 | C49: 132145.09 | D49: 0 | E49: 0 | F49: 0 | G49: 0 | H49: 0 | I49: 0 | J49: 0 | K49: 0 | L49: 0 | M49: 0 | N49: 0 | O49: 129666.79 | P49: 0 | Q49: 18070.49 | R49: 18070.49 | S49: 18070.49 | T49: 18070.49 | U49: 18070.49 | V49: 18070.49 | W49: 18070.49 | X49: 18070.49 | Y49: 18070.49 | Z49: 424446.29
A50: Mortgage - Other | B50: 0 | C50: 0 | D50: 0 | E50: 0 | F50: 0 | G50: 18070.49 | H50: 18070.49 | I50: 18070.49 | J50: 0 | K50: 0 | L50: 0 | M50: 0 | N50: 0 | O50: -54211.47 | P50: 0 | Q50: 0 | R50: 0 | S50: 0 | T50: 0 | U50: 0 | V50: 0 | W50: 0 | X50: 0 | Y50: 0 | Z50: 0
A51: Other interest | B51: 0 | C51: 0 | D51: 0 | E51: 0 | F51: 0 | G51: 0 | H51: 0 | I51: 0 | J51: 0 | K51: 0 | L51: 0 | M51: 0 | N51: 0 | O51: 107926.89 | P51: 0 | Q51: 0 | R51: 0 | S51: 0 | T51: 0 | U51: 0 | V51: 0 | W51: 0 | X51: 0 | Y51: 0 | Z51: 107926.89
A52: TOTAL MORTGAGE | B52: 0 | C52: 132145.09 | D52: 0 | E52: 0 | F52: 0 | G52: 18070.49 | H52: 18070.49 | I52: 18070.49 | J52: 0 | K52: 0 | L52: 0 | M52: 0 | N52: 0 | O52: 183382.21 | P52: 0 | Q52: 18070.49 | R52: 18070.49 | S52: 18070.49 | T52: 18070.49 | U52: 18070.49 | V52: 18070.49 | W52: 18070.49 | X52: 18070.49 | Y52: 18070.49 | Z52: 532373.18
A53: REPAIRS AND MAINTENANCE
A54: Painting | B54: -150 | C54: 150 | D54: 0 | E54: 0 | F54: 0 | G54: 0 | H54: 0 | I54: 0 | J54: 0 | K54: 0 | L54: 0 | M54: 0 | N54: 0 | O54: 0 | P54: 0 | Q54: 0 | R54: 0 | S54: 0 | T54: 0 | U54: 0 | V54: 0 | W54: 0 | X54: 0 | Y54: 0 | Z54: 0
A55: Plumbing | B55: 550 | C55: 499.59 | D55: 0 | E55: 0 | F55: 0 | G55: 500 | H55: 0 | I55: 0 | J55: 0 | K55: 0 | L55: 0 | M55: 260 | N55: 0 | O55: 3000 | P55: 0 | Q55: 0 | R55: 945 | S55: 0 | T55: 0 | U55: 0 | V55: 0 | W55: 0 | X55: 0 | Y55: 0 | Z55: 5754.59
A56: Flooring | B56: -670 | C56: 670 | D56: 0 | E56: 0 | F56: 0 | G56: 0 | H56: 0 | I56: 0 | J56: 0 | K56: 0 | L56: 0 | M56: 0 | N56: 0 | O56: 0 | P56: 0 | Q56: 0 | R56: 0 | S56: 0 | T56: 0 | U56: 0 | V56: 0 | W56: 0 | X56: 0 | Y56: 0 | Z56: 0
A57: HVAC (Heat Ventilation Air) | B57: 21403.22 | C57: -17317 | D57: 0 | E57: 575 | F57: 0 | G57: 0 | H57: 0 | I57: 764.6 | J57: 0 | K57: 0 | L57: 764.6 | M57: 0 | N57: 3403.75 | O57: 0 | P57: 0 | Q57: 175 | R57: 2775.22 | S57: 0 | T57: 0 | U57: 0 | V57: 0 | W57: 0 | X57: 0 | Y57: 0 | Z57: 12544.39
A58: Sub Contractor | B58: 0 | C58: 0 | D58: 0 | E58: 0 | F58: 0 | G58: 0 | H58: 0 | I58: 0 | J58: 0 | K58: 0 | L58: 0 | M58: 0 | N58: 0 | O58: 23900 | P58: 0 | Q58: 5800 | R58: 11600 | S58: 5800 | T58: 0 | U58: 0 | V58: 0 | W58: 0 | X58: 0 | Y58: 0 | Z58: 47100
A59: Key/Lock Replacement | B59: -31 | C59: 31 | D59: 0 | E59: 0 | F59: 0 | G59: 0 | H59: 0 | I59: 0 | J59: 0 | K59: 0 | L59: 0 | M59: 0 | N59: 0 | O59: 0 | P59: 0 | Q59: 0 | R59: 0 | S59: 0 | T59: 0 | U59: 0 | V59: 0 | W59: 0 | X59: 0 | Y59: 0 | Z59: 0
A60: Security Service | B60: 2851.6 | C60: 2425 | D60: 386.7 | E60: 0 | F60: 0 | G60: 501.7 | H60: 0 | I60: 2926.7 | J60: 0 | K60: 0 | L60: 1261.7 | M60: 0 | N60: 602.7 | O60: 290 | P60: 0 | Q60: 0 | R60: 0 | S60: 0 | T60: 0 | U60: 0 | V60: 0 | W60: 0 | X60: 875 | Y60: 492.37 | Z60: 12613.47
A61: Roof Repair | B61: 0 | C61: 0 | D61: 0 | E61: 0 | F61: 0 | G61: 0 | H61: 0 | I61: 0 | J61: 0 | K61: 0 | L61: 1890 | M61: 1890 | N61: 1890 | O61: 0 | P61: 0 | Q61: 0 | R61: 0 | S61: 0 | T61: 0 | U61: 2500 | V61: 0 | W61: 0 | X61: 0 | Y61: 0 | Z61: 8170
A62: Elevator Contract | B62: 7919.57 | C62: 0 | D62: 956.29 | E62: 0 | F62: 0 | G62: 0 | H62: 0 | I62: 1912.58 | J62: 102.6 | K62: 956.29 | L62: 956.29 | M62: 0 | N62: 1032.78 | O62: 3383.2 | P62: 0 | Q62: 386.7 | R62: 1032.78 | S62: 0 | T62: 135 | U62: 1419.48 | V62: 0 | W62: 230 | X62: 386.7 | Y62: 0 | Z62: 20810.26
A63: Elevator Repair Expense | B63: 0 | C63: 0 | D63: 0 | E63: 0 | F63: 0 | G63: 0 | H63: 0 | I63: 0 | J63: 0 | K63: 0 | L63: 0 | M63: 0 | N63: 0 | O63: 0 | P63: 0 | Q63: 0 | R63: 0 | S63: 0 | T63: 0 | U63: 0 | V63: 0 | W63: 1032.78 | X63: 0 | Y63: 0 | Z63: 1032.78
A64: Appliance Repair | B64: 0 | C64: 611.74 | D64: 0 | E64: 0 | F64: 0 | G64: 0 | H64: 0 | I64: 0 | J64: 0 | K64: 0 | L64: 0 | M64: 0 | N64: 0 | O64: 0 | P64: 0 | Q64: 0 | R64: 0 | S64: 0 | T64: 0 | U64: 0 | V64: 0 | W64: 0 | X64: 0 | Y64: 0 | Z64: 611.74
A65: Repairs - Other | B65: -1353.75 | C65: 1353.75 | D65: 0 | E65: 0 | F65: 0 | G65: 0 | H65: 0 | I65: 0 | J65: 0 | K65: 0 | L65: 0 | M65: 577.5 | N65: 577.5 | O65: 2290.4 | P65: 0 | Q65: 0 | R65: 0 | S65: 0 | T65: 0 | U65: 0 | V65: 0 | W65: 0 | X65: 412.64 | Y65: 0 | Z65: 3858.04
... A67: TOTAL REPAIRS AND MAINTENANCE | B67: 31758.65 | C67: -11445.51 | D67: 1342.99 | E67: 739.91 | F67: 26.97 | G67: 1231.7 | H67: 0 | I67: 5603.88 | J67: 102.6 | K67: 956.29 | L67: 4902.24 | M67: 2727.5 | N67: 7506.73 | O67: 33650.9 | P67: 0 | Q67: 6361.7 | R67: 16583 | S67: 5800 | T67: 135 | U67: 3919.48 | V67: 500 | W67: 1262.78 | X67: 1674.34 | Y67: 492.37 | Z67: 115833.52
A68: TAXES
A69: Property Tax | B69: 84946.44 | C69: -84946.44 | D69: 0 | E69: 47156.06 | F69: 0 | G69: 0 | H69: 0 | I69: 0 | J69: 10000 | K69: 0 | L69: 0 | M69: 0 | N69: 0 | O69: 82.18 | P69: 0 | Q69: 0 | R69: 11000 | S69: 0 | T69: 6000 | U69: 6000 | V69: 0 | W69: 1150 | X69: 1000 | Y69: 0 | Z69: 82388.24
A70: Taxes - Other | B70: 1480 | C70: 0 | D70: 0 | E70: 0 | F70: 0 | G70: 0 | H70: 0 | I70: 0 | J70: 0 | K70: 0 | L70: 0 | M70: 0 | N70: 0 | O70: 0 | P70: 0 | Q70: 0 | R70: 0 | S70: 0 | T70: 0 | U70: 0 | V70: 0 | W70: 0 | X70: 0 | Y70: 0 | Z70: 1480
A71: Licenses and Registration Fees | B71: 303 | C71: 1701 | D71: 0 | E71: 0 | F71: 0 | G71: 0 | H71: 0 | I71: 0 | J71: 0 | K71: 0 | L71: 303 | M71: 1701 | N71: 0 | O71: 5617 | P71: 0 | Q71: 0 | R71: 0 | S71: 309 | T71: 0 | U71: 0 | V71: 0 | W71: 0 | X71: 618 | Y71: 0 | Z71: 10552
A72: TOTAL TAXES | B72: 86729.44 | C72: -83245.44 | D72: 0 | E72: 47156.06 | F72: 0 | G72: 0 | H72: 0 | I72: 0 | J72: 10000 | K72: 0 | L72: 303 | M72: 1701 | N72: 0 | O72: 5699.18 | P72: 0 | Q72: 0 | R72: 11000 | S72: 309 | T72: 6000 | U72: 6000 | V72: 0 | W72: 1150 | X72: 1618 | Y72: 0 | Z72: 94420.24
A73: UTILITIES
A74: Electricity | B74: 35902.96 | C74: 6597.35 | D74: 4226.99 | E74: 4989.7 | F74: 0 | G74: 0 | H74: 0 | I74: 319.56 | J74: 0 | K74: 0 | L74: 9074.82 | M74: 106.92 | N74: 3117.83 | O74: 17331.96 | P74: 678.81 | Q74: 13750.02 | R74: 2335.48 | S74: 10094.04 | T74: 2853.76 | U74: 7011.94 | V74: 3104.7 | W74: 3923.45 | X74: 3638.58 | Y74: 2569.11 | Z74: 131627.98
A75: Gas | B75: 4566.48 | C75: 399.63 | D75: 504.61 | E75: 0 | F75: 0 | G75: 611.12 | H75: 0 | I75: 1310.73 | J75: 571.78 | K75: 245.81 | L75: 2190.66 | M75: 1345.89 | N75: 1532.52 | O75: -1144.9 | P75: 0 | Q75: 0 | R75: 584.64 | S75: 583.88 | T75: 1138.62 | U75: 0 | V75: 0 | W75: 2022.03 | X75: 600.82 | Y75: 0 | Z75: 17064.32
A76: Water | B76: 1633.98 | C76: 589.28 | D76: 0 | E76: 0 | F76: 0 | G76: 0 | H76: 0 | I76: 0 | J76: 0 | K76: 0 | L76: 0 | M76: 0 | N76: 0 | O76: 0 | P76: 0 | Q76: 328.72 | R76: 109.48 | S76: 0 | T76: 0 | U76: 0 | V76: 0 | W76: 0 | X76: 4788.08 | Y76: 255.15 | Z76: 7704.69
A77: Telephone | B77: 5053.7 | C77: 791.59 | D77: 159.78 | E77: 159.78 | F77: 159.78 | G77: 159.78 | H77: 159.78 | I77: 988.34 | J77: 1538.98 | K77: 500.29 | L77: 482.66 | M77: 481.61 | N77: 481.58 | O77: 480.99 | P77: 483.36 | Q77: 562.92 | R77: 562.74 | S77: 602.97 | T77: 602.17 | U77: 602.11 | V77: 602.2 | W77: 602.6 | X77: 602.28 | Y77: 602.42 | Z77: 17424.41
A78: TOTAL UTILITIES | B78: 47157.12 | C78: 8377.85 | D78: 4891.38 | E78: 5149.48 | F78: 159.78 | G78: 770.9 | H78: 159.78 | I78: 2618.63 | J78: 2110.76 | K78: 746.1 | L78: 11748.14 | M78: 1934.42 | N78: 5131.93 | O78: 16668.05 | P78: 1162.17 | Q78: 14641.66 | R78: 3592.34 | S78: 11280.89 | T78: 4594.55 | U78: 7614.05 | V78: 3706.9 | W78: 6548.08 | X78: 9629.76 | Y78: 3426.68 | Z78: 173821.4
A79: ADMINISTRATIVE EXPENSES
A80: Office Expense | B80: 0 | C80: 68.95 | D80: 0 | E80: 0 | F80: 0 | G80: 0 | H80: 0 | I80: 0 | J80: 0 | K80: 0 | L80: 0 | M80: 0 | N80: 0 | O80: 0 | P80: 0 | Q80: 0 | R80: 0 | S80: 0 | T80: 0 | U80: 0 | V80: 0 | W80: 0 | X80: 0 | Y80: 0 | Z80: 68.95
A81: Salary Expense | B81: 42300 | C81: 0 | D81: 0 | E81: 3800 | F81: 1900 | G81: 0 | H81: 8600 | I81: 0 | J81: 0 | K81: 11600 | L81: 0 | M81: 0 | N81: -11600 | O81: -14300 | P81: 11600 | Q81: 0 | R81: 0 | S81: 0 | T81: 0 | U81: 0 | V81: 0 | W81: 0 | X81: 0 | Y81: 0 | Z81: 53900
A82: Bank Fees | B82: 289.99 | C82: 1550.05 | D82: 71 | E82: 53 | F82: 41 | G82: 41 | H82: 0 | I82: 16 | J82: 0 | K82: 76 | L82: 10 | M82: 25 | N82: 10 | O82: 16 | P82: 16 | Q82: 10 | R82: 85.79 | S82: 52 | T82: 51 | U82: 41 | V82: 31 | W82: 16 | X82: 16 | Y82: 2.42 | Z82: 2520.25
A83: TOTAL ADMNISTRATIVE EXPENSES | B83: 42589.99 | C83: 1619 | D83: 71 | E83: 3853 | F83: 1941 | G83: 41 | H83: 8600 | I83: 16 | J83: 0 | K83: 11676 | L83: 10 | M83: 25 | N83: -11590 | O83: -14284 | P83: 11616 | Q83: 10 | R83: 85.79 | S83: 52 | T83: 51 | U83: 41 | V83: 31 | W83: 16 | X83: 16 | Y83: 2.42 | Z83: 56489.2
A84: Marketing Expense | B84: 4344.81 | C84: -1215 | D84: 0 | E84: 0 | F84: 0 | G84: 0 | H84: 7835.82 | I84: 0 | J84: 60.82 | K84: 0 | L84: 45 | M84: 0 | N84: 0 | O84: 4000 | P84: 0 | Q84: 0 | R84: 0 | S84: 0 | T84: 0 | U84: 4548.39 | V84: 0 | W84: 0 | X84: 0 | Y84: 0 | Z84: 19619.84
A85: Advertising | B85: 750 | C85: 1650 | D85: 0 | E85: 0 | F85: 7775 | G85: 500 | H85: 0 | I85: 0 | J85: -250 | K85: 0 | L85: 2220.87 | M85: 0 | N85: 0 | O85: 0 | P85: 0 | Q85: 0 | R85: 0 | S85: 0 | T85: 0 | U85: 0 | V85: 0 | W85: 0 | X85: 0 | Y85: 0 | Z85: 12645.87
A86: Meetings and Events | B86: 1220.73 | C86: 0 | D86: 0 | E86: 0 | F86: 0 | G86: 0 | H86: 0 | I86: 0 | J86: 0 | K86: 0 | L86: 0 | M86: 0 | N86: 0 | O86: 0 | P86: 0 | Q86: 0 | R86: 0 | S86: 0 | T86: 0 | U86: 0 | V86: 0 | W86: 0 | X86: 0 | Y86: 0 | Z86: 1220.73
A87: TOTAL MARKETING EXPENSES | B87: 6315.54 | C87: 435 | D87: 0 | E87: 0 | F87: 7775 | G87: 500 | H87: 7835.82 | I87: 0 | J87: -189.18 | K87: 0 | L87: 2265.87 | M87: 0 | N87: 0 | O87: 4000 | P87: 0 | Q87: 0 | R87: 0 | S87: 0 | T87: 0 | U87: 4548.39 | V87: 0 | W87: 0 | X87: 0 | Y87: 0 | Z87: 33486.44
A88: BUILDING EXPENSES
A89: Inspection Costs | B89: 895 | C89: 0 | D89: 0 | E89: 0 | F89: 0 | G89: 0 | H89: 0 | I89: 0 | J89: 0 | K89: 0 | L89: 895 | M89: 0 | N89: 0 | O89: 0 | P89: 1600 | Q89: 0 | R89: 0 | S89: 0 | T89: 0 | U89: 0 | V89: 0 | W89: 0 | X89: 0 | Y89: 0 | Z89: 3390
A90: Depreciation expense | B90: 0 | C90: 0 | D90: 0 | E90: 0 | F90: 0 | G90: 0 | H90: 0 | I90: 0 | J90: 0 | K90: 0 | L90: 0 | M90: 0 | N90: 0 | O90: 55642 | P90: 0 | Q90: 0 | R90: 0 | S90: 0 | T90: 0 | U90: 0 | V90: 0 | W90: 0 | X90: 0 | Y90: 0 | Z90: 55642
A91: Amortization Expense | B91: 0 | C91: 30857 | D91: 0 | E91: 0 | F91: 0 | G91: 0 | H91: 0 | I91: 0 | J91: 0 | K91: 0 | L91: 0 | M91: 0 | N91: 0 | O91: 30857 | P91: 0 | Q91: 0 | R91: 0 | S91: 0 | T91: 0 | U91: 0 | V91: 0 | W91: 0 | X91: 0 | Y91: 0 | Z91: 61714
A92: Refinance Fee Expense | B92: 0 | C92: -642.25 | D92: 0 | E92: 0 | F92: 0 | G92: 0 | H92: 0 | I92: 0 | J92: 0 | K92: 0 | L92: 0 | M92: 0 | N92: 0 | O92: 0 | P92: 0 | Q92: 0 | R92: 0 | S92: 0 | T92: 0 | U92: 0 | V92: 0 | W92: 0 | X92: 0 | Y92: 0 | Z92: -642.25
A93: Miscellaneous Expense | B93: 0 | C93: 0.07 | D93: 0 | E93: 0 | F93: 0 | G93: 0 | H93: 0 | I93: 0 | J93: 0 | K93: 0 | L93: 0 | M93: 0 | N93: 0 | O93: 0 | P93: 0 | Q93: 0 | R93: 0 | S93: 0 | T93: 0 | U93: 0 | V93: 0 | W93: 0 | X93: 0 | Y93: 0 | Z93: 0.07
A94: TOTAL BUILDING EXPENSES | B94: 895 | C94: 30214.82 | D94: 0 | E94: 0 | F94: 0 | G94: 0 | H94: 0 | I94: 0 | J94: 0 | K94: 0 | L94: 895 | M94: 0 | N94: 0 | O94: 86499 | P94: 1600 | Q94: 0 | R94: 0 | S94: 0 | T94: 0 | U94: 0 | V94: 0 | W94: 0 | X94: 0 | Y94: 0 | Z94: 120103.82
A95: Depreciation Expense (Unused) | B95: 0 | C95: 69335 | D95: 0 | E95: 0 | F95: 0 | G95: 0 | H95: 0 | I95: 0 | J95: 0 | K95: 0 | L95: 0 | M95: 0 | N95: 0 | O95: 0 | P95: 0 | Q95: 0 | R95: 0 | S95: 0 | T95: 0 | U95: 0 | V95: 0 | W95: 0 | X95: 0 | Y95: 0 | Z95: 69335
A96: PREFERRED RETURNS
A97: Guaranteed Payments | B97: 0 | C97: 84077.22 | D97: 0 | E97: 0 | F97: 0 | G97: 0 | H97: 0 | I97: 0 | J97: 0 | K97: 0 | L97: 0 | M97: 0 | N97: 0 | O97: 0 | P97: 0 | Q97: 0 | R97: 0 | S97: 0 | T97: 0 | U97: 0 | V97: 0 | W97: 0 | X97: 0 | Y97: 0 | Z97: 84077.22
A98: Pref - Int - Ho Ruiming | B98: 0 | C98: 4643.46 | D98: 0 | E98: 0 | F98: 0 | G98: 0 | H98: 0 | I98: 0 | J98: 0 | K98: 0 | L98: 0 | M98: 0 | N98: 0 | O98: 0 | P98: 0 | Q98: 0 | R98: 0 | S98: 0 | T98: 0 | U98: 0 | V98: 0 | W98: 0 | X98: 0 | Y98: 0 | Z98: 4643.46
A99: TOTAL PREFERRED PAYMENTS | B99: 0 | C99: 88720.68 | D99: 0 | E99: 0 | F99: 0 | G99: 0 | H99: 0 | I99: 0 | J99: 0 | K99: 0 | L99: 0 | M99: 0 | N99: 0 | O99: 0 | P99: 0 | Q99: 0 | R99: 0 | S99: 0 | T99: 0 | U99: 0 | V99: 0 | W99: 0 | X99: 0 | Y99: 0 | Z99: 88720.68
A100: Ask My Accountant | B100: -17213.74 | C100: 17213.74 | D100: 0 | E100: 0 | F100: 0 | G100: 0 | H100: 0 | I100: 0 | J100: 631.47 | K100: 0 | L100: 5617 | M100: 0 | N100: -3880 | O100: -2368.47 | P100: 0 | Q100: 0 | R100: 0 | S100: 0 | T100: 0 | U100: 0 | V100: 0 | W100: 3546.66 | X100: 0 | Y100: 0 | Z100: 3546.66
A101: TOTAL EXPENSES | B101: 251897.91 | C101: 251635.23 | D101: 10867.63 | E101: 56898.45 | F101: 15800.75 | G101: 20992.09 | H101: 42150.6 | I101: 30843.68 | J101: 13183.59 | K101: 13867.89 | L101: 27495.19 | M101: 6485.32 | N101: 393.32 | O101: 313246.87 | P101: 22375.2 | Q101: 42918.51 | R101: 49953.28 | S101: 36134.04 | T101: 29472.7 | U101: 77177.7 | V101: 22930.05 | W101: 34077.67 | X101: 34793.35 | Y101: 23208.04 | Z101: 1428799.1
...

Sheet RR
A1: Rent Roll
A2: Property = Cherry Commons - 1718 N Sydenham
A3: As Of = 11/12/2025
A4: Month = 11/2025
A5: Unit | B5: Unit | C5: Tenant Name | D5: Actual | E5: Actual Rent | F5: Tenant | G5: Other | H5: Misc | I5: Misc | J5: Move In | K5: Lease | L5: Move Out | M5: Balance
B6: SqFt | D6: Rent | E6: per Sqft | F6: Deposit | G6: Deposit | I6: per Sqft | K6: Expiration
A7: Current/Notice/Vacant Tenants
A8: 1A | B8: 540 | C8: Adam Ha | D8: 1450 | E8: 2.69 | F8: 0 | G8: 1450 | H8: 0 | I8: 0 | J8: 45870 | K8: 46234 | M8: 0
A9: 1B | B9: 840 | C9: Wenjie Shen | D9: 1850 | E9: 2.2 | F9: 0 | G9: 3700 | H9: 0 | I9: 0 | J9: 45884 | K9: 46234 | M9: 0
A10: 1C | B10: 540 | C10: Fiona Kwok | D10: 1350 | E10: 2.5 | F10: 0 | G10: 1350 | H10: 0 | I10: 0 | J10: 45873 | K10: 46237 | M10: 0
A11: 1D | B11: 540 | C11: Jake Naese | D11: 1450 | E11: 2.69 | F11: 0 | G11: 1450 | H11: 0 | I11: 0 | J11: 45873 | K11: 46234 | M11: 0
A12: 1E | B12: 840 | C12: OCCUPIED | D12: 1850 | E12: 0 | F12: 0 | G12: 0 | H12: 0 | I12: 0 | M12: 0
A13: 1F | B13: 840 | C13: Brian ODell | D13: 1850 | E13: 2.2 | F13: 0 | G13: 1850 | H13: 0 | I13: 0 | J13: 45474 | K13: 46234 | M13: 0
A14: 2A | B14: 840 | C14: Zhongying Huang | D14: 1850 | E14: 2.2 | F14: 0 | G14: 3700 | H14: 20 | I14: 0.02 | J14: 45884 | K14: 46234 | M14: 0
A15: 2B | B15: 840 | C15: Shimin Yang | D15: 1850 | E15: 2.2 | F15: 0 | G15: 3700 | H15: 20 | I15: 0.02 | J15: 45873 | K15: 46234 | M15: 0
A16: 2C | B16: 540 | C16: You Wang | D16: 1450 | E16: 2.69 | F16: 0 | G16: 2900 | H16: 20 | I16: 0.04 | J16: 45883 | K16: 46234 | M16: 0
A17: 2D | B17: 540 | C17: Justin Ok | D17: 1450 | E17: 2.69 | F17: 0 | G17: 1375 | H17: 20 | I17: 0.04 | J17: 45508 | K17: 46234 | M17: 0
A18: 2E | B18: 840 | C18: Nicholas Afanassiev | D18: 1850 | E18: 2.2 | F18: 0 | G18: 1850 | H18: 0 | I18: 0 | J18: 45895 | K18: 46234 | M18: 0
A19: 2F | B19: 840 | C19: Anna Beshoar | D19: 1850 | E19: 2.2 | F19: 0 | G19: 1850 | H19: 20 | I19: 0.02 | J19: 45895 | K19: 46234 | M19: 0
A20: 2G | B20: 960 | C20: Xinyue Zhang | D20: 1950 | E20: 2.03 | F20: 0 | G20: 3900 | H20: 20 | I20: 0.02 | J20: 45874 | K20: 46234 | M20: 0
A21: 3A | B21: 840 | C21: Dinala Hailati | D21: 1700 | E21: 2.02 | F21: 0 | G21: 1700 | H21: 20 | I21: 0.02 | J21: 45873 | K21: 46234 | M21: 0
A22: 3B | B22: 840 | C22: Zachary Kaminskyj | D22: 800 | E22: 0.95 | F22: 0 | G22: 800 | H22: 10 | I22: 0.01 | J22: 45462 | K22: 46234 | M22: 0
A23: 3C | B23: 540 | C23: John Kim | D23: 1450 | E23: 2.69 | F23: 0 | G23: 0 | H23: 0 | I23: 0 | J23: 45873 | K23: 46234 | M23: 0
A24: 3D | B24: 540 | C24: Evan Blake | D24: 1450 | E24: 2.69 | F24: 0 | G24: 1375 | H24: 20 | I24: 0.04 | J24: 45079 | K24: 46234 | M24: 2495
... A35: 3B-1 | B35: 960 | C35: Trent Wilkinson | D35: 925 | E35: 0.96 | F35: 950 | G35: 0 | H35: 0 | I35: 0 | J35: 45870 | K35: 46234 | M35: 0
A36: Total | C36: Cherry Commons - 1718 N Sydenham | D36: 44160 | E36: 2.07 | F36: 4125 | G36: 45380 | H36: 270 | I36: 0.01 | M36: 2495
D37: =D36*12 -> 529920
A39: Summary Groups | C39: Square | D39: Actual | F39: Security | G39: Other | H39: Misc | J39: # Of | K39: % Unit | L39: % Sqft | M39: Balance
C40: Footage | D40: Rent | F40: Deposit | G40: Deposits | J40: Units | K40: Occupancy | L40: Occupied
A41: Current/Notice/Vacant Tenants | C41: 21300 | D41: 44160 | F41: 4125 | G41: 45380 | H41: 270 | J41: 28 | K41: 96.42 | L41: 96.05 | M41: 2495
A42: Future Tenants/Applicants | C42: 0 | D42: 0 | F42: 0 | G42: 0 | H42: 0 | J42: 0 | K42: 0 | L42: 0 | M42: 0
A43: Occupied Units | C43: 20460 | D43: 0 | F43: 0 | G43: 0 | H43: 0 | J43: 27 | K43: 96.42 | L43: 96.05 | M43: 0
A44: Total Non Rev Units | C44: 0 | D44: 0 | F44: 0 | G44: 0 | H44: 0 | J44: 0 | K44: 0 | L44: 0
A45: Total Vacant Units | C45: 840 | D45: 0 | F45: 0 | G45: 0 | H45: 0 | J45: 1 | K45: 3.57 | L45: 3.94 | M45: 0
A46: Totals: | C46: 21300 | D46: 44160 | F46: 4125 | G46: 45380 | H46: 270 | J46: 28 | K46: 100 | L46: 100 | M46: 2495

Sheet Debt Current
B2: ='Debt Refinance'!B2 -> Address: 1718 North Sydenham Street Philadelphia, PA 19121
B5: Loan Amount | I5: 4000000
B7: Principal | I7: 4200000
B8: Interest per annum | I8: 0.0325
B9: Interest per month | I9: =I8/12 -> 0.0027083333
B10: Mortgage Constant | I10: =I9/(1-(1/(1+I9)^I16)) -> 0.0043520632
B12: Commencement date | I12: 44136
B13: Final maturity date | I13: 19815
B15: Duration (Years) | I15: 30
B16: Duration (Months) | I16: =I15*12 -> 360
B18: Mortgage Insurance Premium
B19: Mortgage Insurance Premium per annum | I19: 0
B20: Mortgage Insurance Premium per month | I20: =I19/12 -> 0
B22: Annual Mortgage Payments 每年房贷还款额 | I22: =E26*12 -> 219343.98
B23: Interest per year Payment | I23: =I7*I8 -> 136500
B25: # Month | C25: Month | D25: Beg Bal | E25: Mortgage Payment | F25: Interest | G25: Amortization | H25: End Bal | I25: Insurance Premium | J25: Mortgage + Insurance Premium | K25: Yearly MIP
B26: 1 | C26: 44136 | D26: =I7 -> 4200000 | E26: =$D$26*$I$10 -> 18278.665 | F26: =D26*$I$9 -> 11375 | G26: =E26-F26 -> 6903.6654 | H26: =D26-G26 -> 4193096.3 | I26: =$I$20*D26 -> 0 | J26: =E26+I26 -> 18278.665 | K26: =SUM(I26:I37) -> 0
B27: =B26+1 -> 2 | C27: 44166 | D27: =H26 -> 4193096.3 | E27: =$D$26*$I$10 -> 18278.665 | F27: =D27*$I$9 -> 11356.303 | G27: =E27-F27 -> 6922.3628 | H27: =D27-G27 -> 4186174 | I27: =$I$20*D27 -> 0 | J27: =E27+I27 -> 18278.665
B28: =B27+1 -> 3 | C28: 44197 | D28: =H27 -> 4186174 | E28: =$D$26*$I$10 -> 18278.665 | F28: =D28*$I$9 -> 11337.555 | G28: =E28-F28 -> 6941.1109 | H28: =D28-G28 -> 4179232.9 | I28: =$I$20*D28 -> 0 | J28: =E28+I28 -> 18278.665
B29: =B28+1 -> 4 | C29: 44228 | D29: =H28 -> 4179232.9 | E29: =$D$26*$I$10 -> 18278.665 | F29: =D29*$I$9 -> 11318.756 | G29: =E29-F29 -> 6959.9097 | H29: =D29-G29 -> 4172273 | I29: =$I$20*D29 -> 0 | J29: =E29+I29 -> 18278.665
B30: =B29+1 -> 5 | C30: 44256 | D30: =H29 -> 4172273 | E30: =$D$26*$I$10 -> 18278.665 | F30: =D30*$I$9 -> 11299.906 | G30: =E30-F30 -> 6978.7595 | H30: =D30-G30 -> 4165294.2 | I30: =$I$20*D30 -> 0 | J30: =E30+I30 -> 18278.665
B31: =B30+1 -> 6 | C31: 44287 | D31: =H30 -> 4165294.2 | E31: =$D$26*$I$10 -> 18278.665 | F31: =D31*$I$9 -> 11281.005 | G31: =E31-F31 -> 6997.6603 | H31: =D31-G31 -> 4158296.5 | I31: =$I$20*D31 -> 0 | J31: =E31+I31 -> 18278.665
B32: =B31+1 -> 7 | C32: 44317 | D32: =H31 -> 4158296.5 | E32: =$D$26*$I$10 -> 18278.665 | F32: =D32*$I$9 -> 11262.053 | G32: =E32-F32 -> 7016.6123 | H32: =D32-G32 -> 4151279.9 | I32: =$I$20*D32 -> 0 | J32: =E32+I32 -> 18278.665
B33: =B32+1 -> 8 | C33: 44348 | D33: =H32 -> 4151279.9 | E33: =$D$26*$I$10 -> 18278.665 | F33: =D33*$I$9 -> 11243.05 | G33: =E33-F33 -> 7035.6156 | H33: =D33-G33 -> 4144244.3 | I33: =$I$20*D33 -> 0 | J33: =E33+I33 -> 18278.665
B34: =B33+1 -> 9 | C34: 44378 | D34: =H33 -> 4144244.3 | E34: =$D$26*$I$10 -> 18278.665 | F34: =D34*$I$9 -> 11223.995 | G34: =E34-F34 -> 7054.6704 | H34: =D34-G34 -> 4137189.6 | I34: =$I$20*D34 -> 0 | J34: =E34+I34 -> 18278.665
B35: =B34+1 -> 10 | C35: 44409 | D35: =H34 -> 4137189.6 | E35: =$D$26*$I$10 -> 18278.665 | F35: =D35*$I$9 -> 11204.889 | G35: =E35-F35 -> 7073.7768 | H35: =D35-G35 -> 4130115.9 | I35: =$I$20*D35 -> 0 | J35: =E35+I35 -> 18278.665
B36: =B35+1 -> 11 | C36: 44440 | D36: =H35 -> 4130115.9 | E36: =$D$26*$I$10 -> 18278.665 | F36: =D36*$I$9 -> 11185.73 | G36: =E36-F36 -> 7092.935 | H36: =D36-G36 -> 4123022.9 | I36: =$I$20*D36 -> 0 | J36: =E36+I36 -> 18278.665
B37: =B36+1 -> 12 | C37: 44470 | D37: =H36 -> 4123022.9 | E37: =$D$26*$I$10 -> 18278.665 | F37: =D37*$I$9 -> 11166.52 | G37: =E37-F37 -> 7112.145 | H37: =D37-G37 -> 4115910.8 | I37: =$I$20*D37 -> 0 | J37: =E37+I37 -> 18278.665
B38: =B37+1 -> 13 | C38: 44501 | D38: =H37 -> 4115910.8 | E38: =$D$26*$I$10 -> 18278.665 | F38: =D38*$I$9 -> 11147.258 | G38: =E38-F38 -> 7131.407 | H38: =D38-G38 -> 4108779.4 | I38: =$I$20*D38 -> 0 | J38: =E38+I38 -> 18278.665 | K38: =SUM(I38:I49) -> 0
B39: =B38+1 -> 14 | C39: 44531 | D39: =H38 -> 4108779.4 | E39: =$D$26*$I$10 -> 18278.665 | F39: =D39*$I$9 -> 11127.944 | G39: =E39-F39 -> 7150.7213 | H39: =D39-G39 -> 4101628.6 | I39: =$I$20*D39 -> 0 | J39: =E39+I39 -> 18278.665
B40: =B39+1 -> 15 | C40: 44562 | D40: =H39 -> 4101628.6 | E40: =$D$26*$I$10 -> 18278.665 | F40: =D40*$I$9 -> 11108.578 | G40: =E40-F40 -> 7170.0878 | H40: =D40-G40 -> 4094458.6 | I40: =$I$20*D40 -> 0 | J40: =E40+I40 -> 18278.665
B41: =B40+1 -> 16 | C41: 44593 | D41: =H40 -> 4094458.6 | E41: =$D$26*$I$10 -> 18278.665 | F41: =D41*$I$9 -> 11089.159 | G41: =E41-F41 -> 7189.5068 | H41: =D41-G41 -> 4087269.1 | I41: =$I$20*D41 -> 0 | J41: =E41+I41 -> 18278.665
B42: =B41+1 -> 17 | C42: 44621 | D42: =H41 -> 4087269.1 | E42: =$D$26*$I$10 -> 18278.665 | F42: =D42*$I$9 -> 11069.687 | G42: =E42-F42 -> 7208.9784 | H42: =D42-G42 -> 4080060.1 | I42: =$I$20*D42 -> 0 | J42: =E42+I42 -> 18278.665
B43: =B42+1 -> 18 | C43: 44652 | D43: =H42 -> 4080060.1 | E43: =$D$26*$I$10 -> 18278.665 | F43: =D43*$I$9 -> 11050.163 | G43: =E43-F43 -> 7228.5027 | H43: =D43-G43 -> 4072831.6 | I43: =$I$20*D43 -> 0 | J43: =E43+I43 -> 18278.665
B44: =B43+1 -> 19 | C44: 44682 | D44: =H43 -> 4072831.6 | E44: =$D$26*$I$10 -> 18278.665 | F44: =D44*$I$9 -> 11030.586 | G44: =E44-F44 -> 7248.0799 | H44: =D44-G44 -> 4065583.5 | I44: =$I$20*D44 -> 0 | J44: =E44+I44 -> 18278.665
B45: =B44+1 -> 20 | C45: 44713 | D45: =H44 -> 4065583.5 | E45: =$D$26*$I$10 -> 18278.665 | F45: =D45*$I$9 -> 11010.955 | G45: =E45-F45 -> 7267.7101 | H45: =D45-G45 -> 4058315.8 | I45: =$I$20*D45 -> 0 | J45: =E45+I45 -> 18278.665
B46: =B45+1 -> 21 | C46: 44743 | D46: =H45 -> 4058315.8 | E46: =$D$26*$I$10 -> 18278.665 | F46: =D46*$I$9 -> 10991.272 | G46: =E46-F46 -> 7287.3935 | H46: =D46-G46 -> 4051028.4 | I46: =$I$20*D46 -> 0 | J46: =E46+I46 -> 18278.665
B47: =B46+1 -> 22 | C47: 44774 | D47: =H46 -> 4051028.4 | E47: =$D$26*$I$10 -> 18278.665 | F47: =D47*$I$9 -> 10971.535 | G47: =E47-F47 -> 7307.1302 | H47: =D47-G47 -> 4043721.3 | I47: =$I$20*D47 -> 0 | J47: =E47+I47 -> 18278.665
B48: =B47+1 -> 23 | C48: 44805 | D48: =H47 -> 4043721.3 | E48: =$D$26*$I$10 -> 18278.665 | F48: =D48*$I$9 -> 10951.745 | G48: =E48-F48 -> 7326.9203 | H48: =D48-G48 -> 4036394.3 | I48: =$I$20*D48 -> 0 | J48: =E48+I48 -> 18278.665
B49: =B48+1 -> 24 | C49: 44835 | D49: =H48 -> 4036394.3 | E49: =$D$26*$I$10 -> 18278.665 | F49: =D49*$I$9 -> 10931.901 | G49: =E49-F49 -> 7346.7641 | H49: =D49-G49 -> 4029047.6 | I49: =$I$20*D49 -> 0 | J49: =E49+I49 -> 18278.665
B50: =B49+1 -> 25 | C50: 44866 | D50: =H49 -> 4029047.6 | E50: =$D$26*$I$10 -> 18278.665 | F50: =D50*$I$9 -> 10912.004 | G50: =E50-F50 -> 7366.6616 | H50: =D50-G50 -> 4021680.9 | I50: =$I$20*D50 -> 0 | J50: =E50+I50 -> 18278.665 | K50: =SUM(I50:I61) -> 0
B51: =B50+1 -> 26 | C51: 44896 | D51: =H50 -> 4021680.9 | E51: =$D$26*$I$10 -> 18278.665 | F51: =D51*$I$9 -> 10892.052 | G51: =E51-F51 -> 7386.6129 | H51: =D51-G51 -> 4014294.3 | I51: =$I$20*D51 -> 0 | J51: =E51+I51 -> 18278.665
B52: =B51+1 -> 27 | C52: 44927 | D52: =H51 -> 4014294.3 | E52: =$D$26*$I$10 -> 18278.665 | F52: =D52*$I$9 -> 10872.047 | G52: =E52-F52 -> 7406.6183 | H52: =D52-G52 -> 4006887.7 | I52: =$I$20*D52 -> 0 | J52: =E52+I52 -> 18278.665
B53: =B52+1 -> 28 | C53: 44958 | D53: =H52 -> 4006887.7 | E53: =$D$26*$I$10 -> 18278.665 | F53: =D53*$I$9 -> 10851.987 | G53: =E53-F53 -> 7426.6779 | H53: =D53-G53 -> 3999461 | I53: =$I$20*D53 -> 0 | J53: =E53+I53 -> 18278.665
B54: =B53+1 -> 29 | C54: 44986 | D54: =H53 -> 3999461 | E54: =$D$26*$I$10 -> 18278.665 | F54: =D54*$I$9 -> 10831.874 | G54: =E54-F54 -> 7446.7919 | H54: =D54-G54 -> 3992014.2 | I54: =$I$20*D54 -> 0 | J54: =E54+I54 -> 18278.665
B55: =B54+1 -> 30 | C55: 45017 | D55: =H54 -> 3992014.2 | E55: =$D$26*$I$10 -> 18278.665 | F55: =D55*$I$9 -> 10811.705 | G55: =E55-F55 -> 7466.9602 | H55: =D55-G55 -> 3984547.3 | I55: =$I$20*D55 -> 0 | J55: =E55+I55 -> 18278.665
B56: =B55+1 -> 31 | C56: 45047 | D56: =H55 -> 3984547.3 | E56: =$D$26*$I$10 -> 18278.665 | F56: =D56*$I$9 -> 10791.482 | G56: =E56-F56 -> 7487.1833 | H56: =D56-G56 -> 3977060.1 | I56: =$I$20*D56 -> 0 | J56: =E56+I56 -> 18278.665
B57: =B56+1 -> 32 | C57: 45078 | D57: =H56 -> 3977060.1 | E57: =$D$26*$I$10 -> 18278.665 | F57: =D57*$I$9 -> 10771.204 | G57: =E57-F57 -> 7507.4611 | H57: =D57-G57 -> 3969552.6 | I57: =$I$20*D57 -> 0 | J57: =E57+I57 -> 18278.665
B58: =B57+1 -> 33 | C58: 45108 | D58: =H57 -> 3969552.6 | E58: =$D$26*$I$10 -> 18278.665 | F58: =D58*$I$9 -> 10750.872 | G58: =E58-F58 -> 7527.7938 | H58: =D58-G58 -> 3962024.8 | I58: =$I$20*D58 -> 0 | J58: =E58+I58 -> 18278.665
B59: =B58+1 -> 34 | C59: 45139 | D59: =H58 -> 3962024.8 | E59: =$D$26*$I$10 -> 18278.665 | F59: =D59*$I$9 -> 10730.484 | G59: =E59-F59 -> 7548.1815 | H59: =D59-G59 -> 3954476.6 | I59: =$I$20*D59 -> 0 | J59: =E59+I59 -> 18278.665
B60: =B59+1 -> 35 | C60: 45170 | D60: =H59 -> 3954476.6 | E60: =$D$26*$I$10 -> 18278.665 | F60: =D60*$I$9 -> 10710.041 | G60: =E60-F60 -> 7568.6245 | H60: =D60-G60 -> 3946908 | I60: =$I$20*D60 -> 0 | J60: =E60+I60 -> 18278.665
B61: =B60+1 -> 36 | C61: 45200 | D61: =H60 -> 3946908 | E61: =$D$26*$I$10 -> 18278.665 | F61: =D61*$I$9 -> 10689.543 | G61: =E61-F61 -> 7589.1229 | H61: =D61-G61 -> 3939318.9 | I61: =$I$20*D61 -> 0 | J61: =E61+I61 -> 18278.665
B62: =B61+1 -> 37 | C62: 45231 | D62: =H61 -> 3939318.9 | E62: =$D$26*$I$10 -> 18278.665 | F62: =D62*$I$9 -> 10668.989 | G62: =E62-F62 -> 7609.6768 | H62: =D62-G62 -> 3931709.2 | I62: =$I$20*D62 -> 0 | J62: =E62+I62 -> 18278.665 | K62: =SUM(I62:I73) -> 0
B63: =B62+1 -> 38 | C63: 45261 | D63: =H62 -> 3931709.2 | E63: =$D$26*$I$10 -> 18278.665 | F63: =D63*$I$9 -> 10648.379 | G63: =E63-F63 -> 7630.2863 | H63: =D63-G63 -> 3924078.9 | I63: =$I$20*D63 -> 0 | J63: =E63+I63 -> 18278.665
B64: =B63+1 -> 39 | C64: 45292 | D64: =H63 -> 3924078.9 | E64: =$D$26*$I$10 -> 18278.665 | F64: =D64*$I$9 -> 10627.714 | G64: =E64-F64 -> 7650.9517 | H64: =D64-G64 -> 3916428 | I64: =$I$20*D64 -> 0 | J64: =E64+I64 -> 18278.665
B65: =B64+1 -> 40 | C65: 45323 | D65: =H64 -> 3916428 | E65: =$D$26*$I$10 -> 18278.665 | F65: =D65*$I$9 -> 10606.992 | G65: =E65-F65 -> 7671.673 | H65: =D65-G65 -> 3908756.3 | I65: =$I$20*D65 -> 0 | J65: =E65+I65 -> 18278.665
B66: =B65+1 -> 41 | C66: 45352 | D66: =H65 -> 3908756.3 | E66: =$D$26*$I$10 -> 18278.665 | F66: =D66*$I$9 -> 10586.215 | G66: =E66-F66 -> 7692.4504 | H66: =D66-G66 -> 3901063.8 | I66: =$I$20*D66 -> 0 | J66: =E66+I66 -> 18278.665
B67: =B66+1 -> 42 | C67: 45383 | D67: =H66 -> 3901063.8 | E67: =$D$26*$I$10 -> 18278.665 | F67: =D67*$I$9 -> 10565.381 | G67: =E67-F67 -> 7713.2842 | H67: =D67-G67 -> 3893350.6 | I67: =$I$20*D67 -> 0 | J67: =E67+I67 -> 18278.665
B68: =B67+1 -> 43 | C68: 45413 | D68: =H67 -> 3893350.6 | E68: =$D$26*$I$10 -> 18278.665 | F68: =D68*$I$9 -> 10544.491 | G68: =E68-F68 -> 7734.1743 | H68: =D68-G68 -> 3885616.4 | I68: =$I$20*D68 -> 0 | J68: =E68+I68 -> 18278.665
B69: =B68+1 -> 44 | C69: 45444 | D69: =H68 -> 3885616.4 | E69: =$D$26*$I$10 -> 18278.665 | F69: =D69*$I$9 -> 10523.544 | G69: =E69-F69 -> 7755.121 | H69: =D69-G69 -> 3877861.3 | I69: =$I$20*D69 -> 0 | J69: =E69+I69 -> 18278.665
B70: =B69+1 -> 45 | C70: 45474 | D70: =H69 -> 3877861.3 | E70: =$D$26*$I$10 -> 18278.665 | F70: =D70*$I$9 -> 10502.541 | G70: =E70-F70 -> 7776.1245 | H70: =D70-G70 -> 3870085.1 | I70: =$I$20*D70 -> 0 | J70: =E70+I70 -> 18278.665
B71: =B70+1 -> 46 | C71: 45505 | D71: =H70 -> 3870085.1 | E71: =$D$26*$I$10 -> 18278.665 | F71: =D71*$I$9 -> 10481.481 | G71: =E71-F71 -> 7797.1848 | H71: =D71-G71 -> 3862288 | I71: =$I$20*D71 -> 0 | J71: =E71+I71 -> 18278.665
B72: =B71+1 -> 47 | C72: 45536 | D72: =H71 -> 3862288 | E72: =$D$26*$I$10 -> 18278.665 | F72: =D72*$I$9 -> 10460.363 | G72: =E72-F72 -> 7818.3022 | H72: =D72-G72 -> 3854469.7 | I72: =$I$20*D72 -> 0 | J72: =E72+I72 -> 18278.665
B73: =B72+1 -> 48 | C73: 45566 | D73: =H72 -> 3854469.7 | E73: =$D$26*$I$10 -> 18278.665 | F73: =D73*$I$9 -> 10439.189 | G73: =E73-F73 -> 7839.4768 | H73: =D73-G73 -> 3846630.2 | I73: =$I$20*D73 -> 0 | J73: =E73+I73 -> 18278.665
B74: =B73+1 -> 49 | C74: 45597 | D74: =H73 -> 3846630.2 | E74: =$D$26*$I$10 -> 18278.665 | F74: =D74*$I$9 -> 10417.957 | G74: =E74-F74 -> 7860.7087 | H74: =D74-G74 -> 3838769.5 | I74: =$I$20*D74 -> 0 | J74: =E74+I74 -> 18278.665 | K74: =SUM(I74:I85) -> 0
B75: =B74+1 -> 50 | C75: 45627 | D75: =H74 -> 3838769.5 | E75: =$D$26*$I$10 -> 18278.665 | F75: =D75*$I$9 -> 10396.667 | G75: =E75-F75 -> 7881.9981 | H75: =D75-G75 -> 3830887.5 | I75: =$I$20*D75 -> 0 | J75: =E75+I75 -> 18278.665
B76: =B75+1 -> 51 | C76: 45658 | D76: =H75 -> 3830887.5 | E76: =$D$26*$I$10 -> 18278.665 | F76: =D76*$I$9 -> 10375.32 | G76: =E76-F76 -> 7903.3452 | H76: =D76-G76 -> 3822984.1 | I76: =$I$20*D76 -> 0 | J76: =E76+I76 -> 18278.665
B77: =B76+1 -> 52 | C77: 45689 | D77: =H76 -> 3822984.1 | E77: =$D$26*$I$10 -> 18278.665 | F77: =D77*$I$9 -> 10353.915 | G77: =E77-F77 -> 7924.7501 | H77: =D77-G77 -> 3815059.4 | I77: =$I$20*D77 -> 0 | J77: =E77+I77 -> 18278.665
B78: =B77+1 -> 53 | C78: 45717 | D78: =H77 -> 3815059.4 | E78: =$D$26*$I$10 -> 18278.665 | F78: =D78*$I$9 -> 10332.452 | G78: =E78-F78 -> 7946.2129 | H78: =D78-G78 -> 3807113.2 | I78: =$I$20*D78 -> 0 | J78: =E78+I78 -> 18278.665
B79: =B78+1 -> 54 | C79: 45748 | D79: =H78 -> 3807113.2 | E79: =$D$26*$I$10 -> 18278.665 | F79: =D79*$I$9 -> 10310.931 | G79: =E79-F79 -> 7967.7339 | H79: =D79-G79 -> 3799145.4 | I79: =$I$20*D79 -> 0 | J79: =E79+I79 -> 18278.665
B80: =B79+1 -> 55 | C80: 45778 | D80: =H79 -> 3799145.4 | E80: =$D$26*$I$10 -> 18278.665 | F80: =D80*$I$9 -> 10289.352 | G80: =E80-F80 -> 7989.3132 | H80: =D80-G80 -> 3791156.1 | I80: =$I$20*D80 -> 0 | J80: =E80+I80 -> 18278.665
B81: =B80+1 -> 56 | C81: 45809 | D81: =H80 -> 3791156.1 | E81: =$D$26*$I$10 -> 18278.665 | F81: =D81*$I$9 -> 10267.714 | G81: =E81-F81 -> 8010.9509 | H81: =D81-G81 -> 3783145.2 | I81: =$I$20*D81 -> 0 | J81: =E81+I81 -> 18278.665
B82: =B81+1 -> 57 | C82: 45839 | D82: =H81 -> 3783145.2 | E82: =$D$26*$I$10 -> 18278.665 | F82: =D82*$I$9 -> 10246.018 | G82: =E82-F82 -> 8032.6472 | H82: =D82-G82 -> 3775112.5 | I82: =$I$20*D82 -> 0 | J82: =E82+I82 -> 18278.665
B83: =B82+1 -> 58 | C83: 45870 | D83: =H82 -> 3775112.5 | E83: =$D$26*$I$10 -> 18278.665 | F83: =D83*$I$9 -> 10224.263 | G83: =E83-F83 -> 8054.4023 | H83: =D83-G83 -> 3767058.1 | I83: =$I$20*D83 -> 0 | J83: =E83+I83 -> 18278.665
B84: =B83+1 -> 59 | C84: 45901 | D84: =H83 -> 3767058.1 | E84: =$D$26*$I$10 -> 18278.665 | F84: =D84*$I$9 -> 10202.449 | G84: =E84-F84 -> 8076.2163 | H84: =D84-G84 -> 3758981.9 | I84: =$I$20*D84 -> 0 | J84: =E84+I84 -> 18278.665
B85: =B84+1 -> 60 | C85: 45931 | D85: =H84 -> 3758981.9 | E85: =$D$26*$I$10 -> 18278.665 | F85: =D85*$I$9 -> 10180.576 | G85: =E85-F85 -> 8098.0894 | H85: =D85-G85 -> 3750883.8 | I85: =$I$20*D85 -> 0 | J85: =E85+I85 -> 18278.665
B86: =B85+1 -> 61 | C86: 45962 | D86: =H85 -> 3750883.8 | E86: =$D$26*$I$10 -> 18278.665 | F86: =D86*$I$9 -> 10158.644 | G86: =E86-F86 -> 8120.0217 | H86: =D86-G86 -> 3742763.8 | I86: =$I$20*D86 -> 0 | J86: =E86+I86 -> 18278.665 | K86: =SUM(I86:I97) -> 0
B87: =B86+1 -> 62 | C87: 45992 | D87: =H86 -> 3742763.8 | E87: =$D$26*$I$10 -> 18278.665 | F87: =D87*$I$9 -> 10136.652 | G87: =E87-F87 -> 8142.0135 | H87: =D87-G87 -> 3734621.8 | I87: =$I$20*D87 -> 0 | J87: =E87+I87 -> 18278.665
B88: =B87+1 -> 63 | C88: 46023 | D88: =H87 -> 3734621.8 | E88: =$D$26*$I$10 -> 18278.665 | F88: =D88*$I$9 -> 10114.601 | G88: =E88-F88 -> 8164.0648 | H88: =D88-G88 -> 3726457.7 | I88: =$I$20*D88 -> 0 | J88: =E88+I88 -> 18278.665
B89: =B88+1 -> 64 | C89: 46054 | D89: =H88 -> 3726457.7 | E89: =$D$26*$I$10 -> 18278.665 | F89: =D89*$I$9 -> 10092.49 | G89: =E89-F89 -> 8186.1758 | H89: =D89-G89 -> 3718271.5 | I89: =$I$20*D89 -> 0 | J89: =E89+I89 -> 18278.665
B90: =B89+1 -> 65 | C90: 46082 | D90: =H89 -> 3718271.5 | E90: =$D$26*$I$10 -> 18278.665 | F90: =D90*$I$9 -> 10070.319 | G90: =E90-F90 -> 8208.3467 | H90: =D90-G90 -> 3710063.2 | I90: =$I$20*D90 -> 0 | J90: =E90+I90 -> 18278.665
B91: =B90+1 -> 66 | C91: 46113 | D91: =H90 -> 3710063.2 | E91: =$D$26*$I$10 -> 18278.665 | F91: =D91*$I$9 -> 10048.088 | G91: =E91-F91 -> 8230.5776 | H91: =D91-G91 -> 3701832.6 | I91: =$I$20*D91 -> 0 | J91: =E91+I91 -> 18278.665
B92: =B91+1 -> 67 | C92: 46143 | D92: =H91 -> 3701832.6 | E92: =$D$26*$I$10 -> 18278.665 | F92: =D92*$I$9 -> 10025.797 | G92: =E92-F92 -> 8252.8687 | H92: =D92-G92 -> 3693579.7 | I92: =$I$20*D92 -> 0 | J92: =E92+I92 -> 18278.665
B93: =B92+1 -> 68 | C93: 46174 | D93: =H92 -> 3693579.7 | E93: =$D$26*$I$10 -> 18278.665 | F93: =D93*$I$9 -> 10003.445 | G93: =E93-F93 -> 8275.2203 | H93: =D93-G93 -> 3685304.5 | I93: =$I$20*D93 -> 0 | J93: =E93+I93 -> 18278.665
B94: =B93+1 -> 69 | C94: 46204 | D94: =H93 -> 3685304.5 | E94: =$D$26*$I$10 -> 18278.665 | F94: =D94*$I$9 -> 9981.0331 | G94: =E94-F94 -> 8297.6323 | H94: =D94-G94 -> 3677006.9 | I94: =$I$20*D94 -> 0 | J94: =E94+I94 -> 18278.665
B95: =B94+1 -> 70 | C95: 46235 | D95: =H94 -> 3677006.9 | E95: =$D$26*$I$10 -> 18278.665 | F95: =D95*$I$9 -> 9958.5603 | G95: =E95-F95 -> 8320.1051 | H95: =D95-G95 -> 3668686.8 | I95: =$I$20*D95 -> 0 | J95: =E95+I95 -> 18278.665
B96: =B95+1 -> 71 | C96: 46266 | D96: =H95 -> 3668686.8 | E96: =$D$26*$I$10 -> 18278.665 | F96: =D96*$I$9 -> 9936.0267 | G96: =E96-F96 -> 8342.6387 | H96: =D96-G96 -> 3660344.1 | I96: =$I$20*D96 -> 0 | J96: =E96+I96 -> 18278.665
B97: =B96+1 -> 72 | C97: 46296 | D97: =H96 -> 3660344.1 | E97: =$D$26*$I$10 -> 18278.665 | F97: =D97*$I$9 -> 9913.4321 | G97: =E97-F97 -> 8365.2333 | H97: =D97-G97 -> 3651978.9 | I97: =$I$20*D97 -> 0 | J97: =E97+I97 -> 18278.665
B98: =B97+1 -> 73 | C98: 46327 | D98: =H97 -> 3651978.9 | E98: =$D$26*$I$10 -> 18278.665 | F98: =D98*$I$9 -> 9890.7762 | G98: =E98-F98 -> 8387.8892 | H98: =D98-G98 -> 3643591 | I98: =$I$20*D98 -> 0 | J98: =E98+I98 -> 18278.665 | K98: =SUM(I98:I109) -> 0
B99: =B98+1 -> 74 | C99: 46357 | D99: =H98 -> 3643591 | E99: =$D$26*$I$10 -> 18278.665 | F99: =D99*$I$9 -> 9868.059 | G99: =E99-F99 -> 8410.6064 | H99: =D99-G99 -> 3635180.4 | I99: =$I$20*D99 -> 0 | J99: =E99+I99 -> 18278.665
B100: =B99+1 -> 75 | C100: 46388 | D100: =H99 -> 3635180.4 | E100: =$D$26*$I$10 -> 18278.665 | F100: =D100*$I$9 -> 9845.2803 | G100: =E100-F100 -> 8433.3851 | H100: =D100-G100 -> 3626747 | I100: =$I$20*D100 -> 0 | J100: =E100+I100 -> 18278.665
B101: =B100+1 -> 76 | C101: 46419 | D101: =H100 -> 3626747 | E101: =$D$26*$I$10 -> 18278.665 | F101: =D101*$I$9 -> 9822.4399 | G101: =E101-F101 -> 8456.2255 | H101: =D101-G101 -> 3618290.8 | I101: =$I$20*D101 -> 0 | J101: =E101+I101 -> 18278.665
B102: =B101+1 -> 77 | C102: 46447 | D102: =H101 -> 3618290.8 | E102: =$D$26*$I$10 -> 18278.665 | F102: =D102*$I$9 -> 9799.5376 | G102: =E102-F102 -> 8479.1278 | H102: =D102-G102 -> 3609811.7 | I102: =$I$20*D102 -> 0 | J102: =E102+I102 -> 18278.665
B103: =B102+1 -> 78 | C103: 46478 | D103: =H102 -> 3609811.7 | E103: =$D$26*$I$10 -> 18278.665 | F103: =D103*$I$9 -> 9776.5733 | G103: =E103-F103 -> 8502.0921 | H103: =D103-G103 -> 3601309.6 | I103: =$I$20*D103 -> 0 | J103: =E103+I103 -> 18278.665
B104: =B103+1 -> 79 | C104: 46508 | D104: =H103 -> 3601309.6 | E104: =$D$26*$I$10 -> 18278.665 | F104: =D104*$I$9 -> 9753.5468 | G104: =E104-F104 -> 8525.1186 | H104: =D104-G104 -> 3592784.5 | I104: =$I$20*D104 -> 0 | J104: =E104+I104 -> 18278.665
B105: =B104+1 -> 80 | C105: 46539 | D105: =H104 -> 3592784.5 | E105: =$D$26*$I$10 -> 18278.665 | F105: =D105*$I$9 -> 9730.4579 | G105: =E105-F105 -> 8548.2075 | H105: =D105-G105 -> 3584236.3 | I105: =$I$20*D105 -> 0 | J105: =E105+I105 -> 18278.665
B106: =B105+1 -> 81 | C106: 46569 | D106: =H105 -> 3584236.3 | E106: =$D$26*$I$10 -> 18278.665 | F106: =D106*$I$9 -> 9707.3065 | G106: =E106-F106 -> 8571.3589 | H106: =D106-G106 -> 3575664.9 | I106: =$I$20*D106 -> 0 | J106: =E106+I106 -> 18278.665
B107: =B106+1 -> 82 | C107: 46600 | D107: =H106 -> 3575664.9 | E107: =$D$26*$I$10 -> 18278.665 | F107: =D107*$I$9 -> 9684.0924 | G107: =E107-F107 -> 8594.573 | H107: =D107-G107 -> 3567070.3 | I107: =$I$20*D107 -> 0 | J107: =E107+I107 -> 18278.665
B108: =B107+1 -> 83 | C108: 46631 | D108: =H107 -> 3567070.3 | E108: =$D$26*$I$10 -> 18278.665 | F108: =D108*$I$9 -> 9660.8155 | G108: =E108-F108 -> 8617.8499 | H108: =D108-G108 -> 3558452.5 | I108: =$I$20*D108 -> 0 | J108: =E108+I108 -> 18278.665
B109: =B108+1 -> 84 | C109: 46661 | D109: =H108 -> 3558452.5 | E109: =$D$26*$I$10 -> 18278.665 | F109: =D109*$I$9 -> 9637.4755 | G109: =E109-F109 -> 8641.1899 | H109: =D109-G109 -> 3549811.3 | I109: =$I$20*D109 -> 0 | J109: =E109+I109 -> 18278.665
...

Sheet Debt Refinance
B2: ='Pro-forma'!B3 -> Address: 1718 North Sydenham Street Philadelphia, PA 19121
B5: Loan Amount | I5: ='Pro-forma'!U133 -> 3962686.5
B7: Principal | I7: =I5 -> 3962686.5
B8: Interest per annum | I8: 0.055
B9: Interest per month | I9: =I8/12 -> 0.0045833333
B10: Mortgage Constant | I10: =I9/(1-(1/(1+I9)^I16)) -> 0.00567789
B12: Commencement date | I12: 47058
B13: Final maturity date | I13: 19815
B15: Duration (Years) | I15: 30
B16: Duration (Months) | I16: =I15*12 -> 360
B18: Mortgage Insurance Premium
B19: Mortgage Insurance Premium per annum | I19: 0
B20: Mortgage Insurance Premium per month | I20: =I19/12 -> 0
B22: Annual Mortgage Payments | I22: =E26*12 -> 269996.37 | J22: =I22*15 -> 4049945.6
H23: I/O | I23: =I7*I8 -> 217947.76
B25: # Month | C25: Month | D25: Beg Bal | E25: Mortgage Payment | F25: Interest | G25: Amortization | H25: End Bal | I25: Insurance Premium | J25: Mortgage + Insurance Premium | K25: Yearly MIP
B26: 1 | C26: 44136 | D26: =I7 -> 3962686.5 | E26: =$D$26*$I$10 -> 22499.698 | F26: =D26*$I$9 -> 18162.313 | G26: =E26-F26 -> 4337.3849 | H26: =D26-G26 -> 3958349.1 | I26: =$I$20*D26 -> 0 | J26: =E26+I26 -> 22499.698 | K26: =SUM(I26:I37) -> 0
B27: =B26+1 -> 2 | C27: 44166 | D27: =H26 -> 3958349.1 | E27: =$D$26*$I$10 -> 22499.698 | F27: =D27*$I$9 -> 18142.433 | G27: =E27-F27 -> 4357.2646 | H27: =D27-G27 -> 3953991.8 | I27: =$I$20*D27 -> 0 | J27: =E27+I27 -> 22499.698
B28: =B27+1 -> 3 | C28: 44197 | D28: =H27 -> 3953991.8 | E28: =$D$26*$I$10 -> 22499.698 | F28: =D28*$I$9 -> 18122.462 | G28: =E28-F28 -> 4377.2354 | H28: =D28-G28 -> 3949614.6 | I28: =$I$20*D28 -> 0 | J28: =E28+I28 -> 22499.698
B29: =B28+1 -> 4 | C29: 44228 | D29: =H28 -> 3949614.6 | E29: =$D$26*$I$10 -> 22499.698 | F29: =D29*$I$9 -> 18102.4 | G29: =E29-F29 -> 4397.2977 | H29: =D29-G29 -> 3945217.3 | I29: =$I$20*D29 -> 0 | J29: =E29+I29 -> 22499.698
B30: =B29+1 -> 5 | C30: 44256 | D30: =H29 -> 3945217.3 | E30: =$D$26*$I$10 -> 22499.698 | F30: =D30*$I$9 -> 18082.246 | G30: =E30-F30 -> 4417.452 | H30: =D30-G30 -> 3940799.8 | I30: =$I$20*D30 -> 0 | J30: =E30+I30 -> 22499.698
B31: =B30+1 -> 6 | C31: 44287 | D31: =H30 -> 3940799.8 | E31: =$D$26*$I$10 -> 22499.698 | F31: =D31*$I$9 -> 18061.999 | G31: =E31-F31 -> 4437.6987 | H31: =D31-G31 -> 3936362.1 | I31: =$I$20*D31 -> 0 | J31: =E31+I31 -> 22499.698
B32: =B31+1 -> 7 | C32: 44317 | D32: =H31 -> 3936362.1 | E32: =$D$26*$I$10 -> 22499.698 | F32: =D32*$I$9 -> 18041.66 | G32: =E32-F32 -> 4458.0381 | H32: =D32-G32 -> 3931904.1 | I32: =$I$20*D32 -> 0 | J32: =E32+I32 -> 22499.698
B33: =B32+1 -> 8 | C33: 44348 | D33: =H32 -> 3931904.1 | E33: =$D$26*$I$10 -> 22499.698 | F33: =D33*$I$9 -> 18021.227 | G33: =E33-F33 -> 4478.4708 | H33: =D33-G33 -> 3927425.6 | I33: =$I$20*D33 -> 0 | J33: =E33+I33 -> 22499.698
B34: =B33+1 -> 9 | C34: 44378 | D34: =H33 -> 3927425.6 | E34: =$D$26*$I$10 -> 22499.698 | F34: =D34*$I$9 -> 18000.701 | G34: =E34-F34 -> 4498.9971 | H34: =D34-G34 -> 3922926.6 | I34: =$I$20*D34 -> 0 | J34: =E34+I34 -> 22499.698
B35: =B34+1 -> 10 | C35: 44409 | D35: =H34 -> 3922926.6 | E35: =$D$26*$I$10 -> 22499.698 | F35: =D35*$I$9 -> 17980.08 | G35: =E35-F35 -> 4519.6175 | H35: =D35-G35 -> 3918407 | I35: =$I$20*D35 -> 0 | J35: =E35+I35 -> 22499.698
B36: =B35+1 -> 11 | C36: 44440 | D36: =H35 -> 3918407 | E36: =$D$26*$I$10 -> 22499.698 | F36: =D36*$I$9 -> 17959.365 | G36: =E36-F36 -> 4540.3325 | H36: =D36-G36 -> 3913866.7 | I36: =$I$20*D36 -> 0 | J36: =E36+I36 -> 22499.698
B37: =B36+1 -> 12 | C37: 44470 | D37: =H36 -> 3913866.7 | E37: =$D$26*$I$10 -> 22499.698 | F37: =D37*$I$9 -> 17938.556 | G37: =E37-F37 -> 4561.1423 | H37: =D37-G37 -> 3909305.5 | I37: =$I$20*D37 -> 0 | J37: =E37+I37 -> 22499.698
B38: =B37+1 -> 13 | C38: 44501 | D38: =H37 -> 3909305.5 | E38: =$D$26*$I$10 -> 22499.698 | F38: =D38*$I$9 -> 17917.65 | G38: =E38-F38 -> 4582.0475 | H38: =D38-G38 -> 3904723.5 | I38: =$I$20*D38 -> 0 | J38: =E38+I38 -> 22499.698 | K38: =SUM(I38:I49) -> 0
B39: =B38+1 -> 14 | C39: 44531 | D39: =H38 -> 3904723.5 | E39: =$D$26*$I$10 -> 22499.698 | F39: =D39*$I$9 -> 17896.649 | G39: =E39-F39 -> 4603.0486 | H39: =D39-G39 -> 3900120.4 | I39: =$I$20*D39 -> 0 | J39: =E39+I39 -> 22499.698
B40: =B39+1 -> 15 | C40: 44562 | D40: =H39 -> 3900120.4 | E40: =$D$26*$I$10 -> 22499.698 | F40: =D40*$I$9 -> 17875.552 | G40: =E40-F40 -> 4624.1459 | H40: =D40-G40 -> 3895496.3 | I40: =$I$20*D40 -> 0 | J40: =E40+I40 -> 22499.698
B41: =B40+1 -> 16 | C41: 44593 | D41: =H40 -> 3895496.3 | E41: =$D$26*$I$10 -> 22499.698 | F41: =D41*$I$9 -> 17854.358 | G41: =E41-F41 -> 4645.3399 | H41: =D41-G41 -> 3890851 | I41: =$I$20*D41 -> 0 | J41: =E41+I41 -> 22499.698
B42: =B41+1 -> 17 | C42: 44621 | D42: =H41 -> 3890851 | E42: =$D$26*$I$10 -> 22499.698 | F42: =D42*$I$9 -> 17833.067 | G42: =E42-F42 -> 4666.631 | H42: =D42-G42 -> 3886184.3 | I42: =$I$20*D42 -> 0 | J42: =E42+I42 -> 22499.698
B43: =B42+1 -> 18 | C43: 44652 | D43: =H42 -> 3886184.3 | E43: =$D$26*$I$10 -> 22499.698 | F43: =D43*$I$9 -> 17811.678 | G43: =E43-F43 -> 4688.0198 | H43: =D43-G43 -> 3881496.3 | I43: =$I$20*D43 -> 0 | J43: =E43+I43 -> 22499.698
B44: =B43+1 -> 19 | C44: 44682 | D44: =H43 -> 3881496.3 | E44: =$D$26*$I$10 -> 22499.698 | F44: =D44*$I$9 -> 17790.191 | G44: =E44-F44 -> 4709.5065 | H44: =D44-G44 -> 3876786.8 | I44: =$I$20*D44 -> 0 | J44: =E44+I44 -> 22499.698
B45: =B44+1 -> 20 | C45: 44713 | D45: =H44 -> 3876786.8 | E45: =$D$26*$I$10 -> 22499.698 | F45: =D45*$I$9 -> 17768.606 | G45: =E45-F45 -> 4731.0918 | H45: =D45-G45 -> 3872055.7 | I45: =$I$20*D45 -> 0 | J45: =E45+I45 -> 22499.698
B46: =B45+1 -> 21 | C46: 44743 | D46: =H45 -> 3872055.7 | E46: =$D$26*$I$10 -> 22499.698 | F46: =D46*$I$9 -> 17746.922 | G46: =E46-F46 -> 4752.7759 | H46: =D46-G46 -> 3867302.9 | I46: =$I$20*D46 -> 0 | J46: =E46+I46 -> 22499.698
B47: =B46+1 -> 22 | C47: 44774 | D47: =H46 -> 3867302.9 | E47: =$D$26*$I$10 -> 22499.698 | F47: =D47*$I$9 -> 17725.138 | G47: =E47-F47 -> 4774.5595 | H47: =D47-G47 -> 3862528.4 | I47: =$I$20*D47 -> 0 | J47: =E47+I47 -> 22499.698
B48: =B47+1 -> 23 | C48: 44805 | D48: =H47 -> 3862528.4 | E48: =$D$26*$I$10 -> 22499.698 | F48: =D48*$I$9 -> 17703.255 | G48: =E48-F48 -> 4796.4429 | H48: =D48-G48 -> 3857731.9 | I48: =$I$20*D48 -> 0 | J48: =E48+I48 -> 22499.698
B49: =B48+1 -> 24 | C49: 44835 | D49: =H48 -> 3857731.9 | E49: =$D$26*$I$10 -> 22499.698 | F49: =D49*$I$9 -> 17681.271 | G49: =E49-F49 -> 4818.4266 | H49: =D49-G49 -> 3852913.5 | I49: =$I$20*D49 -> 0 | J49: =E49+I49 -> 22499.698
B50: =B49+1 -> 25 | C50: 44866 | D50: =H49 -> 3852913.5 | E50: =$D$26*$I$10 -> 22499.698 | F50: =D50*$I$9 -> 17659.187 | G50: =E50-F50 -> 4840.511 | H50: =D50-G50 -> 3848073 | I50: =$I$20*D50 -> 0 | J50: =E50+I50 -> 22499.698 | K50: =SUM(I50:I61) -> 0
B51: =B50+1 -> 26 | C51: 44896 | D51: =H50 -> 3848073 | E51: =$D$26*$I$10 -> 22499.698 | F51: =D51*$I$9 -> 17637.001 | G51: =E51-F51 -> 4862.6967 | H51: =D51-G51 -> 3843210.3 | I51: =$I$20*D51 -> 0 | J51: =E51+I51 -> 22499.698
B52: =B51+1 -> 27 | C52: 44927 | D52: =H51 -> 3843210.3 | E52: =$D$26*$I$10 -> 22499.698 | F52: =D52*$I$9 -> 17614.714 | G52: =E52-F52 -> 4884.9841 | H52: =D52-G52 -> 3838325.3 | I52: =$I$20*D52 -> 0 | J52: =E52+I52 -> 22499.698
B53: =B52+1 -> 28 | C53: 44958 | D53: =H52 -> 3838325.3 | E53: =$D$26*$I$10 -> 22499.698 | F53: =D53*$I$9 -> 17592.324 | G53: =E53-F53 -> 4907.3736 | H53: =D53-G53 -> 3833417.9 | I53: =$I$20*D53 -> 0 | J53: =E53+I53 -> 22499.698
B54: =B53+1 -> 29 | C54: 44986 | D54: =H53 -> 3833417.9 | E54: =$D$26*$I$10 -> 22499.698 | F54: =D54*$I$9 -> 17569.832 | G54: =E54-F54 -> 4929.8657 | H54: =D54-G54 -> 3828488.1 | I54: =$I$20*D54 -> 0 | J54: =E54+I54 -> 22499.698
B55: =B54+1 -> 30 | C55: 45017 | D55: =H54 -> 3828488.1 | E55: =$D$26*$I$10 -> 22499.698 | F55: =D55*$I$9 -> 17547.237 | G55: =E55-F55 -> 4952.4609 | H55: =D55-G55 -> 3823535.6 | I55: =$I$20*D55 -> 0 | J55: =E55+I55 -> 22499.698
B56: =B55+1 -> 31 | C56: 45047 | D56: =H55 -> 3823535.6 | E56: =$D$26*$I$10 -> 22499.698 | F56: =D56*$I$9 -> 17524.538 | G56: =E56-F56 -> 4975.1597 | H56: =D56-G56 -> 3818560.4 | I56: =$I$20*D56 -> 0 | J56: =E56+I56 -> 22499.698
B57: =B56+1 -> 32 | C57: 45078 | D57: =H56 -> 3818560.4 | E57: =$D$26*$I$10 -> 22499.698 | F57: =D57*$I$9 -> 17501.735 | G57: =E57-F57 -> 4997.9625 | H57: =D57-G57 -> 3813562.5 | I57: =$I$20*D57 -> 0 | J57: =E57+I57 -> 22499.698
B58: =B57+1 -> 33 | C58: 45108 | D58: =H57 -> 3813562.5 | E58: =$D$26*$I$10 -> 22499.698 | F58: =D58*$I$9 -> 17478.828 | G58: =E58-F58 -> 5020.8699 | H58: =D58-G58 -> 3808541.6 | I58: =$I$20*D58 -> 0 | J58: =E58+I58 -> 22499.698
B59: =B58+1 -> 34 | C59: 45139 | D59: =H58 -> 3808541.6 | E59: =$D$26*$I$10 -> 22499.698 | F59: =D59*$I$9 -> 17455.816 | G59: =E59-F59 -> 5043.8822 | H59: =D59-G59 -> 3803497.7 | I59: =$I$20*D59 -> 0 | J59: =E59+I59 -> 22499.698
B60: =B59+1 -> 35 | C60: 45170 | D60: =H59 -> 3803497.7 | E60: =$D$26*$I$10 -> 22499.698 | F60: =D60*$I$9 -> 17432.698 | G60: =E60-F60 -> 5067 | H60: =D60-G60 -> 3798430.7 | I60: =$I$20*D60 -> 0 | J60: =E60+I60 -> 22499.698
B61: =B60+1 -> 36 | C61: 45200 | D61: =H60 -> 3798430.7 | E61: =$D$26*$I$10 -> 22499.698 | F61: =D61*$I$9 -> 17409.474 | G61: =E61-F61 -> 5090.2237 | H61: =D61-G61 -> 3793340.5 | I61: =$I$20*D61 -> 0 | J61: =E61+I61 -> 22499.698
B62: =B61+1 -> 37 | C62: 45231 | D62: =H61 -> 3793340.5 | E62: =$D$26*$I$10 -> 22499.698 | F62: =D62*$I$9 -> 17386.144 | G62: =E62-F62 -> 5113.5539 | H62: =D62-G62 -> 3788227 | I62: =$I$20*D62 -> 0 | J62: =E62+I62 -> 22499.698 | K62: =SUM(I62:I73) -> 0
B63: =B62+1 -> 38 | C63: 45261 | D63: =H62 -> 3788227 | E63: =$D$26*$I$10 -> 22499.698 | F63: =D63*$I$9 -> 17362.707 | G63: =E63-F63 -> 5136.991 | H63: =D63-G63 -> 3783090 | I63: =$I$20*D63 -> 0 | J63: =E63+I63 -> 22499.698
B64: =B63+1 -> 39 | C64: 45292 | D64: =H63 -> 3783090 | E64: =$D$26*$I$10 -> 22499.698 | F64: =D64*$I$9 -> 17339.162 | G64: =E64-F64 -> 5160.5356 | H64: =D64-G64 -> 3777929.4 | I64: =$I$20*D64 -> 0 | J64: =E64+I64 -> 22499.698
B65: =B64+1 -> 40 | C65: 45323 | D65: =H64 -> 3777929.4 | E65: =$D$26*$I$10 -> 22499.698 | F65: =D65*$I$9 -> 17315.51 | G65: =E65-F65 -> 5184.188 | H65: =D65-G65 -> 3772745.2 | I65: =$I$20*D65 -> 0 | J65: =E65+I65 -> 22499.698
B66: =B65+1 -> 41 | C66: 45352 | D66: =H65 -> 3772745.2 | E66: =$D$26*$I$10 -> 22499.698 | F66: =D66*$I$9 -> 17291.749 | G66: =E66-F66 -> 5207.9489 | H66: =D66-G66 -> 3767537.3 | I66: =$I$20*D66 -> 0 | J66: =E66+I66 -> 22499.698
B67: =B66+1 -> 42 | C67: 45383 | D67: =H66 -> 3767537.3 | E67: =$D$26*$I$10 -> 22499.698 | F67: =D67*$I$9 -> 17267.879 | G67: =E67-F67 -> 5231.8187 | H67: =D67-G67 -> 3762305.5 | I67: =$I$20*D67 -> 0 | J67: =E67+I67 -> 22499.698
B68: =B67+1 -> 43 | C68: 45413 | D68: =H67 -> 3762305.5 | E68: =$D$26*$I$10 -> 22499.698 | F68: =D68*$I$9 -> 17243.9 | G68: =E68-F68 -> 5255.7978 | H68: =D68-G68 -> 3757049.7 | I68: =$I$20*D68 -> 0 | J68: =E68+I68 -> 22499.698
B69: =B68+1 -> 44 | C69: 45444 | D69: =H68 -> 3757049.7 | E69: =$D$26*$I$10 -> 22499.698 | F69: =D69*$I$9 -> 17219.811 | G69: =E69-F69 -> 5279.8869 | H69: =D69-G69 -> 3751769.8 | I69: =$I$20*D69 -> 0 | J69: =E69+I69 -> 22499.698
B70: =B69+1 -> 45 | C70: 45474 | D70: =H69 -> 3751769.8 | E70: =$D$26*$I$10 -> 22499.698 | F70: =D70*$I$9 -> 17195.612 | G70: =E70-F70 -> 5304.0864 | H70: =D70-G70 -> 3746465.7 | I70: =$I$20*D70 -> 0 | J70: =E70+I70 -> 22499.698
B71: =B70+1 -> 46 | C71: 45505 | D71: =H70 -> 3746465.7 | E71: =$D$26*$I$10 -> 22499.698 | F71: =D71*$I$9 -> 17171.301 | G71: =E71-F71 -> 5328.3968 | H71: =D71-G71 -> 3741137.3 | I71: =$I$20*D71 -> 0 | J71: =E71+I71 -> 22499.698
B72: =B71+1 -> 47 | C72: 45536 | D72: =H71 -> 3741137.3 | E72: =$D$26*$I$10 -> 22499.698 | F72: =D72*$I$9 -> 17146.879 | G72: =E72-F72 -> 5352.8186 | H72: =D72-G72 -> 3735784.5 | I72: =$I$20*D72 -> 0 | J72: =E72+I72 -> 22499.698
B73: =B72+1 -> 48 | C73: 45566 | D73: =H72 -> 3735784.5 | E73: =$D$26*$I$10 -> 22499.698 | F73: =D73*$I$9 -> 17122.346 | G73: =E73-F73 -> 5377.3524 | H73: =D73-G73 -> 3730407.1 | I73: =$I$20*D73 -> 0 | J73: =E73+I73 -> 22499.698
B74: =B73+1 -> 49 | C74: 45597 | D74: =H73 -> 3730407.1 | E74: =$D$26*$I$10 -> 22499.698 | F74: =D74*$I$9 -> 17097.699 | G74: =E74-F74 -> 5401.9985 | H74: =D74-G74 -> 3725005.1 | I74: =$I$20*D74 -> 0 | J74: =E74+I74 -> 22499.698 | K74: =SUM(I74:I85) -> 0
B75: =B74+1 -> 50 | C75: 45627 | D75: =H74 -> 3725005.1 | E75: =$D$26*$I$10 -> 22499.698 | F75: =D75*$I$9 -> 17072.94 | G75: =E75-F75 -> 5426.7577 | H75: =D75-G75 -> 3719578.4 | I75: =$I$20*D75 -> 0 | J75: =E75+I75 -> 22499.698
B76: =B75+1 -> 51 | C76: 45658 | D76: =H75 -> 3719578.4 | E76: =$D$26*$I$10 -> 22499.698 | F76: =D76*$I$9 -> 17048.068 | G76: =E76-F76 -> 5451.6303 | H76: =D76-G76 -> 3714126.7 | I76: =$I$20*D76 -> 0 | J76: =E76+I76 -> 22499.698
B77: =B76+1 -> 52 | C77: 45689 | D77: =H76 -> 3714126.7 | E77: =$D$26*$I$10 -> 22499.698 | F77: =D77*$I$9 -> 17023.081 | G77: =E77-F77 -> 5476.617 | H77: =D77-G77 -> 3708650.1 | I77: =$I$20*D77 -> 0 | J77: =E77+I77 -> 22499.698
B78: =B77+1 -> 53 | C78: 45717 | D78: =H77 -> 3708650.1 | E78: =$D$26*$I$10 -> 22499.698 | F78: =D78*$I$9 -> 16997.98 | G78: =E78-F78 -> 5501.7181 | H78: =D78-G78 -> 3703148.4 | I78: =$I$20*D78 -> 0 | J78: =E78+I78 -> 22499.698
B79: =B78+1 -> 54 | C79: 45748 | D79: =H78 -> 3703148.4 | E79: =$D$26*$I$10 -> 22499.698 | F79: =D79*$I$9 -> 16972.764 | G79: =E79-F79 -> 5526.9344 | H79: =D79-G79 -> 3697621.5 | I79: =$I$20*D79 -> 0 | J79: =E79+I79 -> 22499.698
B80: =B79+1 -> 55 | C80: 45778 | D80: =H79 -> 3697621.5 | E80: =$D$26*$I$10 -> 22499.698 | F80: =D80*$I$9 -> 16947.432 | G80: =E80-F80 -> 5552.2661 | H80: =D80-G80 -> 3692069.2 | I80: =$I$20*D80 -> 0 | J80: =E80+I80 -> 22499.698
B81: =B80+1 -> 56 | C81: 45809 | D81: =H80 -> 3692069.2 | E81: =$D$26*$I$10 -> 22499.698 | F81: =D81*$I$9 -> 16921.984 | G81: =E81-F81 -> 5577.714 | H81: =D81-G81 -> 3686491.5 | I81: =$I$20*D81 -> 0 | J81: =E81+I81 -> 22499.698
B82: =B81+1 -> 57 | C82: 45839 | D82: =H81 -> 3686491.5 | E82: =$D$26*$I$10 -> 22499.698 | F82: =D82*$I$9 -> 16896.419 | G82: =E82-F82 -> 5603.2785 | H82: =D82-G82 -> 3680888.2 | I82: =$I$20*D82 -> 0 | J82: =E82+I82 -> 22499.698
B83: =B82+1 -> 58 | C83: 45870 | D83: =H82 -> 3680888.2 | E83: =$D$26*$I$10 -> 22499.698 | F83: =D83*$I$9 -> 16870.738 | G83: =E83-F83 -> 5628.9602 | H83: =D83-G83 -> 3675259.3 | I83: =$I$20*D83 -> 0 | J83: =E83+I83 -> 22499.698
B84: =B83+1 -> 59 | C84: 45901 | D84: =H83 -> 3675259.3 | E84: =$D$26*$I$10 -> 22499.698 | F84: =D84*$I$9 -> 16844.938 | G84: =E84-F84 -> 5654.7596 | H84: =D84-G84 -> 3669604.5 | I84: =$I$20*D84 -> 0 | J84: =E84+I84 -> 22499.698
B85: =B84+1 -> 60 | C85: 45931 | D85: =H84 -> 3669604.5 | E85: =$D$26*$I$10 -> 22499.698 | F85: =D85*$I$9 -> 16819.021 | G85: =E85-F85 -> 5680.6773 | H85: =D85-G85 -> 3663923.8 | I85: =$I$20*D85 -> 0 | J85: =E85+I85 -> 22499.698
B86: =B85+1 -> 61 | C86: 45962 | D86: =H85 -> 3663923.8 | E86: =$D$26*$I$10 -> 22499.698 | F86: =D86*$I$9 -> 16792.984 | G86: =E86-F86 -> 5706.7137 | H86: =D86-G86 -> 3658217.1 | I86: =$I$20*D86 -> 0 | J86: =E86+I86 -> 22499.698 | K86: =SUM(I86:I97) -> 0
B87: =B86+1 -> 62 | C87: 45992 | D87: =H86 -> 3658217.1 | E87: =$D$26*$I$10 -> 22499.698 | F87: =D87*$I$9 -> 16766.828 | G87: =E87-F87 -> 5732.8695 | H87: =D87-G87 -> 3652484.2 | I87: =$I$20*D87 -> 0 | J87: =E87+I87 -> 22499.698
B88: =B87+1 -> 63 | C88: 46023 | D88: =H87 -> 3652484.2 | E88: =$D$26*$I$10 -> 22499.698 | F88: =D88*$I$9 -> 16740.553 | G88: =E88-F88 -> 5759.1452 | H88: =D88-G88 -> 3646725.1 | I88: =$I$20*D88 -> 0 | J88: =E88+I88 -> 22499.698
B89: =B88+1 -> 64 | C89: 46054 | D89: =H88 -> 3646725.1 | E89: =$D$26*$I$10 -> 22499.698 | F89: =D89*$I$9 -> 16714.157 | G89: =E89-F89 -> 5785.5412 | H89: =D89-G89 -> 3640939.6 | I89: =$I$20*D89 -> 0 | J89: =E89+I89 -> 22499.698
B90: =B89+1 -> 65 | C90: 46082 | D90: =H89 -> 3640939.6 | E90: =$D$26*$I$10 -> 22499.698 | F90: =D90*$I$9 -> 16687.64 | G90: =E90-F90 -> 5812.0583 | H90: =D90-G90 -> 3635127.5 | I90: =$I$20*D90 -> 0 | J90: =E90+I90 -> 22499.698
B91: =B90+1 -> 66 | C91: 46113 | D91: =H90 -> 3635127.5 | E91: =$D$26*$I$10 -> 22499.698 | F91: =D91*$I$9 -> 16661.001 | G91: =E91-F91 -> 5838.6969 | H91: =D91-G91 -> 3629288.8 | I91: =$I$20*D91 -> 0 | J91: =E91+I91 -> 22499.698
B92: =B91+1 -> 67 | C92: 46143 | D92: =H91 -> 3629288.8 | E92: =$D$26*$I$10 -> 22499.698 | F92: =D92*$I$9 -> 16634.24 | G92: =E92-F92 -> 5865.4576 | H92: =D92-G92 -> 3623423.3 | I92: =$I$20*D92 -> 0 | J92: =E92+I92 -> 22499.698
B93: =B92+1 -> 68 | C93: 46174 | D93: =H92 -> 3623423.3 | E93: =$D$26*$I$10 -> 22499.698 | F93: =D93*$I$9 -> 16607.357 | G93: =E93-F93 -> 5892.3409 | H93: =D93-G93 -> 3617531 | I93: =$I$20*D93 -> 0 | J93: =E93+I93 -> 22499.698
B94: =B93+1 -> 69 | C94: 46204 | D94: =H93 -> 3617531 | E94: =$D$26*$I$10 -> 22499.698 | F94: =D94*$I$9 -> 16580.35 | G94: =E94-F94 -> 5919.3475 | H94: =D94-G94 -> 3611611.6 | I94: =$I$20*D94 -> 0 | J94: =E94+I94 -> 22499.698
B95: =B94+1 -> 70 | C95: 46235 | D95: =H94 -> 3611611.6 | E95: =$D$26*$I$10 -> 22499.698 | F95: =D95*$I$9 -> 16553.22 | G95: =E95-F95 -> 5946.4778 | H95: =D95-G95 -> 3605665.2 | I95: =$I$20*D95 -> 0 | J95: =E95+I95 -> 22499.698
B96: =B95+1 -> 71 | C96: 46266 | D96: =H95 -> 3605665.2 | E96: =$D$26*$I$10 -> 22499.698 | F96: =D96*$I$9 -> 16525.965 | G96: =E96-F96 -> 5973.7325 | H96: =D96-G96 -> 3599691.4 | I96: =$I$20*D96 -> 0 | J96: =E96+I96 -> 22499.698
B97: =B96+1 -> 72 | C97: 46296 | D97: =H96 -> 3599691.4 | E97: =$D$26*$I$10 -> 22499.698 | F97: =D97*$I$9 -> 16498.586 | G97: =E97-F97 -> 6001.1121 | H97: =D97-G97 -> 3593690.3 | I97: =$I$20*D97 -> 0 | J97: =E97+I97 -> 22499.698
B98: =B97+1 -> 73 | C98: 46327 | D98: =H97 -> 3593690.3 | E98: =$D$26*$I$10 -> 22499.698 | F98: =D98*$I$9 -> 16471.081 | G98: =E98-F98 -> 6028.6172 | H98: =D98-G98 -> 3587661.7 | I98: =$I$20*D98 -> 0 | J98: =E98+I98 -> 22499.698 | K98: =SUM(I98:I109) -> 0
B99: =B98+1 -> 74 | C99: 46357 | D99: =H98 -> 3587661.7 | E99: =$D$26*$I$10 -> 22499.698 | F99: =D99*$I$9 -> 16443.449 | G99: =E99-F99 -> 6056.2484 | H99: =D99-G99 -> 3581605.5 | I99: =$I$20*D99 -> 0 | J99: =E99+I99 -> 22499.698
B100: =B99+1 -> 75 | C100: 46388 | D100: =H99 -> 3581605.5 | E100: =$D$26*$I$10 -> 22499.698 | F100: =D100*$I$9 -> 16415.692 | G100: =E100-F100 -> 6084.0062 | H100: =D100-G100 -> 3575521.5 | I100: =$I$20*D100 -> 0 | J100: =E100+I100 -> 22499.698
B101: =B100+1 -> 76 | C101: 46419 | D101: =H100 -> 3575521.5 | E101: =$D$26*$I$10 -> 22499.698 | F101: =D101*$I$9 -> 16387.807 | G101: =E101-F101 -> 6111.8912 | H101: =D101-G101 -> 3569409.6 | I101: =$I$20*D101 -> 0 | J101: =E101+I101 -> 22499.698
B102: =B101+1 -> 77 | C102: 46447 | D102: =H101 -> 3569409.6 | E102: =$D$26*$I$10 -> 22499.698 | F102: =D102*$I$9 -> 16359.794 | G102: =E102-F102 -> 6139.9041 | H102: =D102-G102 -> 3563269.7 | I102: =$I$20*D102 -> 0 | J102: =E102+I102 -> 22499.698
B103: =B102+1 -> 78 | C103: 46478 | D103: =H102 -> 3563269.7 | E103: =$D$26*$I$10 -> 22499.698 | F103: =D103*$I$9 -> 16331.653 | G103: =E103-F103 -> 6168.0453 | H103: =D103-G103 -> 3557101.6 | I103: =$I$20*D103 -> 0 | J103: =E103+I103 -> 22499.698
B104: =B103+1 -> 79 | C104: 46508 | D104: =H103 -> 3557101.6 | E104: =$D$26*$I$10 -> 22499.698 | F104: =D104*$I$9 -> 16303.382 | G104: =E104-F104 -> 6196.3155 | H104: =D104-G104 -> 3550905.3 | I104: =$I$20*D104 -> 0 | J104: =E104+I104 -> 22499.698
B105: =B104+1 -> 80 | C105: 46539 | D105: =H104 -> 3550905.3 | E105: =$D$26*$I$10 -> 22499.698 | F105: =D105*$I$9 -> 16274.983 | G105: =E105-F105 -> 6224.7153 | H105: =D105-G105 -> 3544680.6 | I105: =$I$20*D105 -> 0 | J105: =E105+I105 -> 22499.698
B106: =B105+1 -> 81 | C106: 46569 | D106: =H105 -> 3544680.6 | E106: =$D$26*$I$10 -> 22499.698 | F106: =D106*$I$9 -> 16246.453 | G106: =E106-F106 -> 6253.2452 | H106: =D106-G106 -> 3538427.3 | I106: =$I$20*D106 -> 0 | J106: =E106+I106 -> 22499.698
B107: =B106+1 -> 82 | C107: 46600 | D107: =H106 -> 3538427.3 | E107: =$D$26*$I$10 -> 22499.698 | F107: =D107*$I$9 -> 16217.792 | G107: =E107-F107 -> 6281.9059 | H107: =D107-G107 -> 3532145.4 | I107: =$I$20*D107 -> 0 | J107: =E107+I107 -> 22499.698
B108: =B107+1 -> 83 | C108: 46631 | D108: =H107 -> 3532145.4 | E108: =$D$26*$I$10 -> 22499.698 | F108: =D108*$I$9 -> 16189 | G108: =E108-F108 -> 6310.698 | H108: =D108-G108 -> 3525834.7 | I108: =$I$20*D108 -> 0 | J108: =E108+I108 -> 22499.698
B109: =B108+1 -> 84 | C109: 46661 | D109: =H108 -> 3525834.7 | E109: =$D$26*$I$10 -> 22499.698 | F109: =D109*$I$9 -> 16160.076 | G109: =E109-F109 -> 6339.622 | H109: =D109-G109 -> 3519495.1 | I109: =$I$20*D109 -> 0 | J109: =E109+I109 -> 22499.698
...
